Workbook
Name \0: #REF!
Name \0: #REF!
Name \0: #REF!
Name \0: #REF!
Name \5: #REF!
Name \5: #REF!
Name \7: #REF!
Name \7: #REF!
Name \8: #REF!
Name \A: #REF!
Name \a: #N/A
Name \A: #REF!
Name \A: #REF!
Name \B: #REF!
Name \b: #REF!
Name \B: #REF!
Name \B: #REF!
Name \c: #REF!
Name \c: #REF!
Name \D: #REF!
Name \d: #REF!
Name \E: #REF!
Name \E: #REF!
Name \E: #REF!
Name \f: #REF!
Name \G: #REF!
Name \G: #REF!
Name \G: #REF!
Name \H: #REF!
Name \H: #REF!
Name \H: #REF!
Name \I: #REF!
Name \I: #REF!
Name \I: #REF!
Name \J: #REF!
Name \J: #REF!
Name \J: #REF!
Name \K: #REF!
Name \K: #REF!
Name \K: #REF!
Name \L: #REF!
Name \L: #REF!
Name \L: #REF!
Name \m: #REF!
Name \m: #REF!
Name \m: #REF!
Name \n: #REF!
Name \n: #REF!
Name \n: #REF!
Name \O: #REF!
Name \O: #REF!
Name \O: #REF!
Name \P: #REF!
Name \P: #REF!
Name \P: #REF!
Name \P24: #REF!
Name \P24: #REF!
Name \P24: #REF!
Name \PP: #REF!
Name \PP: #REF!

Sheet Cover
C13: Project BORACAY
C14: Bonchon Financial Model
C15: January 2026

Sheet Table of Contents
C2: Project BORACAY
C3: Bonchon Financial Model
C5: Table of Contents
C6: Assumptions
C8: Annual P&Ls
C9: Consolidated P&L
C10: Bonchon U.S. P&L
C11: Bonchon International P&L
C12: Consolidations P&L
C14: 2025 Monthly P&Ls
C15: Consolidated P&L (Monthly)
C16: Bonchon U.S. P&L (Monthly)
... C41: Embedded Growth

Sheet Summary>>

Sheet Assumptions
B3: Basis of Financial Presentation
B16: 2025A-2030P Growth Assumptions
B46: Sauce Economics Overview
B83: SG&A Detail
B130: Capex Detail
B142: FX Treatment and Assumptions

Sheet Annual P&Ls>>

Sheet Consolidated P&L
B2: Bonchon Consolidated P&L
C4: Historical | H4: Projected | N4: CAGR
B5: ($ in millions) | C5: 2021 | D5: 2022 | E5: 2023 | F5: 2024 | G5: 2025A | H5: 2026E | I5: 2027P | J5: 2028P | K5: 2029P | L5: 2030P | N5: '21A-'25E | O5: '25E-'30P
B7: U.S. Restaurants | C7: ='Bonchon U.S. P&L'!C9 -> 115 | D7: ='Bonchon U.S. P&L'!D9 -> 122 | E7: ='Bonchon U.S. P&L'!E9 -> 131 | F7: ='Bonchon U.S. P&L'!F9 -> 147 | G7: ='Bonchon U.S. P&L'!G9 -> 151 | H7: ='Bonchon U.S. P&L'!H9 -> 179 | I7: ='Bonchon U.S. P&L'!I9 -> 209 | J7: ='Bonchon U.S. P&L'!J9 -> 244 | ... L7: ='Bonchon U.S. P&L'!L9 -> 344 | N7: =IFERROR(_xlfn.RRI(4,C7,G7),"-") -> 0.070458356 | O7: =IFERROR(_xlfn.RRI(5,G7,L7),"-") -> 0.17900677
B8: International Restaurants | C8: ='Bonchon International P&L'!C20 -> 274 | D8: ='Bonchon International P&L'!D20 -> 287 | E8: ='Bonchon International P&L'!E20 -> 304 | F8: ='Bonchon International P&L'!F20 -> 324 | G8: ='Bonchon International P&L'!G20 -> 347 | H8: ='Bonchon International P&L'!H20 -> 376 | I8: ='Bonchon International P&L'!I20 -> 414 | J8: ='Bonchon International P&L'!J20 -> 459 | ... L8: ='Bonchon International P&L'!L20 -> 561 | N8: =IFERROR(_xlfn.RRI(4,C8,G8),"-") -> 0.060827399 | O8: =IFERROR(_xlfn.RRI(5,G8,L8),"-") -> 0.10084628
B9: Systemwide Restaurants | C9: =SUM(C7:C8) -> 389 | D9: =SUM(D7:D8) -> 409 | E9: =SUM(E7:E8) -> 435 | F9: =SUM(F7:F8) -> 471 | G9: =SUM(G7:G8) -> 498 | H9: =SUM(H7:H8) -> 555 | I9: =SUM(I7:I8) -> 623 | J9: =SUM(J7:J8) -> 703 | ... L9: =SUM(L7:L8) -> 905 | N9: =IFERROR(_xlfn.RRI(4,C9,G9),"-") -> 0.063701901 | O9: =IFERROR(_xlfn.RRI(5,G9,L9),"-") -> 0.12689603
B10: % Growth | D10: =IFERROR(D9/C9-1,0) -> 0.051413882 | E10: =IFERROR(E9/D9-1,0) -> 0.063569682 | F10: =IFERROR(F9/E9-1,0) -> 0.082758621 | G10: =IFERROR(G9/F9-1,0) -> 0.057324841 | H10: =IFERROR(H9/G9-1,0) -> 0.11445783 | I10: =IFERROR(I9/H9-1,0) -> 0.12252252 | J10: =IFERROR(J9/I9-1,0) -> 0.12841091 | K10: =IFERROR(K9/J9-1,0) -> 0.13513514 | L10: =IFERROR(L9/K9-1,0) -> 0.13408521
B12: U.S. | C12: ='Bonchon U.S. P&L'!C12 -> 173.415 | D12: ='Bonchon U.S. P&L'!D12 -> 193.64356 | E12: ='Bonchon U.S. P&L'!E12 -> 200.67402 | F12: ='Bonchon U.S. P&L'!F12 -> 202.35598 | G12: ='Bonchon U.S. P&L'!G12 -> 211.07983 | H12: ='Bonchon U.S. P&L'!H12 -> 236.36305 | I12: ='Bonchon U.S. P&L'!I12 -> 290.17861 | J12: ='Bonchon U.S. P&L'!J12 -> 352.66562 | ... L12: ='Bonchon U.S. P&L'!L12 -> 533.59659 | N12: =IFERROR(_xlfn.RRI(4,C12,G12),"-") -> 0.050364462 | O12: =IFERROR(_xlfn.RRI(5,G12,L12),"-") -> 0.20379702
B13: International | C13: ='Bonchon International P&L'!C23 -> 103.10846 | D13: ='Bonchon International P&L'!D23 -> 133.7085 | E13: ='Bonchon International P&L'!E23 -> 144.83545 | F13: ='Bonchon International P&L'!F23 -> 154.48318 | G13: ='Bonchon International P&L'!G23 -> 170.03361 | H13: ='Bonchon International P&L'!H23 -> 181.55199 | I13: ='Bonchon International P&L'!I23 -> 207.69386 | J13: ='Bonchon International P&L'!J23 -> 239.16518 | ... L13: ='Bonchon International P&L'!L23 -> 319.15817 | N13: =IFERROR(_xlfn.RRI(4,C13,G13),"-") -> 0.13320926 | O13: =IFERROR(_xlfn.RRI(5,G13,L13),"-") -> 0.13421201
B14: Systemwide Sales | C14: =SUM(C12:C13) -> 276.52346 | D14: =SUM(D12:D13) -> 327.35207 | E14: =SUM(E12:E13) -> 345.50947 | F14: =SUM(F12:F13) -> 356.83916 | G14: =SUM(G12:G13) -> 381.11344 | H14: =SUM(H12:H13) -> 417.91503 | I14: =SUM(I12:I13) -> 497.87246 | J14: =SUM(J12:J13) -> 591.8308 | ... L14: =SUM(L12:L13) -> 852.75476 | N14: =IFERROR(_xlfn.RRI(4,C14,G14),"-") -> 0.083504126 | O14: =IFERROR(_xlfn.RRI(5,G14,L14),"-") -> 0.17477306
B15: % Growth | D15: =IFERROR(D14/C14-1,0) -> 0.183813 | E15: =IFERROR(E14/D14-1,0) -> 0.055467502 | F15: =IFERROR(F14/E14-1,0) -> 0.032791251 | G15: =IFERROR(G14/F14-1,0) -> 0.068025831 | H15: =IFERROR(H14/G14-1,0) -> 0.096563363 | I15: =IFERROR(I14/H14-1,0) -> 0.19132461 | J15: =IFERROR(J14/I14-1,0) -> 0.1887197 | K15: =IFERROR(K14/J14-1,0) -> 0.19692414 | L15: =IFERROR(L14/K14-1,0) -> 0.20381559
B17: U.S. Same Store Sales | C17: ='Bonchon U.S. P&L'!C15 -> 0.16753805 | D17: ='Bonchon U.S. P&L'!D15 -> 0.049974743 | E17: ='Bonchon U.S. P&L'!E15 -> -0.033246735 | F17: ='Bonchon U.S. P&L'!F15 -> -0.079297458 | G17: ='Bonchon U.S. P&L'!G15 -> 8.3373689e-05 | H17: ='Bonchon U.S. P&L'!H15 -> 0.05043868 | I17: ='Bonchon U.S. P&L'!I15 -> 0.04 | J17: ='Bonchon U.S. P&L'!J15 -> 0.04 | ... L17: ='Bonchon U.S. P&L'!L15 -> 0.04
B18: International Same Store Sales | C18: ='Bonchon International P&L'!C29 -> -0.16075935 | D18: ='Bonchon International P&L'!D29 -> 0.15699898 | E18: ='Bonchon International P&L'!E29 -> 0.019225146 | F18: ='Bonchon International P&L'!F29 -> 0.010998005 | G18: ='Bonchon International P&L'!G29 -> 0.055085803 | H18: ='Bonchon International P&L'!H29 -> 0.05 | I18: ='Bonchon International P&L'!I29 -> 0.05 | J18: ='Bonchon International P&L'!J29 -> 0.05 | ... L18: ='Bonchon International P&L'!L29 -> 0.05
B19: Systemwide Same Store Sales | C19: 0.020999098 | D19: 0.092648212 | E19: -0.010871634 | F19: -0.039606542 | G19: 0.024720986 | H19: =(H17*(H12/H14))+(H18*(H13/H14)) -> 0.050248107 | I19: =(I17*(I12/I14))+(I18*(I13/I14)) -> 0.044171628 | J19: =(J17*(J12/J14))+(J18*(J13/J14)) -> 0.044041107 | K19: =(K17*(K12/K14))+(K18*(K13/K14)) -> 0.043903941 | L19: =(L17*(L12/L14))+(L18*(L13/L14)) -> 0.043742672
B21: Franchise Revenue | C21: ='Bonchon U.S. P&L'!C17+'Bonchon International P&L'!C31-'Consolidations P&L'!C7 -> 11.362014 | D21: ='Bonchon U.S. P&L'!D17+'Bonchon International P&L'!D31-'Consolidations P&L'!D7 -> 13.069418 | E21: ='Bonchon U.S. P&L'!E17+'Bonchon International P&L'!E31-'Consolidations P&L'!E7 -> 13.946716 | F21: ='Bonchon U.S. P&L'!F17+'Bonchon International P&L'!F31-'Consolidations P&L'!F7 -> 14.441046 | G21: ='Bonchon U.S. P&L'!G17+'Bonchon International P&L'!G31-'Consolidations P&L'!G7 -> 15.092833 | H21: ='Bonchon U.S. P&L'!H17+'Bonchon International P&L'!H31-'Consolidations P&L'!H7 -> 16.733238 | I21: ='Bonchon U.S. P&L'!I17+'Bonchon International P&L'!I31-'Consolidations P&L'!I7 -> 19.88653 | J21: ='Bonchon U.S. P&L'!J17+'Bonchon International P&L'!J31-'Consolidations P&L'!J7 -> 25.43262 | ... L21: ='Bonchon U.S. P&L'!L17+'Bonchon International P&L'!L31-'Consolidations P&L'!L7 -> 37.79932 | N21: =IFERROR(_xlfn.RRI(4,C21,G21),"-") -> 0.073566279 | O21: =IFERROR(_xlfn.RRI(5,G21,L21),"-") -> 0.2015522
B22: Sauce Revenue | C22: ='Bonchon U.S. P&L'!C18+'Bonchon International P&L'!C32-'Consolidations P&L'!C8 -> 5.7911749 | D22: ='Bonchon U.S. P&L'!D18+'Bonchon International P&L'!D32-'Consolidations P&L'!D8 -> 7.1760565 | E22: ='Bonchon U.S. P&L'!E18+'Bonchon International P&L'!E32-'Consolidations P&L'!E8 -> 7.8954667 | F22: ='Bonchon U.S. P&L'!F18+'Bonchon International P&L'!F32-'Consolidations P&L'!F8 -> 8.2833766 | G22: ='Bonchon U.S. P&L'!G18+'Bonchon International P&L'!G32-'Consolidations P&L'!G8 -> 7.3720481 | H22: ='Bonchon U.S. P&L'!H18+'Bonchon International P&L'!H32-'Consolidations P&L'!H8 -> 8.0986798 | I22: ='Bonchon U.S. P&L'!I18+'Bonchon International P&L'!I32-'Consolidations P&L'!I8 -> 9.3248687 | J22: ='Bonchon U.S. P&L'!J18+'Bonchon International P&L'!J32-'Consolidations P&L'!J8 -> 11.033129 | ... L22: ='Bonchon U.S. P&L'!L18+'Bonchon International P&L'!L32-'Consolidations P&L'!L8 -> 17.244961 | N22: =IFERROR(_xlfn.RRI(4,C22,G22),"-") -> 0.062197733 | O22: =IFERROR(_xlfn.RRI(5,G22,L22),"-") -> 0.18526323
B23: Company-Owned Store Revenue | C23: ='Bonchon U.S. P&L'!C19+'Bonchon International P&L'!C33-'Consolidations P&L'!C9 -> 1.7976949 | D23: ='Bonchon U.S. P&L'!D19+'Bonchon International P&L'!D33-'Consolidations P&L'!D9 -> 5.1372586 | E23: ='Bonchon U.S. P&L'!E19+'Bonchon International P&L'!E33-'Consolidations P&L'!E9 -> 5.0760827 | F23: ='Bonchon U.S. P&L'!F19+'Bonchon International P&L'!F33-'Consolidations P&L'!F9 -> 4.1612575 | G23: ='Bonchon U.S. P&L'!G19+'Bonchon International P&L'!G33-'Consolidations P&L'!G9 -> 3.7884491 | H23: ='Bonchon U.S. P&L'!H19+'Bonchon International P&L'!H33-'Consolidations P&L'!H9 -> 4.3374481 | I23: ='Bonchon U.S. P&L'!I19+'Bonchon International P&L'!I33-'Consolidations P&L'!I9 -> 6.2884611 | J23: ='Bonchon U.S. P&L'!J19+'Bonchon International P&L'!J33-'Consolidations P&L'!J9 -> 6.9173072 | ... L23: ='Bonchon U.S. P&L'!L19+'Bonchon International P&L'!L33-'Consolidations P&L'!L9 -> 8.3699417 | N23: =IFERROR(_xlfn.RRI(4,C23,G23),"-") -> 0.20485939 | O23: =IFERROR(_xlfn.RRI(5,G23,L23),"-") -> 0.17179649
B24: Marketing Fund | C24: ='Bonchon U.S. P&L'!C20+'Bonchon International P&L'!C34-'Consolidations P&L'!C10 -> 1.7094527 | D24: ='Bonchon U.S. P&L'!D20+'Bonchon International P&L'!D34-'Consolidations P&L'!D10 -> 2.1685849 | E24: ='Bonchon U.S. P&L'!E20+'Bonchon International P&L'!E34-'Consolidations P&L'!E10 -> 2.8156541 | F24: ='Bonchon U.S. P&L'!F20+'Bonchon International P&L'!F34-'Consolidations P&L'!F10 -> 3.2534763 | G24: ='Bonchon U.S. P&L'!G20+'Bonchon International P&L'!G34-'Consolidations P&L'!G10 -> 3.2282713 | H24: ='Bonchon U.S. P&L'!H20+'Bonchon International P&L'!H34-'Consolidations P&L'!H10 -> 4.9917485 | I24: ='Bonchon U.S. P&L'!I20+'Bonchon International P&L'!I34-'Consolidations P&L'!I10 -> 8.5167043 | J24: ='Bonchon U.S. P&L'!J20+'Bonchon International P&L'!J34-'Consolidations P&L'!J10 -> 13.829933 | ... L24: ='Bonchon U.S. P&L'!L20+'Bonchon International P&L'!L34-'Consolidations P&L'!L10 -> 21.009066 | N24: =IFERROR(_xlfn.RRI(4,C24,G24),"-") -> 0.17227159 | O24: =IFERROR(_xlfn.RRI(5,G24,L24),"-") -> 0.45441164
B25: Other Product Revenue | C25: ='Bonchon U.S. P&L'!C21+'Bonchon International P&L'!C35-'Consolidations P&L'!C11 -> -0.035375888 | D25: ='Bonchon U.S. P&L'!D21+'Bonchon International P&L'!D35-'Consolidations P&L'!D11 -> -0.070617026 | E25: ='Bonchon U.S. P&L'!E21+'Bonchon International P&L'!E35-'Consolidations P&L'!E11 -> 0.37069759 | F25: ='Bonchon U.S. P&L'!F21+'Bonchon International P&L'!F35-'Consolidations P&L'!F11 -> 0.15019239 | G25: ='Bonchon U.S. P&L'!G21+'Bonchon International P&L'!G35-'Consolidations P&L'!G11 -> 0.0063102521 | H25: ='Bonchon U.S. P&L'!H21+'Bonchon International P&L'!H35-'Consolidations P&L'!H11 -> 0.026584105 | I25: ='Bonchon U.S. P&L'!I21+'Bonchon International P&L'!I35-'Consolidations P&L'!I11 -> 0.040422701 | J25: ='Bonchon U.S. P&L'!J21+'Bonchon International P&L'!J35-'Consolidations P&L'!J11 -> 0.047549874 | ... L25: ='Bonchon U.S. P&L'!L21+'Bonchon International P&L'!L35-'Consolidations P&L'!L11 -> 0.064551041 | N25: =IFERROR(_xlfn.RRI(4,C25,G25),"-") -> - | O25: =IFERROR(_xlfn.RRI(5,G25,L25),"-") -> 0.59210354
B26: Other Revenue | C26: ='Bonchon U.S. P&L'!C22+'Bonchon International P&L'!C36-'Consolidations P&L'!C12 -> 0.30773293 | D26: ='Bonchon U.S. P&L'!D22+'Bonchon International P&L'!D36-'Consolidations P&L'!D12 -> 0.12628718 | E26: ='Bonchon U.S. P&L'!E22+'Bonchon International P&L'!E36-'Consolidations P&L'!E12 -> 0.27595889 | F26: ='Bonchon U.S. P&L'!F22+'Bonchon International P&L'!F36-'Consolidations P&L'!F12 -> 0.1570314 | G26: ='Bonchon U.S. P&L'!G22+'Bonchon International P&L'!G36-'Consolidations P&L'!G12 -> 0.17322978 | H26: ='Bonchon U.S. P&L'!H22+'Bonchon International P&L'!H36-'Consolidations P&L'!H12 -> 0.20392759 | I26: ='Bonchon U.S. P&L'!I22+'Bonchon International P&L'!I36-'Consolidations P&L'!I12 -> 0.2275 | J26: ='Bonchon U.S. P&L'!J22+'Bonchon International P&L'!J36-'Consolidations P&L'!J12 -> 0.26 | ... L26: ='Bonchon U.S. P&L'!L22+'Bonchon International P&L'!L36-'Consolidations P&L'!L12 -> 0.39 | N26: =IFERROR(_xlfn.RRI(4,C26,G26),"-") -> -0.13381203 | O26: =IFERROR(_xlfn.RRI(5,G26,L26),"-") -> 0.1762196
B27: Other | C27: =SUM(C25:C26) -> 0.27235704 | D27: =SUM(D25:D26) -> 0.055670154 | E27: =SUM(E25:E26) -> 0.64665648 | F27: =SUM(F25:F26) -> 0.30722379 | G27: =SUM(G25:G26) -> 0.17954003 | H27: =SUM(H25:H26) -> 0.23051169 | I27: =SUM(I25:I26) -> 0.2679227 | J27: =SUM(J25:J26) -> 0.30754987 | ... L27: =SUM(L25:L26) -> 0.45455104 | N27: =IFERROR(_xlfn.RRI(4,C27,G27),"-") -> -0.098935928 | O27: =IFERROR(_xlfn.RRI(5,G27,L27),"-") -> 0.20416021
B28: Total Revenue | C28: =SUM(C21:C24,C27) -> 20.932693 | D28: =SUM(D21:D24,D27) -> 27.606988 | E28: =SUM(E21:E24,E27) -> 30.380576 | F28: =SUM(F21:F24,F27) -> 30.44638 | G28: =SUM(G21:G24,G27) -> 29.661142 | H28: =SUM(H21:H24,H27) -> 34.391626 | I28: =SUM(I21:I24,I27) -> 44.284486 | J28: =SUM(J21:J24,J27) -> 57.520539 | ... L28: =SUM(L21:L24,L27) -> 84.877839 | N28: =IFERROR(_xlfn.RRI(4,C28,G28),"-") -> 0.091040035 | O28: =IFERROR(_xlfn.RRI(5,G28,L28),"-") -> 0.23401742
B29: % Growth | D29: =IFERROR(D28/C28-1,0) -> 0.31884547 | E29: =IFERROR(E28/D28-1,0) -> 0.1004669 | F29: =IFERROR(F28/E28-1,0) -> 0.0021659763 | G29: =IFERROR(G28/F28-1,0) -> -0.025790865 | H29: =IFERROR(H28/G28-1,0) -> 0.15948424 | I29: =IFERROR(I28/H28-1,0) -> 0.28765317 | J29: =IFERROR(J28/I28-1,0) -> 0.29888688 | K29: =IFERROR(K28/J28-1,0) -> 0.22427322 | L29: =IFERROR(L28/K28-1,0) -> 0.20529408
B31: Sauce COGS | C31: ='Bonchon U.S. P&L'!C27+'Bonchon International P&L'!C41-'Consolidations P&L'!C17 -> 0.86757262 | D31: ='Bonchon U.S. P&L'!D27+'Bonchon International P&L'!D41-'Consolidations P&L'!D17 -> 1.2818111 | E31: ='Bonchon U.S. P&L'!E27+'Bonchon International P&L'!E41-'Consolidations P&L'!E17 -> 1.5984929 | F31: ='Bonchon U.S. P&L'!F27+'Bonchon International P&L'!F41-'Consolidations P&L'!F17 -> 1.4781993 | G31: ='Bonchon U.S. P&L'!G27+'Bonchon International P&L'!G41-'Consolidations P&L'!G17 -> 1.3179227 | H31: ='Bonchon U.S. P&L'!H27+'Bonchon International P&L'!H41-'Consolidations P&L'!H17 -> 1.3505507 | I31: ='Bonchon U.S. P&L'!I27+'Bonchon International P&L'!I41-'Consolidations P&L'!I17 -> 1.5339579 | J31: ='Bonchon U.S. P&L'!J27+'Bonchon International P&L'!J41-'Consolidations P&L'!J17 -> 1.7648955 | ... L31: ='Bonchon U.S. P&L'!L27+'Bonchon International P&L'!L41-'Consolidations P&L'!L17 -> 2.3941645 | N31: =IFERROR(_xlfn.RRI(4,C31,G31),"-") -> 0.1101867 | O31: =IFERROR(_xlfn.RRI(5,G31,L31),"-") -> 0.1268155
B32: Company-Owned Store COGS | C32: ='Bonchon U.S. P&L'!C28+'Bonchon International P&L'!C42-'Consolidations P&L'!C18 -> 0.57564599 | D32: ='Bonchon U.S. P&L'!D28+'Bonchon International P&L'!D42-'Consolidations P&L'!D18 -> 1.5265284 | E32: ='Bonchon U.S. P&L'!E28+'Bonchon International P&L'!E42-'Consolidations P&L'!E18 -> 1.4018693 | F32: ='Bonchon U.S. P&L'!F28+'Bonchon International P&L'!F42-'Consolidations P&L'!F18 -> 1.4141352 | G32: ='Bonchon U.S. P&L'!G28+'Bonchon International P&L'!G42-'Consolidations P&L'!G18 -> 1.0689561 | H32: ='Bonchon U.S. P&L'!H28+'Bonchon International P&L'!H42-'Consolidations P&L'!H18 -> 1.2437544 | I32: ='Bonchon U.S. P&L'!I28+'Bonchon International P&L'!I42-'Consolidations P&L'!I18 -> 1.7413943 | J32: ='Bonchon U.S. P&L'!J28+'Bonchon International P&L'!J42-'Consolidations P&L'!J18 -> 1.8960876 | ... L32: ='Bonchon U.S. P&L'!L28+'Bonchon International P&L'!L42-'Consolidations P&L'!L18 -> 2.2650287 | N32: =IFERROR(_xlfn.RRI(4,C32,G32),"-") -> 0.16735002 | O32: =IFERROR(_xlfn.RRI(5,G32,L32),"-") -> 0.16204453
B33: Other Product COGS | C33: ='Bonchon U.S. P&L'!C29+'Bonchon International P&L'!C43-'Consolidations P&L'!C19 -> -0.0054500074 | D33: ='Bonchon U.S. P&L'!D29+'Bonchon International P&L'!D43-'Consolidations P&L'!D19 -> -0.040312736 | E33: ='Bonchon U.S. P&L'!E29+'Bonchon International P&L'!E43-'Consolidations P&L'!E19 -> 0.30606265 | F33: ='Bonchon U.S. P&L'!F29+'Bonchon International P&L'!F43-'Consolidations P&L'!F19 -> 0.13779985 | G33: ='Bonchon U.S. P&L'!G29+'Bonchon International P&L'!G43-'Consolidations P&L'!G19 -> 0.020230089 | H33: ='Bonchon U.S. P&L'!H29+'Bonchon International P&L'!H43-'Consolidations P&L'!H19 -> 0.014566179 | I33: ='Bonchon U.S. P&L'!I29+'Bonchon International P&L'!I43-'Consolidations P&L'!I19 -> 0.028579146 | J33: ='Bonchon U.S. P&L'!J29+'Bonchon International P&L'!J43-'Consolidations P&L'!J19 -> 0.033588067 | ... L33: ='Bonchon U.S. P&L'!L29+'Bonchon International P&L'!L43-'Consolidations P&L'!L19 -> 0.045372077 | N33: =IFERROR(_xlfn.RRI(4,C33,G33),"-") -> - | O33: =IFERROR(_xlfn.RRI(5,G33,L33),"-") -> 0.17532554
B34: D&A In COGS | C34: ='Bonchon U.S. P&L'!C30+'Bonchon International P&L'!C44-'Consolidations P&L'!C20 -> -0.23105642 | D34: ='Bonchon U.S. P&L'!D30+'Bonchon International P&L'!D44-'Consolidations P&L'!D20 -> -0.18562071 | E34: ='Bonchon U.S. P&L'!E30+'Bonchon International P&L'!E44-'Consolidations P&L'!E20 -> -0.16436635 | F34: ='Bonchon U.S. P&L'!F30+'Bonchon International P&L'!F44-'Consolidations P&L'!F20 -> -0.16295527 | G34: ='Bonchon U.S. P&L'!G30+'Bonchon International P&L'!G44-'Consolidations P&L'!G20 -> -0.14490381 | H34: ='Bonchon U.S. P&L'!H30+'Bonchon International P&L'!H44-'Consolidations P&L'!H20 -> -0.14684124 | I34: ='Bonchon U.S. P&L'!I30+'Bonchon International P&L'!I44-'Consolidations P&L'!I20 -> -0.14684124 | J34: ='Bonchon U.S. P&L'!J30+'Bonchon International P&L'!J44-'Consolidations P&L'!J20 -> -0.14893897 | ... L34: ='Bonchon U.S. P&L'!L30+'Bonchon International P&L'!L44-'Consolidations P&L'!L20 -> -0.14893897 | N34: =IFERROR(_xlfn.RRI(4,C34,G34),"-") -> -0.11010158 | O34: =IFERROR(_xlfn.RRI(5,G34,L34),"-") -> 0.0055084163
B35: Other | C35: =SUM(C33:C34) -> -0.23650643 | D35: =SUM(D33:D34) -> -0.22593345 | E35: =SUM(E33:E34) -> 0.1416963 | F35: =SUM(F33:F34) -> -0.025155423 | G35: =SUM(G33:G34) -> -0.12467372 | H35: =SUM(H33:H34) -> -0.13227506 | I35: =SUM(I33:I34) -> -0.11826209 | J35: =SUM(J33:J34) -> -0.1153509 | ... L35: =SUM(L33:L34) -> -0.10356689 | N35: =IFERROR(_xlfn.RRI(4,C35,G35),"-") -> -0.14791486 | O35: =IFERROR(_xlfn.RRI(5,G35,L35),"-") -> -0.036416828
B36: Total Cost of Goods Sold | C36: =SUM(C31:C32,C35) -> 1.2067122 | D36: =SUM(D31:D32,D35) -> 2.5824061 | E36: =SUM(E31:E32,E35) -> 3.1420585 | F36: =SUM(F31:F32,F35) -> 2.8671791 | G36: =SUM(G31:G32,G35) -> 2.262205 | H36: =SUM(H31:H32,H35) -> 2.4620301 | I36: =SUM(I31:I32,I35) -> 3.1570901 | J36: =SUM(J31:J32,J35) -> 3.5456321 | ... L36: =SUM(L31:L32,L35) -> 4.5556263 | N36: =IFERROR(_xlfn.RRI(4,C36,G36),"-") -> 0.17012448 | O36: =IFERROR(_xlfn.RRI(5,G36,L36),"-") -> 0.15027909
B37: Gross Profit | C37: =C28-C36 -> 19.725981 | D37: =D28-D36 -> 25.024582 | E37: =E28-E36 -> 27.238518 | F37: =F28-F36 -> 27.579201 | G37: =G28-G36 -> 27.398937 | H37: =H28-H36 -> 31.929596 | I37: =I28-I36 -> 41.127396 | J37: =J28-J36 -> 53.974906 | ... L37: =L28-L36 -> 80.322213 | N37: =IFERROR(_xlfn.RRI(4,C37,G37),"-") -> 0.085609844 | O37: =IFERROR(_xlfn.RRI(5,G37,L37),"-") -> 0.23999631
B38: % Margin | C38: =IFERROR(C37/C28,"-") -> 0.94235275 | D38: =IFERROR(D37/D28,"-") -> 0.90645825 | E38: =IFERROR(E37/E28,"-") -> 0.89657673 | F38: =IFERROR(F37/F28,"-") -> 0.90582857 | G38: =IFERROR(G37/G28,"-") -> 0.92373169 | H38: =IFERROR(H37/H28,"-") -> 0.92841193 | I38: =IFERROR(I37/I28,"-") -> 0.92870889 | J38: =IFERROR(J37/J28,"-") -> 0.93835885 | ... L38: =IFERROR(L37/L28,"-") -> 0.94632726
B40: Corporate Labor | C40: ='Bonchon U.S. P&L'!C36+'Bonchon International P&L'!C50-'Consolidations P&L'!C26 -> 5.4884768 | D40: ='Bonchon U.S. P&L'!D36+'Bonchon International P&L'!D50-'Consolidations P&L'!D26 -> 6.3232292 | E40: ='Bonchon U.S. P&L'!E36+'Bonchon International P&L'!E50-'Consolidations P&L'!E26 -> 6.2162056 | F40: ='Bonchon U.S. P&L'!F36+'Bonchon International P&L'!F50-'Consolidations P&L'!F26 -> 6.7169363 | G40: ='Bonchon U.S. P&L'!G36+'Bonchon International P&L'!G50-'Consolidations P&L'!G26 -> 6.9007152 | H40: ='Bonchon U.S. P&L'!H36+'Bonchon International P&L'!H50-'Consolidations P&L'!H26 -> 7.3788678 | I40: ='Bonchon U.S. P&L'!I36+'Bonchon International P&L'!I50-'Consolidations P&L'!I26 -> 8.125476 | J40: ='Bonchon U.S. P&L'!J36+'Bonchon International P&L'!J50-'Consolidations P&L'!J26 -> 9.3177628 | ... L40: ='Bonchon U.S. P&L'!L36+'Bonchon International P&L'!L50-'Consolidations P&L'!L26 -> 11.857117 | N40: =IFERROR(_xlfn.RRI(4,C40,G40),"-") -> 0.058913704 | O40: =IFERROR(_xlfn.RRI(5,G40,L40),"-") -> 0.11433816
B41: Company-Owned Store Labor | C41: ='Bonchon U.S. P&L'!C37+'Bonchon International P&L'!C51-'Consolidations P&L'!C27 -> 0.81641997 | D41: ='Bonchon U.S. P&L'!D37+'Bonchon International P&L'!D51-'Consolidations P&L'!D27 -> 1.8055031 | E41: ='Bonchon U.S. P&L'!E37+'Bonchon International P&L'!E51-'Consolidations P&L'!E27 -> 1.5318652 | F41: ='Bonchon U.S. P&L'!F37+'Bonchon International P&L'!F51-'Consolidations P&L'!F27 -> 1.5250931 | G41: ='Bonchon U.S. P&L'!G37+'Bonchon International P&L'!G51-'Consolidations P&L'!G27 -> 1.2511717 | H41: ='Bonchon U.S. P&L'!H37+'Bonchon International P&L'!H51-'Consolidations P&L'!H27 -> 1.3382442 | I41: ='Bonchon U.S. P&L'!I37+'Bonchon International P&L'!I51-'Consolidations P&L'!I27 -> 1.864387 | J41: ='Bonchon U.S. P&L'!J37+'Bonchon International P&L'!J51-'Consolidations P&L'!J27 -> 2.0379038 | ... L41: ='Bonchon U.S. P&L'!L37+'Bonchon International P&L'!L51-'Consolidations P&L'!L27 -> 2.4345925 | N41: =IFERROR(_xlfn.RRI(4,C41,G41),"-") -> 0.11263014 | O41: =IFERROR(_xlfn.RRI(5,G41,L41),"-") -> 0.14240968
B42: Total Labor | C42: =SUM(C40:C41) -> 6.3048967 | D42: =SUM(D40:D41) -> 8.1287322 | E42: =SUM(E40:E41) -> 7.7480708 | F42: =SUM(F40:F41) -> 8.2420294 | G42: =SUM(G40:G41) -> 8.1518869 | H42: =SUM(H40:H41) -> 8.717112 | I42: =SUM(I40:I41) -> 9.989863 | J42: =SUM(J40:J41) -> 11.355667 | ... L42: =SUM(L40:L41) -> 14.29171 | N42: =IFERROR(_xlfn.RRI(4,C42,G42),"-") -> 0.066338382 | O42: =IFERROR(_xlfn.RRI(5,G42,L42),"-") -> 0.11883285
B43: Marketing Fund | C43: ='Bonchon U.S. P&L'!C39+'Bonchon International P&L'!C53-'Consolidations P&L'!C29 -> 1.7094527 | D43: ='Bonchon U.S. P&L'!D39+'Bonchon International P&L'!D53-'Consolidations P&L'!D29 -> 2.1685849 | E43: ='Bonchon U.S. P&L'!E39+'Bonchon International P&L'!E53-'Consolidations P&L'!E29 -> 2.8156541 | F43: ='Bonchon U.S. P&L'!F39+'Bonchon International P&L'!F53-'Consolidations P&L'!F29 -> 3.2534763 | G43: ='Bonchon U.S. P&L'!G39+'Bonchon International P&L'!G53-'Consolidations P&L'!G29 -> 3.2282713 | H43: ='Bonchon U.S. P&L'!H39+'Bonchon International P&L'!H53-'Consolidations P&L'!H29 -> 4.9917485 | I43: ='Bonchon U.S. P&L'!I39+'Bonchon International P&L'!I53-'Consolidations P&L'!I29 -> 8.5167043 | J43: ='Bonchon U.S. P&L'!J39+'Bonchon International P&L'!J53-'Consolidations P&L'!J29 -> 13.829933 | ... L43: ='Bonchon U.S. P&L'!L39+'Bonchon International P&L'!L53-'Consolidations P&L'!L29 -> 21.009066 | N43: =IFERROR(_xlfn.RRI(4,C43,G43),"-") -> 0.17227159 | O43: =IFERROR(_xlfn.RRI(5,G43,L43),"-") -> 0.45441164
B44: Service Fees | C44: ='Bonchon U.S. P&L'!C40+'Bonchon International P&L'!C54-'Consolidations P&L'!C30 -> 1.5810293 | D44: ='Bonchon U.S. P&L'!D40+'Bonchon International P&L'!D54-'Consolidations P&L'!D30 -> 1.9173266 | E44: ='Bonchon U.S. P&L'!E40+'Bonchon International P&L'!E54-'Consolidations P&L'!E30 -> 2.0300026 | F44: ='Bonchon U.S. P&L'!F40+'Bonchon International P&L'!F54-'Consolidations P&L'!F30 -> 1.8569612 | G44: ='Bonchon U.S. P&L'!G40+'Bonchon International P&L'!G54-'Consolidations P&L'!G30 -> 2.1299289 | H44: ='Bonchon U.S. P&L'!H40+'Bonchon International P&L'!H54-'Consolidations P&L'!H30 -> 2.1977609 | I44: ='Bonchon U.S. P&L'!I40+'Bonchon International P&L'!I54-'Consolidations P&L'!I30 -> 2.4372438 | J44: ='Bonchon U.S. P&L'!J40+'Bonchon International P&L'!J54-'Consolidations P&L'!J30 -> 2.6562904 | ... L44: ='Bonchon U.S. P&L'!L40+'Bonchon International P&L'!L54-'Consolidations P&L'!L30 -> 3.0661305 | N44: =IFERROR(_xlfn.RRI(4,C44,G44),"-") -> 0.077348703 | O44: =IFERROR(_xlfn.RRI(5,G44,L44),"-") -> 0.075585918
B45: Travel & Entertainment | C45: ='Bonchon U.S. P&L'!C41+'Bonchon International P&L'!C55-'Consolidations P&L'!C31 -> 0.37251615 | D45: ='Bonchon U.S. P&L'!D41+'Bonchon International P&L'!D55-'Consolidations P&L'!D31 -> 0.62507617 | E45: ='Bonchon U.S. P&L'!E41+'Bonchon International P&L'!E55-'Consolidations P&L'!E31 -> 0.99585521 | F45: ='Bonchon U.S. P&L'!F41+'Bonchon International P&L'!F55-'Consolidations P&L'!F31 -> 1.0170407 | G45: ='Bonchon U.S. P&L'!G41+'Bonchon International P&L'!G55-'Consolidations P&L'!G31 -> 0.81764289 | H45: ='Bonchon U.S. P&L'!H41+'Bonchon International P&L'!H55-'Consolidations P&L'!H31 -> 1.2534341 | I45: ='Bonchon U.S. P&L'!I41+'Bonchon International P&L'!I55-'Consolidations P&L'!I31 -> 1.3425663 | J45: ='Bonchon U.S. P&L'!J41+'Bonchon International P&L'!J55-'Consolidations P&L'!J31 -> 1.6950299 | ... L45: ='Bonchon U.S. P&L'!L41+'Bonchon International P&L'!L55-'Consolidations P&L'!L31 -> 2.5246005 | N45: =IFERROR(_xlfn.RRI(4,C45,G45),"-") -> 0.21717953 | O45: =IFERROR(_xlfn.RRI(5,G45,L45),"-") -> 0.25292709
B46: Rent | C46: ='Bonchon U.S. P&L'!C42+'Bonchon International P&L'!C56-'Consolidations P&L'!C32 -> 0.50192166 | D46: ='Bonchon U.S. P&L'!D42+'Bonchon International P&L'!D56-'Consolidations P&L'!D32 -> 0.66905733 | E46: ='Bonchon U.S. P&L'!E42+'Bonchon International P&L'!E56-'Consolidations P&L'!E32 -> 0.77520518 | F46: ='Bonchon U.S. P&L'!F42+'Bonchon International P&L'!F56-'Consolidations P&L'!F32 -> 0.73765761 | G46: ='Bonchon U.S. P&L'!G42+'Bonchon International P&L'!G56-'Consolidations P&L'!G32 -> 0.74150514 | H46: ='Bonchon U.S. P&L'!H42+'Bonchon International P&L'!H56-'Consolidations P&L'!H32 -> 0.79208247 | I46: ='Bonchon U.S. P&L'!I42+'Bonchon International P&L'!I56-'Consolidations P&L'!I32 -> 0.90336045 | J46: ='Bonchon U.S. P&L'!J42+'Bonchon International P&L'!J56-'Consolidations P&L'!J32 -> 0.94500754 | ... L46: ='Bonchon U.S. P&L'!L42+'Bonchon International P&L'!L56-'Consolidations P&L'!L32 -> 1.0228392 | N46: =IFERROR(_xlfn.RRI(4,C46,G46),"-") -> 0.10247705 | O46: =IFERROR(_xlfn.RRI(5,G46,L46),"-") -> 0.066445437
B47: Freight | C47: ='Bonchon U.S. P&L'!C43+'Bonchon International P&L'!C57-'Consolidations P&L'!C33 -> 0.69323992 | D47: ='Bonchon U.S. P&L'!D43+'Bonchon International P&L'!D57-'Consolidations P&L'!D33 -> 0.98323817 | E47: ='Bonchon U.S. P&L'!E43+'Bonchon International P&L'!E57-'Consolidations P&L'!E33 -> 0.75590531 | F47: ='Bonchon U.S. P&L'!F43+'Bonchon International P&L'!F57-'Consolidations P&L'!F33 -> 0.56354548 | G47: ='Bonchon U.S. P&L'!G43+'Bonchon International P&L'!G57-'Consolidations P&L'!G33 -> 0.43534247 | H47: ='Bonchon U.S. P&L'!H43+'Bonchon International P&L'!H57-'Consolidations P&L'!H33 -> 0.503025 | I47: ='Bonchon U.S. P&L'!I43+'Bonchon International P&L'!I57-'Consolidations P&L'!I33 -> 0.64097381 | J47: ='Bonchon U.S. P&L'!J43+'Bonchon International P&L'!J57-'Consolidations P&L'!J33 -> 0.69770306 | ... L47: ='Bonchon U.S. P&L'!L43+'Bonchon International P&L'!L57-'Consolidations P&L'!L33 -> 0.82806665 | N47: =IFERROR(_xlfn.RRI(4,C47,G47),"-") -> -0.10980148 | O47: =IFERROR(_xlfn.RRI(5,G47,L47),"-") -> 0.13722619
B48: Advertising Expense | C48: ='Bonchon U.S. P&L'!C44+'Bonchon International P&L'!C58-'Consolidations P&L'!C34 -> 0.15082599 | D48: ='Bonchon U.S. P&L'!D44+'Bonchon International P&L'!D58-'Consolidations P&L'!D34 -> 0.45786222 | E48: ='Bonchon U.S. P&L'!E44+'Bonchon International P&L'!E58-'Consolidations P&L'!E34 -> 0.45619212 | F48: ='Bonchon U.S. P&L'!F44+'Bonchon International P&L'!F58-'Consolidations P&L'!F34 -> 0.50157127 | G48: ='Bonchon U.S. P&L'!G44+'Bonchon International P&L'!G58-'Consolidations P&L'!G34 -> 0.47832907 | H48: ='Bonchon U.S. P&L'!H44+'Bonchon International P&L'!H58-'Consolidations P&L'!H34 -> 0.5741027 | I48: ='Bonchon U.S. P&L'!I44+'Bonchon International P&L'!I58-'Consolidations P&L'!I34 -> 0.85984071 | J48: ='Bonchon U.S. P&L'!J44+'Bonchon International P&L'!J58-'Consolidations P&L'!J34 -> 1.1375016 | ... L48: ='Bonchon U.S. P&L'!L44+'Bonchon International P&L'!L58-'Consolidations P&L'!L34 -> 1.5780826 | N48: =IFERROR(_xlfn.RRI(4,C48,G48),"-") -> 0.33448178 | O48: =IFERROR(_xlfn.RRI(5,G48,L48),"-") -> 0.26963999
B49: Other | C49: ='Bonchon U.S. P&L'!C45+'Bonchon International P&L'!C59-'Consolidations P&L'!C35 -> 0.87455154 | D49: ='Bonchon U.S. P&L'!D45+'Bonchon International P&L'!D59-'Consolidations P&L'!D35 -> 1.3543569 | E49: ='Bonchon U.S. P&L'!E45+'Bonchon International P&L'!E59-'Consolidations P&L'!E35 -> 1.4254529 | F49: ='Bonchon U.S. P&L'!F45+'Bonchon International P&L'!F59-'Consolidations P&L'!F35 -> 1.1782237 | G49: ='Bonchon U.S. P&L'!G45+'Bonchon International P&L'!G59-'Consolidations P&L'!G35 -> 1.2017549 | H49: ='Bonchon U.S. P&L'!H45+'Bonchon International P&L'!H59-'Consolidations P&L'!H35 -> 1.2809054 | I49: ='Bonchon U.S. P&L'!I45+'Bonchon International P&L'!I59-'Consolidations P&L'!I35 -> 1.4730734 | J49: ='Bonchon U.S. P&L'!J45+'Bonchon International P&L'!J59-'Consolidations P&L'!J35 -> 1.7495956 | ... L49: ='Bonchon U.S. P&L'!L45+'Bonchon International P&L'!L59-'Consolidations P&L'!L35 -> 2.5496371 | N49: =IFERROR(_xlfn.RRI(4,C49,G49),"-") -> 0.082698722 | O49: =IFERROR(_xlfn.RRI(5,G49,L49),"-") -> 0.16233815
B50: SG&A | C50: =SUM(C42:C49) -> 12.188434 | D50: =SUM(D42:D49) -> 16.304235 | E50: =SUM(E42:E49) -> 17.002338 | F50: =SUM(F42:F49) -> 17.350506 | G50: =SUM(G42:G49) -> 17.184662 | H50: =SUM(H42:H49) -> 20.310171 | I50: =SUM(I42:I49) -> 26.163626 | J50: =SUM(J42:J49) -> 34.066727 | ... L50: =SUM(L42:L49) -> 46.870132 | N50: =IFERROR(_xlfn.RRI(4,C50,G50),"-") -> 0.089678215 | O50: =IFERROR(_xlfn.RRI(5,G50,L50),"-") -> 0.22222465
B51: % of Revenue | C51: =IFERROR(C50/C28,"-") -> 0.58226783 | D51: =IFERROR(D50/D28,"-") -> 0.59058361 | E51: =IFERROR(E50/E28,"-") -> 0.55964502 | F51: =IFERROR(F50/F28,"-") -> 0.56987089 | G51: =IFERROR(G50/G28,"-") -> 0.57936616 | H51: =IFERROR(H50/H28,"-") -> 0.59055571 | I51: =IFERROR(I50/I28,"-") -> 0.59080793 | J51: =IFERROR(J50/J28,"-") -> 0.59225327 | ... L51: =IFERROR(L50/L28,"-") -> 0.55220694
B53: Adj. EBITDA | C53: =C37-C50 -> 7.5375473 | D53: =D37-D50 -> 8.7203473 | E53: =E37-E50 -> 10.23618 | F53: =F37-F50 -> 10.228695 | G53: =G37-G50 -> 10.214275 | H53: =H37-H50 -> 11.619425 | I53: =I37-I50 -> 14.963771 | J53: =J37-J50 -> 19.908179 | ... L53: =L37-L50 -> 33.452081 | N53: =IFERROR(_xlfn.RRI(4,C53,G53),"-") -> 0.078932745 | O53: =IFERROR(_xlfn.RRI(5,G53,L53),"-") -> 0.26777773
B54: % Margin | C54: =IFERROR(C53/C28,"-") -> 0.36008492 | D54: =IFERROR(D53/D28,"-") -> 0.31587464 | E54: =IFERROR(E53/E28,"-") -> 0.33693172 | F54: =IFERROR(F53/F28,"-") -> 0.33595768 | G54: =IFERROR(G53/G28,"-") -> 0.34436554 | H54: =IFERROR(H53/H28,"-") -> 0.33785622 | I54: =IFERROR(I53/I28,"-") -> 0.33790096 | J54: =IFERROR(J53/J28,"-") -> 0.34610558 | ... L54: =IFERROR(L53/L28,"-") -> 0.39412031
B55: % Margin (Excl. Marketing Fund) | C55: =C53/(C28-C24) -> 0.39210596 | D55: =D53/(D28-D24) -> 0.34280247 | E55: =E53/(E28-E24) -> 0.37134804 | F55: =F53/(F28-F24) -> 0.37615311 | G55: =G53/(G28-G24) -> 0.38642323 | H55: =H53/(H28-H24) -> 0.39522018 | I55: =I53/(I28-I24) -> 0.41835892 | J55: =J53/(J28-J24) -> 0.45566269 | ... L55: =L53/(L28-L24) -> 0.52376269
B57: Pro Forma Adjustment | G57: =SUM('Bonchon U.S. P&L'!G53,'Bonchon International P&L'!G67) -> 1.2316708 | H57: =SUM('Bonchon U.S. P&L'!H53,'Bonchon International P&L'!H67) -> 2.4914083 | I57: =SUMIF('Bonchon U.S. P&L'!$B:$B,$B57,'Bonchon U.S. P&L'!I:I)+SUMIF('Bonchon International P&L'!$B:$B,$B57,'Bonchon International P&L'!I:I) -> 2.3145919 | J57: =SUMIF('Bonchon U.S. P&L'!$B:$B,$B57,'Bonchon U.S. P&L'!J:J)+SUMIF('Bonchon International P&L'!$B:$B,$B57,'Bonchon International P&L'!J:J) -> 2.5999471 | K57: =SUMIF('Bonchon U.S. P&L'!$B:$B,$B57,'Bonchon U.S. P&L'!K:K)+SUMIF('Bonchon International P&L'!$B:$B,$B57,'Bonchon International P&L'!K:K) -> 3.3960517 | L57: =SUMIF('Bonchon U.S. P&L'!$B:$B,$B57,'Bonchon U.S. P&L'!L:L)+SUMIF('Bonchon International P&L'!$B:$B,$B57,'Bonchon International P&L'!L:L) -> 4.1308463 | N57: =IFERROR(_xlfn.RRI(4,C57,G57),"-") -> - | O57: =IFERROR(_xlfn.RRI(5,G57,L57),"-") -> 0.27382238
B58: PF Adj. EBITDA | G58: =G53+G57 -> 11.445946 | H58: =H53+H57 -> 14.110833 | I58: =I53+I57 -> 17.278363 | J58: =J53+J57 -> 22.508126 | K58: =K53+K57 -> 29.930436 | L58: =L53+L57 -> 37.582927 | N58: =IFERROR(_xlfn.RRI(4,C58,G58),"-") -> - | O58: =IFERROR(_xlfn.RRI(5,G58,L58),"-") -> 0.26843373
B60: Memo: Adj. EBITDA (At Constant Currency) | C60: ='Bonchon U.S. P&L'!C49+'Bonchon International P&L'!C72+'Consolidations P&L'!C39 -> 6.7884611 | D60: ='Bonchon U.S. P&L'!D49+'Bonchon International P&L'!D72-'Consolidations P&L'!D39 -> 8.1921021 | E60: ='Bonchon U.S. P&L'!E49+'Bonchon International P&L'!E72-'Consolidations P&L'!E39 -> 9.7884683 | F60: ='Bonchon U.S. P&L'!F49+'Bonchon International P&L'!F72-'Consolidations P&L'!F39 -> 9.9536681 | G60: ='Bonchon U.S. P&L'!G49+'Bonchon International P&L'!G72-'Consolidations P&L'!G39 -> 10.214275 | H60: ='Bonchon U.S. P&L'!H49+'Bonchon International P&L'!H72-'Consolidations P&L'!H39 -> 11.625237 | I60: ='Bonchon U.S. P&L'!I49+'Bonchon International P&L'!I72-'Consolidations P&L'!I39 -> 15.031305 | J60: ='Bonchon U.S. P&L'!J49+'Bonchon International P&L'!J72-'Consolidations P&L'!J39 -> 19.985155 | K60: ='Bonchon U.S. P&L'!K49+'Bonchon International P&L'!K72-'Consolidations P&L'!K39 -> 26.623421 | L60: ='Bonchon U.S. P&L'!L49+'Bonchon International P&L'!L72-'Consolidations P&L'!L39 -> 33.552774 | N60: =IFERROR(_xlfn.RRI(4,C60,G60),"-") -> 0.10753906 | O60: =IFERROR(_xlfn.RRI(5,G60,L60),"-") -> 0.26854003
B62: Notes:
B63: U.S. Same store sales represents franchised locations only. All same store sales metrics exclude ultimately closed locations and geographies.
B64: Other Revenue and COGS includes franchisee training fees and other items sold to franchisees through legacy supply chain (i.e., kitchen supplies, packaging, etc.).
B65: Other SG&A includes utilities, insurance, research & development, taxes & dues, and other repair and maintenance expenses.
B66: Constant currency assumes 2025 KRW/USD exchange rate.

Sheet Bonchon U.S. P&L
B2: Bonchon U.S. P&L
C4: Historical | H4: Projected | N4: CAGR
B5: ($ in millions) | C5: 2021 | D5: 2022 | E5: 2023 | F5: 2024 | G5: 2025A | H5: 2026E | I5: 2027P | J5: 2028P | K5: 2029P | L5: 2030P | N5: '21A-'25E | O5: '25E-'30P
B7: Franchise Restaurants | C7: ='U.S. Restaurant Count Detail'!C13 -> 111 | D7: ='U.S. Restaurant Count Detail'!D13 -> 117 | E7: ='U.S. Restaurant Count Detail'!E13 -> 127 | F7: ='U.S. Restaurant Count Detail'!F13 -> 143 | G7: ='U.S. Restaurant Count Detail'!G13 -> 148 | H7: ='U.S. Restaurant Count Detail'!H13 -> 175 | I7: ='U.S. Restaurant Count Detail'!I13 -> 205 | J7: ='U.S. Restaurant Count Detail'!J13 -> 240 | ... L7: ='U.S. Restaurant Count Detail'!L13 -> 340 | N7: =IFERROR(_xlfn.RRI(4,C7,G7),"-") -> 0.074569932 | O7: =IFERROR(_xlfn.RRI(5,G7,L7),"-") -> 0.18098244
B8: Company-Owned Restaurants | C8: ='U.S. Restaurant Count Detail'!C19 -> 4 | D8: ='U.S. Restaurant Count Detail'!D19 -> 5 | E8: ='U.S. Restaurant Count Detail'!E19 -> 4 | F8: ='U.S. Restaurant Count Detail'!F19 -> 4 | G8: ='U.S. Restaurant Count Detail'!G19 -> 3 | H8: ='U.S. Restaurant Count Detail'!H19 -> 4 | I8: ='U.S. Restaurant Count Detail'!I19 -> 4 | J8: ='U.S. Restaurant Count Detail'!J19 -> 4 | ... L8: ='U.S. Restaurant Count Detail'!L19 -> 4 | N8: =IFERROR(_xlfn.RRI(4,C8,G8),"-") -> -0.069395141 | O8: =IFERROR(_xlfn.RRI(5,G8,L8),"-") -> 0.059223841
B9: Total Restaurants | C9: =SUM(C7:C8) -> 115 | D9: =SUM(D7:D8) -> 122 | E9: =SUM(E7:E8) -> 131 | F9: =SUM(F7:F8) -> 147 | G9: =SUM(G7:G8) -> 151 | H9: =SUM(H7:H8) -> 179 | I9: =SUM(I7:I8) -> 209 | J9: =SUM(J7:J8) -> 244 | ... L9: =SUM(L7:L8) -> 344 | N9: =IFERROR(_xlfn.RRI(4,C9,G9),"-") -> 0.070458356 | O9: =IFERROR(_xlfn.RRI(5,G9,L9),"-") -> 0.17900677
B10: % Growth | D10: =IFERROR(D9/C9-1,0) -> 0.060869565 | E10: =IFERROR(E9/D9-1,0) -> 0.073770492 | F10: =IFERROR(F9/E9-1,0) -> 0.1221374 | G10: =IFERROR(G9/F9-1,0) -> 0.027210884 | H10: =IFERROR(H9/G9-1,0) -> 0.18543046 | I10: =IFERROR(I9/H9-1,0) -> 0.16759777 | J10: =IFERROR(J9/I9-1,0) -> 0.16746411 | K10: =IFERROR(K9/J9-1,0) -> 0.18442623 | L10: =IFERROR(L9/K9-1,0) -> 0.19031142
B12: Systemwide Sales | C12: ='U.S. Restaurant Count Detail'!C31 -> 173.415 | D12: ='U.S. Restaurant Count Detail'!D31 -> 193.64356 | E12: ='U.S. Restaurant Count Detail'!E31 -> 200.67402 | F12: ='U.S. Restaurant Count Detail'!F31 -> 202.35598 | G12: 211.07983 | H12: ='U.S. Restaurant Count Detail'!H31 -> 236.36305 | I12: ='U.S. Restaurant Count Detail'!I31 -> 290.17861 | J12: ='U.S. Restaurant Count Detail'!J31 -> 352.66562 | K12: ='U.S. Restaurant Count Detail'!K31 -> 431.83056 | L12: ='U.S. Restaurant Count Detail'!L31 -> 533.59659 | N12: =IFERROR(_xlfn.RRI(4,C12,G12),"-") -> 0.050364462 | O12: =IFERROR(_xlfn.RRI(5,G12,L12),"-") -> 0.20379702
B13: % Growth | D13: =IFERROR(D12/C12-1,0) -> 0.1166483 | E13: =IFERROR(E12/D12-1,0) -> 0.036306147 | F13: =IFERROR(F12/E12-1,0) -> 0.0083815659 | G13: =IFERROR(G12/F12-1,0) -> 0.043111413 | H13: =IFERROR(H12/G12-1,0) -> 0.11978035 | I13: =IFERROR(I12/H12-1,0) -> 0.22768178 | J13: =IFERROR(J12/I12-1,0) -> 0.21533984 | K13: =IFERROR(K12/J12-1,0) -> 0.22447593 | L13: =IFERROR(L12/K12-1,0) -> 0.23566194
B15: U.S. Same Store Sales | C15: 0.16753805 | D15: 0.049974743 | E15: -0.033246735 | F15: -0.079297458 | G15: 8.3373689e-05 | H15: ='U.S. Franchise Sales & Dev'!D14 -> 0.05043868 | I15: ='U.S. Franchise Sales & Dev'!E14 -> 0.04 | J15: ='U.S. Franchise Sales & Dev'!F14 -> 0.04 | K15: ='U.S. Franchise Sales & Dev'!G14 -> 0.04 | L15: ='U.S. Franchise Sales & Dev'!H14 -> 0.04
B17: Franchise Revenue | C17: 8.4856376 | D17: 9.2181573 | E17: 9.8702525 | F17: 9.8424246 | G17: =SUM('Bonchon U.S. P&L (Monthly''25)'!C7:N7) -> 10.201735 | H17: =SUM('Bonchon U.S. P&L (Monthly''26)'!C7:N7) -> 11.624896 | I17: ='U.S. Franchise Sales & Dev'!E36 -> 13.864917 | J17: ='U.S. Franchise Sales & Dev'!F36 -> 18.229997 | K17: ='U.S. Franchise Sales & Dev'!G36 -> 22.455913 | L17: ='U.S. Franchise Sales & Dev'!H36 -> 27.847593 | N17: =IFERROR(_xlfn.RRI(4,C17,G17),"-") -> 0.047122246 | O17: =IFERROR(_xlfn.RRI(5,G17,L17),"-") -> 0.22242642
B18: Sauce Revenue | C18: 1.5092535 | D18: 1.7763786 | E18: 3.0626712 | F18: 2.7871825 | G18: =SUM('Bonchon U.S. P&L (Monthly''25)'!C8:N8) -> 2.351576 | H18: =SUM('Bonchon U.S. P&L (Monthly''26)'!C8:N8) -> 2.6228589 | I18: ='Sauce Economics Overview'!I33 -> 2.8194106 | J18: ='Sauce Economics Overview'!J33 -> 3.500338 | K18: ='Sauce Economics Overview'!K33 -> 5.2782141 | L18: ='Sauce Economics Overview'!L33 -> 6.6315479 | N18: =IFERROR(_xlfn.RRI(4,C18,G18),"-") -> 0.11724703 | O18: =IFERROR(_xlfn.RRI(5,G18,L18),"-") -> 0.23041376
B19: Company-Owned Store Revenue | C19: 1.7976949 | D19: 5.1372586 | E19: 5.0760827 | F19: 4.1612575 | G19: =SUM('Bonchon U.S. P&L (Monthly''25)'!C9:N9) -> 3.7884491 | H19: =SUM('Bonchon U.S. P&L (Monthly''26)'!C9:N9) -> 4.3374481 | I19: ='Company-Owned Store Detail'!E21+'Company-Owned Store Detail'!E22 -> 6.2884611 | J19: ='Company-Owned Store Detail'!F21+'Company-Owned Store Detail'!F22 -> 6.9173072 | K19: ='Company-Owned Store Detail'!G21+'Company-Owned Store Detail'!G22 -> 7.6090379 | L19: ='Company-Owned Store Detail'!H21+'Company-Owned Store Detail'!H22 -> 8.3699417 | N19: =IFERROR(_xlfn.RRI(4,C19,G19),"-") -> 0.20485939 | O19: =IFERROR(_xlfn.RRI(5,G19,L19),"-") -> 0.17179649
B20: Marketing Fund | C20: 1.7094527 | D20: 2.1685849 | E20: 2.8156541 | F20: 3.2534763 | G20: =SUM('Bonchon U.S. P&L (Monthly''25)'!C10:N10) -> 3.2282713 | H20: =SUM('Bonchon U.S. P&L (Monthly''26)'!C10:N10) -> 4.9917485 | I20: ='U.S. Franchise Sales & Dev'!E44 -> 8.5167043 | J20: ='U.S. Franchise Sales & Dev'!F44 -> 13.829933 | K20: ='U.S. Franchise Sales & Dev'!G44 -> 16.968861 | L20: ='U.S. Franchise Sales & Dev'!H44 -> 21.009066 | N20: =IFERROR(_xlfn.RRI(4,C20,G20),"-") -> 0.17227159 | O20: =IFERROR(_xlfn.RRI(5,G20,L20),"-") -> 0.45441164
B21: Other Product Revenue | C21: -0.08183353 | D21: -0.10277591 | E21: 0.34332006 | F21: 0.12552208 | G21: =SUM('Bonchon U.S. P&L (Monthly''25)'!C11:N11) -> -0.01468906 | H21: =SUM('Bonchon U.S. P&L (Monthly''26)'!C11:N11) -> 0.00954 | I21: ='Sauce Economics Overview'!I41 -> 0.011789964 | J21: ='Sauce Economics Overview'!J41 -> 0.01407253 | K21: ='Sauce Economics Overview'!K41 -> 0.016952911 | L21: ='Sauce Economics Overview'!L41 -> 0.020631851 | N21: =IFERROR(_xlfn.RRI(4,C21,G21),"-") -> -0.34909789 | O21: =IFERROR(_xlfn.RRI(5,G21,L21),"-") -> -
B22: Other Revenue | C22: 0.30773293 | D22: 0.12628718 | E22: 0.27595889 | F22: 0.1570314 | G22: =SUM('Bonchon U.S. P&L (Monthly''25)'!C12:N12) -> 0.17322978 | H22: =SUM('Bonchon U.S. P&L (Monthly''26)'!C12:N12) -> 0.20392759 | I22: ='U.S. Franchise Sales & Dev'!E40 -> 0.2275 | J22: ='U.S. Franchise Sales & Dev'!F40 -> 0.26 | K22: ='U.S. Franchise Sales & Dev'!G40 -> 0.325 | L22: ='U.S. Franchise Sales & Dev'!H40 -> 0.39 | N22: =IFERROR(_xlfn.RRI(4,C22,G22),"-") -> -0.13381203 | O22: =IFERROR(_xlfn.RRI(5,G22,L22),"-") -> 0.1762196
B23: Other | C23: =SUM(C21:C22) -> 0.2258994 | D23: =SUM(D21:D22) -> 0.02351127 | E23: =SUM(E21:E22) -> 0.61927895 | F23: =SUM(F21:F22) -> 0.28255348 | G23: =SUM(G21:G22) -> 0.15854072 | H23: =SUM(H21:H22) -> 0.21346759 | I23: =SUM(I21:I22) -> 0.23928996 | J23: =SUM(J21:J22) -> 0.27407253 | ... L23: =SUM(L21:L22) -> 0.41063185 | N23: =IFERROR(_xlfn.RRI(4,C23,G23),"-") -> -0.084714806 | O23: =IFERROR(_xlfn.RRI(5,G23,L23),"-") -> 0.20965733
B24: Total Revenue | C24: =SUM(C17:C20,C23) -> 13.727938 | D24: =SUM(D17:D20,D23) -> 18.323891 | E24: =SUM(E17:E20,E23) -> 21.443939 | F24: =SUM(F17:F20,F23) -> 20.326894 | G24: =SUM(G17:G20,G23) -> 19.728572 | H24: =SUM(H17:H20,H23) -> 23.790419 | I24: =SUM(I17:I20,I23) -> 31.728783 | J24: =SUM(J17:J20,J23) -> 42.751647 | ... L24: =SUM(L17:L20,L23) -> 64.268781 | N24: =IFERROR(_xlfn.RRI(4,C24,G24),"-") -> 0.094895282 | O24: =IFERROR(_xlfn.RRI(5,G24,L24),"-") -> 0.2664291
B25: % Growth | D25: =IFERROR(D24/C24-1,0) -> 0.33478826 | E25: =IFERROR(E24/D24-1,0) -> 0.17027218 | F25: =IFERROR(F24/E24-1,0) -> -0.052091411 | G25: =IFERROR(G24/F24-1,0) -> -0.029435015 | H25: =IFERROR(H24/G24-1,0) -> 0.20588652 | I25: =IFERROR(I24/H24-1,0) -> 0.33367903 | J25: =IFERROR(J24/I24-1,0) -> 0.34740897 | K25: =IFERROR(K24/J24-1,0) -> 0.23162457 | L25: =IFERROR(L24/K24-1,0) -> 0.22058736
B27: Sauce COGS | C27: ='Sauce Economics Overview'!C34 -> 0.0009373 | D27: ='Sauce Economics Overview'!D34 -> 0.03314327 | E27: ='Sauce Economics Overview'!E34 -> 0.22863007 | F27: ='Sauce Economics Overview'!F34 -> 0.12063587 | G27: =SUM('Bonchon U.S. P&L (Monthly''25)'!C16:N16) -> 0.01355097 | H27: =SUM('Bonchon U.S. P&L (Monthly''26)'!C16:N16) -> 0 | I27: ='Sauce Economics Overview'!I34 -> 0 | J27: ='Sauce Economics Overview'!J34 -> 0 | K27: ='Sauce Economics Overview'!K34 -> 0 | L27: ='Sauce Economics Overview'!L34 -> 0 | N27: =IFERROR(_xlfn.RRI(4,C27,G27),"-") -> 0.9499476 | O27: =IFERROR(_xlfn.RRI(5,G27,L27),"-") -> -1
B28: Company-Owned Store COGS | C28: 0.57564599 | D28: 1.5265284 | E28: 1.4018693 | F28: 1.4141352 | G28: =SUM('Bonchon U.S. P&L (Monthly''25)'!C17:N17) -> 1.0689561 | H28: =SUM('Bonchon U.S. P&L (Monthly''26)'!C17:N17) -> 1.2437544 | I28: ='Company-Owned Store Detail'!E36+'Company-Owned Store Detail'!E68 -> 1.7413943 | J28: ='Company-Owned Store Detail'!F36+'Company-Owned Store Detail'!F68 -> 1.8960876 | K28: ='Company-Owned Store Detail'!G36+'Company-Owned Store Detail'!G68 -> 2.0805078 | L28: ='Company-Owned Store Detail'!H36+'Company-Owned Store Detail'!H68 -> 2.2650287 | N28: =IFERROR(_xlfn.RRI(4,C28,G28),"-") -> 0.16735002 | O28: =IFERROR(_xlfn.RRI(5,G28,L28),"-") -> 0.16204453
B29: Other Product COGS | C29: 0.0324647 | D29: 0.02571077 | E29: 0.30932278 | F29: 0.12200699 | G29: =SUM('Bonchon U.S. P&L (Monthly''25)'!C18:N18) -> 0.01238843 | H29: =SUM('Bonchon U.S. P&L (Monthly''26)'!C18:N18) -> 0.0057487721 | I29: ='Sauce Economics Overview'!I42 -> 0.0071045931 | J29: ='Sauce Economics Overview'!J42 -> 0.0084800596 | K29: ='Sauce Economics Overview'!K42 -> 0.010215767 | L29: ='Sauce Economics Overview'!L42 -> 0.012432684 | N29: =IFERROR(_xlfn.RRI(4,C29,G29),"-") -> -0.2140386 | O29: =IFERROR(_xlfn.RRI(5,G29,L29),"-") -> 0.00071342788
B30: D&A In COGS | C30: 0 | D30: 0 | E30: 0 | F30: 0 | G30: =SUM('Bonchon U.S. P&L (Monthly''26)'!B19:M19) -> 0 | H30: =SUM('Bonchon U.S. P&L (Monthly''26)'!C19:N19) -> 0 | I30: 0 | J30: 0 | K30: 0 | L30: 0 | N30: =IFERROR(_xlfn.RRI(4,C30,G30),"-") -> 0 | O30: =IFERROR(_xlfn.RRI(5,G30,L30),"-") -> 0
B31: Other | C31: =SUM(C29:C30) -> 0.0324647 | D31: =SUM(D29:D30) -> 0.02571077 | E31: =SUM(E29:E30) -> 0.30932278 | F31: =SUM(F29:F30) -> 0.12200699 | G31: =SUM(G29:G30) -> 0.01238843 | H31: =SUM(H29:H30) -> 0.0057487721 | I31: =SUM(I29:I30) -> 0.0071045931 | J31: =SUM(J29:J30) -> 0.0084800596 | ... L31: =SUM(L29:L30) -> 0.012432684 | N31: =IFERROR(_xlfn.RRI(4,C31,G31),"-") -> -0.2140386 | O31: =IFERROR(_xlfn.RRI(5,G31,L31),"-") -> 0.00071342788
B32: Total Cost of Goods Sold | C32: =SUM(C27:C28,C31) -> 0.60904799 | D32: =SUM(D27:D28,D31) -> 1.5853825 | E32: =SUM(E27:E28,E31) -> 1.9398222 | F32: =SUM(F27:F28,F31) -> 1.6567781 | G32: =SUM(G27:G28,G31) -> 1.0948955 | H32: =SUM(H27:H28,H31) -> 1.2495032 | I32: =SUM(I27:I28,I31) -> 1.7484989 | J32: =SUM(J27:J28,J31) -> 1.9045676 | ... L32: =SUM(L27:L28,L31) -> 2.2774614 | N32: =IFERROR(_xlfn.RRI(4,C32,G32),"-") -> 0.15792462 | O32: =IFERROR(_xlfn.RRI(5,G32,L32),"-") -> 0.15775235
B33: Gross Profit | C33: =C24-C32 -> 13.11889 | D33: =D24-D32 -> 16.738508 | E33: =E24-E32 -> 19.504117 | F33: =F24-F32 -> 18.670116 | G33: =G24-G32 -> 18.633676 | H33: =H24-H32 -> 22.540916 | I33: =I24-I32 -> 29.980284 | J33: =J24-J32 -> 40.847079 | ... L33: =L24-L32 -> 61.99132 | N33: =IFERROR(_xlfn.RRI(4,C33,G33),"-") -> 0.091692594 | O33: =IFERROR(_xlfn.RRI(5,G33,L33),"-") -> 0.27176382
B34: % Margin | C34: =IFERROR(C33/C24,"-") -> 0.95563442 | D34: =IFERROR(D33/D24,"-") -> 0.91348003 | E34: =IFERROR(E33/E24,"-") -> 0.90953984 | F34: =IFERROR(F33/F24,"-") -> 0.9184933 | G34: =IFERROR(G33/G24,"-") -> 0.94450204 | H34: =IFERROR(H33/H24,"-") -> 0.94747872 | I34: =IFERROR(I33/I24,"-") -> 0.94489234 | J34: =IFERROR(J33/J24,"-") -> 0.95545043 | ... L34: =IFERROR(L33/L24,"-") -> 0.96456349
B36: Corporate Labor | C36: =(4.9932962429754)-0.81641997 -> 4.1768763 | D36: 5.139958 | E36: 5.3966265 | F36: 5.5795328 | G36: =SUM('Bonchon U.S. P&L (Monthly''25)'!C25:N25) -> 5.6734943 | H36: =SUM('Bonchon U.S. P&L (Monthly''26)'!C25:N25) -> 6.0878854 | I36: ='U.S. SG&A'!I17 -> 6.6813384 | J36: ='U.S. SG&A'!J17 -> 7.7123117 | K36: ='U.S. SG&A'!K17 -> 8.7158088 | L36: ='U.S. SG&A'!L17 -> 9.9223485 | N36: =IFERROR(_xlfn.RRI(4,C38,G38),"-") -> 0.08518273 | O36: =IFERROR(_xlfn.RRI(5,G38,L38),"-") -> 0.12280006
B37: Company-Owned Store Labor | C37: 0.81641997 | D37: 1.8055031 | E37: 1.5318652 | F37: 1.5250931 | G37: =SUM('Bonchon U.S. P&L (Monthly''25)'!C26:N26) -> 1.2511717 | H37: =SUM('Bonchon U.S. P&L (Monthly''26)'!C26:N26) -> 1.3382442 | I37: ='Company-Owned Store Detail'!E40+'Company-Owned Store Detail'!E72 -> 1.864387 | J37: ='Company-Owned Store Detail'!F40+'Company-Owned Store Detail'!F72 -> 2.0379038 | K37: ='Company-Owned Store Detail'!G40+'Company-Owned Store Detail'!G72 -> 2.22748 | L37: ='Company-Owned Store Detail'!H40+'Company-Owned Store Detail'!H72 -> 2.4345925 | N37: =IFERROR(_xlfn.RRI(4,C39,G39),"-") -> 0.17227159 | O37: =IFERROR(_xlfn.RRI(5,G39,L39),"-") -> 0.45441164
B38: Total Labor | C38: =SUM(C36:C37) -> 4.9932962 | D38: =SUM(D36:D37) -> 6.9454611 | E38: =SUM(E36:E37) -> 6.9284917 | F38: =SUM(F36:F37) -> 7.1046259 | G38: =SUM(G36:G37) -> 6.924666 | H38: =SUM(H36:H37) -> 7.4261296 | I38: =SUM(I36:I37) -> 8.5457254 | J38: =SUM(J36:J37) -> 9.7502155 | ... L38: =SUM(L36:L37) -> 12.356941 | N38: =IFERROR(_xlfn.RRI(4,C40,G40),"-") -> 0.09422476 | O38: =IFERROR(_xlfn.RRI(5,G40,L40),"-") -> 0.079570638
B39: Marketing Fund | C39: =C20 -> 1.7094527 | D39: =D20 -> 2.1685849 | E39: =E20 -> 2.8156541 | F39: =F20 -> 3.2534763 | G39: =SUM('Bonchon U.S. P&L (Monthly''25)'!C28:N28) -> 3.2282713 | H39: =H20 -> 4.9917485 | I39: =I20 -> 8.5167043 | J39: =J20 -> 13.829933 | K39: =K20 -> 16.968861 | L39: =L20 -> 21.009066 | N39: =IFERROR(_xlfn.RRI(4,C39,G39),"-") -> 0.17227159 | O39: =IFERROR(_xlfn.RRI(5,G39,L39),"-") -> 0.45441164
B40: Service Fees | C40: 1.2327444 | D40: 1.6513941 | E40: 1.7693728 | F40: 1.6195792 | G40: =SUM('Bonchon U.S. P&L (Monthly''25)'!C29:N29) -> 1.7672548 | H40: =SUM('Bonchon U.S. P&L (Monthly''26)'!C29:N29) -> 1.8172835 | I40: ='U.S. SG&A'!I19+'Company-Owned Store Detail'!E42+'Company-Owned Store Detail'!E74 -> 2.0332062 | J40: ='U.S. SG&A'!J19+'Company-Owned Store Detail'!F42+'Company-Owned Store Detail'!F74 -> 2.2294639 | K40: ='U.S. SG&A'!K19+'Company-Owned Store Detail'!G42+'Company-Owned Store Detail'!G74 -> 2.4034682 | L40: ='U.S. SG&A'!L19+'Company-Owned Store Detail'!H42+'Company-Owned Store Detail'!H74 -> 2.5915196 | N40: =IFERROR(_xlfn.RRI(4,C40,G40),"-") -> 0.09422476 | O40: =IFERROR(_xlfn.RRI(5,G40,L40),"-") -> 0.079570638
B41: Travel & Entertainment | C41: 0.30548267 | D41: 0.44892336 | E41: 0.63691371 | F41: 0.69853945 | G41: =SUM('Bonchon U.S. P&L (Monthly''25)'!C30:N30) -> 0.6301413 | H41: =SUM('Bonchon U.S. P&L (Monthly''26)'!C30:N30) -> 0.98442005 | I41: ='U.S. SG&A'!I20+'Company-Owned Store Detail'!E48 -> 0.99505803 | J41: ='U.S. SG&A'!J20+'Company-Owned Store Detail'!F48 -> 1.2862873 | K41: ='U.S. SG&A'!K20+'Company-Owned Store Detail'!G48 -> 1.5770858 | L41: ='U.S. SG&A'!L20+'Company-Owned Store Detail'!H48 -> 1.9542553 | N41: =IFERROR(_xlfn.RRI(4,C41,G41),"-") -> 0.19843047 | O41: =IFERROR(_xlfn.RRI(5,G41,L41),"-") -> 0.25403215
B42: Rent | C42: 0.3899499 | D42: 0.5677604 | E42: 0.6716284 | F42: 0.61910609 | G42: =SUM('Bonchon U.S. P&L (Monthly''25)'!C31:N31) -> 0.62726085 | H42: =SUM('Bonchon U.S. P&L (Monthly''26)'!C31:N31) -> 0.67419975 | I42: ='U.S. SG&A'!I21+'Company-Owned Store Detail'!E44 -> 0.78091388 | J42: ='U.S. SG&A'!J21+'Company-Owned Store Detail'!F44 -> 0.81831287 | K42: ='U.S. SG&A'!K21+'Company-Owned Store Detail'!G44 -> 0.85133105 | L42: ='U.S. SG&A'!L21+'Company-Owned Store Detail'!H44 -> 0.88756633 | N42: =IFERROR(_xlfn.RRI(4,C42,G42),"-") -> 0.12618527 | O42: =IFERROR(_xlfn.RRI(5,G42,L42),"-") -> 0.071890761
B43: Freight | C43: 0.67884456 | D43: 0.96982432 | E43: 0.74838686 | F43: 0.54956246 | G43: =SUM('Bonchon U.S. P&L (Monthly''25)'!C32:N32) -> 0.426513 | H43: =SUM('Bonchon U.S. P&L (Monthly''26)'!C32:N32) -> 0.49288415 | I43: ='U.S. SG&A'!I22+'Company-Owned Store Detail'!E46+'Company-Owned Store Detail'!E78 -> 0.62787402 | J43: ='U.S. SG&A'!J22+'Company-Owned Store Detail'!F46+'Company-Owned Store Detail'!F78 -> 0.68229496 | K43: ='U.S. SG&A'!K22+'Company-Owned Store Detail'!G46+'Company-Owned Store Detail'!G78 -> 0.74131975 | L43: ='U.S. SG&A'!L22+'Company-Owned Store Detail'!H46+'Company-Owned Store Detail'!H78 -> 0.80656673 | N43: =IFERROR(_xlfn.RRI(4,C43,G43),"-") -> -0.10969158 | O43: =IFERROR(_xlfn.RRI(5,G43,L43),"-") -> 0.13590394
B44: Advertising Expense | C44: 0.14672548 | D44: 0.2688334 | E44: 0.38128166 | F44: 0.44761616 | G44: =SUM('Bonchon U.S. P&L (Monthly''25)'!C33:N33) -> 0.44908484 | H44: =SUM('Bonchon U.S. P&L (Monthly''26)'!C33:N33) -> 0.55720129 | I44: ='U.S. SG&A'!I23+'Company-Owned Store Detail'!E50+'Company-Owned Store Detail'!E82 -> 0.79637898 | J44: ='U.S. SG&A'!J23+'Company-Owned Store Detail'!F50+'Company-Owned Store Detail'!F82 -> 1.0629397 | K44: ='U.S. SG&A'!K23+'Company-Owned Store Detail'!G50+'Company-Owned Store Detail'!G82 -> 1.2536412 | L44: ='U.S. SG&A'!L23+'Company-Owned Store Detail'!H50+'Company-Owned Store Detail'!H82 -> 1.4742464 | N44: =IFERROR(_xlfn.RRI(4,C44,G44),"-") -> 0.32268282 | O44: =IFERROR(_xlfn.RRI(5,G44,L44),"-") -> 0.26837694
B45: Other | C45: 0.49172948 | D45: 0.82281255 | E45: 0.79861605 | F45: 0.86382923 | G45: =SUM('Bonchon U.S. P&L (Monthly''25)'!C34:N34) -> 0.81988274 | H45: =SUM('Bonchon U.S. P&L (Monthly''26)'!C34:N34) -> 0.9874354 | I45: ='U.S. SG&A'!I24+'Company-Owned Store Detail'!E52+'Company-Owned Store Detail'!E84 -> 1.0903767 | J45: ='U.S. SG&A'!J24+'Company-Owned Store Detail'!F52+'Company-Owned Store Detail'!F84 -> 1.2648517 | K45: ='U.S. SG&A'!K24+'Company-Owned Store Detail'!G52+'Company-Owned Store Detail'!G84 -> 1.5085243 | L45: ='U.S. SG&A'!L24+'Company-Owned Store Detail'!H52+'Company-Owned Store Detail'!H84 -> 1.7813147 | N45: =IFERROR(_xlfn.RRI(4,C45,G45),"-") -> 0.13633498 | O45: =IFERROR(_xlfn.RRI(5,G45,L45),"-") -> 0.16787881
B46: SG&A | C46: =SUM(C38:C45) -> 9.9482253 | D46: =SUM(D38:D45) -> 13.843594 | E46: =SUM(E38:E45) -> 14.750345 | F46: =SUM(F38:F45) -> 15.156335 | G46: =SUM(G38:G45) -> 14.873075 | H46: =SUM(H38:H45) -> 17.931302 | I46: =SUM(I38:I45) -> 23.386237 | J46: =SUM(J38:J45) -> 30.924298 | ... L46: =SUM(L38:L45) -> 42.861476 | N46: =IFERROR(_xlfn.RRI(4,C46,G46),"-") -> 0.10576741 | O46: =IFERROR(_xlfn.RRI(5,G46,L46),"-") -> 0.23575755
B47: % of Revenue | C47: =IFERROR(C46/C24,"-") -> 0.72467003 | D47: =IFERROR(D46/D24,"-") -> 0.75549426 | E47: =IFERROR(E46/E24,"-") -> 0.68785613 | F47: =IFERROR(F46/F24,"-") -> 0.74562963 | G47: =IFERROR(G46/G24,"-") -> 0.75388502 | H47: =IFERROR(H46/H24,"-") -> 0.75371948 | I47: =IFERROR(I46/I24,"-") -> 0.73706696 | J47: =IFERROR(J46/J24,"-") -> 0.72334754 | ... L47: =IFERROR(L46/L24,"-") -> 0.66690974
B49: Adj. EBITDA | C49: =C33-C46 -> 3.1706648 | D49: =D33-D46 -> 2.894914 | E49: =E33-E46 -> 4.753772 | F49: =F33-F46 -> 3.5137815 | G49: =G33-G46 -> 3.7606016 | H49: =H33-H46 -> 4.6096135 | I49: =I33-I46 -> 6.5940465 | J49: =J33-J46 -> 9.9227807 | ... L49: =L33-L46 -> 19.129844 | N49: =IFERROR(_xlfn.RRI(4,C49,G49),"-") -> 0.04358241 | O49: =IFERROR(_xlfn.RRI(5,G49,L49),"-") -> 0.38449317
B50: % Margin | C50: =IFERROR(C49/C24,"-") -> 0.23096438 | D50: =IFERROR(D49/D24,"-") -> 0.15798577 | E50: =IFERROR(E49/E24,"-") -> 0.22168371 | F50: =IFERROR(F49/F24,"-") -> 0.17286367 | G50: =IFERROR(G49/G24,"-") -> 0.19061702 | H50: =IFERROR(H49/H24,"-") -> 0.19375924 | I50: =IFERROR(I49/I24,"-") -> 0.20782539 | J50: =IFERROR(J49/J24,"-") -> 0.23210289 | ... L50: =IFERROR(L49/L24,"-") -> 0.29765375
B51: % Margin (Excl. Marketing Fund) | C51: =C49/(C24-C20) -> 0.26381567 | D51: =D49/(D24-D20) -> 0.17919277 | E51: =E49/(E24-E20) -> 0.25519107 | F51: =F49/(F24-F20) -> 0.20580422 | G51: =G49/(G24-G20) -> 0.2279111 | H51: =H49/(H24-H20) -> 0.24520955 | I51: =I49/(I24-I20) -> 0.28407824 | J51: =J49/(J24-J20) -> 0.34309103 | ... L51: =L49/(L24-L20) -> 0.44220919
N52: =IFERROR(_xlfn.RRI(4,C52,G52),"-") -> 0 | O52: =IFERROR(_xlfn.RRI(5,G52,L52),"-") -> 0
B53: Pro Forma Adjustment | G53: ='EBITDA Adjustment Detail'!G25/10^3 -> 0.74606413 | H53: ='2026 PF Adjustment Detail'!O30 -> 1.8890197 | I53: ='U.S. Franchise Sales & Dev'!E30+'Sauce Economics Overview'!I38+'Company-Owned Store Detail'!E92 -> 1.5617171 | J53: ='U.S. Franchise Sales & Dev'!F30+'Sauce Economics Overview'!J38+'Company-Owned Store Detail'!F92 -> 1.8630056 | K53: ='U.S. Franchise Sales & Dev'!G30+'Sauce Economics Overview'!K38+'Company-Owned Store Detail'!G92 -> 2.5152445 | L53: ='U.S. Franchise Sales & Dev'!H30+'Sauce Economics Overview'!L38+'Company-Owned Store Detail'!H92 -> 3.1496707 | N53: =IFERROR(_xlfn.RRI(4,C53,G53),"-") -> - | O53: =IFERROR(_xlfn.RRI(5,G53,L53),"-") -> 0.33382176
B54: PF Adj. EBITDA | G54: =G49+G53 -> 4.5066657 | H54: =H49+H53 -> 6.4986332 | I54: =I49+I53 -> 8.1557636 | J54: =J49+J53 -> 11.785786 | K54: =K49+K53 -> 16.830979 | L54: =L49+L53 -> 22.279514 | N54: =IFERROR(_xlfn.RRI(4,C54,G54),"-") -> - | O54: =IFERROR(_xlfn.RRI(5,G54,L54),"-") -> 0.37660732
B56: Notes:
B57: Same store sales represents franchised locations and excludes ultimately closed locations.
B58: Other Revenue and COGS includes franchisee training fees and other items sold to franchisees through legacy supply chain (i.e., kitchen supplies, packaging, etc.).
B59: Other SG&A includes utilities, insurance, research & development, taxes & dues, and other repair and maintenance expenses.

Sheet Bonchon International P&L
B2: Bonchon International P&L
C4: Historical | H4: Projected | N4: CAGR
B5: ($ in millions) | C5: 2021 | D5: 2022 | E5: 2023 | F5: 2024 | G5: 2025A | H5: 2026E | I5: 2027P | J5: 2028P | K5: 2029P | L5: 2030P | N5: '21A-'25E | O5: '25E-'30P
B7: Philippines | C7: =_xlfn.XLOOKUP($B7,'INTL Restaurant Count Detail'!$B:$B,'INTL Restaurant Count Detail'!D:D) -> 144 | D7: =_xlfn.XLOOKUP($B7,'INTL Restaurant Count Detail'!$B:$B,'INTL Restaurant Count Detail'!E:E) -> 139 | E7: =_xlfn.XLOOKUP($B7,'INTL Restaurant Count Detail'!$B:$B,'INTL Restaurant Count Detail'!F:F) -> 149 | F7: =_xlfn.XLOOKUP($B7,'INTL Restaurant Count Detail'!$B:$B,'INTL Restaurant Count Detail'!G:G) -> 153 | G7: =_xlfn.XLOOKUP($B7,'INTL Restaurant Count Detail'!$B:$B,'INTL Restaurant Count Detail'!H:H) -> 157 | H7: =_xlfn.XLOOKUP($B7,'INTL Restaurant Count Detail'!$B:$B,'INTL Restaurant Count Detail'!I:I) -> 167 | I7: =_xlfn.XLOOKUP($B7,'INTL Restaurant Count Detail'!$B:$B,'INTL Restaurant Count Detail'!J:J) -> 177 | J7: =_xlfn.XLOOKUP($B7,'INTL Restaurant Count Detail'!$B:$B,'INTL Restaurant Count Detail'!K:K) -> 187 | K7: =_xlfn.XLOOKUP($B7,'INTL Restaurant Count Detail'!$B:$B,'INTL Restaurant Count Detail'!L:L) -> 197 | L7: =_xlfn.XLOOKUP($B7,'INTL Restaurant Count Detail'!$B:$B,'INTL Restaurant Count Detail'!M:M) -> 207 | N7: =IFERROR(_xlfn.RRI(4,C7,G7),"-") -> 0.021843273 | O7: =IFERROR(_xlfn.RRI(5,G7,L7),"-") -> 0.056851915
B8: Thailand | C8: =_xlfn.XLOOKUP($B8,'INTL Restaurant Count Detail'!$B:$B,'INTL Restaurant Count Detail'!D:D) -> 101 | D8: =_xlfn.XLOOKUP($B8,'INTL Restaurant Count Detail'!$B:$B,'INTL Restaurant Count Detail'!E:E) -> 112 | E8: =_xlfn.XLOOKUP($B8,'INTL Restaurant Count Detail'!$B:$B,'INTL Restaurant Count Detail'!F:F) -> 118 | F8: =_xlfn.XLOOKUP($B8,'INTL Restaurant Count Detail'!$B:$B,'INTL Restaurant Count Detail'!G:G) -> 122 | G8: =_xlfn.XLOOKUP($B8,'INTL Restaurant Count Detail'!$B:$B,'INTL Restaurant Count Detail'!H:H) -> 134 | H8: =_xlfn.XLOOKUP($B8,'INTL Restaurant Count Detail'!$B:$B,'INTL Restaurant Count Detail'!I:I) -> 138 | I8: =_xlfn.XLOOKUP($B8,'INTL Restaurant Count Detail'!$B:$B,'INTL Restaurant Count Detail'!J:J) -> 146 | J8: =_xlfn.XLOOKUP($B8,'INTL Restaurant Count Detail'!$B:$B,'INTL Restaurant Count Detail'!K:K) -> 157 | K8: =_xlfn.XLOOKUP($B8,'INTL Restaurant Count Detail'!$B:$B,'INTL Restaurant Count Detail'!L:L) -> 171 | L8: =_xlfn.XLOOKUP($B8,'INTL Restaurant Count Detail'!$B:$B,'INTL Restaurant Count Detail'!M:M) -> 188 | N8: =IFERROR(_xlfn.RRI(4,C8,G8),"-") -> 0.073237542 | O8: =IFERROR(_xlfn.RRI(5,G8,L8),"-") -> 0.070066111
B9: Vietnam | C9: =_xlfn.XLOOKUP($B9,'INTL Restaurant Count Detail'!$B:$B,'INTL Restaurant Count Detail'!D:D) -> 6 | D9: =_xlfn.XLOOKUP($B9,'INTL Restaurant Count Detail'!$B:$B,'INTL Restaurant Count Detail'!E:E) -> 11 | E9: =_xlfn.XLOOKUP($B9,'INTL Restaurant Count Detail'!$B:$B,'INTL Restaurant Count Detail'!F:F) -> 14 | F9: =_xlfn.XLOOKUP($B9,'INTL Restaurant Count Detail'!$B:$B,'INTL Restaurant Count Detail'!G:G) -> 24 | G9: =_xlfn.XLOOKUP($B9,'INTL Restaurant Count Detail'!$B:$B,'INTL Restaurant Count Detail'!H:H) -> 26 | H9: =_xlfn.XLOOKUP($B9,'INTL Restaurant Count Detail'!$B:$B,'INTL Restaurant Count Detail'!I:I) -> 33 | I9: =_xlfn.XLOOKUP($B9,'INTL Restaurant Count Detail'!$B:$B,'INTL Restaurant Count Detail'!J:J) -> 39 | J9: =_xlfn.XLOOKUP($B9,'INTL Restaurant Count Detail'!$B:$B,'INTL Restaurant Count Detail'!K:K) -> 45 | K9: =_xlfn.XLOOKUP($B9,'INTL Restaurant Count Detail'!$B:$B,'INTL Restaurant Count Detail'!L:L) -> 51 | L9: =_xlfn.XLOOKUP($B9,'INTL Restaurant Count Detail'!$B:$B,'INTL Restaurant Count Detail'!M:M) -> 57 | N9: =IFERROR(_xlfn.RRI(4,C9,G9),"-") -> 0.44279798 | O9: =IFERROR(_xlfn.RRI(5,G9,L9),"-") -> 0.16998502
B10: Cambodia | C10: =_xlfn.XLOOKUP($B10,'INTL Restaurant Count Detail'!$B:$B,'INTL Restaurant Count Detail'!D:D) -> 11 | D10: =_xlfn.XLOOKUP($B10,'INTL Restaurant Count Detail'!$B:$B,'INTL Restaurant Count Detail'!E:E) -> 11 | E10: =_xlfn.XLOOKUP($B10,'INTL Restaurant Count Detail'!$B:$B,'INTL Restaurant Count Detail'!F:F) -> 11 | F10: =_xlfn.XLOOKUP($B10,'INTL Restaurant Count Detail'!$B:$B,'INTL Restaurant Count Detail'!G:G) -> 11 | G10: =_xlfn.XLOOKUP($B10,'INTL Restaurant Count Detail'!$B:$B,'INTL Restaurant Count Detail'!H:H) -> 10 | H10: =_xlfn.XLOOKUP($B10,'INTL Restaurant Count Detail'!$B:$B,'INTL Restaurant Count Detail'!I:I) -> 10 | I10: =_xlfn.XLOOKUP($B10,'INTL Restaurant Count Detail'!$B:$B,'INTL Restaurant Count Detail'!J:J) -> 11 | J10: =_xlfn.XLOOKUP($B10,'INTL Restaurant Count Detail'!$B:$B,'INTL Restaurant Count Detail'!K:K) -> 11 | K10: =_xlfn.XLOOKUP($B10,'INTL Restaurant Count Detail'!$B:$B,'INTL Restaurant Count Detail'!L:L) -> 12 | L10: =_xlfn.XLOOKUP($B10,'INTL Restaurant Count Detail'!$B:$B,'INTL Restaurant Count Detail'!M:M) -> 12 | N10: =IFERROR(_xlfn.RRI(4,C10,G10),"-") -> -0.02354591 | O10: =IFERROR(_xlfn.RRI(5,G10,L10),"-") -> 0.037137289
B11: Myanmar | C11: =_xlfn.XLOOKUP($B11,'INTL Restaurant Count Detail'!$B:$B,'INTL Restaurant Count Detail'!D:D) -> 6 | D11: =_xlfn.XLOOKUP($B11,'INTL Restaurant Count Detail'!$B:$B,'INTL Restaurant Count Detail'!E:E) -> 7 | E11: =_xlfn.XLOOKUP($B11,'INTL Restaurant Count Detail'!$B:$B,'INTL Restaurant Count Detail'!F:F) -> 7 | F11: =_xlfn.XLOOKUP($B11,'INTL Restaurant Count Detail'!$B:$B,'INTL Restaurant Count Detail'!G:G) -> 7 | G11: =_xlfn.XLOOKUP($B11,'INTL Restaurant Count Detail'!$B:$B,'INTL Restaurant Count Detail'!H:H) -> 10 | H11: =_xlfn.XLOOKUP($B11,'INTL Restaurant Count Detail'!$B:$B,'INTL Restaurant Count Detail'!I:I) -> 10 | I11: =_xlfn.XLOOKUP($B11,'INTL Restaurant Count Detail'!$B:$B,'INTL Restaurant Count Detail'!J:J) -> 10 | J11: =_xlfn.XLOOKUP($B11,'INTL Restaurant Count Detail'!$B:$B,'INTL Restaurant Count Detail'!K:K) -> 11 | K11: =_xlfn.XLOOKUP($B11,'INTL Restaurant Count Detail'!$B:$B,'INTL Restaurant Count Detail'!L:L) -> 12 | L11: =_xlfn.XLOOKUP($B11,'INTL Restaurant Count Detail'!$B:$B,'INTL Restaurant Count Detail'!M:M) -> 13 | N11: =IFERROR(_xlfn.RRI(4,C11,G11),"-") -> 0.13621937 | O11: =IFERROR(_xlfn.RRI(5,G11,L11),"-") -> 0.053873952
B12: Taiwan | C12: =_xlfn.XLOOKUP($B12,'INTL Restaurant Count Detail'!$B:$B,'INTL Restaurant Count Detail'!D:D) -> 0 | D12: =_xlfn.XLOOKUP($B12,'INTL Restaurant Count Detail'!$B:$B,'INTL Restaurant Count Detail'!E:E) -> 0 | E12: =_xlfn.XLOOKUP($B12,'INTL Restaurant Count Detail'!$B:$B,'INTL Restaurant Count Detail'!F:F) -> 0 | F12: =_xlfn.XLOOKUP($B12,'INTL Restaurant Count Detail'!$B:$B,'INTL Restaurant Count Detail'!G:G) -> 3 | G12: =_xlfn.XLOOKUP($B12,'INTL Restaurant Count Detail'!$B:$B,'INTL Restaurant Count Detail'!H:H) -> 6 | H12: =_xlfn.XLOOKUP($B12,'INTL Restaurant Count Detail'!$B:$B,'INTL Restaurant Count Detail'!I:I) -> 9 | I12: =_xlfn.XLOOKUP($B12,'INTL Restaurant Count Detail'!$B:$B,'INTL Restaurant Count Detail'!J:J) -> 12 | J12: =_xlfn.XLOOKUP($B12,'INTL Restaurant Count Detail'!$B:$B,'INTL Restaurant Count Detail'!K:K) -> 15 | K12: =_xlfn.XLOOKUP($B12,'INTL Restaurant Count Detail'!$B:$B,'INTL Restaurant Count Detail'!L:L) -> 15 | L12: =_xlfn.XLOOKUP($B12,'INTL Restaurant Count Detail'!$B:$B,'INTL Restaurant Count Detail'!M:M) -> 15 | N12: =IFERROR(_xlfn.RRI(4,C12,G12),"-") -> - | O12: =IFERROR(_xlfn.RRI(5,G12,L12),"-") -> 0.20112443
B13: Laos | C13: =_xlfn.XLOOKUP($B13,'INTL Restaurant Count Detail'!$B:$B,'INTL Restaurant Count Detail'!D:D) -> 0 | D13: =_xlfn.XLOOKUP($B13,'INTL Restaurant Count Detail'!$B:$B,'INTL Restaurant Count Detail'!E:E) -> 0 | E13: =_xlfn.XLOOKUP($B13,'INTL Restaurant Count Detail'!$B:$B,'INTL Restaurant Count Detail'!F:F) -> 0 | F13: =_xlfn.XLOOKUP($B13,'INTL Restaurant Count Detail'!$B:$B,'INTL Restaurant Count Detail'!G:G) -> 2 | G13: =_xlfn.XLOOKUP($B13,'INTL Restaurant Count Detail'!$B:$B,'INTL Restaurant Count Detail'!H:H) -> 4 | H13: =_xlfn.XLOOKUP($B13,'INTL Restaurant Count Detail'!$B:$B,'INTL Restaurant Count Detail'!I:I) -> 7 | I13: =_xlfn.XLOOKUP($B13,'INTL Restaurant Count Detail'!$B:$B,'INTL Restaurant Count Detail'!J:J) -> 10 | J13: =_xlfn.XLOOKUP($B13,'INTL Restaurant Count Detail'!$B:$B,'INTL Restaurant Count Detail'!K:K) -> 13 | K13: =_xlfn.XLOOKUP($B13,'INTL Restaurant Count Detail'!$B:$B,'INTL Restaurant Count Detail'!L:L) -> 16 | L13: =_xlfn.XLOOKUP($B13,'INTL Restaurant Count Detail'!$B:$B,'INTL Restaurant Count Detail'!M:M) -> 19 | N13: =IFERROR(_xlfn.RRI(4,C13,G13),"-") -> - | O13: =IFERROR(_xlfn.RRI(5,G13,L13),"-") -> 0.36564784
B14: Singapore | C14: =_xlfn.XLOOKUP($B14,'INTL Restaurant Count Detail'!$B:$B,'INTL Restaurant Count Detail'!D:D) -> 5 | D14: =_xlfn.XLOOKUP($B14,'INTL Restaurant Count Detail'!$B:$B,'INTL Restaurant Count Detail'!E:E) -> 5 | E14: =_xlfn.XLOOKUP($B14,'INTL Restaurant Count Detail'!$B:$B,'INTL Restaurant Count Detail'!F:F) -> 4 | F14: =_xlfn.XLOOKUP($B14,'INTL Restaurant Count Detail'!$B:$B,'INTL Restaurant Count Detail'!G:G) -> 0 | G14: =_xlfn.XLOOKUP($B14,'INTL Restaurant Count Detail'!$B:$B,'INTL Restaurant Count Detail'!H:H) -> 0 | H14: =_xlfn.XLOOKUP($B14,'INTL Restaurant Count Detail'!$B:$B,'INTL Restaurant Count Detail'!I:I) -> 0 | I14: =_xlfn.XLOOKUP($B14,'INTL Restaurant Count Detail'!$B:$B,'INTL Restaurant Count Detail'!J:J) -> 0 | J14: =_xlfn.XLOOKUP($B14,'INTL Restaurant Count Detail'!$B:$B,'INTL Restaurant Count Detail'!K:K) -> 0 | K14: =_xlfn.XLOOKUP($B14,'INTL Restaurant Count Detail'!$B:$B,'INTL Restaurant Count Detail'!L:L) -> 0 | L14: =_xlfn.XLOOKUP($B14,'INTL Restaurant Count Detail'!$B:$B,'INTL Restaurant Count Detail'!M:M) -> 0 | N14: =IFERROR(_xlfn.RRI(4,C14,G14),"-") -> -1 | O14: =IFERROR(_xlfn.RRI(5,G14,L14),"-") -> 0
B15: Australia | C15: =_xlfn.XLOOKUP($B15,'INTL Restaurant Count Detail'!$B:$B,'INTL Restaurant Count Detail'!D:D) -> 1 | D15: =_xlfn.XLOOKUP($B15,'INTL Restaurant Count Detail'!$B:$B,'INTL Restaurant Count Detail'!E:E) -> 2 | E15: =_xlfn.XLOOKUP($B15,'INTL Restaurant Count Detail'!$B:$B,'INTL Restaurant Count Detail'!F:F) -> 0 | F15: =_xlfn.XLOOKUP($B15,'INTL Restaurant Count Detail'!$B:$B,'INTL Restaurant Count Detail'!G:G) -> 0 | G15: =_xlfn.XLOOKUP($B15,'INTL Restaurant Count Detail'!$B:$B,'INTL Restaurant Count Detail'!H:H) -> 0 | H15: =_xlfn.XLOOKUP($B15,'INTL Restaurant Count Detail'!$B:$B,'INTL Restaurant Count Detail'!I:I) -> 0 | I15: =_xlfn.XLOOKUP($B15,'INTL Restaurant Count Detail'!$B:$B,'INTL Restaurant Count Detail'!J:J) -> 0 | J15: =_xlfn.XLOOKUP($B15,'INTL Restaurant Count Detail'!$B:$B,'INTL Restaurant Count Detail'!K:K) -> 0 | K15: =_xlfn.XLOOKUP($B15,'INTL Restaurant Count Detail'!$B:$B,'INTL Restaurant Count Detail'!L:L) -> 0 | L15: =_xlfn.XLOOKUP($B15,'INTL Restaurant Count Detail'!$B:$B,'INTL Restaurant Count Detail'!M:M) -> 0 | N15: =IFERROR(_xlfn.RRI(4,C15,G15),"-") -> -1 | O15: =IFERROR(_xlfn.RRI(5,G15,L15),"-") -> 0
B16: France | C16: =_xlfn.XLOOKUP($B16,'INTL Restaurant Count Detail'!$B:$B,'INTL Restaurant Count Detail'!D:D) -> 0 | D16: =_xlfn.XLOOKUP($B16,'INTL Restaurant Count Detail'!$B:$B,'INTL Restaurant Count Detail'!E:E) -> 0 | E16: =_xlfn.XLOOKUP($B16,'INTL Restaurant Count Detail'!$B:$B,'INTL Restaurant Count Detail'!F:F) -> 1 | F16: =_xlfn.XLOOKUP($B16,'INTL Restaurant Count Detail'!$B:$B,'INTL Restaurant Count Detail'!G:G) -> 2 | G16: =_xlfn.XLOOKUP($B16,'INTL Restaurant Count Detail'!$B:$B,'INTL Restaurant Count Detail'!H:H) -> 0 | H16: =_xlfn.XLOOKUP($B16,'INTL Restaurant Count Detail'!$B:$B,'INTL Restaurant Count Detail'!I:I) -> 0 | I16: =_xlfn.XLOOKUP($B16,'INTL Restaurant Count Detail'!$B:$B,'INTL Restaurant Count Detail'!J:J) -> 0 | J16: =_xlfn.XLOOKUP($B16,'INTL Restaurant Count Detail'!$B:$B,'INTL Restaurant Count Detail'!K:K) -> 0 | K16: =_xlfn.XLOOKUP($B16,'INTL Restaurant Count Detail'!$B:$B,'INTL Restaurant Count Detail'!L:L) -> 0 | L16: =_xlfn.XLOOKUP($B16,'INTL Restaurant Count Detail'!$B:$B,'INTL Restaurant Count Detail'!M:M) -> 0 | N16: =IFERROR(_xlfn.RRI(4,C16,G16),"-") -> 0 | O16: =IFERROR(_xlfn.RRI(5,G16,L16),"-") -> 0
B17: Malaysia | C17: =_xlfn.XLOOKUP($B17,'INTL Restaurant Count Detail'!$B:$B,'INTL Restaurant Count Detail'!D:D) -> 0 | D17: =_xlfn.XLOOKUP($B17,'INTL Restaurant Count Detail'!$B:$B,'INTL Restaurant Count Detail'!E:E) -> 0 | E17: =_xlfn.XLOOKUP($B17,'INTL Restaurant Count Detail'!$B:$B,'INTL Restaurant Count Detail'!F:F) -> 0 | F17: =_xlfn.XLOOKUP($B17,'INTL Restaurant Count Detail'!$B:$B,'INTL Restaurant Count Detail'!G:G) -> 0 | G17: =_xlfn.XLOOKUP($B17,'INTL Restaurant Count Detail'!$B:$B,'INTL Restaurant Count Detail'!H:H) -> 0 | H17: =_xlfn.XLOOKUP($B17,'INTL Restaurant Count Detail'!$B:$B,'INTL Restaurant Count Detail'!I:I) -> 2 | I17: =_xlfn.XLOOKUP($B17,'INTL Restaurant Count Detail'!$B:$B,'INTL Restaurant Count Detail'!J:J) -> 5 | J17: =_xlfn.XLOOKUP($B17,'INTL Restaurant Count Detail'!$B:$B,'INTL Restaurant Count Detail'!K:K) -> 8 | K17: =_xlfn.XLOOKUP($B17,'INTL Restaurant Count Detail'!$B:$B,'INTL Restaurant Count Detail'!L:L) -> 11 | L17: =_xlfn.XLOOKUP($B17,'INTL Restaurant Count Detail'!$B:$B,'INTL Restaurant Count Detail'!M:M) -> 14 | N17: =IFERROR(_xlfn.RRI(4,C17,G17),"-") -> 0 | O17: =IFERROR(_xlfn.RRI(5,G17,L17),"-") -> -
B18: Other Countries | C18: =_xlfn.XLOOKUP($B18,'INTL Restaurant Count Detail'!$B:$B,'INTL Restaurant Count Detail'!D:D) -> 0 | D18: =_xlfn.XLOOKUP($B18,'INTL Restaurant Count Detail'!$B:$B,'INTL Restaurant Count Detail'!E:E) -> 0 | E18: =_xlfn.XLOOKUP($B18,'INTL Restaurant Count Detail'!$B:$B,'INTL Restaurant Count Detail'!F:F) -> 0 | F18: =_xlfn.XLOOKUP($B18,'INTL Restaurant Count Detail'!$B:$B,'INTL Restaurant Count Detail'!G:G) -> 0 | G18: =_xlfn.XLOOKUP($B18,'INTL Restaurant Count Detail'!$B:$B,'INTL Restaurant Count Detail'!H:H) -> 0 | H18: =_xlfn.XLOOKUP($B18,'INTL Restaurant Count Detail'!$B:$B,'INTL Restaurant Count Detail'!I:I) -> 0 | I18: =_xlfn.XLOOKUP($B18,'INTL Restaurant Count Detail'!$B:$B,'INTL Restaurant Count Detail'!J:J) -> 4 | J18: =_xlfn.XLOOKUP($B18,'INTL Restaurant Count Detail'!$B:$B,'INTL Restaurant Count Detail'!K:K) -> 12 | K18: =_xlfn.XLOOKUP($B18,'INTL Restaurant Count Detail'!$B:$B,'INTL Restaurant Count Detail'!L:L) -> 24 | L18: =_xlfn.XLOOKUP($B18,'INTL Restaurant Count Detail'!$B:$B,'INTL Restaurant Count Detail'!M:M) -> 36 | N18: =IFERROR(_xlfn.RRI(4,C18,G18),"-") -> 0 | O18: =IFERROR(_xlfn.RRI(5,G18,L18),"-") -> -
B19: All Other | C19: =SUM(C10:C18) -> 23 | D19: =SUM(D10:D18) -> 25 | E19: =SUM(E10:E18) -> 23 | F19: =SUM(F10:F18) -> 25 | G19: =SUM(G10:G18) -> 30 | H19: =SUM(H10:H18) -> 38 | I19: =SUM(I10:I18) -> 52 | J19: =SUM(J10:J18) -> 70 | ... L19: =SUM(L10:L18) -> 109 | N19: =IFERROR(_xlfn.RRI(4,C19,G19),"-") -> 0.068681656 | O19: =IFERROR(_xlfn.RRI(5,G19,L19),"-") -> 0.29437778
B20: Total Restaurants | C20: =SUM(C7:C9,C19) -> 274 | D20: =SUM(D7:D9,D19) -> 287 | E20: =SUM(E7:E9,E19) -> 304 | F20: =SUM(F7:F9,F19) -> 324 | G20: =SUM(G7:G9,G19) -> 347 | H20: =SUM(H7:H9,H19) -> 376 | I20: =SUM(I7:I9,I19) -> 414 | J20: =SUM(J7:J9,J19) -> 459 | ... L20: =SUM(L7:L9,L19) -> 561 | N20: =IFERROR(_xlfn.RRI(4,C20,G20),"-") -> 0.060827399 | O20: =IFERROR(_xlfn.RRI(5,G20,L20),"-") -> 0.10084628
B21: % Growth | D21: =IFERROR(D20/C20-1,0) -> 0.047445255 | E21: =IFERROR(E20/D20-1,0) -> 0.059233449 | F21: =IFERROR(F20/E20-1,0) -> 0.065789474 | G21: =IFERROR(G20/F20-1,0) -> 0.070987654 | H21: =IFERROR(H20/G20-1,0) -> 0.083573487 | I21: =IFERROR(I20/H20-1,0) -> 0.10106383 | J21: =IFERROR(J20/I20-1,0) -> 0.10869565 | K21: =IFERROR(K20/J20-1,0) -> 0.10893246 | L21: =IFERROR(L20/K20-1,0) -> 0.1021611
B23: Systemwide Sales | C23: ='INTL Restaurant Count Detail'!D123 -> 103.10846 | D23: ='INTL Restaurant Count Detail'!E123 -> 133.7085 | E23: ='INTL Restaurant Count Detail'!F123 -> 144.83545 | F23: ='INTL Restaurant Count Detail'!G123 -> 154.48318 | G23: ='INTL Restaurant Count Detail'!H123 -> 170.03361 | H23: ='INTL Restaurant Count Detail'!I123 -> 181.55199 | I23: ='INTL Restaurant Count Detail'!J123 -> 207.69386 | J23: ='INTL Restaurant Count Detail'!K123 -> 239.16518 | ... L23: ='INTL Restaurant Count Detail'!M123 -> 319.15817 | N23: =IFERROR(_xlfn.RRI(4,C23,G23),"-") -> 0.13320926 | O23: =IFERROR(_xlfn.RRI(5,G23,L23),"-") -> 0.13421201
B24: % Growth | D24: =IFERROR(D23/C23-1,0) -> 0.29677529 | E24: =IFERROR(E23/D23-1,0) -> 0.083217967 | F24: =IFERROR(F23/E23-1,0) -> 0.066611626 | G24: =IFERROR(G23/F23-1,0) -> 0.10066098 | H24: =IFERROR(H23/G23-1,0) -> 0.067741774 | I24: =IFERROR(I23/H23-1,0) -> 0.1439911 | J24: =IFERROR(J23/I23-1,0) -> 0.15152747 | K24: =IFERROR(K23/J23-1,0) -> 0.15629712 | L24: =IFERROR(L23/K23-1,0) -> 0.15408706
B26: Philippines Same Store Sales | C26: 0.20436819 | D26: 0.36571561 | E26: 0.12889686 | F26: 0.10041183 | G26: 0.004830525 | H26: ='INTL Franchised Sales & Dev'!E28 -> 0.05 | I26: ='INTL Franchised Sales & Dev'!F28 -> 0.05 | J26: ='INTL Franchised Sales & Dev'!G28 -> 0.05 | K26: ='INTL Franchised Sales & Dev'!H28 -> 0.05 | L26: ='INTL Franchised Sales & Dev'!I28 -> 0.05
B27: Thailand Same Store Sales | C27: -0.3599435 | D27: -0.00788309 | E27: -0.058614665 | F27: -0.063721738 | G27: 0.10356836 | H27: ='INTL Franchised Sales & Dev'!E64 -> 0.05 | I27: ='INTL Franchised Sales & Dev'!F64 -> 0.05 | J27: ='INTL Franchised Sales & Dev'!G64 -> 0.05 | K27: ='INTL Franchised Sales & Dev'!H64 -> 0.05 | L27: ='INTL Franchised Sales & Dev'!I64 -> 0.05
B28: All Other Same Store Sales | C28: -0.23187221 | D28: 0.5043279 | E28: -0.044022315 | F28: 0.030743022 | G28: 0.035758522 | H28: ='INTL Franchised Sales & Dev'!E386 -> 0.05 | I28: ='INTL Franchised Sales & Dev'!F386 -> 0.05 | J28: ='INTL Franchised Sales & Dev'!G386 -> 0.05 | K28: ='INTL Franchised Sales & Dev'!H386 -> 0.05 | L28: ='INTL Franchised Sales & Dev'!I386 -> 0.05
B29: International Same Store Sales | C29: -0.16075935 | D29: 0.15699898 | E29: 0.019225146 | F29: 0.010998005 | G29: 0.055085803 | H29: 0.05 | I29: 0.05 | J29: 0.05 | K29: 0.05 | L29: 0.05
B31: Franchise Revenue | C31: 2.8763763 | D31: 3.8512605 | E31: 4.076464 | F31: 4.5986212 | G31: =SUM('Bonchon Int''l P&L (Monthly''25)'!C7:N7) -> 4.8910982 | H31: =SUM('Bonchon Int''l P&L (Monthly''26)'!C7:N7) -> 5.1083422 | I31: ='INTL Franchised Sales & Dev'!F12 -> 6.0216128 | J31: ='INTL Franchised Sales & Dev'!G12 -> 7.2026239 | K31: ='INTL Franchised Sales & Dev'!H12 -> 8.6168541 | L31: ='INTL Franchised Sales & Dev'!I12 -> 9.9517262 | N31: =IFERROR(_xlfn.RRI(4,C31,G31),"-") -> 0.14193181 | O31: =IFERROR(_xlfn.RRI(5,G31,L31),"-") -> 0.15265253
B32: Sauce Revenue | C32: 4.2819214 | D32: 5.3996779 | E32: 4.8327955 | F32: 5.4961941 | G32: =SUM('Bonchon Int''l P&L (Monthly''25)'!C8:N8) -> 5.0204721 | H32: =SUM('Bonchon Int''l P&L (Monthly''26)'!C8:N8) -> 5.4758208 | I32: =SUM('Sauce Economics Overview'!I61,'Sauce Economics Overview'!I82) -> 6.5054581 | J32: =SUM('Sauce Economics Overview'!J61,'Sauce Economics Overview'!J82) -> 7.5327905 | K32: =SUM('Sauce Economics Overview'!K61,'Sauce Economics Overview'!K82) -> 9.1115199 | L32: =SUM('Sauce Economics Overview'!L61,'Sauce Economics Overview'!L82) -> 10.613413 | N32: =IFERROR(_xlfn.RRI(4,C32,G32),"-") -> 0.040582377 | O32: =IFERROR(_xlfn.RRI(5,G32,L32),"-") -> 0.16150772
B33: Company-Owned Store Revenue | C33: 0 | D33: 0 | E33: 0 | F33: 0 | G33: =SUM('Bonchon Int''l P&L (Monthly''25)'!C9:N9) -> 0 | H33: =SUM('Bonchon Int''l P&L (Monthly''26)'!C9:N9) -> 0 | I33: 0 | J33: 0 | K33: 0 | L33: 0 | N33: =IFERROR(_xlfn.RRI(4,C33,G33),"-") -> 0 | O33: =IFERROR(_xlfn.RRI(5,G33,L33),"-") -> 0
B34: Marketing Fund | C34: 0 | D34: 0 | E34: 0 | F34: 0 | G34: =SUM('Bonchon Int''l P&L (Monthly''25)'!C10:N10) -> 0 | H34: =SUM('Bonchon Int''l P&L (Monthly''26)'!C10:N10) -> 0 | I34: 0 | J34: 0 | K34: 0 | L34: 0 | N34: =IFERROR(_xlfn.RRI(4,C34,G34),"-") -> 0 | O34: =IFERROR(_xlfn.RRI(5,G34,L34),"-") -> 0
B35: Other Product Revenue | C35: 0.53602977 | D35: 0.12491332 | E35: 0.035815814 | F35: 0.032899886 | G35: =SUM('Bonchon Int''l P&L (Monthly''25)'!C11:N11) -> 0.02867745 | H35: =SUM('Bonchon Int''l P&L (Monthly''26)'!C11:N11) -> 0.017044105 | I35: ='Sauce Economics Overview'!I90 -> 0.028632737 | J35: ='Sauce Economics Overview'!J90 -> 0.033477344 | K35: ='Sauce Economics Overview'!K90 -> 0.038502338 | L35: ='Sauce Economics Overview'!L90 -> 0.04391919 | N35: =IFERROR(_xlfn.RRI(4,C35,G35),"-") -> -0.51906331 | O35: =IFERROR(_xlfn.RRI(5,G35,L35),"-") -> 0.088987157
B36: Other Revenue | C36: 0.11329416 | D36: 0.11911519 | E36: 0.13006411 | F36: 0.12903044 | G36: =SUM('Bonchon Int''l P&L (Monthly''25)'!C12:N12) -> 0.097052309 | H36: =SUM('Bonchon Int''l P&L (Monthly''26)'!C12:N12) -> 0.1301371 | I36: 0.13664396 | J36: 0.14347615 | K36: 0.15064996 | L36: 0.15818246 | N36: =IFERROR(_xlfn.RRI(4,C36,G36),"-") -> -0.037945695 | O36: =IFERROR(_xlfn.RRI(5,G36,L36),"-") -> 0.10263174
B37: Other | C37: =SUM(C35:C36) -> 0.64932393 | D37: =SUM(D35:D36) -> 0.24402851 | E37: =SUM(E35:E36) -> 0.16587992 | F37: =SUM(F35:F36) -> 0.16193033 | G37: =SUM(G35:G36) -> 0.12572976 | H37: =SUM(H35:H36) -> 0.1471812 | I37: =SUM(I35:I36) -> 0.16527669 | J37: =SUM(J35:J36) -> 0.1769535 | ... L37: =SUM(L35:L36) -> 0.20210165 | N37: =IFERROR(_xlfn.RRI(4,C37,G37),"-") -> -0.33664781 | O37: =IFERROR(_xlfn.RRI(5,G37,L37),"-") -> 0.099578791
B38: Total Revenue | C38: =SUM(C31:C34,C37) -> 7.8076216 | D38: =SUM(D31:D34,D37) -> 9.4949669 | E38: =SUM(E31:E34,E37) -> 9.0751394 | F38: =SUM(F31:F34,F37) -> 10.256746 | G38: =SUM(G31:G34,G37) -> 10.0373 | H38: =SUM(H31:H34,H37) -> 10.731344 | I38: =SUM(I31:I34,I37) -> 12.692348 | J38: =SUM(J31:J34,J37) -> 14.912368 | ... L38: =SUM(L31:L34,L37) -> 20.767241 | N38: =IFERROR(_xlfn.RRI(4,C38,G38),"-") -> 0.064815925 | O38: =IFERROR(_xlfn.RRI(5,G38,L38),"-") -> 0.15651795
B39: % Growth | D39: =IFERROR(D38/C38-1,0) -> 0.21611514 | E39: =IFERROR(E38/D38-1,0) -> -0.044215791 | F39: =IFERROR(F38/E38-1,0) -> 0.13020255 | G39: =IFERROR(G38/F38-1,0) -> -0.021395246 | H39: =IFERROR(H38/G38-1,0) -> 0.069146502 | I39: =IFERROR(I38/H38-1,0) -> 0.18273603 | J39: =IFERROR(J38/I38-1,0) -> 0.17491015 | K39: =IFERROR(K38/J38-1,0) -> 0.20152121 | L39: =IFERROR(L38/K38-1,0) -> 0.1590462
B41: Sauce COGS | C41: =SUM('Sauce Economics Overview'!C62,'Sauce Economics Overview'!C83) -> 0.86663532 | D41: =SUM('Sauce Economics Overview'!D62,'Sauce Economics Overview'!D83) -> 1.2486678 | E41: =SUM('Sauce Economics Overview'!E62,'Sauce Economics Overview'!E83) -> 1.3810089 | F41: =SUM('Sauce Economics Overview'!F62,'Sauce Economics Overview'!F83) -> 1.3575635 | G41: =SUM('Bonchon Int''l P&L (Monthly''25)'!C16:N16) -> 1.3043717 | H41: =SUM('Bonchon Int''l P&L (Monthly''26)'!C16:N16) -> 1.3505507 | I41: =SUM('Sauce Economics Overview'!I62,'Sauce Economics Overview'!I83) -> 1.5339579 | J41: =SUM('Sauce Economics Overview'!J62,'Sauce Economics Overview'!J83) -> 1.7648955 | K41: =SUM('Sauce Economics Overview'!K62,'Sauce Economics Overview'!K83) -> 2.0482712 | L41: =SUM('Sauce Economics Overview'!L62,'Sauce Economics Overview'!L83) -> 2.3941645 | N41: =IFERROR(_xlfn.RRI(4,C41,G41),"-") -> 0.10762116 | O41: =IFERROR(_xlfn.RRI(5,G41,L41),"-") -> 0.1291471
B42: Company-Owned Store COGS | C42: 0 | D42: 0 | E42: 0 | F42: 0 | G42: =SUM('Bonchon Int''l P&L (Monthly''25)'!C17:N17) -> 0 | H42: =SUM('Bonchon Int''l P&L (Monthly''26)'!C17:N17) -> 0 | I42: 0 | J42: 0 | K42: 0 | L42: 0 | N42: =IFERROR(_xlfn.RRI(4,C42,G42),"-") -> 0 | O42: =IFERROR(_xlfn.RRI(5,G42,L42),"-") -> 0
B43: Other Product COGS | C43: 0.39409009 | D43: 0.085058874 | E43: 0.025328933 | F43: 0.02277794 | G43: =SUM('Bonchon Int''l P&L (Monthly''25)'!C18:N18) -> 0.019442561 | H43: =SUM('Bonchon Int''l P&L (Monthly''26)'!C18:N18) -> 0.010947958 | I43: ='Sauce Economics Overview'!I91 -> 0.021474553 | J43: ='Sauce Economics Overview'!J91 -> 0.025108008 | K43: ='Sauce Economics Overview'!K91 -> 0.028876753 | L43: ='Sauce Economics Overview'!L91 -> 0.032939393 | N43: =IFERROR(_xlfn.RRI(4,C43,G43),"-") -> -0.52870863 | O43: =IFERROR(_xlfn.RRI(5,G43,L43),"-") -> 0.11120049
B44: D&A In COGS | C44: -0.23105642 | D44: -0.18562071 | E44: -0.16436635 | F44: -0.16295527 | G44: =SUM('Bonchon Int''l P&L (Monthly''25)'!C19:N19) -> -0.14490381 | H44: =SUM('Bonchon Int''l P&L (Monthly''26)'!C19:N19) -> -0.14684124 | I44: -0.14684124 | J44: -0.14893897 | K44: -0.14893897 | L44: -0.14893897 | N44: =IFERROR(_xlfn.RRI(4,C44,G44),"-") -> -0.11010158 | O44: =IFERROR(_xlfn.RRI(5,G44,L44),"-") -> 0.0055084163
B45: Other | C45: =SUM(C43:C44) -> 0.16303367 | D45: =SUM(D43:D44) -> -0.10056184 | E45: =SUM(E43:E44) -> -0.13903742 | F45: =SUM(F43:F44) -> -0.14017733 | G45: =SUM(G43:G44) -> -0.12546124 | H45: =SUM(H43:H44) -> -0.13589328 | I45: =SUM(I43:I44) -> -0.12536668 | J45: =SUM(J43:J44) -> -0.12383096 | ... L45: =SUM(L43:L44) -> -0.11599958 | N45: =IFERROR(_xlfn.RRI(4,C45,G45),"-") -> - | O45: =IFERROR(_xlfn.RRI(5,G45,L45),"-") -> -0.01555975
B46: Total Cost of Goods Sold | C46: =SUM(C41:C42,C45) -> 1.029669 | D46: =SUM(D41:D42,D45) -> 1.148106 | E46: =SUM(E41:E42,E45) -> 1.2419715 | F46: =SUM(F41:F42,F45) -> 1.2173861 | G46: =SUM(G41:G42,G45) -> 1.1789104 | H46: =SUM(H41:H42,H45) -> 1.2146575 | I46: =SUM(I41:I42,I45) -> 1.4085912 | J46: =SUM(J41:J42,J45) -> 1.6410645 | ... L46: =SUM(L41:L42,L45) -> 2.2781649 | N46: =IFERROR(_xlfn.RRI(4,C46,G46),"-") -> 0.034417348 | O46: =IFERROR(_xlfn.RRI(5,G46,L46),"-") -> 0.14082983
B47: Gross Profit | C47: =C38-C46 -> 6.7779526 | D47: =D38-D46 -> 8.3468609 | E47: =E38-E46 -> 7.8331679 | F47: =F38-F46 -> 9.0393595 | G47: =G38-G46 -> 8.8583896 | H47: =H38-H46 -> 9.5166868 | I47: =I38-I46 -> 11.283756 | J47: =J38-J46 -> 13.271303 | ... L47: =L38-L46 -> 18.489076 | N47: =IFERROR(_xlfn.RRI(4,C47,G47),"-") -> 0.069212586 | O47: =IFERROR(_xlfn.RRI(5,G47,L47),"-") -> 0.15854281
B48: % Margin | C48: =IFERROR(C47/C38,"-") -> 0.86812002 | D48: =IFERROR(D47/D38,"-") -> 0.87908268 | E48: =IFERROR(E47/E38,"-") -> 0.86314574 | F48: =IFERROR(F47/F38,"-") -> 0.88130873 | G48: =IFERROR(G47/G38,"-") -> 0.88254706 | H48: =IFERROR(H47/H38,"-") -> 0.88681218 | I48: =IFERROR(I47/I38,"-") -> 0.88902044 | J48: =IFERROR(J47/J38,"-") -> 0.88995279 | ... L48: =IFERROR(L47/L38,"-") -> 0.89030007
B50: Corporate Labor | C50: 1.3116005 | D50: 1.1832712 | E50: 0.8195791 | F50: 1.1374036 | G50: =SUM('Bonchon Int''l P&L (Monthly''25)'!C27:N27) -> 1.2272209 | H50: =SUM('Bonchon Int''l P&L (Monthly''26)'!C27:N27) -> 1.2909824 | I50: ='INTL SG&A Detail'!I16 -> 1.4441376 | J50: ='INTL SG&A Detail'!J16 -> 1.6054511 | K50: ='INTL SG&A Detail'!K16 -> 1.7891835 | L50: ='INTL SG&A Detail'!L16 -> 1.9347688 | N50: =IFERROR(_xlfn.RRI(4,C50,G50),"-") -> -0.016486567 | O50: =IFERROR(_xlfn.RRI(5,G50,L50),"-") -> 0.095320622
B51: Company-Owned Store Labor | C51: 0 | D51: 0 | E51: 0 | F51: 0 | G51: =SUM('Bonchon Int''l P&L (Monthly''25)'!C28:N28) -> 0 | H51: =SUM('Bonchon Int''l P&L (Monthly''26)'!C28:N28) -> 0 | I51: 0 | J51: 0 | K51: 0 | L51: 0
B52: Total Labor | C52: =SUM(C50:C51) -> 1.3116005 | D52: =SUM(D50:D51) -> 1.1832712 | E52: =SUM(E50:E51) -> 0.8195791 | F52: =SUM(F50:F51) -> 1.1374036 | G52: =SUM(G50:G51) -> 1.2272209 | H52: =SUM(H50:H51) -> 1.2909824 | I52: =SUM(I50:I51) -> 1.4441376 | J52: =SUM(J50:J51) -> 1.6054511 | ... L52: =SUM(L50:L51) -> 1.9347688
B53: Marketing Fund | C53: =C34 -> 0 | D53: =D34 -> 0 | E53: =E34 -> 0 | F53: =F34 -> 0 | G53: =SUM('Bonchon Int''l P&L (Monthly''25)'!C28:N28) -> 0 | H53: =H34 -> 0 | I53: =I34 -> 0 | J53: =J34 -> 0 | K53: =K34 -> 0 | L53: =L34 -> 0 | N53: =IFERROR(_xlfn.RRI(4,C53,G53),"-") -> 0 | O53: =IFERROR(_xlfn.RRI(5,G53,L53),"-") -> 0
B54: Service Fees | C54: 0.46157914 | D54: 0.38504766 | E54: 0.39069387 | F54: 0.3664124 | G54: =SUM('Bonchon Int''l P&L (Monthly''25)'!C29:N29) -> 0.45972636 | H54: =SUM('Bonchon Int''l P&L (Monthly''26)'!C29:N29) -> 0.51061442 | I54: ='INTL SG&A Detail'!I18 -> 0.54068162 | J54: ='INTL SG&A Detail'!J18 -> 0.57030272 | K54: ='INTL SG&A Detail'!K18 -> 0.60872075 | L54: ='INTL SG&A Detail'!L18 -> 0.6327934 | N54: =IFERROR(_xlfn.RRI(4,C54,G54),"-") -> -0.0010050128 | O54: =IFERROR(_xlfn.RRI(5,G54,L54),"-") -> 0.065988467
B55: Travel & Entertainment | C55: 0.06703348 | D55: 0.17615281 | E55: 0.3589415 | F55: 0.31850126 | G55: =SUM('Bonchon Int''l P&L (Monthly''25)'!C30:N30) -> 0.18750159 | H55: =SUM('Bonchon Int''l P&L (Monthly''26)'!C30:N30) -> 0.26901408 | I55: ='INTL SG&A Detail'!I19 -> 0.34750825 | J55: ='INTL SG&A Detail'!J19 -> 0.40874264 | K55: ='INTL SG&A Detail'!K19 -> 0.49164501 | L55: ='INTL SG&A Detail'!L19 -> 0.57034514 | N55: =IFERROR(_xlfn.RRI(4,C55,G55),"-") -> 0.29323752 | O55: =IFERROR(_xlfn.RRI(5,G55,L55),"-") -> 0.24918442
B56: Rent | C56: 0.11197176 | D56: 0.10129693 | E56: 0.10357678 | F56: 0.11855152 | G56: =SUM('Bonchon Int''l P&L (Monthly''25)'!C31:N31) -> 0.11424429 | H56: =SUM('Bonchon Int''l P&L (Monthly''26)'!C31:N31) -> 0.11788272 | I56: ='INTL SG&A Detail'!I20 -> 0.12244657 | J56: ='INTL SG&A Detail'!J20 -> 0.12669468 | K56: ='INTL SG&A Detail'!K20 -> 0.13265358 | L56: ='INTL SG&A Detail'!L20 -> 0.13527287 | N56: =IFERROR(_xlfn.RRI(4,C56,G56),"-") -> 0.0050357253 | O56: =IFERROR(_xlfn.RRI(5,G56,L56),"-") -> 0.034368398
B57: Freight | C57: 0.01439536 | D57: 0.01341385 | E57: 0.00751845 | F57: 0.01398302 | G57: =SUM('Bonchon Int''l P&L (Monthly''25)'!C32:N32) -> 0.00882947 | H57: =SUM('Bonchon Int''l P&L (Monthly''26)'!C32:N32) -> 0.01014085 | I57: ='INTL SG&A Detail'!I21 -> 0.013099787 | J57: ='INTL SG&A Detail'!J21 -> 0.015408099 | K57: ='INTL SG&A Detail'!K21 -> 0.018533215 | L57: ='INTL SG&A Detail'!L21 -> 0.021499921 | N57: =IFERROR(_xlfn.RRI(4,C57,G57),"-") -> -0.11503106 | O57: =IFERROR(_xlfn.RRI(5,G57,L57),"-") -> 0.1948144
B58: Advertising Expense | C58: 0.00410051 | D58: 0.18902882 | E58: 0.07491046 | F58: 0.05395511 | G58: =SUM('Bonchon Int''l P&L (Monthly''25)'!C33:N33) -> 0.02924423 | H58: =SUM('Bonchon Int''l P&L (Monthly''26)'!C33:N33) -> 0.01690141 | I58: ='INTL SG&A Detail'!I22 -> 0.063461738 | J58: ='INTL SG&A Detail'!J22 -> 0.07456184 | K58: ='INTL SG&A Detail'!K22 -> 0.089587632 | L58: ='INTL SG&A Detail'!L22 -> 0.1038362 | N58: =IFERROR(_xlfn.RRI(4,C58,G58),"-") -> 0.63418259 | O58: =IFERROR(_xlfn.RRI(5,G58,L58),"-") -> 0.28843265
B59: Other | C59: 0.38282206 | D59: 0.53154436 | E59: 0.62683687 | F59: 0.31439444 | G59: =SUM('Bonchon Int''l P&L (Monthly''25)'!C34:N34) -> 0.38187217 | H59: =SUM('Bonchon Int''l P&L (Monthly''26)'!C34:N34) -> 0.29346997 | I59: ='INTL SG&A Detail'!I23 -> 0.38269668 | J59: ='INTL SG&A Detail'!J23 -> 0.48474396 | K59: ='INTL SG&A Detail'!K23 -> 0.64034404 | L59: ='INTL SG&A Detail'!L23 -> 0.76832243 | N59: =IFERROR(_xlfn.RRI(4,C59,G59),"-") -> -0.00062089887 | O59: =IFERROR(_xlfn.RRI(5,G59,L59),"-") -> 0.15007219
B60: SG&A | C60: =SUM(C52:C59) -> 2.3535028 | D60: =SUM(D52:D59) -> 2.5797556 | E60: =SUM(E52:E59) -> 2.382057 | F60: =SUM(F52:F59) -> 2.3232013 | G60: =SUM(G52:G59) -> 2.408639 | H60: =SUM(H52:H59) -> 2.5090059 | I60: =SUM(I52:I59) -> 2.9140323 | J60: =SUM(J52:J59) -> 3.2859051 | ... L60: =SUM(L52:L59) -> 4.1668388 | N60: =IFERROR(_xlfn.RRI(4,C60,G60),"-") -> 0.0058060663 | O60: =IFERROR(_xlfn.RRI(5,G60,L60),"-") -> 0.11585302
B61: % of Revenue | C61: =IFERROR(C60/C38,"-") -> 0.30143659 | D61: =IFERROR(D60/D38,"-") -> 0.27169717 | E61: =IFERROR(E60/E38,"-") -> 0.26248159 | F61: =IFERROR(F60/F38,"-") -> 0.22650472 | G61: =IFERROR(G60/G38,"-") -> 0.23996882 | H61: =IFERROR(H60/H38,"-") -> 0.23380164 | I61: =IFERROR(I60/I38,"-") -> 0.2295897 | J61: =IFERROR(J60/J38,"-") -> 0.22034764 | ... L61: =IFERROR(L60/L38,"-") -> 0.20064479
N62: =IFERROR(_xlfn.RRI(4,C62,G62),"-") -> 0 | O62: =IFERROR(_xlfn.RRI(5,G62,L62),"-") -> 0
B63: Adj. EBITDA | C63: =C47-C60 -> 4.4244498 | D63: =D47-D60 -> 5.7671053 | E63: =E47-E60 -> 5.4511109 | F63: =F47-F60 -> 6.7161582 | G63: =G47-G60 -> 6.4497506 | H63: =H47-H60 -> 7.0076809 | I63: =I47-I60 -> 8.3697241 | J63: =J47-J60 -> 9.9853983 | ... L63: =L47-L60 -> 14.322237 | N63: =IFERROR(_xlfn.RRI(4,C63,G63),"-") -> 0.09880572 | O63: =IFERROR(_xlfn.RRI(5,G63,L63),"-") -> 0.17298805
B64: % Margin | C64: =IFERROR(C63/C38,"-") -> 0.56668343 | D64: =IFERROR(D63/D38,"-") -> 0.60738551 | E64: =IFERROR(E63/E38,"-") -> 0.60066415 | F64: =IFERROR(F63/F38,"-") -> 0.65480401 | G64: =IFERROR(G63/G38,"-") -> 0.64257824 | H64: =IFERROR(H63/H38,"-") -> 0.65301054 | I64: =IFERROR(I63/I38,"-") -> 0.65943074 | J64: =IFERROR(J63/J38,"-") -> 0.66960515 | ... L64: =IFERROR(L63/L38,"-") -> 0.68965527
B65: % Margin (Excl. Marketing Fund) | C65: =C63/(C38-C34) -> 0.56668343 | D65: =D63/(D38-D34) -> 0.60738551 | E65: =E63/(E38-E34) -> 0.60066415 | F65: =F63/(F38-F34) -> 0.65480401 | G65: =G63/(G38-G34) -> 0.64257824 | H65: =H63/(H38-H34) -> 0.65301054 | I65: =I63/(I38-I34) -> 0.65943074 | J65: =J63/(J38-J34) -> 0.66960515 | ... L65: =L63/(L38-L34) -> 0.68965527
B67: Pro Forma Adjustment | G67: =('EBITDA Adjustment Detail'!G26+'EBITDA Adjustment Detail'!G27)/10^3 -> 0.48560671 | H67: ='2026 PF Adjustment Detail'!O151 -> 0.60238856 | I67: ='INTL Franchised Sales & Dev'!F16+'Sauce Economics Overview'!I66+'Sauce Economics Overview'!I87 -> 0.75287477 | J67: ='INTL Franchised Sales & Dev'!G16+'Sauce Economics Overview'!J66+'Sauce Economics Overview'!J87 -> 0.73694145 | K67: ='INTL Franchised Sales & Dev'!H16+'Sauce Economics Overview'!K66+'Sauce Economics Overview'!K87 -> 0.88080716 | L67: ='INTL Franchised Sales & Dev'!I16+'Sauce Economics Overview'!L66+'Sauce Economics Overview'!L87 -> 0.98117565 | N67: =IFERROR(_xlfn.RRI(4,C67,G67),"-") -> - | O67: =IFERROR(_xlfn.RRI(5,G67,L67),"-") -> 0.1510453
B68: PF Adj. EBITDA | G68: =G63+G67 -> 6.9353573 | H68: =H63+H67 -> 7.6100695 | I68: =I63+I67 -> 9.1225989 | J68: =J63+J67 -> 10.72234 | K68: =K63+K67 -> 13.099457 | L68: =L63+L67 -> 15.303413 | N68: =IFERROR(_xlfn.RRI(4,C68,G68),"-") -> - | O68: =IFERROR(_xlfn.RRI(5,G68,L68),"-") -> 0.17150431
B70: FX Rate | C70: 1144.42 | D70: 1291.95 | E70: 1305.41 | F70: 1363.98 | G70: 1422.22 | H70: 1420 | I70: 1400 | J70: 1400 | K70: 1400 | L70: 1400
B71: Constant FX | C71: =G70 -> 1422.22 | D71: =C71 -> 1422.22 | E71: =D71 -> 1422.22 | F71: =E71 -> 1422.22 | G71: =F71 -> 1422.22 | H71: =G71 -> 1422.22 | I71: =H71 -> 1422.22 | J71: =I71 -> 1422.22 | K71: =J71 -> 1422.22 | L71: =K71 -> 1422.22
B72: Memo: Adj. EBITDA (At Constant Currency) | C72: =C63*C70/C71 -> 3.560229 | D72: =D63*D70/D71 -> 5.2388601 | E72: =E63*E70/E71 -> 5.0033994 | F72: =F63*F70/F71 -> 6.4411311 | G72: =G63*G70/G71 -> 6.4497506 | H72: =H38-(H46+H60)*H70/H71 -> 7.0134934 | I72: =I38-(I46+I60)*I70/I71 -> 8.4372585 | J72: =J38-(J46+J60)*J70/J71 -> 10.062375 | K72: =K38-(K46+K60)*K70/K71 -> 12.307686 | L72: =L38-(L46+L60)*L70/L71 -> 14.42293 | N72: =IFERROR(_xlfn.RRI(4,C72,G72),"-") -> 0.16015562 | O72: =IFERROR(_xlfn.RRI(5,G72,L72),"-") -> 0.17463278
B74: Notes:
B75: Same store sales metrics exclude ultimately closed locations and geographies.
B76: Other Revenue and COGS includes franchisee training fees and other items sold to franchisees through legacy supply chain (i.e., kitchen supplies, packaging, etc.).
B77: Other SG&A includes utilities, insurance, research & development, taxes & dues, and other repair and maintenance expenses.
B78: Constant currency assumes 2025 KRW/USD exchange rate.

Sheet Consolidations P&L
B2: Consolidations Annual P&L
C4: Historical | H4: Projected
B5: ($ in millions) | C5: 2021 | D5: 2022 | E5: 2023 | F5: 2024 | G5: 2025A | H5: 2026E | I5: 2027P | J5: 2028P | K5: 2029P | L5: 2030P
B7: Franchise Revenue | C7: 0 | D7: 0 | E7: 0 | F7: 0 | G7: =SUM('Consolidations P&L (Monthly''25)'!C7:N7) -> 0 | H7: =SUM('Consolidations P&L (Monthly''26)'!C7:N7) -> 0 | I7: =SUM('Consolidations P&L (Monthly''26)'!D7:O7) -> 0 | J7: =SUM('Consolidations P&L (Monthly''26)'!E7:O7) -> 0 | K7: =SUM('Consolidations P&L (Monthly''26)'!F7:O7) -> 0 | L7: =SUM('Consolidations P&L (Monthly''26)'!G7:O7) -> 0
B8: Sauce Revenue | C8: 0 | D8: 0 | E8: 0 | F8: 0 | G8: =SUM('Consolidations P&L (Monthly''25)'!C8:N8) -> 0 | H8: =SUM('Consolidations P&L (Monthly''26)'!C8:N8) -> 0 | I8: =SUM('Consolidations P&L (Monthly''26)'!D8:O8) -> 0 | J8: =SUM('Consolidations P&L (Monthly''26)'!E8:O8) -> 0 | K8: =SUM('Consolidations P&L (Monthly''26)'!F8:O8) -> 0 | L8: =SUM('Consolidations P&L (Monthly''26)'!G8:O8) -> 0
B9: Company-Owned Store Revenue | C9: 0 | D9: 0 | E9: 0 | F9: 0 | G9: =SUM('Consolidations P&L (Monthly''25)'!C9:N9) -> 0 | H9: =SUM('Consolidations P&L (Monthly''26)'!C9:N9) -> 0 | I9: =SUM('Consolidations P&L (Monthly''26)'!D9:O9) -> 0 | J9: =SUM('Consolidations P&L (Monthly''26)'!E9:O9) -> 0 | K9: =SUM('Consolidations P&L (Monthly''26)'!F9:O9) -> 0 | L9: =SUM('Consolidations P&L (Monthly''26)'!G9:O9) -> 0
B10: Marketing Fund | C10: 0 | D10: 0 | E10: 0 | F10: 0 | G10: =SUM('Consolidations P&L (Monthly''25)'!C10:N10) -> 0 | H10: =SUM('Consolidations P&L (Monthly''26)'!C10:N10) -> 0 | I10: =SUM('Consolidations P&L (Monthly''26)'!D10:O10) -> 0 | J10: =SUM('Consolidations P&L (Monthly''26)'!E10:O10) -> 0 | K10: =SUM('Consolidations P&L (Monthly''26)'!F10:O10) -> 0 | L10: =SUM('Consolidations P&L (Monthly''26)'!G10:O10) -> 0
B11: Other Product Revenue | C11: 0.48957212 | D11: 0.09275444 | E11: 0.0084382838 | F11: 0.0082295781 | G11: =SUM('Consolidations P&L (Monthly''25)'!C11:N11) -> 0.0076781383 | H11: =SUM('Consolidations P&L (Monthly''26)'!C11:N11) -> 0 | I11: =SUM('Consolidations P&L (Monthly''26)'!D11:O11) -> 0 | J11: =SUM('Consolidations P&L (Monthly''26)'!E11:O11) -> 0 | K11: =SUM('Consolidations P&L (Monthly''26)'!F11:O11) -> 0 | L11: =SUM('Consolidations P&L (Monthly''26)'!G11:O11) -> 0
B12: Other Revenue | C12: 0.11329416 | D12: 0.11911519 | E12: 0.13006411 | F12: 0.12903044 | G12: =SUM('Consolidations P&L (Monthly''25)'!C12:N12) -> 0.097052309 | H12: =SUM('Consolidations P&L (Monthly''26)'!C12:N12) -> 0.1301371 | I12: 0.13664396 | J12: 0.14347615 | K12: 0.15064996 | L12: 0.15818246
B13: Other | C13: =C11+C12 -> 0.60286629 | D13: =D11+D12 -> 0.21186963 | E13: =E11+E12 -> 0.1385024 | F13: =F11+F12 -> 0.13726002 | G13: =G11+G12 -> 0.10473045 | H13: =H11+H12 -> 0.1301371 | I13: =I11+I12 -> 0.13664396 | J13: =J11+J12 -> 0.14347615 | ... L13: =L11+L12 -> 0.15818246
B14: Total Revenue | C14: =SUM(C7:C10,C13) -> 0.60286629 | D14: =SUM(D7:D10,D13) -> 0.21186963 | E14: =SUM(E7:E10,E13) -> 0.1385024 | F14: =SUM(F7:F10,F13) -> 0.13726002 | G14: =SUM(G7:G10,G13) -> 0.10473045 | H14: =SUM(H7:H10,H13) -> 0.1301371 | I14: =SUM(I7:I10,I13) -> 0.13664396 | J14: =SUM(J7:J10,J13) -> 0.14347615 | ... L14: =SUM(L7:L10,L13) -> 0.15818246
B15: % Growth
B17: Sauce COGS | C17: 0 | D17: 3.9968029e-15 | E17: 0.011146117 | F17: 0 | G17: =SUM('Consolidations P&L (Monthly''25)'!C16:N16) -> 0 | H17: =SUM('Consolidations P&L (Monthly''26)'!C16:N16) -> 0 | I17: =SUM('Consolidations P&L (Monthly''26)'!D16:O16) -> 0 | J17: =SUM('Consolidations P&L (Monthly''26)'!E16:O16) -> 0 | K17: =SUM('Consolidations P&L (Monthly''26)'!F16:O16) -> 0 | L17: =SUM('Consolidations P&L (Monthly''26)'!G16:O16) -> 0
B18: Company-Owned Store COGS | C18: 0 | D18: 0 | E18: 0 | F18: 0 | G18: =SUM('Consolidations P&L (Monthly''25)'!C17:N17) -> 0 | H18: =SUM('Consolidations P&L (Monthly''26)'!C17:N17) -> 0 | I18: =SUM('Consolidations P&L (Monthly''26)'!D17:O17) -> 0 | J18: =SUM('Consolidations P&L (Monthly''26)'!E17:O17) -> 0 | K18: =SUM('Consolidations P&L (Monthly''26)'!F17:O17) -> 0 | L18: =SUM('Consolidations P&L (Monthly''26)'!G17:O17) -> 0
B19: Other Product COGS | C19: 0.4320048 | D19: 0.15108238 | E19: 0.028589065 | F19: 0.0069850824 | G19: =SUM('Consolidations P&L (Monthly''25)'!C18:N18) -> 0.011600902 | H19: =SUM('Consolidations P&L (Monthly''26)'!C18:N18) -> 0.0021305507
B20: D&A In COGS | C20: 0 | D20: 0 | E20: 0 | F20: 0 | G20: =SUM('Consolidations P&L (Monthly''25)'!C19:N19) -> 0 | H20: =SUM('Consolidations P&L (Monthly''26)'!C19:N19) -> 0
B21: Other | C21: =SUM(C19:C20) -> 0.4320048 | D21: =SUM(D19:D20) -> 0.15108238 | E21: =SUM(E19:E20) -> 0.028589065 | F21: =SUM(F19:F20) -> 0.0069850824 | G21: =SUM(G19:G20) -> 0.011600902 | H21: =SUM(H19:H20) -> 0.0021305507 | I21: =SUM(I19:I20) -> 0 | J21: =SUM(J19:J20) -> 0 | ... L21: =SUM(L19:L20) -> 0
B22: Total Cost of Goods Sold | C22: =SUM(C17:C18,C21) -> 0.4320048 | D22: =SUM(D17:D18,D21) -> 0.15108238 | E22: =SUM(E17:E18,E21) -> 0.039735182 | F22: =SUM(F17:F18,F21) -> 0.0069850824 | G22: =SUM(G17:G18,G21) -> 0.011600902 | H22: =SUM(H17:H18,H21) -> 0.0021305507 | I22: =SUM(I17:I18,I21) -> 0 | J22: =SUM(J17:J18,J21) -> 0 | ... L22: =SUM(L17:L18,L21) -> 0
B23: Gross Profit | C23: =C14-C22 -> 0.17086149 | D23: =D14-D22 -> 0.06078725 | E23: =E14-E22 -> 0.098767216 | F23: =F14-F22 -> 0.13027494 | G23: =G14-G22 -> 0.093129545 | H23: =H14-H22 -> 0.12800655 | I23: =I14-I22 -> 0.13664396 | J23: =J14-J22 -> 0.14347615 | ... L23: =L14-L22 -> 0.15818246
B24: % Margin
B26: Corporate Labor | C26: 0 | D26: 0 | E26: 0 | F26: 0 | G26: =SUM('Consolidations P&L (Monthly''25)'!C27:N27) -> 0 | H26: =SUM('Consolidations P&L (Monthly''26)'!C27:N27) -> 0 | I26: =SUM('Consolidations P&L (Monthly''26)'!D27:O27) -> 0 | J26: =SUM('Consolidations P&L (Monthly''26)'!E27:O27) -> 0 | K26: =SUM('Consolidations P&L (Monthly''26)'!F27:O27) -> 0 | L26: =SUM('Consolidations P&L (Monthly''26)'!G27:O27) -> 0
B27: Company-Owned Store Labor | C27: 0 | D27: 0 | E27: 0 | F27: 0 | G27: =SUM('Consolidations P&L (Monthly''25)'!C28:N28) -> 0 | H27: =SUM('Consolidations P&L (Monthly''26)'!C28:N28) -> 0 | I27: =SUM('Consolidations P&L (Monthly''26)'!D28:O28) -> 0 | J27: =SUM('Consolidations P&L (Monthly''26)'!E28:O28) -> 0 | K27: =SUM('Consolidations P&L (Monthly''26)'!F28:O28) -> 0 | L27: =SUM('Consolidations P&L (Monthly''26)'!G28:O28) -> 0
B28: Total Labor | C28: =SUM(C26:C27) -> 0 | D28: =SUM(D26:D27) -> 0 | E28: =SUM(E26:E27) -> 0 | F28: =SUM(F26:F27) -> 0 | G28: =SUM(G26:G27) -> 0 | H28: =SUM(H26:H27) -> 0 | I28: =SUM(I26:I27) -> 0 | J28: =SUM(J26:J27) -> 0 | ... L28: =SUM(L26:L27) -> 0
B29: Marketing Fund Expense | C29: 0 | D29: 0 | E29: 0 | F29: 0 | G29: =SUM('Consolidations P&L (Monthly''25)'!C28:N28) -> 0 | H29: =SUM('Consolidations P&L (Monthly''26)'!C28:N28) -> 0 | I29: =SUM('Consolidations P&L (Monthly''26)'!D28:O28) -> 0 | J29: =SUM('Consolidations P&L (Monthly''26)'!E28:O28) -> 0 | K29: =SUM('Consolidations P&L (Monthly''26)'!F28:O28) -> 0 | L29: =SUM('Consolidations P&L (Monthly''26)'!G28:O28) -> 0
B30: Service Fees | C30: 0.11329416 | D30: 0.11911519 | E30: 0.13006411 | F30: 0.12903044 | G30: =SUM('Consolidations P&L (Monthly''25)'!C29:N29) -> 0.097052309 | H30: =SUM('Consolidations P&L (Monthly''26)'!C29:N29) -> 0.1301371 | I30: 0.13664396 | J30: 0.14347615 | K30: 0.15064996 | L30: 0.15818246
B31: Travel & Entertainment | C31: 0 | D31: 0 | E31: 0 | F31: 0 | G31: =SUM('Consolidations P&L (Monthly''25)'!C30:N30) -> 0 | H31: =SUM('Consolidations P&L (Monthly''26)'!C30:N30) -> 0 | I31: =SUM('Consolidations P&L (Monthly''26)'!D30:O30) -> 0 | J31: =SUM('Consolidations P&L (Monthly''26)'!E30:O30) -> 0 | K31: =SUM('Consolidations P&L (Monthly''26)'!F30:O30) -> 0 | L31: =SUM('Consolidations P&L (Monthly''26)'!G30:O30) -> 0
B32: Rent | C32: 0 | D32: 0 | E32: 0 | F32: 0 | G32: =SUM('Consolidations P&L (Monthly''25)'!C31:N31) -> 0 | H32: =SUM('Consolidations P&L (Monthly''26)'!C31:N31) -> 0 | I32: =SUM('Consolidations P&L (Monthly''26)'!D31:O31) -> 0 | J32: =SUM('Consolidations P&L (Monthly''26)'!E31:O31) -> 0 | K32: =SUM('Consolidations P&L (Monthly''26)'!F31:O31) -> 0 | L32: =SUM('Consolidations P&L (Monthly''26)'!G31:O31) -> 0
B33: Freight | C33: 0 | D33: 0 | E33: 0 | F33: 0 | G33: =SUM('Consolidations P&L (Monthly''25)'!C32:N32) -> 0 | H33: =SUM('Consolidations P&L (Monthly''26)'!C32:N32) -> 0 | I33: =SUM('Consolidations P&L (Monthly''26)'!D32:O32) -> 0 | J33: =SUM('Consolidations P&L (Monthly''26)'!E32:O32) -> 0 | K33: =SUM('Consolidations P&L (Monthly''26)'!F32:O32) -> 0 | L33: =SUM('Consolidations P&L (Monthly''26)'!G32:O32) -> 0
B34: Advertising Expense | C34: 0 | D34: 0 | E34: 0 | F34: 0 | G34: =SUM('Consolidations P&L (Monthly''25)'!C33:N33) -> 0 | H34: =SUM('Consolidations P&L (Monthly''26)'!C33:N33) -> 0 | I34: =SUM('Consolidations P&L (Monthly''26)'!D33:O33) -> 0 | J34: =SUM('Consolidations P&L (Monthly''26)'!E33:O33) -> 0 | K34: =SUM('Consolidations P&L (Monthly''26)'!F33:O33) -> 0 | L34: =SUM('Consolidations P&L (Monthly''26)'!G33:O33) -> 0
B35: Other | C35: 0 | D35: 0 | E35: 0 | F35: 0 | G35: =SUM('Consolidations P&L (Monthly''25)'!C34:N34) -> 0 | H35: =SUM('Consolidations P&L (Monthly''26)'!C34:N34) -> 0 | I35: =SUM('Consolidations P&L (Monthly''26)'!D34:O34) -> 0 | J35: =SUM('Consolidations P&L (Monthly''26)'!E34:O34) -> 0 | K35: =SUM('Consolidations P&L (Monthly''26)'!F34:O34) -> 0 | L35: =SUM('Consolidations P&L (Monthly''26)'!G34:O34) -> 0
B36: SG&A | C36: =SUM(C28:C35) -> 0.11329416 | D36: =SUM(D28:D35) -> 0.11911519 | E36: =SUM(E28:E35) -> 0.13006411 | F36: =SUM(F28:F35) -> 0.12903044 | G36: =SUM(G28:G35) -> 0.097052309 | H36: =SUM(H28:H35) -> 0.1301371 | I36: =SUM(I28:I35) -> 0.13664396 | J36: =SUM(J28:J35) -> 0.14347615 | ... L36: =SUM(L28:L35) -> 0.15818246
B37: % of Revenue
B39: Adj. EBITDA | C39: =C23-C36 -> 0.057567327 | D39: =D23-D36 -> -0.05832794 | E39: =E23-E36 -> -0.031296898 | F39: =F23-F36 -> 0.0012444957 | G39: =G23-G36 -> -0.0039227642 | H39: =H23-H36 -> -0.0021305507 | I39: =I23-I36 -> 0 | J39: =J23-J36 -> 0 | ... L39: =L23-L36 -> 0
B40: % Margin
B42: Pro Forma Adjustment
B43: PF Adj. EBITDA | C43: =C39+C42 -> 0.057567327 | D43: =D39+D42 -> -0.05832794 | E43: =E39+E42 -> -0.031296898 | F43: =F39+F42 -> 0.0012444957 | G43: =G39+G42 -> -0.0039227642 | H43: =H39+H42 -> -0.0021305507 | I43: =I39+I42 -> 0 | J43: =J39+J42 -> 0 | ... L43: =L39+L42 -> 0

Sheet 2025 Monthly P&Ls>>

Sheet Consolidated P&L (Monthly'25)
B2: Bonchon Consolidated 2025 Monthly P&L
C4: Historical
B5: ($ in millions) | C5: 45688 | D5: =EOMONTH(C5,1) -> 45716 | E5: =EOMONTH(D5,1) -> 45747 | F5: =EOMONTH(E5,1) -> 45777 | G5: =EOMONTH(F5,1) -> 45808 | H5: =EOMONTH(G5,1) -> 45838 | I5: =EOMONTH(H5,1) -> 45869 | J5: =EOMONTH(I5,1) -> 45900 | K5: =EOMONTH(J5,1) -> 45930 | ... N5: =EOMONTH(M5,1) -> 46022
B7: Franchise Revenue | C7: ='Bonchon U.S. P&L (Monthly''25)'!C7+'Bonchon Int''l P&L (Monthly''25)'!C7-'Consolidations P&L (Monthly''25)'!C7 -> 1.1756963 | D7: ='Bonchon U.S. P&L (Monthly''25)'!D7+'Bonchon Int''l P&L (Monthly''25)'!D7-'Consolidations P&L (Monthly''25)'!D7 -> 1.1164127 | E7: ='Bonchon U.S. P&L (Monthly''25)'!E7+'Bonchon Int''l P&L (Monthly''25)'!E7-'Consolidations P&L (Monthly''25)'!E7 -> 1.2671563 | F7: ='Bonchon U.S. P&L (Monthly''25)'!F7+'Bonchon Int''l P&L (Monthly''25)'!F7-'Consolidations P&L (Monthly''25)'!F7 -> 1.2127964 | G7: ='Bonchon U.S. P&L (Monthly''25)'!G7+'Bonchon Int''l P&L (Monthly''25)'!G7-'Consolidations P&L (Monthly''25)'!G7 -> 1.3223264 | H7: ='Bonchon U.S. P&L (Monthly''25)'!H7+'Bonchon Int''l P&L (Monthly''25)'!H7-'Consolidations P&L (Monthly''25)'!H7 -> 1.2396562 | I7: ='Bonchon U.S. P&L (Monthly''25)'!I7+'Bonchon Int''l P&L (Monthly''25)'!I7-'Consolidations P&L (Monthly''25)'!I7 -> 1.2860267 | J7: ='Bonchon U.S. P&L (Monthly''25)'!J7+'Bonchon Int''l P&L (Monthly''25)'!J7-'Consolidations P&L (Monthly''25)'!J7 -> 1.3194452 | ... N7: ='Bonchon U.S. P&L (Monthly''25)'!N7+'Bonchon Int''l P&L (Monthly''25)'!N7-'Consolidations P&L (Monthly''25)'!N7 -> 1.3548915
B8: Sauce Revenue | C8: ='Bonchon U.S. P&L (Monthly''25)'!C8+'Bonchon Int''l P&L (Monthly''25)'!C8-'Consolidations P&L (Monthly''25)'!C8 -> 0.88153904 | D8: ='Bonchon U.S. P&L (Monthly''25)'!D8+'Bonchon Int''l P&L (Monthly''25)'!D8-'Consolidations P&L (Monthly''25)'!D8 -> 0.74131437 | E8: ='Bonchon U.S. P&L (Monthly''25)'!E8+'Bonchon Int''l P&L (Monthly''25)'!E8-'Consolidations P&L (Monthly''25)'!E8 -> 0.59760531 | F8: ='Bonchon U.S. P&L (Monthly''25)'!F8+'Bonchon Int''l P&L (Monthly''25)'!F8-'Consolidations P&L (Monthly''25)'!F8 -> 0.87546165 | G8: ='Bonchon U.S. P&L (Monthly''25)'!G8+'Bonchon Int''l P&L (Monthly''25)'!G8-'Consolidations P&L (Monthly''25)'!G8 -> 0.67304158 | H8: ='Bonchon U.S. P&L (Monthly''25)'!H8+'Bonchon Int''l P&L (Monthly''25)'!H8-'Consolidations P&L (Monthly''25)'!H8 -> 0.57837226 | I8: ='Bonchon U.S. P&L (Monthly''25)'!I8+'Bonchon Int''l P&L (Monthly''25)'!I8-'Consolidations P&L (Monthly''25)'!I8 -> 0.80074364 | J8: ='Bonchon U.S. P&L (Monthly''25)'!J8+'Bonchon Int''l P&L (Monthly''25)'!J8-'Consolidations P&L (Monthly''25)'!J8 -> 0.35228889 | ... N8: ='Bonchon U.S. P&L (Monthly''25)'!N8+'Bonchon Int''l P&L (Monthly''25)'!N8-'Consolidations P&L (Monthly''25)'!N8 -> 0.39162061
B9: Company-Owned Store Revenue | C9: ='Bonchon U.S. P&L (Monthly''25)'!C9+'Bonchon Int''l P&L (Monthly''25)'!C9-'Consolidations P&L (Monthly''25)'!C9 -> 0.27662877 | D9: ='Bonchon U.S. P&L (Monthly''25)'!D9+'Bonchon Int''l P&L (Monthly''25)'!D9-'Consolidations P&L (Monthly''25)'!D9 -> 0.26859163 | E9: ='Bonchon U.S. P&L (Monthly''25)'!E9+'Bonchon Int''l P&L (Monthly''25)'!E9-'Consolidations P&L (Monthly''25)'!E9 -> 0.29818624 | F9: ='Bonchon U.S. P&L (Monthly''25)'!F9+'Bonchon Int''l P&L (Monthly''25)'!F9-'Consolidations P&L (Monthly''25)'!F9 -> 0.30736304 | G9: ='Bonchon U.S. P&L (Monthly''25)'!G9+'Bonchon Int''l P&L (Monthly''25)'!G9-'Consolidations P&L (Monthly''25)'!G9 -> 0.32976541 | H9: ='Bonchon U.S. P&L (Monthly''25)'!H9+'Bonchon Int''l P&L (Monthly''25)'!H9-'Consolidations P&L (Monthly''25)'!H9 -> 0.28344493 | I9: ='Bonchon U.S. P&L (Monthly''25)'!I9+'Bonchon Int''l P&L (Monthly''25)'!I9-'Consolidations P&L (Monthly''25)'!I9 -> 0.29538173 | J9: ='Bonchon U.S. P&L (Monthly''25)'!J9+'Bonchon Int''l P&L (Monthly''25)'!J9-'Consolidations P&L (Monthly''25)'!J9 -> 0.34740922 | ... N9: ='Bonchon U.S. P&L (Monthly''25)'!N9+'Bonchon Int''l P&L (Monthly''25)'!N9-'Consolidations P&L (Monthly''25)'!N9 -> 0.34941774
B10: Marketing Fund | C10: ='Bonchon U.S. P&L (Monthly''25)'!C10+'Bonchon Int''l P&L (Monthly''25)'!C10-'Consolidations P&L (Monthly''25)'!C10 -> 0.25040226 | D10: ='Bonchon U.S. P&L (Monthly''25)'!D10+'Bonchon Int''l P&L (Monthly''25)'!D10-'Consolidations P&L (Monthly''25)'!D10 -> 0.23089278 | E10: ='Bonchon U.S. P&L (Monthly''25)'!E10+'Bonchon Int''l P&L (Monthly''25)'!E10-'Consolidations P&L (Monthly''25)'!E10 -> 0.25462936 | F10: ='Bonchon U.S. P&L (Monthly''25)'!F10+'Bonchon Int''l P&L (Monthly''25)'!F10-'Consolidations P&L (Monthly''25)'!F10 -> 0.28966546 | G10: ='Bonchon U.S. P&L (Monthly''25)'!G10+'Bonchon Int''l P&L (Monthly''25)'!G10-'Consolidations P&L (Monthly''25)'!G10 -> 0.26946647 | H10: ='Bonchon U.S. P&L (Monthly''25)'!H10+'Bonchon Int''l P&L (Monthly''25)'!H10-'Consolidations P&L (Monthly''25)'!H10 -> 0.25958082 | I10: ='Bonchon U.S. P&L (Monthly''25)'!I10+'Bonchon Int''l P&L (Monthly''25)'!I10-'Consolidations P&L (Monthly''25)'!I10 -> 0.26904213 | J10: ='Bonchon U.S. P&L (Monthly''25)'!J10+'Bonchon Int''l P&L (Monthly''25)'!J10-'Consolidations P&L (Monthly''25)'!J10 -> 0.27583441 | ... N10: ='Bonchon U.S. P&L (Monthly''25)'!N10+'Bonchon Int''l P&L (Monthly''25)'!N10-'Consolidations P&L (Monthly''25)'!N10 -> 0.27951482
B11: Other Product Revenue | C11: ='Bonchon U.S. P&L (Monthly''25)'!C11+'Bonchon Int''l P&L (Monthly''25)'!C11-'Consolidations P&L (Monthly''25)'!C11 -> 0.00091032 | D11: ='Bonchon U.S. P&L (Monthly''25)'!D11+'Bonchon Int''l P&L (Monthly''25)'!D11-'Consolidations P&L (Monthly''25)'!D11 -> 0.0021538135 | E11: ='Bonchon U.S. P&L (Monthly''25)'!E11+'Bonchon Int''l P&L (Monthly''25)'!E11-'Consolidations P&L (Monthly''25)'!E11 -> -0.00070824209 | F11: ='Bonchon U.S. P&L (Monthly''25)'!F11+'Bonchon Int''l P&L (Monthly''25)'!F11-'Consolidations P&L (Monthly''25)'!F11 -> 0.0078047426 | G11: ='Bonchon U.S. P&L (Monthly''25)'!G11+'Bonchon Int''l P&L (Monthly''25)'!G11-'Consolidations P&L (Monthly''25)'!G11 -> 0.0047060043 | H11: ='Bonchon U.S. P&L (Monthly''25)'!H11+'Bonchon Int''l P&L (Monthly''25)'!H11-'Consolidations P&L (Monthly''25)'!H11 -> 0.0035804387 | I11: ='Bonchon U.S. P&L (Monthly''25)'!I11+'Bonchon Int''l P&L (Monthly''25)'!I11-'Consolidations P&L (Monthly''25)'!I11 -> 0.0024587544 | J11: ='Bonchon U.S. P&L (Monthly''25)'!J11+'Bonchon Int''l P&L (Monthly''25)'!J11-'Consolidations P&L (Monthly''25)'!J11 -> 0.0033635107 | ... N11: ='Bonchon U.S. P&L (Monthly''25)'!N11+'Bonchon Int''l P&L (Monthly''25)'!N11-'Consolidations P&L (Monthly''25)'!N11 -> -0.0026606573
B12: Other Revenue | C12: ='Bonchon U.S. P&L (Monthly''25)'!C12+'Bonchon Int''l P&L (Monthly''25)'!C12-'Consolidations P&L (Monthly''25)'!C12 -> 0.00839232 | D12: ='Bonchon U.S. P&L (Monthly''25)'!D12+'Bonchon Int''l P&L (Monthly''25)'!D12-'Consolidations P&L (Monthly''25)'!D12 -> 0.0146508 | E12: ='Bonchon U.S. P&L (Monthly''25)'!E12+'Bonchon Int''l P&L (Monthly''25)'!E12-'Consolidations P&L (Monthly''25)'!E12 -> 0.01376495 | F12: ='Bonchon U.S. P&L (Monthly''25)'!F12+'Bonchon Int''l P&L (Monthly''25)'!F12-'Consolidations P&L (Monthly''25)'!F12 -> 0.00719265 | G12: ='Bonchon U.S. P&L (Monthly''25)'!G12+'Bonchon Int''l P&L (Monthly''25)'!G12-'Consolidations P&L (Monthly''25)'!G12 -> 0.05088173 | H12: ='Bonchon U.S. P&L (Monthly''25)'!H12+'Bonchon Int''l P&L (Monthly''25)'!H12-'Consolidations P&L (Monthly''25)'!H12 -> 0.01391394 | I12: ='Bonchon U.S. P&L (Monthly''25)'!I12+'Bonchon Int''l P&L (Monthly''25)'!I12-'Consolidations P&L (Monthly''25)'!I12 -> 0.00220506 | J12: ='Bonchon U.S. P&L (Monthly''25)'!J12+'Bonchon Int''l P&L (Monthly''25)'!J12-'Consolidations P&L (Monthly''25)'!J12 -> 0.00418672 | ... N12: ='Bonchon U.S. P&L (Monthly''25)'!N12+'Bonchon Int''l P&L (Monthly''25)'!N12-'Consolidations P&L (Monthly''25)'!N12 -> 0.00192864
B13: Other | C13: =SUM(C11:C12) -> 0.00930264 | D13: =SUM(D11:D12) -> 0.016804613 | E13: =SUM(E11:E12) -> 0.013056708 | F13: =SUM(F11:F12) -> 0.014997393 | G13: =SUM(G11:G12) -> 0.055587734 | H13: =SUM(H11:H12) -> 0.017494379 | I13: =SUM(I11:I12) -> 0.0046638144 | J13: =SUM(J11:J12) -> 0.0075502307 | ... N13: =SUM(N11:N12) -> -0.00073201725
B14: Total Revenue | C14: =SUM(C7:C10,C13) -> 2.593569 | D14: =SUM(D7:D10,D13) -> 2.3740161 | E14: =SUM(E7:E10,E13) -> 2.4306339 | F14: =SUM(F7:F10,F13) -> 2.7002839 | G14: =SUM(G7:G10,G13) -> 2.6501876 | H14: =SUM(H7:H10,H13) -> 2.3785486 | I14: =SUM(I7:I10,I13) -> 2.655858 | J14: =SUM(J7:J10,J13) -> 2.302528 | ... N14: =SUM(N7:N10,N13) -> 2.3747127
B16: Sauce COGS | C16: ='Bonchon U.S. P&L (Monthly''25)'!C16+'Bonchon Int''l P&L (Monthly''25)'!C16-'Consolidations P&L (Monthly''25)'!C16 -> 0.16254555 | D16: ='Bonchon U.S. P&L (Monthly''25)'!D16+'Bonchon Int''l P&L (Monthly''25)'!D16-'Consolidations P&L (Monthly''25)'!D16 -> 0.1291191 | E16: ='Bonchon U.S. P&L (Monthly''25)'!E16+'Bonchon Int''l P&L (Monthly''25)'!E16-'Consolidations P&L (Monthly''25)'!E16 -> 0.089057522 | F16: ='Bonchon U.S. P&L (Monthly''25)'!F16+'Bonchon Int''l P&L (Monthly''25)'!F16-'Consolidations P&L (Monthly''25)'!F16 -> 0.15129305 | G16: ='Bonchon U.S. P&L (Monthly''25)'!G16+'Bonchon Int''l P&L (Monthly''25)'!G16-'Consolidations P&L (Monthly''25)'!G16 -> 0.11224335 | H16: ='Bonchon U.S. P&L (Monthly''25)'!H16+'Bonchon Int''l P&L (Monthly''25)'!H16-'Consolidations P&L (Monthly''25)'!H16 -> 0.096840546 | I16: ='Bonchon U.S. P&L (Monthly''25)'!I16+'Bonchon Int''l P&L (Monthly''25)'!I16-'Consolidations P&L (Monthly''25)'!I16 -> 0.14356097 | J16: ='Bonchon U.S. P&L (Monthly''25)'!J16+'Bonchon Int''l P&L (Monthly''25)'!J16-'Consolidations P&L (Monthly''25)'!J16 -> 0.045964943 | ... N16: ='Bonchon U.S. P&L (Monthly''25)'!N16+'Bonchon Int''l P&L (Monthly''25)'!N16-'Consolidations P&L (Monthly''25)'!N16 -> 0.10674445
B17: Company-Owned Store COGS | C17: ='Bonchon U.S. P&L (Monthly''25)'!C17+'Bonchon Int''l P&L (Monthly''25)'!C17-'Consolidations P&L (Monthly''25)'!C17 -> 0.08514469 | D17: ='Bonchon U.S. P&L (Monthly''25)'!D17+'Bonchon Int''l P&L (Monthly''25)'!D17-'Consolidations P&L (Monthly''25)'!D17 -> 0.08347054 | E17: ='Bonchon U.S. P&L (Monthly''25)'!E17+'Bonchon Int''l P&L (Monthly''25)'!E17-'Consolidations P&L (Monthly''25)'!E17 -> 0.09041345 | F17: ='Bonchon U.S. P&L (Monthly''25)'!F17+'Bonchon Int''l P&L (Monthly''25)'!F17-'Consolidations P&L (Monthly''25)'!F17 -> 0.09148361 | G17: ='Bonchon U.S. P&L (Monthly''25)'!G17+'Bonchon Int''l P&L (Monthly''25)'!G17-'Consolidations P&L (Monthly''25)'!G17 -> 0.09486322 | H17: ='Bonchon U.S. P&L (Monthly''25)'!H17+'Bonchon Int''l P&L (Monthly''25)'!H17-'Consolidations P&L (Monthly''25)'!H17 -> 0.07775556 | I17: ='Bonchon U.S. P&L (Monthly''25)'!I17+'Bonchon Int''l P&L (Monthly''25)'!I17-'Consolidations P&L (Monthly''25)'!I17 -> 0.08551146 | J17: ='Bonchon U.S. P&L (Monthly''25)'!J17+'Bonchon Int''l P&L (Monthly''25)'!J17-'Consolidations P&L (Monthly''25)'!J17 -> 0.10422529 | ... N17: ='Bonchon U.S. P&L (Monthly''25)'!N17+'Bonchon Int''l P&L (Monthly''25)'!N17-'Consolidations P&L (Monthly''25)'!N17 -> 0.09283688
B18: Other Product COGS | C18: ='Bonchon U.S. P&L (Monthly''25)'!C18+'Bonchon Int''l P&L (Monthly''25)'!C18-'Consolidations P&L (Monthly''25)'!C18 -> 0.00026452809 | D18: ='Bonchon U.S. P&L (Monthly''25)'!D18+'Bonchon Int''l P&L (Monthly''25)'!D18-'Consolidations P&L (Monthly''25)'!D18 -> 0.0019455745 | E18: ='Bonchon U.S. P&L (Monthly''25)'!E18+'Bonchon Int''l P&L (Monthly''25)'!E18-'Consolidations P&L (Monthly''25)'!E18 -> 0.00077268892 | F18: ='Bonchon U.S. P&L (Monthly''25)'!F18+'Bonchon Int''l P&L (Monthly''25)'!F18-'Consolidations P&L (Monthly''25)'!F18 -> 0.0064887781 | G18: ='Bonchon U.S. P&L (Monthly''25)'!G18+'Bonchon Int''l P&L (Monthly''25)'!G18-'Consolidations P&L (Monthly''25)'!G18 -> -0.00088509548 | H18: ='Bonchon U.S. P&L (Monthly''25)'!H18+'Bonchon Int''l P&L (Monthly''25)'!H18-'Consolidations P&L (Monthly''25)'!H18 -> 0.0056019837 | I18: ='Bonchon U.S. P&L (Monthly''25)'!I18+'Bonchon Int''l P&L (Monthly''25)'!I18-'Consolidations P&L (Monthly''25)'!I18 -> 0.0042607386 | J18: ='Bonchon U.S. P&L (Monthly''25)'!J18+'Bonchon Int''l P&L (Monthly''25)'!J18-'Consolidations P&L (Monthly''25)'!J18 -> 0.003590667 | ... N18: ='Bonchon U.S. P&L (Monthly''25)'!N18+'Bonchon Int''l P&L (Monthly''25)'!N18-'Consolidations P&L (Monthly''25)'!N18 -> 0.0016808108
B19: D&A In COGS | C19: ='Bonchon U.S. P&L (Monthly''25)'!C19+'Bonchon Int''l P&L (Monthly''25)'!C19-'Consolidations P&L (Monthly''25)'!C19 -> -0.011663985 | D19: ='Bonchon U.S. P&L (Monthly''25)'!D19+'Bonchon Int''l P&L (Monthly''25)'!D19-'Consolidations P&L (Monthly''25)'!D19 -> -0.011750515 | E19: ='Bonchon U.S. P&L (Monthly''25)'!E19+'Bonchon Int''l P&L (Monthly''25)'!E19-'Consolidations P&L (Monthly''25)'!E19 -> -0.011652854 | F19: ='Bonchon U.S. P&L (Monthly''25)'!F19+'Bonchon Int''l P&L (Monthly''25)'!F19-'Consolidations P&L (Monthly''25)'!F19 -> -0.011762941 | G19: ='Bonchon U.S. P&L (Monthly''25)'!G19+'Bonchon Int''l P&L (Monthly''25)'!G19-'Consolidations P&L (Monthly''25)'!G19 -> -0.012143871 | H19: ='Bonchon U.S. P&L (Monthly''25)'!H19+'Bonchon Int''l P&L (Monthly''25)'!H19-'Consolidations P&L (Monthly''25)'!H19 -> -0.012374686 | I19: ='Bonchon U.S. P&L (Monthly''25)'!I19+'Bonchon Int''l P&L (Monthly''25)'!I19-'Consolidations P&L (Monthly''25)'!I19 -> -0.012642496 | J19: ='Bonchon U.S. P&L (Monthly''25)'!J19+'Bonchon Int''l P&L (Monthly''25)'!J19-'Consolidations P&L (Monthly''25)'!J19 -> -0.012511127 | ... N19: ='Bonchon U.S. P&L (Monthly''25)'!N19+'Bonchon Int''l P&L (Monthly''25)'!N19-'Consolidations P&L (Monthly''25)'!N19 -> -0.011789288
B20: Other | C20: =SUM(C18:C19) -> -0.011399457 | D20: =SUM(D18:D19) -> -0.0098049404 | E20: =SUM(E18:E19) -> -0.010880165 | F20: =SUM(F18:F19) -> -0.0052741626 | G20: =SUM(G18:G19) -> -0.013028966 | H20: =SUM(H18:H19) -> -0.0067727027 | I20: =SUM(I18:I19) -> -0.0083817579 | J20: =SUM(J18:J19) -> -0.0089204602 | ... N20: =SUM(N18:N19) -> -0.010108477
B21: Total Cost of Goods Sold | C21: =SUM(C16:C17,C20) -> 0.23629078 | D21: =SUM(D16:D17,D20) -> 0.2027847 | E21: =SUM(E16:E17,E20) -> 0.16859081 | F21: =SUM(F16:F17,F20) -> 0.23750249 | G21: =SUM(G16:G17,G20) -> 0.1940776 | H21: =SUM(H16:H17,H20) -> 0.1678234 | I21: =SUM(I16:I17,I20) -> 0.22069067 | J21: =SUM(J16:J17,J20) -> 0.14126977 | ... N21: =SUM(N16:N17,N20) -> 0.18947285
B22: Gross Profit | C22: =C14-C21 -> 2.3572783 | D22: =D14-D21 -> 2.1712314 | E22: =E14-E21 -> 2.2620431 | F22: =F14-F21 -> 2.4627814 | G22: =G14-G21 -> 2.45611 | H22: =H14-H21 -> 2.2107252 | I22: =I14-I21 -> 2.4351674 | J22: =J14-J21 -> 2.1612582 | ... N22: =N14-N21 -> 2.1852398
B23: % Margin | C23: =IFERROR(C22/C14,"-") -> 0.90889358 | D23: =IFERROR(D22/D14,"-") -> 0.91458158 | E23: =IFERROR(E22/E14,"-") -> 0.93063916 | F23: =IFERROR(F22/F14,"-") -> 0.91204536 | G23: =IFERROR(G22/G14,"-") -> 0.92676836 | H23: =IFERROR(H22/H14,"-") -> 0.92944294 | I23: =IFERROR(I22/I14,"-") -> 0.91690419 | J23: =IFERROR(J22/J14,"-") -> 0.93864579 | ... N23: =IFERROR(N22/N14,"-") -> 0.92021231
B25: Corporate Labor | C25: ='Bonchon U.S. P&L (Monthly''25)'!C25+'Bonchon Int''l P&L (Monthly''25)'!C25-'Consolidations P&L (Monthly''25)'!C25 -> 0.59749339 | D25: ='Bonchon U.S. P&L (Monthly''25)'!D25+'Bonchon Int''l P&L (Monthly''25)'!D25-'Consolidations P&L (Monthly''25)'!D25 -> 0.60048508 | E25: ='Bonchon U.S. P&L (Monthly''25)'!E25+'Bonchon Int''l P&L (Monthly''25)'!E25-'Consolidations P&L (Monthly''25)'!E25 -> 0.55080095 | F25: ='Bonchon U.S. P&L (Monthly''25)'!F25+'Bonchon Int''l P&L (Monthly''25)'!F25-'Consolidations P&L (Monthly''25)'!F25 -> 0.6085378 | G25: ='Bonchon U.S. P&L (Monthly''25)'!G25+'Bonchon Int''l P&L (Monthly''25)'!G25-'Consolidations P&L (Monthly''25)'!G25 -> 0.60618652 | H25: ='Bonchon U.S. P&L (Monthly''25)'!H25+'Bonchon Int''l P&L (Monthly''25)'!H25-'Consolidations P&L (Monthly''25)'!H25 -> 0.58023829 | I25: ='Bonchon U.S. P&L (Monthly''25)'!I25+'Bonchon Int''l P&L (Monthly''25)'!I25-'Consolidations P&L (Monthly''25)'!I25 -> 0.57023305 | J25: ='Bonchon U.S. P&L (Monthly''25)'!J25+'Bonchon Int''l P&L (Monthly''25)'!J25-'Consolidations P&L (Monthly''25)'!J25 -> 0.52127854 | ... N25: ='Bonchon U.S. P&L (Monthly''25)'!N25+'Bonchon Int''l P&L (Monthly''25)'!N25-'Consolidations P&L (Monthly''25)'!N25 -> 0.58750482
B26: Company-Owned Store Labor | C26: ='Bonchon U.S. P&L (Monthly''25)'!C26+'Bonchon Int''l P&L (Monthly''25)'!C26-'Consolidations P&L (Monthly''25)'!C26 -> 0.11461161 | D26: ='Bonchon U.S. P&L (Monthly''25)'!D26+'Bonchon Int''l P&L (Monthly''25)'!D26-'Consolidations P&L (Monthly''25)'!D26 -> 0.10637966 | E26: ='Bonchon U.S. P&L (Monthly''25)'!E26+'Bonchon Int''l P&L (Monthly''25)'!E26-'Consolidations P&L (Monthly''25)'!E26 -> 0.10328765 | F26: ='Bonchon U.S. P&L (Monthly''25)'!F26+'Bonchon Int''l P&L (Monthly''25)'!F26-'Consolidations P&L (Monthly''25)'!F26 -> 0.10334307 | G26: ='Bonchon U.S. P&L (Monthly''25)'!G26+'Bonchon Int''l P&L (Monthly''25)'!G26-'Consolidations P&L (Monthly''25)'!G26 -> 0.10714182 | H26: ='Bonchon U.S. P&L (Monthly''25)'!H26+'Bonchon Int''l P&L (Monthly''25)'!H26-'Consolidations P&L (Monthly''25)'!H26 -> 0.09523406 | I26: ='Bonchon U.S. P&L (Monthly''25)'!I26+'Bonchon Int''l P&L (Monthly''25)'!I26-'Consolidations P&L (Monthly''25)'!I26 -> 0.09905268 | J26: ='Bonchon U.S. P&L (Monthly''25)'!J26+'Bonchon Int''l P&L (Monthly''25)'!J26-'Consolidations P&L (Monthly''25)'!J26 -> 0.10807474 | ... N26: ='Bonchon U.S. P&L (Monthly''25)'!N26+'Bonchon Int''l P&L (Monthly''25)'!N26-'Consolidations P&L (Monthly''25)'!N26 -> 0.09876501
B27: Total Labor | C27: =SUM(C25:C26) -> 0.712105 | D27: =SUM(D25:D26) -> 0.70686474 | E27: =SUM(E25:E26) -> 0.6540886 | F27: =SUM(F25:F26) -> 0.71188087 | G27: =SUM(G25:G26) -> 0.71332834 | H27: =SUM(H25:H26) -> 0.67547235 | I27: =SUM(I25:I26) -> 0.66928573 | J27: =SUM(J25:J26) -> 0.62935328 | ... N27: =SUM(N25:N26) -> 0.68626983
B28: Marketing Fund | C28: ='Bonchon U.S. P&L (Monthly''25)'!C28+'Bonchon Int''l P&L (Monthly''25)'!C28-'Consolidations P&L (Monthly''25)'!C28 -> 0.25040226 | D28: ='Bonchon U.S. P&L (Monthly''25)'!D28+'Bonchon Int''l P&L (Monthly''25)'!D28-'Consolidations P&L (Monthly''25)'!D28 -> 0.23089278 | E28: ='Bonchon U.S. P&L (Monthly''25)'!E28+'Bonchon Int''l P&L (Monthly''25)'!E28-'Consolidations P&L (Monthly''25)'!E28 -> 0.25462936 | F28: ='Bonchon U.S. P&L (Monthly''25)'!F28+'Bonchon Int''l P&L (Monthly''25)'!F28-'Consolidations P&L (Monthly''25)'!F28 -> 0.28966546 | G28: ='Bonchon U.S. P&L (Monthly''25)'!G28+'Bonchon Int''l P&L (Monthly''25)'!G28-'Consolidations P&L (Monthly''25)'!G28 -> 0.26946647 | H28: ='Bonchon U.S. P&L (Monthly''25)'!H28+'Bonchon Int''l P&L (Monthly''25)'!H28-'Consolidations P&L (Monthly''25)'!H28 -> 0.25958082 | I28: ='Bonchon U.S. P&L (Monthly''25)'!I28+'Bonchon Int''l P&L (Monthly''25)'!I28-'Consolidations P&L (Monthly''25)'!I28 -> 0.26904213 | J28: ='Bonchon U.S. P&L (Monthly''25)'!J28+'Bonchon Int''l P&L (Monthly''25)'!J28-'Consolidations P&L (Monthly''25)'!J28 -> 0.27583441 | ... N28: ='Bonchon U.S. P&L (Monthly''25)'!N28+'Bonchon Int''l P&L (Monthly''25)'!N28-'Consolidations P&L (Monthly''25)'!N28 -> 0.27951482
B29: Service Fees | C29: ='Bonchon U.S. P&L (Monthly''25)'!C29+'Bonchon Int''l P&L (Monthly''25)'!C29-'Consolidations P&L (Monthly''25)'!C29 -> 0.16271575 | D29: ='Bonchon U.S. P&L (Monthly''25)'!D29+'Bonchon Int''l P&L (Monthly''25)'!D29-'Consolidations P&L (Monthly''25)'!D29 -> 0.15659915 | E29: ='Bonchon U.S. P&L (Monthly''25)'!E29+'Bonchon Int''l P&L (Monthly''25)'!E29-'Consolidations P&L (Monthly''25)'!E29 -> 0.17347829 | F29: ='Bonchon U.S. P&L (Monthly''25)'!F29+'Bonchon Int''l P&L (Monthly''25)'!F29-'Consolidations P&L (Monthly''25)'!F29 -> 0.18161582 | G29: ='Bonchon U.S. P&L (Monthly''25)'!G29+'Bonchon Int''l P&L (Monthly''25)'!G29-'Consolidations P&L (Monthly''25)'!G29 -> 0.20660628 | H29: ='Bonchon U.S. P&L (Monthly''25)'!H29+'Bonchon Int''l P&L (Monthly''25)'!H29-'Consolidations P&L (Monthly''25)'!H29 -> 0.18952608 | I29: ='Bonchon U.S. P&L (Monthly''25)'!I29+'Bonchon Int''l P&L (Monthly''25)'!I29-'Consolidations P&L (Monthly''25)'!I29 -> 0.19173999 | J29: ='Bonchon U.S. P&L (Monthly''25)'!J29+'Bonchon Int''l P&L (Monthly''25)'!J29-'Consolidations P&L (Monthly''25)'!J29 -> 0.1885254 | ... N29: ='Bonchon U.S. P&L (Monthly''25)'!N29+'Bonchon Int''l P&L (Monthly''25)'!N29-'Consolidations P&L (Monthly''25)'!N29 -> 0.18500797
B30: Travel & Entertainment | C30: ='Bonchon U.S. P&L (Monthly''25)'!C30+'Bonchon Int''l P&L (Monthly''25)'!C30-'Consolidations P&L (Monthly''25)'!C30 -> 0.04633267 | D30: ='Bonchon U.S. P&L (Monthly''25)'!D30+'Bonchon Int''l P&L (Monthly''25)'!D30-'Consolidations P&L (Monthly''25)'!D30 -> 0.07141145 | E30: ='Bonchon U.S. P&L (Monthly''25)'!E30+'Bonchon Int''l P&L (Monthly''25)'!E30-'Consolidations P&L (Monthly''25)'!E30 -> 0.08715818 | F30: ='Bonchon U.S. P&L (Monthly''25)'!F30+'Bonchon Int''l P&L (Monthly''25)'!F30-'Consolidations P&L (Monthly''25)'!F30 -> 0.09954403 | G30: ='Bonchon U.S. P&L (Monthly''25)'!G30+'Bonchon Int''l P&L (Monthly''25)'!G30-'Consolidations P&L (Monthly''25)'!G30 -> 0.10188543 | H30: ='Bonchon U.S. P&L (Monthly''25)'!H30+'Bonchon Int''l P&L (Monthly''25)'!H30-'Consolidations P&L (Monthly''25)'!H30 -> 0.1028301 | I30: ='Bonchon U.S. P&L (Monthly''25)'!I30+'Bonchon Int''l P&L (Monthly''25)'!I30-'Consolidations P&L (Monthly''25)'!I30 -> 0.06669176 | J30: ='Bonchon U.S. P&L (Monthly''25)'!J30+'Bonchon Int''l P&L (Monthly''25)'!J30-'Consolidations P&L (Monthly''25)'!J30 -> 0.06929898 | ... N30: ='Bonchon U.S. P&L (Monthly''25)'!N30+'Bonchon Int''l P&L (Monthly''25)'!N30-'Consolidations P&L (Monthly''25)'!N30 -> 0.0214698
B31: Rent | C31: ='Bonchon U.S. P&L (Monthly''25)'!C31+'Bonchon Int''l P&L (Monthly''25)'!C31-'Consolidations P&L (Monthly''25)'!C31 -> 0.06212336 | D31: ='Bonchon U.S. P&L (Monthly''25)'!D31+'Bonchon Int''l P&L (Monthly''25)'!D31-'Consolidations P&L (Monthly''25)'!D31 -> 0.06219995 | E31: ='Bonchon U.S. P&L (Monthly''25)'!E31+'Bonchon Int''l P&L (Monthly''25)'!E31-'Consolidations P&L (Monthly''25)'!E31 -> 0.06243743 | F31: ='Bonchon U.S. P&L (Monthly''25)'!F31+'Bonchon Int''l P&L (Monthly''25)'!F31-'Consolidations P&L (Monthly''25)'!F31 -> 0.06226236 | G31: ='Bonchon U.S. P&L (Monthly''25)'!G31+'Bonchon Int''l P&L (Monthly''25)'!G31-'Consolidations P&L (Monthly''25)'!G31 -> 0.06455608 | H31: ='Bonchon U.S. P&L (Monthly''25)'!H31+'Bonchon Int''l P&L (Monthly''25)'!H31-'Consolidations P&L (Monthly''25)'!H31 -> 0.06482641 | I31: ='Bonchon U.S. P&L (Monthly''25)'!I31+'Bonchon Int''l P&L (Monthly''25)'!I31-'Consolidations P&L (Monthly''25)'!I31 -> 0.06486316 | J31: ='Bonchon U.S. P&L (Monthly''25)'!J31+'Bonchon Int''l P&L (Monthly''25)'!J31-'Consolidations P&L (Monthly''25)'!J31 -> 0.06480041 | ... N31: ='Bonchon U.S. P&L (Monthly''25)'!N31+'Bonchon Int''l P&L (Monthly''25)'!N31-'Consolidations P&L (Monthly''25)'!N31 -> 0.06310334
B32: Freight | C32: ='Bonchon U.S. P&L (Monthly''25)'!C32+'Bonchon Int''l P&L (Monthly''25)'!C32-'Consolidations P&L (Monthly''25)'!C32 -> 0.03283545 | D32: ='Bonchon U.S. P&L (Monthly''25)'!D32+'Bonchon Int''l P&L (Monthly''25)'!D32-'Consolidations P&L (Monthly''25)'!D32 -> 0.03108862 | E32: ='Bonchon U.S. P&L (Monthly''25)'!E32+'Bonchon Int''l P&L (Monthly''25)'!E32-'Consolidations P&L (Monthly''25)'!E32 -> 0.0304902 | F32: ='Bonchon U.S. P&L (Monthly''25)'!F32+'Bonchon Int''l P&L (Monthly''25)'!F32-'Consolidations P&L (Monthly''25)'!F32 -> 0.03312424 | G32: ='Bonchon U.S. P&L (Monthly''25)'!G32+'Bonchon Int''l P&L (Monthly''25)'!G32-'Consolidations P&L (Monthly''25)'!G32 -> 0.03703459 | H32: ='Bonchon U.S. P&L (Monthly''25)'!H32+'Bonchon Int''l P&L (Monthly''25)'!H32-'Consolidations P&L (Monthly''25)'!H32 -> 0.03039018 | I32: ='Bonchon U.S. P&L (Monthly''25)'!I32+'Bonchon Int''l P&L (Monthly''25)'!I32-'Consolidations P&L (Monthly''25)'!I32 -> 0.03860788 | J32: ='Bonchon U.S. P&L (Monthly''25)'!J32+'Bonchon Int''l P&L (Monthly''25)'!J32-'Consolidations P&L (Monthly''25)'!J32 -> 0.03834101 | ... N32: ='Bonchon U.S. P&L (Monthly''25)'!N32+'Bonchon Int''l P&L (Monthly''25)'!N32-'Consolidations P&L (Monthly''25)'!N32 -> 0.04312908
B33: Advertising Expense | C33: ='Bonchon U.S. P&L (Monthly''25)'!C33+'Bonchon Int''l P&L (Monthly''25)'!C33-'Consolidations P&L (Monthly''25)'!C33 -> 0.03924777 | D33: ='Bonchon U.S. P&L (Monthly''25)'!D33+'Bonchon Int''l P&L (Monthly''25)'!D33-'Consolidations P&L (Monthly''25)'!D33 -> 0.05615407 | E33: ='Bonchon U.S. P&L (Monthly''25)'!E33+'Bonchon Int''l P&L (Monthly''25)'!E33-'Consolidations P&L (Monthly''25)'!E33 -> 0.06456671 | F33: ='Bonchon U.S. P&L (Monthly''25)'!F33+'Bonchon Int''l P&L (Monthly''25)'!F33-'Consolidations P&L (Monthly''25)'!F33 -> 0.04056867 | G33: ='Bonchon U.S. P&L (Monthly''25)'!G33+'Bonchon Int''l P&L (Monthly''25)'!G33-'Consolidations P&L (Monthly''25)'!G33 -> 0.04928362 | H33: ='Bonchon U.S. P&L (Monthly''25)'!H33+'Bonchon Int''l P&L (Monthly''25)'!H33-'Consolidations P&L (Monthly''25)'!H33 -> 0.03397162 | I33: ='Bonchon U.S. P&L (Monthly''25)'!I33+'Bonchon Int''l P&L (Monthly''25)'!I33-'Consolidations P&L (Monthly''25)'!I33 -> 0.04156093 | J33: ='Bonchon U.S. P&L (Monthly''25)'!J33+'Bonchon Int''l P&L (Monthly''25)'!J33-'Consolidations P&L (Monthly''25)'!J33 -> 0.0337568 | ... N33: ='Bonchon U.S. P&L (Monthly''25)'!N33+'Bonchon Int''l P&L (Monthly''25)'!N33-'Consolidations P&L (Monthly''25)'!N33 -> 0.04231283
B34: Other | C34: ='Bonchon U.S. P&L (Monthly''25)'!C34+'Bonchon Int''l P&L (Monthly''25)'!C34-'Consolidations P&L (Monthly''25)'!C34 -> 0.08396315 | D34: ='Bonchon U.S. P&L (Monthly''25)'!D34+'Bonchon Int''l P&L (Monthly''25)'!D34-'Consolidations P&L (Monthly''25)'!D34 -> 0.0931564 | E34: ='Bonchon U.S. P&L (Monthly''25)'!E34+'Bonchon Int''l P&L (Monthly''25)'!E34-'Consolidations P&L (Monthly''25)'!E34 -> 0.11357638 | F34: ='Bonchon U.S. P&L (Monthly''25)'!F34+'Bonchon Int''l P&L (Monthly''25)'!F34-'Consolidations P&L (Monthly''25)'!F34 -> 0.10592601 | G34: ='Bonchon U.S. P&L (Monthly''25)'!G34+'Bonchon Int''l P&L (Monthly''25)'!G34-'Consolidations P&L (Monthly''25)'!G34 -> 0.09917964 | H34: ='Bonchon U.S. P&L (Monthly''25)'!H34+'Bonchon Int''l P&L (Monthly''25)'!H34-'Consolidations P&L (Monthly''25)'!H34 -> 0.1008665 | I34: ='Bonchon U.S. P&L (Monthly''25)'!I34+'Bonchon Int''l P&L (Monthly''25)'!I34-'Consolidations P&L (Monthly''25)'!I34 -> 0.12497965 | J34: ='Bonchon U.S. P&L (Monthly''25)'!J34+'Bonchon Int''l P&L (Monthly''25)'!J34-'Consolidations P&L (Monthly''25)'!J34 -> 0.09798719 | ... N34: ='Bonchon U.S. P&L (Monthly''25)'!N34+'Bonchon Int''l P&L (Monthly''25)'!N34-'Consolidations P&L (Monthly''25)'!N34 -> 0.08014945
B35: SG&A | C35: =SUM(C27:C34) -> 1.3897254 | D35: =SUM(D27:D34) -> 1.4083672 | E35: =SUM(E27:E34) -> 1.4404251 | F35: =SUM(F27:F34) -> 1.5245875 | G35: =SUM(G27:G34) -> 1.5413404 | H35: =SUM(H27:H34) -> 1.4574641 | I35: =SUM(I27:I34) -> 1.4667712 | J35: =SUM(J27:J34) -> 1.3978975 | ... N35: =SUM(N27:N34) -> 1.4009571
B36: % of Revenue | C36: =IFERROR(C35/C14,"-") -> 0.53583513 | D36: =IFERROR(D35/D14,"-") -> 0.59324247 | E36: =IFERROR(E35/E14,"-") -> 0.59261295 | F36: =IFERROR(F35/F14,"-") -> 0.56460266 | G36: =IFERROR(G35/G14,"-") -> 0.58159673 | H36: =IFERROR(H35/H14,"-") -> 0.61275352 | I36: =IFERROR(I35/I14,"-") -> 0.55227772 | J36: =IFERROR(J35/J14,"-") -> 0.60711423 | ... N36: =IFERROR(N35/N14,"-") -> 0.58994806
B38: Adj. EBITDA | C38: =C22-C35 -> 0.96755285 | D38: =D22-D35 -> 0.76286421 | E38: =E22-E35 -> 0.82161798 | F38: =F22-F35 -> 0.93819395 | G38: =G22-G35 -> 0.91476958 | H38: =H22-H35 -> 0.75326118 | I38: =I22-I35 -> 0.96839614 | J38: =J22-J35 -> 0.7633607 | ... N38: =N22-N35 -> 0.7842827
B39: % Margin | C39: =IFERROR(C38/C14,"-") -> 0.37305845 | D39: =IFERROR(D38/D14,"-") -> 0.32133911 | E39: =IFERROR(E38/E14,"-") -> 0.33802621 | F39: =IFERROR(F38/F14,"-") -> 0.34744271 | G39: =IFERROR(G38/G14,"-") -> 0.34517163 | H39: =IFERROR(H38/H14,"-") -> 0.31668941 | I39: =IFERROR(I38/I14,"-") -> 0.36462647 | J39: =IFERROR(J38/J14,"-") -> 0.33153157 | ... N39: =IFERROR(N38/N14,"-") -> 0.33026425

Sheet Bonchon U.S. P&L (Monthly'25)
B2: Bonchon U.S. 2025 Monthly P&L
C4: Historical
B5: ($ in millions) | C5: 45688 | D5: =EOMONTH(C5,1) -> 45716 | E5: =EOMONTH(D5,1) -> 45747 | F5: =EOMONTH(E5,1) -> 45777 | G5: =EOMONTH(F5,1) -> 45808 | H5: =EOMONTH(G5,1) -> 45838 | I5: =EOMONTH(H5,1) -> 45869 | J5: =EOMONTH(I5,1) -> 45900 | K5: =EOMONTH(J5,1) -> 45930 | ... N5: =EOMONTH(M5,1) -> 46022
B7: Franchise Revenue | C7: 0.79228034 | D7: 0.76470944 | E7: 0.86563208 | F7: 0.79790393 | G7: 0.89838344 | H7: 0.85206368 | I7: 0.87913107 | J7: 0.89793222 | K7: 0.81750861 | L7: 0.8367643 | M7: 0.8948671 | N7: 0.9045585
B8: Sauce Revenue | C8: 0.2035894 | D8: 0.18245416 | E8: 0.20482682 | F8: 0.19953749 | G8: 0.2134427 | H8: 0.18601222 | I8: 0.20835112 | J8: 0.19360905 | K8: 0.17253986 | L8: 0.186106 | M8: 0.19374046 | N8: 0.20736673
B9: Company-Owned Store Revenue | C9: 0.27662877 | D9: 0.26859163 | E9: 0.29818624 | F9: 0.30736304 | G9: 0.32976541 | H9: 0.28344493 | I9: 0.29538173 | J9: 0.34740922 | K9: 0.3362522 | L9: 0.36096892 | M9: 0.33503931 | N9: 0.34941774
B10: Marketing Fund | C10: 0.25040226 | D10: 0.23089278 | E10: 0.25462936 | F10: 0.28966546 | G10: 0.26946647 | H10: 0.25958082 | I10: 0.26904213 | J10: 0.27583441 | K10: 0.26159007 | L10: 0.32549496 | M10: 0.26215781 | N10: 0.27951482
B11: Other Product Revenue | C11: 0.000398 | D11: 0.000148 | E11: -0.001094 | F11: 0.0067262 | G11: 0.00363504 | H11: 0.0023876 | I11: 0.0006835 | J11: 0.000618 | K11: 0.000138 | L11: -0.0152354 | M11: -0.0105 | N11: -0.002594
B12: Other Revenue | C12: 0.00839232 | D12: 0.0146508 | E12: 0.01376495 | F12: 0.00719265 | G12: 0.05088173 | H12: 0.01391394 | I12: 0.00220506 | J12: 0.00418672 | K12: 0.00748728 | L12: 0.00075856 | M12: 0.04786713 | N12: 0.00192864
B13: Other | C13: =SUM(C11:C12) -> 0.00879032 | D13: =SUM(D11:D12) -> 0.0147988 | E13: =SUM(E11:E12) -> 0.01267095 | F13: =SUM(F11:F12) -> 0.01391885 | G13: =SUM(G11:G12) -> 0.05451677 | H13: =SUM(H11:H12) -> 0.01630154 | I13: =SUM(I11:I12) -> 0.00288856 | J13: =SUM(J11:J12) -> 0.00480472 | ... N13: =SUM(N11:N12) -> -0.00066536
B14: Total Revenue | C14: =SUM(C7:C10,C13) -> 1.5316911 | D14: =SUM(D7:D10,D13) -> 1.4614468 | E14: =SUM(E7:E10,E13) -> 1.6359454 | F14: =SUM(F7:F10,F13) -> 1.6083888 | G14: =SUM(G7:G10,G13) -> 1.7655748 | H14: =SUM(H7:H10,H13) -> 1.5974032 | I14: =SUM(I7:I10,I13) -> 1.6547946 | J14: =SUM(J7:J10,J13) -> 1.7195896 | ... N14: =SUM(N7:N10,N13) -> 1.7401924
B16: Sauce COGS | C16: 0.00022904 | D16: 0.00030538 | E16: 0.00061076 | F16: 0.00114517 | G16: 0 | H16: 7.634e-05 | I16: 4.8e-05 | J16: 3e-06 | K16: 8e-06 | L16: 0.00354516 | M16: 0.00605444 | N16: 0.00152568
B17: Company-Owned Store COGS | C17: 0.08514469 | D17: 0.08347054 | E17: 0.09041345 | F17: 0.09148361 | G17: 0.09486322 | H17: 0.07775556 | I17: 0.08551146 | J17: 0.10422529 | K17: 0.09964597 | L17: 0.08262018 | M17: 0.08098523 | N17: 0.09283688
B18: Other Product COGS | C18: 0.00081908 | D18: 0.00071288 | E18: 0.00046257 | F18: 0.00637508 | G18: -0.00054967 | H18: 0.00448782 | I18: 0.01331653 | J18: 0.00051909 | K18: 2.717e-05 | L18: -0.01594153 | M18: 0.00016677 | N18: 0.00199264
B19: D&A In COGS | C19: 0 | D19: 0 | E19: 0 | F19: 0 | G19: 0 | H19: 0 | I19: 0 | J19: 0 | K19: 0 | L19: 0 | M19: 0 | N19: 0
B20: Other | C20: =SUM(C18:C19) -> 0.00081908 | D20: =SUM(D18:D19) -> 0.00071288 | E20: =SUM(E18:E19) -> 0.00046257 | F20: =SUM(F18:F19) -> 0.00637508 | G20: =SUM(G18:G19) -> -0.00054967 | H20: =SUM(H18:H19) -> 0.00448782 | I20: =SUM(I18:I19) -> 0.01331653 | J20: =SUM(J18:J19) -> 0.00051909 | ... N20: =SUM(N18:N19) -> 0.00199264
B21: Total Cost of Goods Sold | C21: =SUM(C16:C17,C20) -> 0.08619281 | D21: =SUM(D16:D17,D20) -> 0.0844888 | E21: =SUM(E16:E17,E20) -> 0.09148678 | F21: =SUM(F16:F17,F20) -> 0.09900386 | G21: =SUM(G16:G17,G20) -> 0.09431355 | H21: =SUM(H16:H17,H20) -> 0.08231972 | I21: =SUM(I16:I17,I20) -> 0.09887599 | J21: =SUM(J16:J17,J20) -> 0.10474738 | ... N21: =SUM(N16:N17,N20) -> 0.0963552
B22: Gross Profit | C22: =C14-C21 -> 1.4454983 | D22: =D14-D21 -> 1.376958 | E22: =E14-E21 -> 1.5444587 | F22: =F14-F21 -> 1.5093849 | G22: =G14-G21 -> 1.6712612 | H22: =H14-H21 -> 1.5150835 | I22: =I14-I21 -> 1.5559186 | J22: =J14-J21 -> 1.6148422 | ... N22: =N14-N21 -> 1.6438372
B23: % Margin | C23: =IFERROR(C22/C14,"-") -> 0.94372703 | D23: =IFERROR(D22/D14,"-") -> 0.94218825 | E23: =IFERROR(E22/E14,"-") -> 0.94407712 | F23: =IFERROR(F22/F14,"-") -> 0.93844532 | G23: =IFERROR(G22/G14,"-") -> 0.94658196 | H23: =IFERROR(H22/H14,"-") -> 0.94846654 | I23: =IFERROR(I22/I14,"-") -> 0.94024878 | J23: =IFERROR(J22/J14,"-") -> 0.93908583 | ... N23: =IFERROR(N22/N14,"-") -> 0.94462957
B25: Corporate Labor | C25: 0.50168114 | D25: 0.49861833 | E25: 0.4557006 | F25: 0.5085861 | G25: 0.50292049 | H25: 0.47596055 | I25: 0.46478777 | J25: 0.41442183 | K25: 0.48556149 | L25: 0.45722869 | M25: 0.4285957 | N25: 0.47943159
B26: Company-Owned Store Labor | C26: 0.11461161 | D26: 0.10637966 | E26: 0.10328765 | F26: 0.10334307 | G26: 0.10714182 | H26: 0.09523406 | I26: 0.09905268 | J26: 0.10807474 | K26: 0.10501811 | L26: 0.10856196 | M26: 0.10170131 | N26: 0.09876501
B27: Total Labor | C27: =SUM(C25:C26) -> 0.61629275 | D27: =SUM(D25:D26) -> 0.60499799 | E27: =SUM(E25:E26) -> 0.55898825 | F27: =SUM(F25:F26) -> 0.61192917 | G27: =SUM(G25:G26) -> 0.61006231 | H27: =SUM(H25:H26) -> 0.57119461 | I27: =SUM(I25:I26) -> 0.56384045 | J27: =SUM(J25:J26) -> 0.52249657 | ... N27: =SUM(N25:N26) -> 0.5781966
B28: Marketing Fund | C28: =C10 -> 0.25040226 | D28: =D10 -> 0.23089278 | E28: =E10 -> 0.25462936 | F28: =F10 -> 0.28966546 | G28: =G10 -> 0.26946647 | H28: =H10 -> 0.25958082 | I28: =I10 -> 0.26904213 | J28: =J10 -> 0.27583441 | ... M28: =M10 -> 0.26215781 | N28: 0.27951482
B29: Service Fees | C29: 0.13805579 | D29: 0.13267726 | E29: 0.157353 | F29: 0.1349279 | G29: 0.16694267 | H29: 0.13221012 | I29: 0.15060308 | J29: 0.14688554 | K29: 0.12395428 | L29: 0.12972344 | M29: 0.11518681 | N29: 0.23873492
B30: Travel & Entertainment | C30: 0.04026429 | D30: 0.05358397 | E30: 0.06125503 | F30: 0.0686408 | G30: 0.06569317 | H30: 0.0734099 | I30: 0.04774831 | J30: 0.04690534 | K30: 0.05818304 | L30: 0.03847839 | M30: 0.05167329 | N30: 0.02430577
B31: Rent | C31: 0.05090165 | D31: 0.05086079 | E31: 0.05117602 | F31: 0.05096582 | G31: 0.05288819 | H31: 0.05294087 | I31: 0.05294438 | J31: 0.05301958 | K31: 0.05376623 | L31: 0.05292256 | M31: 0.05292101 | N31: 0.05195375
B32: Freight | C32: 0.03216447 | D32: 0.02942524 | E32: 0.03005072 | F32: 0.03175226 | G32: 0.03570722 | H32: 0.0298849 | I32: 0.03779717 | J32: 0.03804995 | K32: 0.03718965 | L32: 0.04359754 | M32: 0.03803726 | N32: 0.04285662
B33: Advertising Expense | C33: 0.03031473 | D33: 0.0412035 | E33: 0.0604323 | F33: 0.03845732 | G33: 0.04894297 | H33: 0.03710812 | I33: 0.04296692 | J33: 0.03286734 | K33: 0.02106345 | L33: 0.02948171 | M33: 0.02384082 | N33: 0.04240566
B34: Other | C34: 0.06017346 | D34: 0.06885898 | E34: 0.07969329 | F34: 0.0734005 | G34: 0.07704771 | H34: 0.06843793 | I34: 0.08807342 | J34: 0.07243029 | K34: 0.07452747 | L34: 0.06175344 | M34: 0.04935635 | N34: 0.0461299
B35: SG&A | C35: =SUM(C27:C34) -> 1.2185694 | D35: =SUM(D27:D34) -> 1.2125005 | E35: =SUM(E27:E34) -> 1.253578 | F35: =SUM(F27:F34) -> 1.2997392 | G35: =SUM(G27:G34) -> 1.3267507 | H35: =SUM(H27:H34) -> 1.2247673 | I35: =SUM(I27:I34) -> 1.2530159 | J35: =SUM(J27:J34) -> 1.188489 | ... N35: =SUM(N27:N34) -> 1.304098
B36: % of Revenue | C36: =IFERROR(C35/C14,"-") -> 0.79557125 | D36: =IFERROR(D35/D14,"-") -> 0.82965764 | E36: =IFERROR(E35/E14,"-") -> 0.76627125 | F36: =IFERROR(F35/F14,"-") -> 0.80810016 | G36: =IFERROR(G35/G14,"-") -> 0.7514554 | H36: =IFERROR(H35/H14,"-") -> 0.76672394 | I36: =IFERROR(I35/I14,"-") -> 0.75720325 | J36: =IFERROR(J35/J14,"-") -> 0.69114689 | ... N36: =IFERROR(N35/N14,"-") -> 0.74939875
B38: Adj. EBITDA | C38: =C22-C35 -> 0.22692888 | D38: =D22-D35 -> 0.1644575 | E38: =E22-E35 -> 0.2908807 | F38: =F22-F35 -> 0.20964568 | G38: =G22-G35 -> 0.34451053 | H38: =H22-H35 -> 0.2903162 | I38: =I22-I35 -> 0.30290276 | J38: =J22-J35 -> 0.42635322 | ... N38: =N22-N35 -> 0.33973919
B39: % Margin | C39: =C22-C35+C19 -> 0.22692888 | D39: =IFERROR(D38/D14,"-") -> 0.11253061 | E39: =IFERROR(E38/E14,"-") -> 0.17780587 | F39: =IFERROR(F38/F14,"-") -> 0.13034515 | G39: =IFERROR(G38/G14,"-") -> 0.19512656 | H39: =IFERROR(H38/H14,"-") -> 0.18174259 | I39: =IFERROR(I38/I14,"-") -> 0.18304553 | J39: =IFERROR(J38/J14,"-") -> 0.24793894 | K39: =IFERROR(K38/K14,"-") -> 0.17234618 | ... N39: =IFERROR(N38/N14,"-") -> 0.19523082

Sheet Bonchon Int'l P&L (Monthly'25)
B2: Bonchon International 2025 Monthly P&L
C4: Historical
B5: ($ in millions) | C5: 45688 | D5: =EOMONTH(C5,1) -> 45716 | E5: =EOMONTH(D5,1) -> 45747 | F5: =EOMONTH(E5,1) -> 45777 | G5: =EOMONTH(F5,1) -> 45808 | H5: =EOMONTH(G5,1) -> 45838 | I5: =EOMONTH(H5,1) -> 45869 | J5: =EOMONTH(I5,1) -> 45900 | K5: =EOMONTH(J5,1) -> 45930 | ... N5: =EOMONTH(M5,1) -> 46022
B7: Franchise Revenue | C7: 0.38341599 | D7: 0.35170324 | E7: 0.40152424 | F7: 0.41489243 | G7: 0.423943 | H7: 0.38759257 | I7: 0.40689566 | J7: 0.42151299 | K7: 0.38976983 | L7: 0.47108275 | M7: 0.38843251 | N7: 0.45033303
B8: Sauce Revenue | C8: 0.67794964 | D8: 0.55886021 | E8: 0.39277849 | F8: 0.67592416 | G8: 0.45959888 | H8: 0.39236004 | I8: 0.59239252 | J8: 0.15867984 | K8: 0.32330336 | L8: 0.45921543 | M8: 0.14515564 | N8: 0.18425388
B9: Company-Owned Store Revenue | C9: 0 | D9: 0 | E9: 0 | F9: 0 | G9: 0 | H9: 0 | I9: 0 | J9: 0 | K9: 0 | L9: 0 | M9: 0 | N9: 0
B10: Marketing Fund | C10: 0 | D10: 0 | E10: 0 | F10: 0 | G10: 0 | H10: 0 | I10: 0 | J10: 0 | K10: 0 | L10: 0 | M10: 0 | N10: 0
B11: Other Product Revenue | C11: 0.00051232 | D11: 0.0020058135 | E11: 0.00038575791 | F11: 0.0010785426 | G11: 0.0010709643 | H11: 0.0088402188 | I11: 0.001821591 | J11: 0.002765565 | K11: 0.001137426 | L11: 0.0091693877 | M11: -1.9109343e-05 | N11: -9.1027252e-05
B12: Other Revenue | C12: 0 | D12: 0 | E12: 0 | F12: 0 | G12: 0 | H12: 0 | I12: 0 | J12: 0 | K12: 0 | L12: 0 | M12: 0 | N12: 0.097052309
B13: Other | C13: =SUM(C11:C12) -> 0.00051232 | D13: =SUM(D11:D12) -> 0.0020058135 | E13: =SUM(E11:E12) -> 0.00038575791 | F13: =SUM(F11:F12) -> 0.0010785426 | G13: =SUM(G11:G12) -> 0.0010709643 | H13: =SUM(H11:H12) -> 0.0088402188 | I13: =SUM(I11:I12) -> 0.001821591 | J13: =SUM(J11:J12) -> 0.002765565 | ... N13: =SUM(N11:N12) -> 0.096961282
B14: Total Revenue | C14: =SUM(C7:C10,C13) -> 1.0618779 | D14: =SUM(D7:D10,D13) -> 0.91256926 | E14: =SUM(E7:E10,E13) -> 0.79468849 | F14: =SUM(F7:F10,F13) -> 1.0918951 | G14: =SUM(G7:G10,G13) -> 0.88461284 | H14: =SUM(H7:H10,H13) -> 0.78879283 | I14: =SUM(I7:I10,I13) -> 1.0011098 | J14: =SUM(J7:J10,J13) -> 0.58295839 | ... N14: =SUM(N7:N10,N13) -> 0.73154819
B16: Sauce COGS | C16: 0.16231651 | D16: 0.12881372 | E16: 0.088446762 | F16: 0.15014788 | G16: 0.11224335 | H16: 0.096764206 | I16: 0.14351297 | J16: 0.045961943 | K16: 0.10512751 | L16: 0.12528046 | M16: 0.040537625 | N16: 0.10521877
B17: Company-Owned Store COGS | C17: 0 | D17: 0 | E17: 0 | F17: 0 | G17: 0 | H17: 0 | I17: 0 | J17: 0 | K17: 0 | L17: 0 | M17: 0
B18: Other Product COGS | C18: -0.00010477 | D18: 0.0014100739 | E18: 0.00018760773 | F18: 0.00055618352 | G18: 0.00064992487 | H18: 0.0059032539 | I18: 0.0010216807 | J18: 0.0015737367 | K18: 0.0014135412 | L18: 0.0068874216 | M18: 5.9452544e-06 | N18: -6.2038098e-05
B19: D&A In COGS | C19: -0.011663985 | D19: -0.011750515 | E19: -0.011652854 | F19: -0.011762941 | G19: -0.012143871 | H19: -0.012374686 | I19: -0.012642496 | J19: -0.012511127 | K19: -0.012484437 | L19: -0.012207883 | M19: -0.011919722 | N19: -0.011789288
B20: Other | C20: =SUM(C18:C19) -> -0.011768755 | D20: =SUM(D18:D19) -> -0.010340441 | E20: =SUM(E18:E19) -> -0.011465246 | F20: =SUM(F18:F19) -> -0.011206757 | G20: =SUM(G18:G19) -> -0.011493946 | H20: =SUM(H18:H19) -> -0.0064714325 | I20: =SUM(I18:I19) -> -0.011620816 | J20: =SUM(J18:J19) -> -0.01093739 | ... M20: =SUM(M18:M19) -> -0.011913777 | N20: -0.011851326
B21: Total Cost of Goods Sold | C21: =SUM(C16:C17,C20) -> 0.15054775 | D21: =SUM(D16:D17,D20) -> 0.11847328 | E21: =SUM(E16:E17,E20) -> 0.076981516 | F21: =SUM(F16:F17,F20) -> 0.13894112 | G21: =SUM(G16:G17,G20) -> 0.1007494 | H21: =SUM(H16:H17,H20) -> 0.090292774 | I21: =SUM(I16:I17,I20) -> 0.13189215 | J21: =SUM(J16:J17,J20) -> 0.035024553 | ... N21: =SUM(N16:N17,N20) -> 0.093367442
B22: Gross Profit | C22: =C14-C21 -> 0.9113302 | D22: =D14-D21 -> 0.79409598 | E22: =E14-E21 -> 0.71770697 | F22: =F14-F21 -> 0.95295401 | G22: =G14-G21 -> 0.78386344 | H22: =H14-H21 -> 0.69850006 | I22: =I14-I21 -> 0.86921762 | J22: =J14-J21 -> 0.54793384 | ... N22: =N14-N21 -> 0.63818075
B23: % Margin | C23: =IFERROR(C22/C14,"-") -> 0.85822499 | D23: =IFERROR(D22/D14,"-") -> 0.87017613 | E23: =IFERROR(E22/E14,"-") -> 0.90312995 | F23: =IFERROR(F22/F14,"-") -> 0.87275232 | G23: =IFERROR(G22/G14,"-") -> 0.88610905 | H23: =IFERROR(H22/H14,"-") -> 0.88553043 | I23: =IFERROR(I22/I14,"-") -> 0.86825405 | J23: =IFERROR(J22/J14,"-") -> 0.93991929 | ... N23: =IFERROR(N22/N14,"-") -> 0.87237007
B25: Corporate Labor | C25: 0.09581225 | D25: 0.10186675 | E25: 0.09510035 | F25: 0.0999517 | G25: 0.10326603 | H25: 0.10427774 | I25: 0.10544528 | J25: 0.10685671 | K25: 0.10423993 | L25: 0.10413536 | M25: 0.098195593 | N25: 0.10807324
B26: Company-Owned Store Labor | C26: 0 | D26: 0 | E26: 0 | F26: 0 | G26: 0 | H26: 0 | I26: 0 | J26: 0 | K26: 0 | L26: 0 | M26: 0 | N26: 0
B27: Total Labor | C27: =SUM(C25:C26) -> 0.09581225 | D27: =SUM(D25:D26) -> 0.10186675 | E27: =SUM(E25:E26) -> 0.09510035 | F27: =SUM(F25:F26) -> 0.0999517 | G27: =SUM(G25:G26) -> 0.10326603 | H27: =SUM(H25:H26) -> 0.10427774 | I27: =SUM(I25:I26) -> 0.10544528 | J27: =SUM(J25:J26) -> 0.10685671 | ... N27: =SUM(N25:N26) -> 0.10807324
B28: Marketing Fund | C28: =C10 -> 0 | D28: =D10 -> 0 | E28: =E10 -> 0 | F28: =F10 -> 0 | G28: =G10 -> 0 | H28: =H10 -> 0 | I28: =I10 -> 0 | J28: =J10 -> 0 | ... M28: =M10 -> 0 | N28: 0
B29: Service Fees | C29: 0.02465996 | D29: 0.02392189 | E29: 0.01612529 | F29: 0.04668792 | G29: 0.03966361 | H29: 0.05731596 | I29: 0.04113691 | J29: 0.04163986 | K29: 0.05149028 | L29: 0.05152361 | M29: 0.02223571 | N29: 0.043325363
B30: Travel & Entertainment | C30: 0.00606838 | D30: 0.01782748 | E30: 0.02590315 | F30: 0.03090323 | G30: 0.03619226 | H30: 0.0294202 | I30: 0.01894345 | J30: 0.02239364 | K30: 0.01761105 | L30: 0.00155638 | M30: -0.01648166 | N30: -0.00283597
B31: Rent | C31: 0.01122171 | D31: 0.01133916 | E31: 0.01126141 | F31: 0.01129654 | G31: 0.01166789 | H31: 0.01188554 | I31: 0.01191878 | J31: 0.01178083 | K31: 0.0038468 | L31: 0.00355678 | M31: 0.00331926 | N31: 0.01114959
B32: Freight | C32: 0.00067098 | D32: 0.00166338 | E32: 0.00043948 | F32: 0.00137198 | G32: 0.00132737 | H32: 0.00050528 | I32: 0.00081071 | J32: 0.00029106 | K32: 0.00047261 | L32: 0.00077537 | M32: 0.00022879 | N32: 0.00027246
B33: Advertising Expense | C33: 0.00893304 | D33: 0.01495057 | E33: 0.00413441 | F33: 0.00211135 | G33: 0.00034065 | H33: -0.0031365 | I33: -0.00140599 | J33: 0.00088946 | K33: 6.438e-05 | L33: -1.787e-05 | M33: 0.00247356 | N33: -9.283e-05
B34: Other | C34: 0.02378969 | D34: 0.02429742 | E34: 0.03388309 | F34: 0.03252551 | G34: 0.02213193 | H34: 0.03242857 | I34: 0.03690623 | J34: 0.0255569 | K34: 0.02527703 | L34: 0.06081075 | M34: 0.0302455 | N34: 0.03401955
B35: SG&A | C35: =SUM(C27:C34) -> 0.17115601 | D35: =SUM(D27:D34) -> 0.19586665 | E35: =SUM(E27:E34) -> 0.18684718 | F35: =SUM(F27:F34) -> 0.22484823 | G35: =SUM(G27:G34) -> 0.21458974 | H35: =SUM(H27:H34) -> 0.23269679 | I35: =SUM(I27:I34) -> 0.21375537 | J35: =SUM(J27:J34) -> 0.20940846 | ... N35: =SUM(N27:N34) -> 0.1939114
B36: % of Revenue | C36: =IFERROR(C35/C14,"-") -> 0.16118238 | D36: =IFERROR(D35/D14,"-") -> 0.21463209 | E36: =IFERROR(E35/E14,"-") -> 0.23512003 | F36: =IFERROR(F35/F14,"-") -> 0.20592475 | G36: =IFERROR(G35/G14,"-") -> 0.2425804 | H36: =IFERROR(H35/H14,"-") -> 0.29500368 | I36: =IFERROR(I35/I14,"-") -> 0.21351841 | J36: =IFERROR(J35/J14,"-") -> 0.35921682 | ... N36: =IFERROR(N35/N14,"-") -> 0.26506989
B38: Adj. EBITDA | C38: =C22-C35 -> 0.74017419 | D38: =D22-D35 -> 0.59822933 | E38: =E22-E35 -> 0.53085979 | F38: =F22-F35 -> 0.72810578 | G38: =G22-G35 -> 0.5692737 | H38: =H22-H35 -> 0.46580327 | I38: =I22-I35 -> 0.65546225 | J38: =J22-J35 -> 0.33852538 | ... N38: =N22-N35 -> 0.44426935
B39: % Margin | C39: =C22-C35+C19 -> 0.7285102 | D39: =IFERROR(D38/D14,"-") -> 0.65554403 | E39: =IFERROR(E38/E14,"-") -> 0.66800992 | F39: =IFERROR(F38/F14,"-") -> 0.66682757 | G39: =IFERROR(G38/G14,"-") -> 0.64352864 | H39: =IFERROR(H38/H14,"-") -> 0.59052675 | I39: =IFERROR(I38/I14,"-") -> 0.65473564 | J39: =IFERROR(J38/J14,"-") -> 0.58070247 | K39: =IFERROR(K38/K14,"-") -> 0.5840741 | ... N39: =IFERROR(N38/N14,"-") -> 0.60730018

Sheet Consolidations P&L (Monthly'25)
B2: Consolidations 2025 Monthly P&L
C4: Historical
B5: ($ in millions) | C5: 45688 | D5: =EOMONTH(C5,1) -> 45716 | E5: =EOMONTH(D5,1) -> 45747 | F5: =EOMONTH(E5,1) -> 45777 | G5: =EOMONTH(F5,1) -> 45808 | H5: =EOMONTH(G5,1) -> 45838 | I5: =EOMONTH(H5,1) -> 45869 | J5: =EOMONTH(I5,1) -> 45900 | K5: =EOMONTH(J5,1) -> 45930 | ... N5: =EOMONTH(M5,1) -> 46022
B7: Franchise Revenue | C7: 0 | D7: 0 | E7: 0 | F7: 0 | G7: 0 | H7: 0 | I7: 0 | J7: 0 | K7: 0 | L7: 0 | M7: 0 | N7: 0
B8: Sauce Revenue | C8: 0 | D8: 0 | E8: 0 | F8: 0 | G8: 0 | H8: 0 | I8: 0 | J8: 0 | K8: 0 | L8: 0 | M8: 0 | N8: 0
B9: Company-Owned Store Revenue | C9: 0 | D9: 0 | E9: 0 | F9: 0 | G9: 0 | H9: 0 | I9: 0 | J9: 0 | K9: 0 | L9: 0 | M9: 0 | N9: 0
B10: Marketing Fund | C10: 0 | D10: 0 | E10: 0 | F10: 0 | G10: 0 | H10: 0 | I10: 0 | J10: 0 | K10: 0 | L10: 0 | M10: 0 | N10: 0
B11: Other Product Revenue | C11: 0 | D11: 0 | E11: 0 | F11: 0 | G11: 0 | H11: 0.0076473801 | I11: 4.6336656e-05 | J11: 2.0054261e-05 | K11: 1.5615474e-05 | L11: -5.1393288e-06 | M11: -2.1738952e-05 | N11: -2.437e-05
B12: Other Revenue | C12: 0 | D12: 0 | E12: 0 | F12: 0 | G12: 0 | H12: 0 | I12: 0 | J12: 0 | K12: 0 | L12: 0 | M12: 0 | N12: 0.097052309
B13: Other | C13: =SUM(C11:C12) -> 0 | D13: =SUM(D11:D12) -> 0 | E13: =SUM(E11:E12) -> 0 | F13: =SUM(F11:F12) -> 0 | G13: =SUM(G11:G12) -> 0 | H13: =SUM(H11:H12) -> 0.0076473801 | I13: =SUM(I11:I12) -> 4.6336656e-05 | J13: =SUM(J11:J12) -> 2.0054261e-05 | ... N13: =SUM(N11:N12) -> 0.097027939
B14: Total Revenue | C14: =SUM(C7:C10,C13) -> 0 | D14: =SUM(D7:D10,D13) -> 0 | E14: =SUM(E7:E10,E13) -> 0 | F14: =SUM(F7:F10,F13) -> 0 | G14: =SUM(G7:G10,G13) -> 0 | H14: =SUM(H7:H10,H13) -> 0.0076473801 | I14: =SUM(I7:I10,I13) -> 4.6336656e-05 | J14: =SUM(J7:J10,J13) -> 2.0054261e-05 | ... N14: =SUM(N7:N10,N13) -> 0.097027939
B16: Sauce COGS | C16: 0 | D16: 0 | E16: 0 | F16: 0 | G16: 0 | H16: 0 | I16: 0 | J16: 0 | K16: 0 | L16: 0 | M16: 0 | N16: 0
B17: Company-Owned Store COGS | C17: 0 | D17: 0 | E17: 0 | F17: 0 | G17: 0 | H17: 0 | I17: 0 | J17: 0 | K17: 0 | L17: 0 | M17: 0 | N17: 0
B18: Other Product COGS | C18: 0.00044978191 | D18: 0.00017737938 | E18: -0.0001225112 | F18: 0.00044248547 | G18: 0.00098535034 | H18: 0.0047890901 | I18: 0.010077472 | J18: -0.0014978403 | K18: -0.0013280591 | L18: -0.0012776739 | M18: -0.0013443635 | N18: 0.00024979113
B19: D&A In COGS | C19: 0 | D19: 0 | E19: 0 | F19: 0 | G19: 0 | H19: 0 | I19: 0 | J19: 0 | K19: 0 | L19: 0 | M19: 0 | N19: 0
B20: Other | C20: =C18+C19 -> 0.00044978191 | D20: =D18+D19 -> 0.00017737938 | E20: =E18+E19 -> -0.0001225112 | F20: =F18+F19 -> 0.00044248547 | G20: =G18+G19 -> 0.00098535034 | H20: =H18+H19 -> 0.0047890901 | I20: =I18+I19 -> 0.010077472 | J20: =J18+J19 -> -0.0014978403 | ... N20: =N18+N19 -> 0.00024979113
B21: Total Cost of Goods Sold | C21: =SUM(C16:C17,C20) -> 0.00044978191 | D21: =SUM(D16:D17,D20) -> 0.00017737938 | E21: =SUM(E16:E17,E20) -> -0.0001225112 | F21: =SUM(F16:F17,F20) -> 0.00044248547 | G21: =SUM(G16:G17,G20) -> 0.00098535034 | H21: =SUM(H16:H17,H20) -> 0.0047890901 | I21: =SUM(I16:I17,I20) -> 0.010077472 | J21: =SUM(J16:J17,J20) -> -0.0014978403 | ... N21: =SUM(N16:N17,N20) -> 0.00024979113
B22: Gross Profit | C22: =C14-C21 -> -0.00044978191 | D22: =D14-D21 -> -0.00017737938 | E22: =E14-E21 -> 0.0001225112 | F22: =F14-F21 -> -0.00044248547 | G22: =G14-G21 -> -0.00098535034 | H22: =H14-H21 -> 0.00285829 | I22: =I14-I21 -> -0.010031135 | J22: =J14-J21 -> 0.0015178946 | ... N22: =N14-N21 -> 0.096778148
B23: % Margin
B25: Corporate Labor | C25: 0 | D25: 0 | E25: 0 | F25: 0 | G25: 0 | H25: 0 | I25: 0 | J25: 0 | K25: 0 | L25: 0 | M25: 0 | N25: 0
B26: Company-Owned Store Labor | C26: 0 | D26: 0 | E26: 0 | F26: 0 | G26: 0 | H26: 0 | I26: 0 | J26: 0 | K26: 0 | L26: 0 | M26: 0 | N26: 0
B27: Total Labor | C27: =SUM(C25:C26) -> 0 | D27: =SUM(D25:D26) -> 0 | E27: =SUM(E25:E26) -> 0 | F27: =SUM(F25:F26) -> 0 | G27: =SUM(G25:G26) -> 0 | H27: =SUM(H25:H26) -> 0 | I27: =SUM(I25:I26) -> 0 | J27: =SUM(J25:J26) -> 0 | ... N27: =SUM(N25:N26) -> 0
B28: Marketing Fund | C28: 0 | D28: 0 | E28: 0 | F28: 0 | G28: 0 | H28: 0 | I28: 0 | J28: 0 | K28: 0 | L28: 0 | M28: 0
B29: Service Fees | C29: 0 | D29: 0 | E29: 0 | F29: 0 | G29: 0 | H29: 0 | I29: 0 | J29: 0 | K29: 0 | L29: 0 | M29: 0 | N29: 0.097052309
B30: Travel & Entertainment | C30: 0 | D30: 0 | E30: 0 | F30: 0 | G30: 0 | H30: 0 | I30: 0 | J30: 0 | K30: 0 | L30: 0 | M30: 0 | N30: 0
B31: Rent | C31: 0 | D31: 0 | E31: 0 | F31: 0 | G31: 0 | H31: 0 | I31: 0 | J31: 0 | K31: 0 | L31: 0 | M31: 0 | N31: 0
B32: Freight | C32: 0 | D32: 0 | E32: 0 | F32: 0 | G32: 0 | H32: 0 | I32: 0 | J32: 0 | K32: 0 | L32: 0 | M32: 0 | N32: 0
B33: Advertising Expense | C33: 0 | D33: 0 | E33: 0 | F33: 0 | G33: 0 | H33: 0 | I33: 0 | J33: 0 | K33: 0 | L33: 0 | M33: 0 | N33: 0
B34: Other | C34: 0 | D34: 0 | E34: 0 | F34: 0 | G34: 0 | H34: 0 | I34: 0 | J34: 0 | K34: 0 | L34: 0 | M34: 0 | N34: 0
B35: SG&A | C35: =SUM(C27:C34) -> 0 | D35: =SUM(D27:D34) -> 0 | E35: =SUM(E27:E34) -> 0 | F35: =SUM(F27:F34) -> 0 | G35: =SUM(G27:G34) -> 0 | H35: =SUM(H27:H34) -> 0 | I35: =SUM(I27:I34) -> 0 | J35: =SUM(J27:J34) -> 0 | ... N35: =SUM(N27:N34) -> 0.097052309
B36: % of Revenue | C36: =IFERROR(C35/C14,"-") -> - | D36: =IFERROR(D35/D14,"-") -> - | E36: =IFERROR(E35/E14,"-") -> - | F36: =IFERROR(F35/F14,"-") -> - | G36: =IFERROR(G35/G14,"-") -> - | H36: =IFERROR(H35/H14,"-") -> 0 | I36: =IFERROR(I35/I14,"-") -> 0 | J36: =IFERROR(J35/J14,"-") -> 0 | ... N36: =IFERROR(N35/N14,"-") -> 1.0002512
B38: Adj. EBITDA | C38: =C22-C35 -> -0.00044978191 | D38: =D22-D35 -> -0.00017737938 | E38: =E22-E35 -> 0.0001225112 | F38: =F22-F35 -> -0.00044248547 | G38: =G22-G35 -> -0.00098535034 | H38: =H22-H35 -> 0.00285829 | I38: =I22-I35 -> -0.010031135 | J38: =J22-J35 -> 0.0015178946 | ... N38: =N22-N35 -> -0.00027416113
B39: % Margin

Sheet 2026 Monthly P&Ls>>

Sheet Consolidated P&L (Monthly'26)
B2: Bonchon Consolidated 2026 Monthly P&L
C4: Plan
B5: ($ in millions) | C5: 46053 | D5: =EOMONTH(C5,1) -> 46081 | E5: =EOMONTH(D5,1) -> 46112 | F5: =EOMONTH(E5,1) -> 46142 | G5: =EOMONTH(F5,1) -> 46173 | H5: =EOMONTH(G5,1) -> 46203 | I5: =EOMONTH(H5,1) -> 46234 | J5: =EOMONTH(I5,1) -> 46265 | K5: =EOMONTH(J5,1) -> 46295 | ... N5: =EOMONTH(M5,1) -> 46387
B7: Franchise Revenue | C7: ='Bonchon U.S. P&L (Monthly''26)'!C7+'Bonchon Int''l P&L (Monthly''26)'!C7-'Consolidations P&L (Monthly''26)'!C7 -> 1.301355 | D7: ='Bonchon U.S. P&L (Monthly''26)'!D7+'Bonchon Int''l P&L (Monthly''26)'!D7-'Consolidations P&L (Monthly''26)'!D7 -> 1.1675534 | E7: ='Bonchon U.S. P&L (Monthly''26)'!E7+'Bonchon Int''l P&L (Monthly''26)'!E7-'Consolidations P&L (Monthly''26)'!E7 -> 1.3237652 | F7: ='Bonchon U.S. P&L (Monthly''26)'!F7+'Bonchon Int''l P&L (Monthly''26)'!F7-'Consolidations P&L (Monthly''26)'!F7 -> 1.2908551 | G7: ='Bonchon U.S. P&L (Monthly''26)'!G7+'Bonchon Int''l P&L (Monthly''26)'!G7-'Consolidations P&L (Monthly''26)'!G7 -> 1.3789732 | H7: ='Bonchon U.S. P&L (Monthly''26)'!H7+'Bonchon Int''l P&L (Monthly''26)'!H7-'Consolidations P&L (Monthly''26)'!H7 -> 1.3695051 | I7: ='Bonchon U.S. P&L (Monthly''26)'!I7+'Bonchon Int''l P&L (Monthly''26)'!I7-'Consolidations P&L (Monthly''26)'!I7 -> 1.4273085 | J7: ='Bonchon U.S. P&L (Monthly''26)'!J7+'Bonchon Int''l P&L (Monthly''26)'!J7-'Consolidations P&L (Monthly''26)'!J7 -> 1.5216833 | ... N7: ='Bonchon U.S. P&L (Monthly''26)'!N7+'Bonchon Int''l P&L (Monthly''26)'!N7-'Consolidations P&L (Monthly''26)'!N7 -> 1.6475278
B8: Sauce Revenue | C8: ='Bonchon U.S. P&L (Monthly''26)'!C8+'Bonchon Int''l P&L (Monthly''26)'!C8-'Consolidations P&L (Monthly''26)'!C8 -> 0.63152161 | D8: ='Bonchon U.S. P&L (Monthly''26)'!D8+'Bonchon Int''l P&L (Monthly''26)'!D8-'Consolidations P&L (Monthly''26)'!D8 -> 0.66281353 | E8: ='Bonchon U.S. P&L (Monthly''26)'!E8+'Bonchon Int''l P&L (Monthly''26)'!E8-'Consolidations P&L (Monthly''26)'!E8 -> 0.64613732 | F8: ='Bonchon U.S. P&L (Monthly''26)'!F8+'Bonchon Int''l P&L (Monthly''26)'!F8-'Consolidations P&L (Monthly''26)'!F8 -> 0.62673388 | G8: ='Bonchon U.S. P&L (Monthly''26)'!G8+'Bonchon Int''l P&L (Monthly''26)'!G8-'Consolidations P&L (Monthly''26)'!G8 -> 0.70290137 | H8: ='Bonchon U.S. P&L (Monthly''26)'!H8+'Bonchon Int''l P&L (Monthly''26)'!H8-'Consolidations P&L (Monthly''26)'!H8 -> 0.64609681 | I8: ='Bonchon U.S. P&L (Monthly''26)'!I8+'Bonchon Int''l P&L (Monthly''26)'!I8-'Consolidations P&L (Monthly''26)'!I8 -> 0.69055541 | J8: ='Bonchon U.S. P&L (Monthly''26)'!J8+'Bonchon Int''l P&L (Monthly''26)'!J8-'Consolidations P&L (Monthly''26)'!J8 -> 0.65913715 | ... N8: ='Bonchon U.S. P&L (Monthly''26)'!N8+'Bonchon Int''l P&L (Monthly''26)'!N8-'Consolidations P&L (Monthly''26)'!N8 -> 0.67803728
B9: Company-Owned Store Revenue | C9: ='Bonchon U.S. P&L (Monthly''26)'!C9+'Bonchon Int''l P&L (Monthly''26)'!C9-'Consolidations P&L (Monthly''26)'!C9 -> 0.3177992 | D9: ='Bonchon U.S. P&L (Monthly''26)'!D9+'Bonchon Int''l P&L (Monthly''26)'!D9-'Consolidations P&L (Monthly''26)'!D9 -> 0.29569158 | E9: ='Bonchon U.S. P&L (Monthly''26)'!E9+'Bonchon Int''l P&L (Monthly''26)'!E9-'Consolidations P&L (Monthly''26)'!E9 -> 0.33281639 | F9: ='Bonchon U.S. P&L (Monthly''26)'!F9+'Bonchon Int''l P&L (Monthly''26)'!F9-'Consolidations P&L (Monthly''26)'!F9 -> 0.33914562 | G9: ='Bonchon U.S. P&L (Monthly''26)'!G9+'Bonchon Int''l P&L (Monthly''26)'!G9-'Consolidations P&L (Monthly''26)'!G9 -> 0.36193594 | H9: ='Bonchon U.S. P&L (Monthly''26)'!H9+'Bonchon Int''l P&L (Monthly''26)'!H9-'Consolidations P&L (Monthly''26)'!H9 -> 0.33255118 | I9: ='Bonchon U.S. P&L (Monthly''26)'!I9+'Bonchon Int''l P&L (Monthly''26)'!I9-'Consolidations P&L (Monthly''26)'!I9 -> 0.36484346 | J9: ='Bonchon U.S. P&L (Monthly''26)'!J9+'Bonchon Int''l P&L (Monthly''26)'!J9-'Consolidations P&L (Monthly''26)'!J9 -> 0.37344078 | ... N9: ='Bonchon U.S. P&L (Monthly''26)'!N9+'Bonchon Int''l P&L (Monthly''26)'!N9-'Consolidations P&L (Monthly''26)'!N9 -> 0.48012049
B10: Marketing Fund | C10: ='Bonchon U.S. P&L (Monthly''26)'!C10+'Bonchon Int''l P&L (Monthly''26)'!C10-'Consolidations P&L (Monthly''26)'!C10 -> 0.27353066 | D10: ='Bonchon U.S. P&L (Monthly''26)'!D10+'Bonchon Int''l P&L (Monthly''26)'!D10-'Consolidations P&L (Monthly''26)'!D10 -> 0.25054274 | E10: ='Bonchon U.S. P&L (Monthly''26)'!E10+'Bonchon Int''l P&L (Monthly''26)'!E10-'Consolidations P&L (Monthly''26)'!E10 -> 0.27245748 | F10: ='Bonchon U.S. P&L (Monthly''26)'!F10+'Bonchon Int''l P&L (Monthly''26)'!F10-'Consolidations P&L (Monthly''26)'!F10 -> 0.26642327 | G10: ='Bonchon U.S. P&L (Monthly''26)'!G10+'Bonchon Int''l P&L (Monthly''26)'!G10-'Consolidations P&L (Monthly''26)'!G10 -> 0.28520151 | H10: ='Bonchon U.S. P&L (Monthly''26)'!H10+'Bonchon Int''l P&L (Monthly''26)'!H10-'Consolidations P&L (Monthly''26)'!H10 -> 0.27329233 | I10: ='Bonchon U.S. P&L (Monthly''26)'!I10+'Bonchon Int''l P&L (Monthly''26)'!I10-'Consolidations P&L (Monthly''26)'!I10 -> 0.53034696 | J10: ='Bonchon U.S. P&L (Monthly''26)'!J10+'Bonchon Int''l P&L (Monthly''26)'!J10-'Consolidations P&L (Monthly''26)'!J10 -> 0.56233588 | ... N10: ='Bonchon U.S. P&L (Monthly''26)'!N10+'Bonchon Int''l P&L (Monthly''26)'!N10-'Consolidations P&L (Monthly''26)'!N10 -> 0.61620586
B11: Other Product Revenue | C11: ='Bonchon U.S. P&L (Monthly''26)'!C11+'Bonchon Int''l P&L (Monthly''26)'!C11-'Consolidations P&L (Monthly''26)'!C11 -> 0.00196428 | D11: ='Bonchon U.S. P&L (Monthly''26)'!D11+'Bonchon Int''l P&L (Monthly''26)'!D11-'Consolidations P&L (Monthly''26)'!D11 -> 0.0019642903 | E11: ='Bonchon U.S. P&L (Monthly''26)'!E11+'Bonchon Int''l P&L (Monthly''26)'!E11-'Consolidations P&L (Monthly''26)'!E11 -> 0.0020229537 | F11: ='Bonchon U.S. P&L (Monthly''26)'!F11+'Bonchon Int''l P&L (Monthly''26)'!F11-'Consolidations P&L (Monthly''26)'!F11 -> 0.00196428 | G11: ='Bonchon U.S. P&L (Monthly''26)'!G11+'Bonchon Int''l P&L (Monthly''26)'!G11-'Consolidations P&L (Monthly''26)'!G11 -> 0.00226928 | H11: ='Bonchon U.S. P&L (Monthly''26)'!H11+'Bonchon Int''l P&L (Monthly''26)'!H11-'Consolidations P&L (Monthly''26)'!H11 -> 0.0024829438 | I11: ='Bonchon U.S. P&L (Monthly''26)'!I11+'Bonchon Int''l P&L (Monthly''26)'!I11-'Consolidations P&L (Monthly''26)'!I11 -> 0.0019642821 | J11: ='Bonchon U.S. P&L (Monthly''26)'!J11+'Bonchon Int''l P&L (Monthly''26)'!J11-'Consolidations P&L (Monthly''26)'!J11 -> 0.00319872 | ... N11: ='Bonchon U.S. P&L (Monthly''26)'!N11+'Bonchon Int''l P&L (Monthly''26)'!N11-'Consolidations P&L (Monthly''26)'!N11 -> 0.00196428
B12: Other Revenue | C12: ='Bonchon U.S. P&L (Monthly''26)'!C12+'Bonchon Int''l P&L (Monthly''26)'!C12-'Consolidations P&L (Monthly''26)'!C12 -> 0.0137 | D12: ='Bonchon U.S. P&L (Monthly''26)'!D12+'Bonchon Int''l P&L (Monthly''26)'!D12-'Consolidations P&L (Monthly''26)'!D12 -> 0.0007 | E12: ='Bonchon U.S. P&L (Monthly''26)'!E12+'Bonchon Int''l P&L (Monthly''26)'!E12-'Consolidations P&L (Monthly''26)'!E12 -> 0.0072 | F12: ='Bonchon U.S. P&L (Monthly''26)'!F12+'Bonchon Int''l P&L (Monthly''26)'!F12-'Consolidations P&L (Monthly''26)'!F12 -> 0.0072 | G12: ='Bonchon U.S. P&L (Monthly''26)'!G12+'Bonchon Int''l P&L (Monthly''26)'!G12-'Consolidations P&L (Monthly''26)'!G12 -> 0.0072 | H12: ='Bonchon U.S. P&L (Monthly''26)'!H12+'Bonchon Int''l P&L (Monthly''26)'!H12-'Consolidations P&L (Monthly''26)'!H12 -> 0.0267 | I12: ='Bonchon U.S. P&L (Monthly''26)'!I12+'Bonchon Int''l P&L (Monthly''26)'!I12-'Consolidations P&L (Monthly''26)'!I12 -> 0.0202 | J12: ='Bonchon U.S. P&L (Monthly''26)'!J12+'Bonchon Int''l P&L (Monthly''26)'!J12-'Consolidations P&L (Monthly''26)'!J12 -> 0.0332 | ... N12: ='Bonchon U.S. P&L (Monthly''26)'!N12+'Bonchon Int''l P&L (Monthly''26)'!N12-'Consolidations P&L (Monthly''26)'!N12 -> 0.02722759
B13: Other | C13: =SUM(C11:C12) -> 0.01566428 | D13: =SUM(D11:D12) -> 0.0026642903 | E13: =SUM(E11:E12) -> 0.0092229537 | F13: =SUM(F11:F12) -> 0.00916428 | G13: =SUM(G11:G12) -> 0.00946928 | H13: =SUM(H11:H12) -> 0.029182944 | I13: =SUM(I11:I12) -> 0.022164282 | J13: =SUM(J11:J12) -> 0.03639872 | ... N13: =SUM(N11:N12) -> 0.02919187
B14: Total Revenue | C14: =SUM(C7:C10,C13) -> 2.5398707 | D14: =SUM(D7:D10,D13) -> 2.3792656 | E14: =SUM(E7:E10,E13) -> 2.5843994 | F14: =SUM(F7:F10,F13) -> 2.5323222 | G14: =SUM(G7:G10,G13) -> 2.7384813 | H14: =SUM(H7:H10,H13) -> 2.6506284 | I14: =SUM(I7:I10,I13) -> 3.0352186 | J14: =SUM(J7:J10,J13) -> 3.1529959 | ... N14: =SUM(N7:N10,N13) -> 3.4510833
B16: Sauce COGS | C16: ='Bonchon U.S. P&L (Monthly''26)'!C16+'Bonchon Int''l P&L (Monthly''26)'!C16-'Consolidations P&L (Monthly''26)'!C16 -> 0.10488532 | D16: ='Bonchon U.S. P&L (Monthly''26)'!D16+'Bonchon Int''l P&L (Monthly''26)'!D16-'Consolidations P&L (Monthly''26)'!D16 -> 0.11719923 | E16: ='Bonchon U.S. P&L (Monthly''26)'!E16+'Bonchon Int''l P&L (Monthly''26)'!E16-'Consolidations P&L (Monthly''26)'!E16 -> 0.10845707 | F16: ='Bonchon U.S. P&L (Monthly''26)'!F16+'Bonchon Int''l P&L (Monthly''26)'!F16-'Consolidations P&L (Monthly''26)'!F16 -> 0.10488532 | G16: ='Bonchon U.S. P&L (Monthly''26)'!G16+'Bonchon Int''l P&L (Monthly''26)'!G16-'Consolidations P&L (Monthly''26)'!G16 -> 0.12075719 | H16: ='Bonchon U.S. P&L (Monthly''26)'!H16+'Bonchon Int''l P&L (Monthly''26)'!H16-'Consolidations P&L (Monthly''26)'!H16 -> 0.10830347 | I16: ='Bonchon U.S. P&L (Monthly''26)'!I16+'Bonchon Int''l P&L (Monthly''26)'!I16-'Consolidations P&L (Monthly''26)'!I16 -> 0.11590643 | J16: ='Bonchon U.S. P&L (Monthly''26)'!J16+'Bonchon Int''l P&L (Monthly''26)'!J16-'Consolidations P&L (Monthly''26)'!J16 -> 0.10488532 | ... N16: ='Bonchon U.S. P&L (Monthly''26)'!N16+'Bonchon Int''l P&L (Monthly''26)'!N16-'Consolidations P&L (Monthly''26)'!N16 -> 0.10488532
B17: Company-Owned Store COGS | C17: ='Bonchon U.S. P&L (Monthly''26)'!C17+'Bonchon Int''l P&L (Monthly''26)'!C17-'Consolidations P&L (Monthly''26)'!C17 -> 0.090831474 | D17: ='Bonchon U.S. P&L (Monthly''26)'!D17+'Bonchon Int''l P&L (Monthly''26)'!D17-'Consolidations P&L (Monthly''26)'!D17 -> 0.084470296 | E17: ='Bonchon U.S. P&L (Monthly''26)'!E17+'Bonchon Int''l P&L (Monthly''26)'!E17-'Consolidations P&L (Monthly''26)'!E17 -> 0.095007017 | F17: ='Bonchon U.S. P&L (Monthly''26)'!F17+'Bonchon Int''l P&L (Monthly''26)'!F17-'Consolidations P&L (Monthly''26)'!F17 -> 0.096803062 | G17: ='Bonchon U.S. P&L (Monthly''26)'!G17+'Bonchon Int''l P&L (Monthly''26)'!G17-'Consolidations P&L (Monthly''26)'!G17 -> 0.10323126 | H17: ='Bonchon U.S. P&L (Monthly''26)'!H17+'Bonchon Int''l P&L (Monthly''26)'!H17-'Consolidations P&L (Monthly''26)'!H17 -> 0.094882498 | I17: ='Bonchon U.S. P&L (Monthly''26)'!I17+'Bonchon Int''l P&L (Monthly''26)'!I17-'Consolidations P&L (Monthly''26)'!I17 -> 0.10407647 | J17: ='Bonchon U.S. P&L (Monthly''26)'!J17+'Bonchon Int''l P&L (Monthly''26)'!J17-'Consolidations P&L (Monthly''26)'!J17 -> 0.10648666 | ... N17: ='Bonchon U.S. P&L (Monthly''26)'!N17+'Bonchon Int''l P&L (Monthly''26)'!N17-'Consolidations P&L (Monthly''26)'!N17 -> 0.14282435
B18: Other Product COGS | C18: ='Bonchon U.S. P&L (Monthly''26)'!C18+'Bonchon Int''l P&L (Monthly''26)'!C18-'Consolidations P&L (Monthly''26)'!C18 -> 0.0011419666 | D18: ='Bonchon U.S. P&L (Monthly''26)'!D18+'Bonchon Int''l P&L (Monthly''26)'!D18-'Consolidations P&L (Monthly''26)'!D18 -> 0.00090343715 | E18: ='Bonchon U.S. P&L (Monthly''26)'!E18+'Bonchon Int''l P&L (Monthly''26)'!E18-'Consolidations P&L (Monthly''26)'!E18 -> 0.00091790407 | F18: ='Bonchon U.S. P&L (Monthly''26)'!F18+'Bonchon Int''l P&L (Monthly''26)'!F18-'Consolidations P&L (Monthly''26)'!F18 -> 0.00090343561 | G18: ='Bonchon U.S. P&L (Monthly''26)'!G18+'Bonchon Int''l P&L (Monthly''26)'!G18-'Consolidations P&L (Monthly''26)'!G18 -> 0.002429137 | H18: ='Bonchon U.S. P&L (Monthly''26)'!H18+'Bonchon Int''l P&L (Monthly''26)'!H18-'Consolidations P&L (Monthly''26)'!H18 -> 0.0011438998 | I18: ='Bonchon U.S. P&L (Monthly''26)'!I18+'Bonchon Int''l P&L (Monthly''26)'!I18-'Consolidations P&L (Monthly''26)'!I18 -> 0.00090343788 | J18: ='Bonchon U.S. P&L (Monthly''26)'!J18+'Bonchon Int''l P&L (Monthly''26)'!J18-'Consolidations P&L (Monthly''26)'!J18 -> 0.00090343561 | ... N18: ='Bonchon U.S. P&L (Monthly''26)'!N18+'Bonchon Int''l P&L (Monthly''26)'!N18-'Consolidations P&L (Monthly''26)'!N18 -> 0.00089761941
B19: D&A In COGS | C19: ='Bonchon U.S. P&L (Monthly''26)'!C19+'Bonchon Int''l P&L (Monthly''26)'!C19-'Consolidations P&L (Monthly''26)'!C19 -> -0.01223677 | D19: ='Bonchon U.S. P&L (Monthly''26)'!D19+'Bonchon Int''l P&L (Monthly''26)'!D19-'Consolidations P&L (Monthly''26)'!D19 -> -0.01223677 | E19: ='Bonchon U.S. P&L (Monthly''26)'!E19+'Bonchon Int''l P&L (Monthly''26)'!E19-'Consolidations P&L (Monthly''26)'!E19 -> -0.01223677 | F19: ='Bonchon U.S. P&L (Monthly''26)'!F19+'Bonchon Int''l P&L (Monthly''26)'!F19-'Consolidations P&L (Monthly''26)'!F19 -> -0.01223677 | G19: ='Bonchon U.S. P&L (Monthly''26)'!G19+'Bonchon Int''l P&L (Monthly''26)'!G19-'Consolidations P&L (Monthly''26)'!G19 -> -0.01223677 | H19: ='Bonchon U.S. P&L (Monthly''26)'!H19+'Bonchon Int''l P&L (Monthly''26)'!H19-'Consolidations P&L (Monthly''26)'!H19 -> -0.01223677 | I19: ='Bonchon U.S. P&L (Monthly''26)'!I19+'Bonchon Int''l P&L (Monthly''26)'!I19-'Consolidations P&L (Monthly''26)'!I19 -> -0.01223677 | J19: ='Bonchon U.S. P&L (Monthly''26)'!J19+'Bonchon Int''l P&L (Monthly''26)'!J19-'Consolidations P&L (Monthly''26)'!J19 -> -0.01223677 | ... N19: ='Bonchon U.S. P&L (Monthly''26)'!N19+'Bonchon Int''l P&L (Monthly''26)'!N19-'Consolidations P&L (Monthly''26)'!N19 -> -0.01223677
B20: Other | C20: =SUM(C18:C19) -> -0.011094803 | D20: =SUM(D18:D19) -> -0.011333333 | E20: =SUM(E18:E19) -> -0.011318866 | F20: =SUM(F18:F19) -> -0.011333334 | G20: =SUM(G18:G19) -> -0.0098076327 | H20: =SUM(H18:H19) -> -0.01109287 | I20: =SUM(I18:I19) -> -0.011333332 | J20: =SUM(J18:J19) -> -0.011333334 | ... N20: =SUM(N18:N19) -> -0.01133915
B21: Total Cost of Goods Sold | C21: =SUM(C16:C17,C20) -> 0.18462199 | D21: =SUM(D16:D17,D20) -> 0.19033619 | E21: =SUM(E16:E17,E20) -> 0.19214522 | F21: =SUM(F16:F17,F20) -> 0.19035505 | G21: =SUM(G16:G17,G20) -> 0.21418082 | H21: =SUM(H16:H17,H20) -> 0.19209309 | I21: =SUM(I16:I17,I20) -> 0.20864957 | J21: =SUM(J16:J17,J20) -> 0.20003864 | ... N21: =SUM(N16:N17,N20) -> 0.23637052
B22: Gross Profit | C22: =C14-C21 -> 2.3552487 | D22: =D14-D21 -> 2.1889294 | E22: =E14-E21 -> 2.3922541 | F22: =F14-F21 -> 2.3419671 | G22: =G14-G21 -> 2.5243005 | H22: =H14-H21 -> 2.4585353 | I22: =I14-I21 -> 2.826569 | J22: =J14-J21 -> 2.9529572 | ... N22: =N14-N21 -> 3.2147128
B23: % Margin | C23: =IFERROR(C22/C14,"-") -> 0.92731048 | D23: =IFERROR(D22/D14,"-") -> 0.92000212 | E23: =IFERROR(E22/E14,"-") -> 0.92565188 | F23: =IFERROR(F22/F14,"-") -> 0.92482985 | G23: =IFERROR(G22/G14,"-") -> 0.92178847 | H23: =IFERROR(H22/H14,"-") -> 0.92752922 | I23: =IFERROR(I22/I14,"-") -> 0.93125715 | J23: =IFERROR(J22/J14,"-") -> 0.93655601 | ... N23: =IFERROR(N22/N14,"-") -> 0.93150831
B25: Corporate Labor | C25: ='Bonchon U.S. P&L (Monthly''26)'!C25+'Bonchon Int''l P&L (Monthly''26)'!C25-'Consolidations P&L (Monthly''26)'!C25 -> 0.60367845 | D25: ='Bonchon U.S. P&L (Monthly''26)'!D25+'Bonchon Int''l P&L (Monthly''26)'!D25-'Consolidations P&L (Monthly''26)'!D25 -> 0.63044676 | E25: ='Bonchon U.S. P&L (Monthly''26)'!E25+'Bonchon Int''l P&L (Monthly''26)'!E25-'Consolidations P&L (Monthly''26)'!E25 -> 0.61015949 | F25: ='Bonchon U.S. P&L (Monthly''26)'!F25+'Bonchon Int''l P&L (Monthly''26)'!F25-'Consolidations P&L (Monthly''26)'!F25 -> 0.60905211 | G25: ='Bonchon U.S. P&L (Monthly''26)'!G25+'Bonchon Int''l P&L (Monthly''26)'!G25-'Consolidations P&L (Monthly''26)'!G25 -> 0.60552078 | H25: ='Bonchon U.S. P&L (Monthly''26)'!H25+'Bonchon Int''l P&L (Monthly''26)'!H25-'Consolidations P&L (Monthly''26)'!H25 -> 0.61348133 | I25: ='Bonchon U.S. P&L (Monthly''26)'!I25+'Bonchon Int''l P&L (Monthly''26)'!I25-'Consolidations P&L (Monthly''26)'!I25 -> 0.60695099 | J25: ='Bonchon U.S. P&L (Monthly''26)'!J25+'Bonchon Int''l P&L (Monthly''26)'!J25-'Consolidations P&L (Monthly''26)'!J25 -> 0.60556076 | ... N25: ='Bonchon U.S. P&L (Monthly''26)'!N25+'Bonchon Int''l P&L (Monthly''26)'!N25-'Consolidations P&L (Monthly''26)'!N25 -> 0.63832743
B26: Company-Owned Store Labor | C26: ='Bonchon U.S. P&L (Monthly''26)'!C26+'Bonchon Int''l P&L (Monthly''26)'!C26-'Consolidations P&L (Monthly''26)'!C26 -> 0.099439404 | D26: ='Bonchon U.S. P&L (Monthly''26)'!D26+'Bonchon Int''l P&L (Monthly''26)'!D26-'Consolidations P&L (Monthly''26)'!D26 -> 0.09321638 | E26: ='Bonchon U.S. P&L (Monthly''26)'!E26+'Bonchon Int''l P&L (Monthly''26)'!E26-'Consolidations P&L (Monthly''26)'!E26 -> 0.10320413 | F26: ='Bonchon U.S. P&L (Monthly''26)'!F26+'Bonchon Int''l P&L (Monthly''26)'!F26-'Consolidations P&L (Monthly''26)'!F26 -> 0.10496505 | G26: ='Bonchon U.S. P&L (Monthly''26)'!G26+'Bonchon Int''l P&L (Monthly''26)'!G26-'Consolidations P&L (Monthly''26)'!G26 -> 0.1108965 | H26: ='Bonchon U.S. P&L (Monthly''26)'!H26+'Bonchon Int''l P&L (Monthly''26)'!H26-'Consolidations P&L (Monthly''26)'!H26 -> 0.10299025 | I26: ='Bonchon U.S. P&L (Monthly''26)'!I26+'Bonchon Int''l P&L (Monthly''26)'!I26-'Consolidations P&L (Monthly''26)'!I26 -> 0.11149413 | J26: ='Bonchon U.S. P&L (Monthly''26)'!J26+'Bonchon Int''l P&L (Monthly''26)'!J26-'Consolidations P&L (Monthly''26)'!J26 -> 0.11421817 | ... N26: ='Bonchon U.S. P&L (Monthly''26)'!N26+'Bonchon Int''l P&L (Monthly''26)'!N26-'Consolidations P&L (Monthly''26)'!N26 -> 0.15012036
B27: Total Labor | C27: =SUM(C25:C26) -> 0.70311785 | D27: =SUM(D25:D26) -> 0.72366314 | E27: =SUM(E25:E26) -> 0.71336361 | F27: =SUM(F25:F26) -> 0.71401716 | G27: =SUM(G25:G26) -> 0.71641728 | H27: =SUM(H25:H26) -> 0.71647158 | I27: =SUM(I25:I26) -> 0.71844512 | J27: =SUM(J25:J26) -> 0.71977893 | ... N27: =SUM(N25:N26) -> 0.78844778
B28: Marketing Fund | C28: ='Bonchon U.S. P&L (Monthly''26)'!C28+'Bonchon Int''l P&L (Monthly''26)'!C28-'Consolidations P&L (Monthly''26)'!C28 -> 0.27353066 | D28: ='Bonchon U.S. P&L (Monthly''26)'!D28+'Bonchon Int''l P&L (Monthly''26)'!D28-'Consolidations P&L (Monthly''26)'!D28 -> 0.25054274 | E28: ='Bonchon U.S. P&L (Monthly''26)'!E28+'Bonchon Int''l P&L (Monthly''26)'!E28-'Consolidations P&L (Monthly''26)'!E28 -> 0.27245748 | F28: ='Bonchon U.S. P&L (Monthly''26)'!F28+'Bonchon Int''l P&L (Monthly''26)'!F28-'Consolidations P&L (Monthly''26)'!F28 -> 0.26642327 | G28: ='Bonchon U.S. P&L (Monthly''26)'!G28+'Bonchon Int''l P&L (Monthly''26)'!G28-'Consolidations P&L (Monthly''26)'!G28 -> 0.28520151 | H28: ='Bonchon U.S. P&L (Monthly''26)'!H28+'Bonchon Int''l P&L (Monthly''26)'!H28-'Consolidations P&L (Monthly''26)'!H28 -> 0.27329233 | I28: ='Bonchon U.S. P&L (Monthly''26)'!I28+'Bonchon Int''l P&L (Monthly''26)'!I28-'Consolidations P&L (Monthly''26)'!I28 -> 0.53034696 | J28: ='Bonchon U.S. P&L (Monthly''26)'!J28+'Bonchon Int''l P&L (Monthly''26)'!J28-'Consolidations P&L (Monthly''26)'!J28 -> 0.56233588 | ... N28: ='Bonchon U.S. P&L (Monthly''26)'!N28+'Bonchon Int''l P&L (Monthly''26)'!N28-'Consolidations P&L (Monthly''26)'!N28 -> 0.61620586
B29: Service Fees | C29: ='Bonchon U.S. P&L (Monthly''26)'!C29+'Bonchon Int''l P&L (Monthly''26)'!C29-'Consolidations P&L (Monthly''26)'!C29 -> 0.17598415 | D29: ='Bonchon U.S. P&L (Monthly''26)'!D29+'Bonchon Int''l P&L (Monthly''26)'!D29-'Consolidations P&L (Monthly''26)'!D29 -> 0.17316733 | E29: ='Bonchon U.S. P&L (Monthly''26)'!E29+'Bonchon Int''l P&L (Monthly''26)'!E29-'Consolidations P&L (Monthly''26)'!E29 -> 0.18755197 | F29: ='Bonchon U.S. P&L (Monthly''26)'!F29+'Bonchon Int''l P&L (Monthly''26)'!F29-'Consolidations P&L (Monthly''26)'!F29 -> 0.19162717 | G29: ='Bonchon U.S. P&L (Monthly''26)'!G29+'Bonchon Int''l P&L (Monthly''26)'!G29-'Consolidations P&L (Monthly''26)'!G29 -> 0.16376645 | H29: ='Bonchon U.S. P&L (Monthly''26)'!H29+'Bonchon Int''l P&L (Monthly''26)'!H29-'Consolidations P&L (Monthly''26)'!H29 -> 0.18559309 | I29: ='Bonchon U.S. P&L (Monthly''26)'!I29+'Bonchon Int''l P&L (Monthly''26)'!I29-'Consolidations P&L (Monthly''26)'!I29 -> 0.16747996 | J29: ='Bonchon U.S. P&L (Monthly''26)'!J29+'Bonchon Int''l P&L (Monthly''26)'!J29-'Consolidations P&L (Monthly''26)'!J29 -> 0.17429609 | ... N29: ='Bonchon U.S. P&L (Monthly''26)'!N29+'Bonchon Int''l P&L (Monthly''26)'!N29-'Consolidations P&L (Monthly''26)'!N29 -> 0.22756217
B30: Travel & Entertainment | C30: ='Bonchon U.S. P&L (Monthly''26)'!C30+'Bonchon Int''l P&L (Monthly''26)'!C30-'Consolidations P&L (Monthly''26)'!C30 -> 0.057664899 | D30: ='Bonchon U.S. P&L (Monthly''26)'!D30+'Bonchon Int''l P&L (Monthly''26)'!D30-'Consolidations P&L (Monthly''26)'!D30 -> 0.092689908 | E30: ='Bonchon U.S. P&L (Monthly''26)'!E30+'Bonchon Int''l P&L (Monthly''26)'!E30-'Consolidations P&L (Monthly''26)'!E30 -> 0.086190298 | F30: ='Bonchon U.S. P&L (Monthly''26)'!F30+'Bonchon Int''l P&L (Monthly''26)'!F30-'Consolidations P&L (Monthly''26)'!F30 -> 0.1035938 | G30: ='Bonchon U.S. P&L (Monthly''26)'!G30+'Bonchon Int''l P&L (Monthly''26)'!G30-'Consolidations P&L (Monthly''26)'!G30 -> 0.083166438 | H30: ='Bonchon U.S. P&L (Monthly''26)'!H30+'Bonchon Int''l P&L (Monthly''26)'!H30-'Consolidations P&L (Monthly''26)'!H30 -> 0.086120658 | I30: ='Bonchon U.S. P&L (Monthly''26)'!I30+'Bonchon Int''l P&L (Monthly''26)'!I30-'Consolidations P&L (Monthly''26)'!I30 -> 0.081519948 | J30: ='Bonchon U.S. P&L (Monthly''26)'!J30+'Bonchon Int''l P&L (Monthly''26)'!J30-'Consolidations P&L (Monthly''26)'!J30 -> 0.13552415 | ... N30: ='Bonchon U.S. P&L (Monthly''26)'!N30+'Bonchon Int''l P&L (Monthly''26)'!N30-'Consolidations P&L (Monthly''26)'!N30 -> 0.14460413
B31: Rent | C31: ='Bonchon U.S. P&L (Monthly''26)'!C31+'Bonchon Int''l P&L (Monthly''26)'!C31-'Consolidations P&L (Monthly''26)'!C31 -> 0.06548303 | D31: ='Bonchon U.S. P&L (Monthly''26)'!D31+'Bonchon Int''l P&L (Monthly''26)'!D31-'Consolidations P&L (Monthly''26)'!D31 -> 0.06625084 | E31: ='Bonchon U.S. P&L (Monthly''26)'!E31+'Bonchon Int''l P&L (Monthly''26)'!E31-'Consolidations P&L (Monthly''26)'!E31 -> 0.065594053 | F31: ='Bonchon U.S. P&L (Monthly''26)'!F31+'Bonchon Int''l P&L (Monthly''26)'!F31-'Consolidations P&L (Monthly''26)'!F31 -> 0.065604065 | G31: ='Bonchon U.S. P&L (Monthly''26)'!G31+'Bonchon Int''l P&L (Monthly''26)'!G31-'Consolidations P&L (Monthly''26)'!G31 -> 0.065709705 | H31: ='Bonchon U.S. P&L (Monthly''26)'!H31+'Bonchon Int''l P&L (Monthly''26)'!H31-'Consolidations P&L (Monthly''26)'!H31 -> 0.086172234 | I31: ='Bonchon U.S. P&L (Monthly''26)'!I31+'Bonchon Int''l P&L (Monthly''26)'!I31-'Consolidations P&L (Monthly''26)'!I31 -> 0.065339359 | J31: ='Bonchon U.S. P&L (Monthly''26)'!J31+'Bonchon Int''l P&L (Monthly''26)'!J31-'Consolidations P&L (Monthly''26)'!J31 -> 0.065353161 | ... N31: ='Bonchon U.S. P&L (Monthly''26)'!N31+'Bonchon Int''l P&L (Monthly''26)'!N31-'Consolidations P&L (Monthly''26)'!N31 -> 0.074650893
B32: Freight | C32: ='Bonchon U.S. P&L (Monthly''26)'!C32+'Bonchon Int''l P&L (Monthly''26)'!C32-'Consolidations P&L (Monthly''26)'!C32 -> 0.036250274 | D32: ='Bonchon U.S. P&L (Monthly''26)'!D32+'Bonchon Int''l P&L (Monthly''26)'!D32-'Consolidations P&L (Monthly''26)'!D32 -> 0.033869424 | E32: ='Bonchon U.S. P&L (Monthly''26)'!E32+'Bonchon Int''l P&L (Monthly''26)'!E32-'Consolidations P&L (Monthly''26)'!E32 -> 0.037885592 | F32: ='Bonchon U.S. P&L (Monthly''26)'!F32+'Bonchon Int''l P&L (Monthly''26)'!F32-'Consolidations P&L (Monthly''26)'!F32 -> 0.041584822 | G32: ='Bonchon U.S. P&L (Monthly''26)'!G32+'Bonchon Int''l P&L (Monthly''26)'!G32-'Consolidations P&L (Monthly''26)'!G32 -> 0.041035979 | H32: ='Bonchon U.S. P&L (Monthly''26)'!H32+'Bonchon Int''l P&L (Monthly''26)'!H32-'Consolidations P&L (Monthly''26)'!H32 -> 0.037862448 | I32: ='Bonchon U.S. P&L (Monthly''26)'!I32+'Bonchon Int''l P&L (Monthly''26)'!I32-'Consolidations P&L (Monthly''26)'!I32 -> 0.041289624 | J32: ='Bonchon U.S. P&L (Monthly''26)'!J32+'Bonchon Int''l P&L (Monthly''26)'!J32-'Consolidations P&L (Monthly''26)'!J32 -> 0.0423313 | ... N32: ='Bonchon U.S. P&L (Monthly''26)'!N32+'Bonchon Int''l P&L (Monthly''26)'!N32-'Consolidations P&L (Monthly''26)'!N32 -> 0.05218152
B33: Advertising Expense | C33: ='Bonchon U.S. P&L (Monthly''26)'!C33+'Bonchon Int''l P&L (Monthly''26)'!C33-'Consolidations P&L (Monthly''26)'!C33 -> 0.036900104 | D33: ='Bonchon U.S. P&L (Monthly''26)'!D33+'Bonchon Int''l P&L (Monthly''26)'!D33-'Consolidations P&L (Monthly''26)'!D33 -> 0.041604714 | E33: ='Bonchon U.S. P&L (Monthly''26)'!E33+'Bonchon Int''l P&L (Monthly''26)'!E33-'Consolidations P&L (Monthly''26)'!E33 -> 0.063719857 | F33: ='Bonchon U.S. P&L (Monthly''26)'!F33+'Bonchon Int''l P&L (Monthly''26)'!F33-'Consolidations P&L (Monthly''26)'!F33 -> 0.041180144 | G33: ='Bonchon U.S. P&L (Monthly''26)'!G33+'Bonchon Int''l P&L (Monthly''26)'!G33-'Consolidations P&L (Monthly''26)'!G33 -> 0.042545647 | H33: ='Bonchon U.S. P&L (Monthly''26)'!H33+'Bonchon Int''l P&L (Monthly''26)'!H33-'Consolidations P&L (Monthly''26)'!H33 -> 0.038732101 | I33: ='Bonchon U.S. P&L (Monthly''26)'!I33+'Bonchon Int''l P&L (Monthly''26)'!I33-'Consolidations P&L (Monthly''26)'!I33 -> 0.044868112 | J33: ='Bonchon U.S. P&L (Monthly''26)'!J33+'Bonchon Int''l P&L (Monthly''26)'!J33-'Consolidations P&L (Monthly''26)'!J33 -> 0.048698671 | ... N33: ='Bonchon U.S. P&L (Monthly''26)'!N33+'Bonchon Int''l P&L (Monthly''26)'!N33-'Consolidations P&L (Monthly''26)'!N33 -> 0.058156097
B34: Other | C34: ='Bonchon U.S. P&L (Monthly''26)'!C34+'Bonchon Int''l P&L (Monthly''26)'!C34-'Consolidations P&L (Monthly''26)'!C34 -> 0.095941645 | D34: ='Bonchon U.S. P&L (Monthly''26)'!D34+'Bonchon Int''l P&L (Monthly''26)'!D34-'Consolidations P&L (Monthly''26)'!D34 -> 0.098792435 | E34: ='Bonchon U.S. P&L (Monthly''26)'!E34+'Bonchon Int''l P&L (Monthly''26)'!E34-'Consolidations P&L (Monthly''26)'!E34 -> 0.11200436 | F34: ='Bonchon U.S. P&L (Monthly''26)'!F34+'Bonchon Int''l P&L (Monthly''26)'!F34-'Consolidations P&L (Monthly''26)'!F34 -> 0.112745 | G34: ='Bonchon U.S. P&L (Monthly''26)'!G34+'Bonchon Int''l P&L (Monthly''26)'!G34-'Consolidations P&L (Monthly''26)'!G34 -> 0.10234942 | H34: ='Bonchon U.S. P&L (Monthly''26)'!H34+'Bonchon Int''l P&L (Monthly''26)'!H34-'Consolidations P&L (Monthly''26)'!H34 -> 0.10373003 | I34: ='Bonchon U.S. P&L (Monthly''26)'!I34+'Bonchon Int''l P&L (Monthly''26)'!I34-'Consolidations P&L (Monthly''26)'!I34 -> 0.10435165 | J34: ='Bonchon U.S. P&L (Monthly''26)'!J34+'Bonchon Int''l P&L (Monthly''26)'!J34-'Consolidations P&L (Monthly''26)'!J34 -> 0.10520742 | ... N34: ='Bonchon U.S. P&L (Monthly''26)'!N34+'Bonchon Int''l P&L (Monthly''26)'!N34-'Consolidations P&L (Monthly''26)'!N34 -> 0.12102308
B35: SG&A | C35: =SUM(C27:C34) -> 1.4448726 | D35: =SUM(D27:D34) -> 1.4805805 | E35: =SUM(E27:E34) -> 1.5387672 | F35: =SUM(F27:F34) -> 1.5367754 | G35: =SUM(G27:G34) -> 1.5001924 | H35: =SUM(H27:H34) -> 1.5279745 | I35: =SUM(I27:I34) -> 1.7536407 | J35: =SUM(J27:J34) -> 1.8535256 | ... N35: =SUM(N27:N34) -> 2.0828315
B36: % of Revenue | C36: =IFERROR(C35/C14,"-") -> 0.56887644 | D36: =IFERROR(D35/D14,"-") -> 0.62228469 | E36: =IFERROR(E35/E14,"-") -> 0.59540613 | F36: =IFERROR(F35/F14,"-") -> 0.6068641 | G36: =IFERROR(G35/G14,"-") -> 0.54781911 | H36: =IFERROR(H35/H14,"-") -> 0.57645745 | I36: =IFERROR(I35/I14,"-") -> 0.57776424 | J36: =IFERROR(J35/J14,"-") -> 0.58786173 | ... N36: =IFERROR(N35/N14,"-") -> 0.60352978
B38: Adj. EBITDA | C38: =C22-C35 -> 0.91037612 | D38: =D22-D35 -> 0.70834885 | E38: =E22-E35 -> 0.85348692 | F38: =F22-F35 -> 0.8051917 | G38: =G22-G35 -> 1.0241081 | H38: =H22-H35 -> 0.93056082 | I38: =I22-I35 -> 1.0729283 | J38: =J22-J35 -> 1.0994316 | ... N38: =N22-N35 -> 1.1318812
B39: % Margin | C39: =IFERROR(C38/C14,"-") -> 0.35843404 | D39: =IFERROR(D38/D14,"-") -> 0.29771744 | E39: =IFERROR(E38/E14,"-") -> 0.33024576 | F39: =IFERROR(F38/F14,"-") -> 0.31796574 | G39: =IFERROR(G38/G14,"-") -> 0.37396936 | H39: =IFERROR(H38/H14,"-") -> 0.35107178 | I39: =IFERROR(I38/I14,"-") -> 0.35349291 | J39: =IFERROR(J38/J14,"-") -> 0.34869428 | ... N39: =IFERROR(N38/N14,"-") -> 0.32797853

Sheet Bonchon U.S. P&L (Monthly'26)
B2: Bonchon U.S. 2026 Monthly P&L
C4: Plan
B5: ($ in millions) | C5: 46053 | D5: =EOMONTH(C5,1) -> 46081 | E5: =EOMONTH(D5,1) -> 46112 | F5: =EOMONTH(E5,1) -> 46142 | G5: =EOMONTH(F5,1) -> 46173 | H5: =EOMONTH(G5,1) -> 46203 | I5: =EOMONTH(H5,1) -> 46234 | J5: =EOMONTH(I5,1) -> 46265 | K5: =EOMONTH(J5,1) -> 46295 | ... N5: =EOMONTH(M5,1) -> 46387
B7: Franchise Revenue | C7: 0.90116753 | D7: 0.79460911 | E7: 0.8948585 | F7: 0.87235886 | G7: 0.93583142 | H7: 0.9643348 | I7: 1.0026844 | J7: 1.0870175 | K7: 0.99846289 | L7: 1.0498135 | M7: 0.98888835 | N7: 1.1348689
B8: Sauce Revenue | C8: 0.20651344 | D8: 0.19006366 | E8: 0.20591531 | F8: 0.20172571 | G8: 0.21521319 | H8: 0.20650141 | I8: 0.22206118 | J8: 0.23412897 | K8: 0.21926561 | L8: 0.23854431 | M8: 0.22989702 | N8: 0.25302911
B9: Company-Owned Store Revenue | C9: 0.3177992 | D9: 0.29569158 | E9: 0.33281639 | F9: 0.33914562 | G9: 0.36193594 | H9: 0.33255118 | I9: 0.36484346 | J9: 0.37344078 | K9: 0.36174037 | L9: 0.39882367 | M9: 0.37853943 | N9: 0.48012049
B10: Marketing Fund | C10: 0.27353066 | D10: 0.25054274 | E10: 0.27245748 | F10: 0.26642327 | G10: 0.28520151 | H10: 0.27329233 | I10: 0.53034696 | J10: 0.56233588 | K10: 0.52861775 | L10: 0.57675435 | M10: 0.55603972 | N10: 0.61620586
B11: Other Product Revenue | C11: 0.000795 | D11: 0.000795 | E11: 0.000795 | F11: 0.000795 | G11: 0.000795 | H11: 0.000795 | I11: 0.000795 | J11: 0.000795 | K11: 0.000795 | L11: 0.000795 | M11: 0.000795 | N11: 0.000795
B12: Other Revenue | C12: 0.0137 | D12: 0.0007 | E12: 0.0072 | F12: 0.0072 | G12: 0.0072 | H12: 0.0267 | I12: 0.0202 | J12: 0.0332 | K12: 0.0267 | L12: 0.0202 | M12: 0.0137 | N12: 0.02722759
B13: Other | C13: =SUM(C11:C12) -> 0.014495 | D13: =SUM(D11:D12) -> 0.001495 | E13: =SUM(E11:E12) -> 0.007995 | F13: =SUM(F11:F12) -> 0.007995 | G13: =SUM(G11:G12) -> 0.007995 | H13: =SUM(H11:H12) -> 0.027495 | I13: =SUM(I11:I12) -> 0.020995 | J13: =SUM(J11:J12) -> 0.033995 | ... N13: =SUM(N11:N12) -> 0.02802259
B14: Total Revenue | C14: =SUM(C7:C10,C13) -> 1.7135058 | D14: =SUM(D7:D10,D13) -> 1.5324021 | E14: =SUM(E7:E10,E13) -> 1.7140427 | F14: =SUM(F7:F10,F13) -> 1.6876485 | G14: =SUM(G7:G10,G13) -> 1.8061771 | H14: =SUM(H7:H10,H13) -> 1.8041747 | I14: =SUM(I7:I10,I13) -> 2.140931 | J14: =SUM(J7:J10,J13) -> 2.2909182 | ... N14: =SUM(N7:N10,N13) -> 2.5122469
B16: Sauce COGS | C16: 0 | D16: 0 | E16: 0 | F16: 0 | G16: 0 | H16: 0 | I16: 0 | J16: 0 | K16: 0 | L16: 0 | M16: 0 | N16: 0
B17: Company-Owned Store COGS | C17: 0.090831474 | D17: 0.084470296 | E17: 0.095007017 | F17: 0.096803062 | G17: 0.10323126 | H17: 0.094882498 | I17: 0.10407647 | J17: 0.10648666 | K17: 0.10326592 | L17: 0.11379931 | M17: 0.10807608 | N17: 0.14282435
B18: Other Product COGS | C18: 0.00047906434 | D18: 0.00047906434 | E18: 0.00047906434 | F18: 0.00047906434 | G18: 0.00047906434 | H18: 0.00047906434 | I18: 0.00047906434 | J18: 0.00047906434 | K18: 0.00047906434 | L18: 0.00047906434 | M18: 0.00047906434 | N18: 0.00047906434
B19: D&A In COGS | C19: 0 | D19: 0 | E19: 0 | F19: 0 | G19: 0 | H19: 0 | I19: 0 | J19: 0 | K19: 0 | L19: 0 | M19: 0 | N19: 0
B20: Other | C20: =SUM(C18:C19) -> 0.00047906434 | D20: =SUM(D18:D19) -> 0.00047906434 | E20: =SUM(E18:E19) -> 0.00047906434 | F20: =SUM(F18:F19) -> 0.00047906434 | G20: =SUM(G18:G19) -> 0.00047906434 | H20: =SUM(H18:H19) -> 0.00047906434 | I20: =SUM(I18:I19) -> 0.00047906434 | J20: =SUM(J18:J19) -> 0.00047906434 | ... N20: =SUM(N18:N19) -> 0.00047906434
B21: Total Cost of Goods Sold | C21: =SUM(C16:C17,C20) -> 0.091310539 | D21: =SUM(D16:D17,D20) -> 0.08494936 | E21: =SUM(E16:E17,E20) -> 0.095486081 | F21: =SUM(F16:F17,F20) -> 0.097282127 | G21: =SUM(G16:G17,G20) -> 0.10371033 | H21: =SUM(H16:H17,H20) -> 0.095361563 | I21: =SUM(I16:I17,I20) -> 0.10455554 | J21: =SUM(J16:J17,J20) -> 0.10696572 | ... N21: =SUM(N16:N17,N20) -> 0.14330341
B22: Gross Profit | C22: =C14-C21 -> 1.6221953 | D22: =D14-D21 -> 1.4474527 | E22: =E14-E21 -> 1.6185566 | F22: =F14-F21 -> 1.5903663 | G22: =G14-G21 -> 1.7024667 | H22: =H14-H21 -> 1.7088131 | I22: =I14-I21 -> 2.0363755 | J22: =J14-J21 -> 2.1839524 | ... N22: =N14-N21 -> 2.3689435
B23: % Margin | C23: =IFERROR(C22/C14,"-") -> 0.94671128 | D23: =IFERROR(D22/D14,"-") -> 0.94456458 | E23: =IFERROR(E22/E14,"-") -> 0.94429189 | F23: =IFERROR(F22/F14,"-") -> 0.9423564 | G23: =IFERROR(G22/G14,"-") -> 0.9425802 | H23: =IFERROR(H22/H14,"-") -> 0.94714394 | I23: =IFERROR(I22/I14,"-") -> 0.95116352 | J23: =IFERROR(J22/J14,"-") -> 0.9533088 | ... N23: =IFERROR(N22/N14,"-") -> 0.94295807
B25: Corporate Labor | C25: 0.49961129 | D25: 0.51876333 | E25: 0.50263629 | F25: 0.50223316 | G25: 0.49975816 | H25: 0.50595816 | I25: 0.50013201 | J25: 0.49979816 | K25: 0.50365816 | L25: 0.51457889 | M25: 0.51417889 | N25: 0.52657889
B26: Company-Owned Store Labor | C26: 0.099439404 | D26: 0.09321638 | E26: 0.10320413 | F26: 0.10496505 | G26: 0.1108965 | H26: 0.10299025 | I26: 0.11149413 | J26: 0.11421817 | K26: 0.1108654 | L26: 0.12108979 | M26: 0.11574466 | N26: 0.15012036
B27: Total Labor | C27: =SUM(C25:C26) -> 0.59905069 | D27: =SUM(D25:D26) -> 0.61197971 | E27: =SUM(E25:E26) -> 0.60584041 | F27: =SUM(F25:F26) -> 0.60719821 | G27: =SUM(G25:G26) -> 0.61065466 | H27: =SUM(H25:H26) -> 0.60894841 | I27: =SUM(I25:I26) -> 0.61162614 | J27: =SUM(J25:J26) -> 0.61401633 | ... N27: =SUM(N25:N26) -> 0.67669924
B28: Marketing Fund | C28: 0.27353066 | D28: 0.25054274 | E28: 0.27245748 | F28: 0.26642327 | G28: 0.28520151 | H28: 0.27329233 | I28: 0.53034696 | J28: 0.56233588 | K28: 0.52861775 | L28: 0.57675435 | M28: 0.55603972 | N28: 0.61620586
B29: Service Fees | C29: 0.13911922 | D29: 0.13630239 | E29: 0.15068704 | F29: 0.13775519 | G29: 0.12690152 | H29: 0.14872815 | I29: 0.13061503 | J29: 0.13743116 | K29: 0.14355132 | L29: 0.1361586 | M29: 0.14086228 | N29: 0.28917166
B30: Travel & Entertainment | C30: 0.039355039 | D30: 0.059591318 | E30: 0.067176208 | F30: 0.078241698 | G30: 0.057814318 | H30: 0.060064318 | I30: 0.063914318 | J30: 0.11087626 | K30: 0.11190318 | L30: 0.11508454 | M30: 0.096921478 | N30: 0.12347738
B31: Rent | C31: 0.05364078 | D31: 0.05440858 | E31: 0.053751803 | F31: 0.053761805 | G31: 0.053867455 | H31: 0.074329984 | I31: 0.053497099 | J31: 0.053510911 | K31: 0.053525415 | L31: 0.053540643 | M31: 0.053556633 | N31: 0.062808643
B32: Freight | C32: 0.035405204 | D32: 0.033024354 | E32: 0.037040522 | F32: 0.040739752 | G32: 0.040190909 | H32: 0.037017378 | I32: 0.040444554 | J32: 0.04148623 | K32: 0.045096211 | L32: 0.044152289 | M32: 0.046950303 | N32: 0.05133644
B33: Advertising Expense | C33: 0.035491654 | D33: 0.040196264 | E33: 0.062311407 | F33: 0.039771694 | G33: 0.041137197 | H33: 0.037323651 | I33: 0.043459662 | J33: 0.047290211 | K33: 0.045219559 | L33: 0.049658667 | M33: 0.058593678 | N33: 0.056747647
B34: Other | C34: 0.071688995 | D34: 0.074045105 | E34: 0.074343467 | F34: 0.07498188 | G34: 0.078732091 | H34: 0.080063962 | I34: 0.084221305 | J34: 0.084965705 | K34: 0.095735576 | L34: 0.08632048 | M34: 0.081507169 | N34: 0.10082966
B35: SG&A | C35: =SUM(C27:C34) -> 1.2472822 | D35: =SUM(D27:D34) -> 1.2600905 | E35: =SUM(E27:E34) -> 1.3236083 | F35: =SUM(F27:F34) -> 1.2988735 | G35: =SUM(G27:G34) -> 1.2944997 | H35: =SUM(H27:H34) -> 1.3197682 | I35: =SUM(I27:I34) -> 1.5581251 | J35: =SUM(J27:J34) -> 1.6519127 | ... N35: =SUM(N27:N34) -> 1.9772765
B36: % of Revenue | C36: =IFERROR(C35/C14,"-") -> 0.72791246 | D36: =IFERROR(D35/D14,"-") -> 0.82229753 | E36: =IFERROR(E35/E14,"-") -> 0.77221434 | F36: =IFERROR(F35/F14,"-") -> 0.7696351 | G36: =IFERROR(G35/G14,"-") -> 0.71670695 | H36: =IFERROR(H35/H14,"-") -> 0.73150797 | I36: =IFERROR(I35/I14,"-") -> 0.72777921 | J36: =IFERROR(J35/J14,"-") -> 0.72107014 | ... N36: =IFERROR(N35/N14,"-") -> 0.78705501
B38: Adj. EBITDA | C38: =C22-C35 -> 0.37491305 | D38: =D22-D35 -> 0.18736227 | E38: =E22-E35 -> 0.29494827 | F38: =F22-F35 -> 0.29149284 | G38: =G22-G35 -> 0.40796708 | H38: =H22-H35 -> 0.38904497 | I38: =I22-I35 -> 0.4782504 | J38: =J22-J35 -> 0.53203975 | ... N38: =N22-N35 -> 0.39166698
B39: % Margin | C39: =IFERROR(C38/C14,"-") -> 0.21879882 | D39: =IFERROR(D38/D14,"-") -> 0.12226704 | E39: =IFERROR(E38/E14,"-") -> 0.17207755 | F39: =IFERROR(F38/F14,"-") -> 0.1727213 | G39: =IFERROR(G38/G14,"-") -> 0.22587325 | H39: =IFERROR(H38/H14,"-") -> 0.21563597 | I39: =IFERROR(I38/I14,"-") -> 0.22338431 | J39: =IFERROR(J38/J14,"-") -> 0.23223866 | ... N39: =IFERROR(N38/N14,"-") -> 0.15590306

Sheet Bonchon Int'l P&L (Monthly'26)
B2: Bonchon International 2026 Monthly P&L
C4: Plan
B5: ($ in millions) | C5: 46053 | D5: =EOMONTH(C5,1) -> 46081 | E5: =EOMONTH(D5,1) -> 46112 | F5: =EOMONTH(E5,1) -> 46142 | G5: =EOMONTH(F5,1) -> 46173 | H5: =EOMONTH(G5,1) -> 46203 | I5: =EOMONTH(H5,1) -> 46234 | J5: =EOMONTH(I5,1) -> 46265 | K5: =EOMONTH(J5,1) -> 46295 | ... N5: =EOMONTH(M5,1) -> 46387
B7: Franchise Revenue | C7: 0.40018744 | D7: 0.37294432 | E7: 0.42890671 | F7: 0.41849627 | G7: 0.44314183 | H7: 0.40517034 | I7: 0.42462405 | J7: 0.43466579 | K7: 0.40133228 | L7: 0.44286954 | M7: 0.42334475 | N7: 0.51265891
B8: Sauce Revenue | C8: 0.42500817 | D8: 0.47274987 | E8: 0.44022201 | F8: 0.42500817 | G8: 0.48768818 | H8: 0.4395954 | I8: 0.46849423 | J8: 0.42500818 | K8: 0.43938113 | L8: 0.56654577 | M8: 0.46111156 | N8: 0.42500817
B9: Company-Owned Store Revenue | C9: 0 | D9: 0 | E9: 0 | F9: 0 | G9: 0 | H9: 0 | I9: 0 | J9: 0 | K9: 0 | L9: 0 | M9: 0 | N9: 0
B10: Marketing Fund | C10: 0 | D10: 0 | E10: 0 | F10: 0 | G10: 0 | H10: 0 | I10: 0 | J10: 0 | K10: 0 | L10: 0 | M10: 0 | N10: 0
B11: Other Product Revenue | C11: 0.00116928 | D11: 0.0011692903 | E11: 0.0012279537 | F11: 0.00116928 | G11: 0.00147428 | H11: 0.0016879438 | I11: 0.0011692821 | J11: 0.00240372 | K11: 0.001169288 | L11: 0.0020652197 | M11: 0.0011692873 | N11: 0.00116928
B12: Other Revenue | C12: 0 | D12: 0 | E12: 0 | F12: 0 | G12: 0 | H12: 0 | I12: 0 | J12: 0 | K12: 0 | L12: 0 | M12: 0 | N12: 0.1301371
B13: Other | C13: =SUM(C11:C12) -> 0.00116928 | D13: =SUM(D11:D12) -> 0.0011692903 | E13: =SUM(E11:E12) -> 0.0012279537 | F13: =SUM(F11:F12) -> 0.00116928 | G13: =SUM(G11:G12) -> 0.00147428 | H13: =SUM(H11:H12) -> 0.0016879438 | I13: =SUM(I11:I12) -> 0.0011692821 | J13: =SUM(J11:J12) -> 0.00240372 | ... N13: =SUM(N11:N12) -> 0.13130638
B14: Total Revenue | C14: =SUM(C7:C10,C13) -> 0.82636489 | D14: =SUM(D7:D10,D13) -> 0.84686348 | E14: =SUM(E7:E10,E13) -> 0.87035667 | F14: =SUM(F7:F10,F13) -> 0.84467372 | G14: =SUM(G7:G10,G13) -> 0.93230429 | H14: =SUM(H7:H10,H13) -> 0.84645368 | I14: =SUM(I7:I10,I13) -> 0.89428756 | J14: =SUM(J7:J10,J13) -> 0.86207769 | ... N14: =SUM(N7:N10,N13) -> 1.0689735
B16: Sauce COGS | C16: 0.10488532 | D16: 0.11719923 | E16: 0.10845707 | F16: 0.10488532 | G16: 0.12075719 | H16: 0.10830347 | I16: 0.11590643 | J16: 0.10488532 | K16: 0.10817941 | L16: 0.13945222 | M16: 0.11275443 | N16: 0.10488532
B17: Company-Owned Store COGS | C17: 0 | D17: 0 | E17: 0 | F17: 0 | G17: 0 | H17: 0 | I17: 0 | J17: 0 | K17: 0 | L17: 0 | M17: 0 | N17: 0
B18: Other Product COGS | C18: 0.00062131 | D18: 0.00062131225 | E18: 0.00063577847 | F18: 0.00062131 | G18: 0.0021470114 | H18: 0.00086177419 | I18: 0.00062131227 | J18: 0.00062131 | K18: 0.00062131554 | L18: 0.0023329065 | M18: 0.000621307 | N18: 0.00062131
B19: D&A In COGS | C19: -0.01223677 | D19: -0.01223677 | E19: -0.01223677 | F19: -0.01223677 | G19: -0.01223677 | H19: -0.01223677 | I19: -0.01223677 | J19: -0.01223677 | K19: -0.01223677 | L19: -0.01223677 | M19: -0.01223677 | N19: -0.01223677
B20: Other | C20: =SUM(C18:C19) -> -0.01161546 | D20: =SUM(D18:D19) -> -0.011615457 | E20: =SUM(E18:E19) -> -0.011600991 | F20: =SUM(F18:F19) -> -0.01161546 | G20: =SUM(G18:G19) -> -0.010089758 | H20: =SUM(H18:H19) -> -0.011374996 | I20: =SUM(I18:I19) -> -0.011615457 | J20: =SUM(J18:J19) -> -0.01161546 | ... N20: =SUM(N18:N19) -> -0.01161546
B21: Total Cost of Goods Sold | C21: =SUM(C16:C17,C20) -> 0.09326986 | D21: =SUM(D16:D17,D20) -> 0.10558377 | E21: =SUM(E16:E17,E20) -> 0.09685608 | F21: =SUM(F16:F17,F20) -> 0.09326986 | G21: =SUM(G16:G17,G20) -> 0.11066743 | H21: =SUM(H16:H17,H20) -> 0.09692847 | I21: =SUM(I16:I17,I20) -> 0.10429097 | J21: =SUM(J16:J17,J20) -> 0.09326986 | ... N21: =SUM(N16:N17,N20) -> 0.09326986
B22: Gross Profit | C22: =C14-C21 -> 0.73309503 | D22: =D14-D21 -> 0.74127971 | E22: =E14-E21 -> 0.77350059 | F22: =F14-F21 -> 0.75140386 | G22: =G14-G21 -> 0.82163686 | H22: =H14-H21 -> 0.74952521 | I22: =I14-I21 -> 0.78999659 | J22: =J14-J21 -> 0.76880783 | ... N22: =N14-N21 -> 0.9757036
B23: % Margin | C23: =IFERROR(C22/C14,"-") -> 0.88713235 | D23: =IFERROR(D22/D14,"-") -> 0.87532374 | E23: =IFERROR(E22/E14,"-") -> 0.88871679 | F23: =IFERROR(F22/F14,"-") -> 0.88957883 | G23: =IFERROR(G22/G14,"-") -> 0.88129688 | H23: =IFERROR(H22/H14,"-") -> 0.88548875 | I23: =IFERROR(I22/I14,"-") -> 0.88338094 | J23: =IFERROR(J22/J14,"-") -> 0.89180806 | ... N23: =IFERROR(N22/N14,"-") -> 0.9127482
B25: Corporate Labor | C25: 0.10406716 | D25: 0.11168343 | E25: 0.1075232 | F25: 0.10681895 | G25: 0.10576262 | H25: 0.10752317 | I25: 0.10681898 | J25: 0.1057626 | K25: 0.1106922 | L25: 0.10681896 | M25: 0.10576261 | N25: 0.11174854
B26: Company-Owned Store Labor | C26: 0 | D26: 0 | E26: 0 | F26: 0 | G26: 0 | H26: 0 | I26: 0 | J26: 0 | K26: 0 | L26: 0 | M26: 0 | N26: 0
B27: Total Labor | C27: =SUM(C25:C26) -> 0.10406716 | D27: =SUM(D25:D26) -> 0.11168343 | E27: =SUM(E25:E26) -> 0.1075232 | F27: =SUM(F25:F26) -> 0.10681895 | G27: =SUM(G25:G26) -> 0.10576262 | H27: =SUM(H25:H26) -> 0.10752317 | I27: =SUM(I25:I26) -> 0.10681898 | J27: =SUM(J25:J26) -> 0.1057626 | ... N27: =SUM(N25:N26) -> 0.11174854
B28: Marketing Fund | C28: 0 | D28: 0 | E28: 0 | F28: 0 | G28: 0 | H28: 0 | I28: 0 | J28: 0 | K28: 0 | L28: 0 | M28: 0 | N28: 0
B29: Service Fees | C29: 0.03686493 | D29: 0.03686494 | E29: 0.03686493 | F29: 0.05387198 | G29: 0.03686493 | H29: 0.03686494 | I29: 0.03686493 | J29: 0.03686493 | K29: 0.03857304 | L29: 0.03686493 | M29: 0.05472233 | N29: 0.06852761
B30: Travel & Entertainment | C30: 0.01830986 | D30: 0.03309859 | E30: 0.01901409 | F30: 0.0253521 | G30: 0.02535212 | H30: 0.02605634 | I30: 0.01760563 | J30: 0.02464789 | K30: 0.01901408 | L30: 0.02464789 | M30: 0.01478874 | N30: 0.02112675
B31: Rent | C31: 0.01184225 | D31: 0.01184226 | E31: 0.01184225 | F31: 0.01184226 | G31: 0.01184225 | H31: 0.01184225 | I31: 0.01184226 | J31: 0.01184225 | K31: 0.00376748 | L31: 0.00376748 | M31: 0.00376748 | N31: 0.01184225
B32: Freight | C32: 0.00084507 | D32: 0.00084507 | E32: 0.00084507 | F32: 0.00084507 | G32: 0.00084507 | H32: 0.00084507 | I32: 0.00084507 | J32: 0.00084507 | K32: 0.00084507 | L32: 0.00084507 | M32: 0.00084507 | N32: 0.00084508
B33: Advertising Expense | C33: 0.00140845 | D33: 0.00140845 | E33: 0.00140845 | F33: 0.00140845 | G33: 0.00140845 | H33: 0.00140845 | I33: 0.00140845 | J33: 0.00140846 | K33: 0.00140845 | L33: 0.00140845 | M33: 0.00140845 | N33: 0.00140845
B34: Other | C34: 0.02425265 | D34: 0.02474733 | E34: 0.03766089 | F34: 0.03776312 | G34: 0.02361733 | H34: 0.02366607 | I34: 0.02013035 | J34: 0.02024171 | K34: 0.02097959 | L34: 0.02013541 | M34: 0.0200821 | N34: 0.02019342
B35: SG&A | C35: =SUM(C27:C34) -> 0.19759037 | D35: =SUM(D27:D34) -> 0.22049007 | E35: =SUM(E27:E34) -> 0.21515888 | F35: =SUM(F27:F34) -> 0.23790193 | G35: =SUM(G27:G34) -> 0.20569277 | H35: =SUM(H27:H34) -> 0.20820629 | I35: =SUM(I27:I34) -> 0.19551567 | J35: =SUM(J27:J34) -> 0.20161291 | ... N35: =SUM(N27:N34) -> 0.2356921
B36: % of Revenue | C36: =IFERROR(C35/C14,"-") -> 0.2391079 | D36: =IFERROR(D35/D14,"-") -> 0.26036082 | E36: =IFERROR(E35/E14,"-") -> 0.24720771 | F36: =IFERROR(F35/F14,"-") -> 0.2816495 | G36: =IFERROR(G35/G14,"-") -> 0.22062836 | H36: =IFERROR(H35/H14,"-") -> 0.24597482 | I36: =IFERROR(I35/I14,"-") -> 0.21862729 | J36: =IFERROR(J35/J14,"-") -> 0.23386861 | ... N36: =IFERROR(N35/N14,"-") -> 0.22048452
B38: Adj. EBITDA | C38: =C22-C35 -> 0.53550466 | D38: =D22-D35 -> 0.52078964 | E38: =E22-E35 -> 0.55834171 | F38: =F22-F35 -> 0.51350193 | G38: =G22-G35 -> 0.61594409 | H38: =H22-H35 -> 0.54131892 | I38: =I22-I35 -> 0.59448092 | J38: =J22-J35 -> 0.56719492 | ... N38: =N22-N35 -> 0.7400115
B39: % Margin | C39: =IFERROR(C38/C14,"-") -> 0.64802446 | D39: =IFERROR(D38/D14,"-") -> 0.61496292 | E39: =IFERROR(E38/E14,"-") -> 0.64150908 | F39: =IFERROR(F38/F14,"-") -> 0.60792933 | G39: =IFERROR(G38/G14,"-") -> 0.66066851 | H39: =IFERROR(H38/H14,"-") -> 0.63951393 | I39: =IFERROR(I38/I14,"-") -> 0.66475365 | J39: =IFERROR(J38/J14,"-") -> 0.65793945 | ... N39: =IFERROR(N38/N14,"-") -> 0.69226368

Sheet Consolidations P&L (Monthly'26)
B2: Consolidations 2026 Monthly P&L
C4: Plan
B5: ($ in millions) | C5: 46053 | D5: =EOMONTH(C5,1) -> 46081 | E5: =EOMONTH(D5,1) -> 46112 | F5: =EOMONTH(E5,1) -> 46142 | G5: =EOMONTH(F5,1) -> 46173 | H5: =EOMONTH(G5,1) -> 46203 | I5: =EOMONTH(H5,1) -> 46234 | J5: =EOMONTH(I5,1) -> 46265 | K5: =EOMONTH(J5,1) -> 46295 | ... N5: =EOMONTH(M5,1) -> 46387
B7: Franchise Revenue | C7: 0 | D7: 0 | E7: 0 | F7: 0 | G7: 0 | H7: 0 | I7: 0 | J7: 0 | K7: 0 | L7: 0 | M7: 0 | N7: 0
B8: Sauce Revenue | C8: 0 | D8: 0 | E8: 0 | F8: 0 | G8: 0 | H8: 0 | I8: 0 | J8: 0 | K8: 0 | L8: 0 | M8: 0 | N8: 0
B9: Company-Owned Store Revenue | C9: 0 | D9: 0 | E9: 0 | F9: 0 | G9: 0 | H9: 0 | I9: 0 | J9: 0 | K9: 0 | L9: 0 | M9: 0 | N9: 0
B10: Marketing Fund | C10: 0 | D10: 0 | E10: 0 | F10: 0 | G10: 0 | H10: 0 | I10: 0 | J10: 0 | K10: 0 | L10: 0 | M10: 0 | N10: 0
B11: Other Product Revenue | C11: 0 | D11: 0 | E11: 0 | F11: 0 | G11: 0 | H11: 0 | I11: 0 | J11: 0 | K11: 0 | L11: 0 | M11: 0 | N11: 0
B12: Other Revenue | C12: 0 | D12: 0 | E12: 0 | F12: 0 | G12: 0 | H12: 0 | I12: 0 | J12: 0 | K12: 0 | L12: 0 | M12: 0 | N12: 0.1301371
B13: Other | C13: =SUM(C11:C12) -> 0 | D13: =SUM(D11:D12) -> 0 | E13: =SUM(E11:E12) -> 0 | F13: =SUM(F11:F12) -> 0 | G13: =SUM(G11:G12) -> 0 | H13: =SUM(H11:H12) -> 0 | I13: =SUM(I11:I12) -> 0 | J13: =SUM(J11:J12) -> 0 | ... N13: =SUM(N11:N12) -> 0.1301371
