Workbook
Name IQ_CH: 110000
Name IQ_CQ: 5000
Name IQ_CY: 10000
Name IQ_DAILY: 500000
Name IQ_FH: 100000
Name IQ_FQ: 500
Name IQ_FY: 1000
Name IQ_LTM: 2000
Name IQ_MONTH: 15000
Name IQ_NTM: 6000
Name IQ_WEEK: 50000
Name IQ_YTD: 3000
Name mkmkmkmkmk: #REF!
Name mshare: #REF!
Name ohfswhif: #REF!

Sheet Summary
C3: 2022 | D3: 2023 | E3: 2024 | F3: 2025 | G3: 2026 Plan
B4: Working | C4: =-'Marketing Fund 2022'!T108 -> 990072.61 | D4: =-'Marketing Fund 2023'!T108 -> 1572569.3 | E4: =-'Marketing Fund 2024'!T108 -> 1512356.1 | F4: =-'Marketing Fund 2025'!T107 -> 3285202 | G4: =-'Marketing Fund 2026 Plan'!T108 -> 3846000
B5: Non-working | C5: =-'Marketing Fund 2022'!T109 -> 1373816.3 | D5: =-'Marketing Fund 2023'!T109 -> 1611095.5 | E5: =-'Marketing Fund 2024'!T109 -> 2111103.9 | F5: =-'Marketing Fund 2025'!T108 -> 1709340.5 | G5: =-'Marketing Fund 2026 Plan'!T109 -> 2360141
B6: Total Marketing Spending | C6: =C4+C5 -> 2363888.9 | D6: =D4+D5 -> 3183664.8 | E6: =E4+E5 -> 3623459.9 | F6: =F4+F5 -> 4994542.5 | G6: =G4+G5 -> 6206141
B9: 3rd Party Delivery in Working | C9: =-'Marketing Fund 2022'!T111 -> 230660.5 | D9: =-'Marketing Fund 2023'!T111 -> 212987.02 | E9: =-'Marketing Fund 2024'!T111 -> 396833.13 | F9: =-'Marketing Fund 2025'!T110 -> 1241694.1 | G9: =-'Marketing Fund 2026 Plan'!T111 -> 1494000
B13: [Working examples]
B14: 3rd Party Delivery Media
B15: Paid Search
B16: Paid Social
B17: Online Video/Display
B18: NRO/Local Media
B19: Influencer/Content Prod
B20: Bonchon.com/App Promo
B21: EzCater Media

Sheet Marketing Fund 2022
B2: G/L Account | C2: Vendor in SAP | D2: Description | E2: Memo | F2: 3PD | H2: Actual
H3: F22P01 | I3: F22P02 | J3: F22P03 | K3: F22P04 | L3: F22P05 | M3: F22P06 | N3: F22P07 | O3: F22P08 | P3: F22P09 | Q3: F22P10 | R3: F22P11 | S3: F22P12 | T3: F22FY
B4: 4112211 Marketing Fee Incomes | H4: 155849.88 | I4: 150573.56 | J4: 158146.31 | K4: 159719.32 | L4: 161044.4 | M4: 154535.52 | N4: 169977.35 | O4: 164736.46 | P4: 240426.27 | Q4: 246885.45 | R4: 228289.87 | S4: 261922.63 | T4: =SUM(H4:S4) -> 2252107
B5: 4112212 Marketing fee incomes- Pepsi | H5: 0 | I5: 0 | J5: 0 | K5: 0 | L5: 0 | M5: 0 | N5: 0 | O5: 0 | P5: 0 | Q5: 0 | R5: 0 | S5: 0 | T5: =SUM(H5:S5) -> 0
B6: 4112213 Marketing fee incomes- Others | H6: 0 | I6: 0 | J6: 0 | K6: 0 | L6: 0 | M6: 0 | N6: 58.41 | O6: 60.57 | P6: 49.23 | Q6: 61.67 | R6: 3180.22 | S6: 554.01 | T6: =SUM(H6:S6) -> 3964.11
B7: Total Marketing income | H7: =SUM(H4:H6) -> 155849.88 | I7: =SUM(I4:I6) -> 150573.56 | J7: =SUM(J4:J6) -> 158146.31 | K7: =SUM(K4:K6) -> 159719.32 | L7: =SUM(L4:L6) -> 161044.4 | M7: =SUM(M4:M6) -> 154535.52 | N7: =SUM(N4:N6) -> 170035.76 | O7: =SUM(O4:O6) -> 164797.03 | ... T7: =SUM(T4:T6) -> 2256071.1
B9: (M)Agency | C9: Mindstream Media Group,LLC | H9: 0 | I9: -4000 | J9: -4000 | K9: -4000 | L9: -4000 | M9: -4000 | N9: -4000 | O9: -4000 | P9: -4000 | Q9: -4000 | R9: -4000 | S9: -4000 | T9: =SUM(H9:S9) -> -44000
B10: (M)Agency | C10: Propaganda, Inc. | H10: 0 | I10: -10000 | J10: -10000 | K10: -10000 | L10: -10000 | M10: -10000 | N10: -10000 | O10: -10000 | P10: -10000 | Q10: -10000 | R10: -10000 | S10: -10000 | T10: =SUM(H10:S10) -> -110000
B11: (M)Market research | C11: Propaganda, Inc. | H11: 0 | I11: 0 | J11: -1530 | K11: 0 | L11: 0 | M11: 0 | N11: 0 | O11: 0 | P11: 0 | Q11: 0 | R11: 0 | S11: 0 | T11: =SUM(H11:S11) -> -1530
B12: (M)Market research | C12: Strop Insights | H12: 0 | I12: -15500 | J12: -15500 | K12: 0 | L12: 0 | M12: 0 | N12: 0 | O12: 0 | P12: 0 | Q12: 0 | R12: 0 | S12: 0 | T12: =SUM(H12:S12) -> -31000
B13: (M)Menu | C13: The printing center, Inc | H13: -1101.61 | I13: -547.52 | J13: -559.36 | K13: -389.26 | L13: -23523.86 | M13: -3226.04 | N13: -7548.66 | O13: -1293.85 | P13: -3472.58 | Q13: -797.29 | R13: -677.99 | S13: -809.07 | T13: =SUM(H13:S13) -> -43947.09
B14: (M)Brand Development | C14: The printing center, Inc | H14: 0 | I14: -634.14 | J14: 0 | K14: 0 | L14: 0 | M14: 0 | N14: 0 | O14: 0 | P14: 0 | Q14: 0 | R14: 0 | S14: 0 | T14: =SUM(H14:S14) -> -634.14
B15: (M)Brand Development | C15: Magna Marketing LLC | H15: 0 | I15: 0 | J15: 0 | K15: -13833.34 | L15: -13833.34 | M15: -13833.34 | N15: 0 | O15: -13833.34 | P15: -13833.33 | Q15: 0 | R15: 0 | S15: 0 | T15: =SUM(H15:S15) -> -69166.69
B16: (M)Brand Development | C16: Salesforce.com, Inc. | H16: 0 | I16: 0 | J16: -13412.88 | K16: -13412.88 | L16: -13412.88 | M16: -13412.88 | N16: -27246.21 | O16: -13412.88 | P16: -13412.88 | Q16: -15648.36 | R16: -15648.36 | S16: -15648.36 | T16: =SUM(H16:S16) -> -154668.57
B17: (M)Brand Development | C17: Local Store Identity Field Day | H17: -6500 | I17: -6500 | J17: 0 | K17: 0 | L17: 0 | M17: 0 | N17: 0 | O17: 0 | P17: 0 | Q17: 0 | R17: 0 | S17: 0 | T17: =SUM(H17:S17) -> -13000
B18: (M)Brand Development | C18: Stingray Worldwide LLC | H18: 0 | I18: -87.3 | J18: 0 | K18: 0 | L18: 0 | M18: 0 | N18: 0 | O18: 0 | P18: 0 | Q18: 0 | R18: 0 | S18: 0 | T18: =SUM(H18:S18) -> -87.3
B19: (M)Menu Development | C19: Hyde Park Group, LLC | H19: 0 | I19: 0 | J19: 0 | K19: 0 | L19: 0 | M19: 0 | N19: 0 | O19: -54000 | P19: 0 | Q19: -54000 | R19: 0 | S19: 0 | T19: =SUM(H19:S19) -> -108000
B20: (M)Misc | C20: Bank of America | H20: 0 | I20: 0 | J20: -1 | K20: -5 | L20: -2 | M20: -1 | N20: -1 | O20: -2 | P20: -5 | Q20: 0 | R20: -2 | S20: -10 | T20: =SUM(H20:S20) -> -29
... B28: (M)Music | C28: Creative Media Solutions, LLC _Juke Boxy | H28: -780 | I28: -795 | J28: -795 | K28: -795 | L28: -840 | M28: -870 | N28: -900 | O28: -930 | P28: -990 | Q28: -1050 | R28: -2100 | S28: -1095 | T28: =SUM(H28:S28) -> -11940
B29: (M)National Advertisement | C29: Medium Giant Company, Inc Medium Giant | E29: Working | H29: 0 | I29: 0 | J29: 0 | K29: 0 | L29: 0 | M29: 0 | N29: 0 | O29: 0 | P29: 0 | Q29: 0 | R29: 0 | S29: -900 | T29: =SUM(H29:S29) -> -900
B30: (M)National Advertisement | C30: Valassis Direct Mail, Inc | E30: Working | H30: 0 | I30: 0 | J30: 0 | K30: 0 | L30: 0 | M30: 0 | N30: 0 | O30: 0 | P30: 0 | Q30: 0 | R30: 0 | S30: -4956.43 | T30: =SUM(H30:S30) -> -4956.43
B31: (M)Newsletter | C31: MailChimp | H31: -577.04 | I31: 577.04 | J31: 0 | K31: 0 | L31: 0 | M31: 0 | N31: 0 | O31: 0 | P31: 0 | Q31: 0 | R31: 0 | S31: 0 | T31: =SUM(H31:S31) -> 0
B32: (M)Others | C32: Blackbox Intelligence | H32: -1373.16 | I32: -1373.16 | J32: -1373.16 | K32: -1373.16 | L32: -1373.16 | M32: -1373.16 | N32: -1373.16 | O32: -1373.16 | P32: -1373.19 | Q32: -1382.19 | R32: -1492.69 | S32: -1492.69 | T32: =SUM(H32:S32) -> -16726.04
B33: (M)Others | C33: Mirus Information Tech Service, Inc | H33: -6374.18 | I33: 0 | J33: -7123.18 | K33: -14433.99 | L33: -7487.81 | M33: -7566.81 | N33: -7670 | O33: -8847.18 | P33: -8037.18 | Q33: -9657.18 | R33: -8680 | S33: -7915 | T33: =SUM(H33:S33) -> -93792.51
B34: (M)Others | C34: Bonchon Holdings LLC | H34: 0 | I34: 0 | J34: 0 | K34: 0 | L34: 0 | M34: 0 | N34: -8870.89 | O34: 0 | P34: 0 | Q34: 0 | R34: 0 | S34: 0 | T34: =SUM(H34:S34) -> -8870.89
B35: (M)Others | C35: The printing center, Inc | H35: -249.95 | I35: -254.79 | J35: -290.58 | K35: 0 | L35: -358.52 | M35: 0 | N35: 0 | O35: 0 | P35: 0 | Q35: 0 | R35: -302.5 | S35: 0 | T35: =SUM(H35:S35) -> -1456.34
B36: (M)Others | C36: Survey Monkey | H36: 0 | I36: 0 | J36: 0 | K36: 0 | L36: 0 | M36: 0 | N36: 0 | O36: 0 | P36: -418.08 | Q36: 0 | R36: 0 | S36: 0 | T36: =SUM(H36:S36) -> -418.08
B37: (M)Others | C37: ADOBE | H37: 0 | I37: 0 | J37: 0 | K37: 0 | L37: 0 | M37: 57.69 | N37: 0 | O37: 0 | P37: 0 | Q37: 0 | R37: 0 | S37: 0 | T37: =SUM(H37:S37) -> 57.69
B38: (M)Others | C38: Klaviyo Inc. | H38: -1113.08 | I38: -1109.57 | J38: -1124.63 | K38: -1124.63 | L38: -1160.79 | M38: -1177.93 | N38: 0 | O38: -1177.93 | P38: -1364.48 | Q38: -1364.48 | R38: -1364.48 | S38: 0 | T38: =SUM(H38:S38) -> -12082
B39: (M)Others | C39: Displays2go | H39: -1071.38 | I39: 0 | J39: 0 | K39: 0 | L39: 0 | M39: 0 | N39: 0 | O39: 0 | P39: 0 | Q39: 0 | R39: 0 | S39: 0 | T39: =SUM(H39:S39) -> -1071.38
B40: (M)Others | C40: Bank Of America | H40: -6 | I40: -3 | J40: -6 | K40: -2 | L40: 0 | M40: -10 | N40: 0 | O40: 0 | P40: 0 | Q40: 0 | R40: 0 | S40: 0 | T40: =SUM(H40:S40) -> -27
B41: (M)Others | C41: Printmoz.com | H41: 0 | I41: -49.38 | J41: -79 | K41: -32.73 | L41: -190.24 | M41: -110.33 | N41: 0 | O41: -149.16 | P41: 0 | Q41: 0 | R41: 0 | S41: -165.36 | T41: =SUM(H41:S41) -> -776.2
B42: (M)Others | C42: Etsy.com | H42: 0 | I42: 0 | J42: 0 | K42: -7.85 | L42: 0 | M42: 0 | N42: 0 | O42: 0 | P42: 0 | Q42: 0 | R42: 0 | S42: 0 | T42: =SUM(H42:S42) -> -7.85
... B52: (M)Photo & Video | C52: The Food Photo Agency, Inc. | H52: 0 | I52: 0 | J52: 0 | K52: 0 | L52: 0 | M52: -7972.57 | N52: 0 | O52: 0 | P52: 0 | Q52: 0 | R52: 0 | S52: 0 | T52: =SUM(H52:S52) -> -7972.57
B53: (M)Promotions | C53: Doordash, Inc | E53: Working | F53: 3rd Party Delivery | H53: 0 | I53: 0 | J53: -166813.5 | K53: 0 | L53: 0 | M53: 0 | N53: -37506 | O53: -26341 | P53: 0 | Q53: 0 | R53: 0 | S53: 0 | T53: =SUM(H53:S53) -> -230660.5
B54: (M)Promotions | C54: The printing center, Inc | H54: -21523.87 | I54: -503.42 | J54: -2613.69 | K54: -180.02 | L54: 0 | M54: 0 | N54: -10130.27 | O54: -13228.75 | P54: -223.21 | Q54: -324.4 | R54: -14816.1 | S54: 0 | T54: =SUM(H54:S54) -> -63543.73
B55: (M)Promotions | C55: Stingray Worldwide LLC | H55: 0 | I55: 0 | J55: -1474.91 | K55: 0 | L55: 0 | M55: 0 | N55: -933.03 | O55: 0 | P55: 0 | Q55: 0 | R55: 0 | S55: 0 | T55: =SUM(H55:S55) -> -2407.94
B56: (M)Promotions | C56: Bonchon.com | H56: 0 | I56: -300 | J56: 0 | K56: 0 | L56: 0 | M56: 0 | N56: 0 | O56: 0 | P56: 0 | Q56: 0 | R56: 0 | S56: 0 | T56: =SUM(H56:S56) -> -300
B57: (M)Promotions | C57: Cumulus Media Inc. | E57: Working | H57: 0 | I57: 0 | J57: 0 | K57: 0 | L57: 0 | M57: -3075 | N57: 0 | O57: 0 | P57: 0 | Q57: 0 | R57: 0 | S57: 0 | T57: =SUM(H57:S57) -> -3075
B58: (M)Promotions | C58: CDXL LLC | H58: 0 | I58: 0 | J58: 0 | K58: 0 | L58: 0 | M58: 0 | N58: -15000 | O58: 0 | P58: 0 | Q58: 0 | R58: 0 | S58: 0 | T58: =SUM(H58:S58) -> -15000
B59: (M)Promotions | C59: Trilogy L.L.C. | H59: 0 | I59: 0 | J59: 0 | K59: 0 | L59: 0 | M59: 0 | N59: 0 | O59: -13504 | P59: 0 | Q59: 0 | R59: 0 | S59: 0 | T59: =SUM(H59:S59) -> -13504
B60: (M)Promotions | C60: M and H LLC | H60: 0 | I60: 0 | J60: 0 | K60: 0 | L60: 0 | M60: 0 | N60: 0 | O60: 0 | P60: -500 | Q60: 0 | R60: 0 | S60: 0 | T60: =SUM(H60:S60) -> -500
B61: (M)Promotions | C61: Samantha Shepherd | E61: Working | H61: 0 | I61: 0 | J61: 0 | K61: 0 | L61: 0 | M61: 0 | N61: 0 | O61: 0 | P61: -100 | Q61: 0 | R61: 0 | S61: 0 | T61: =SUM(H61:S61) -> -100
B62: (M)Promotions | C62: Face Book | E62: Working | H62: 0 | I62: 0 | J62: 0 | K62: 0 | L62: 0 | M62: 0 | N62: 0 | O62: 0 | P62: -75 | Q62: -25 | R62: 0 | S62: 0 | T62: =SUM(H62:S62) -> -100
B63: (M)Promotions | C63: Hype Film Productions, LLC | H63: 0 | I63: 0 | J63: 0 | K63: 0 | L63: 0 | M63: 0 | N63: 0 | O63: 0 | P63: -300 | Q63: 0 | R63: 0 | S63: 0 | T63: =SUM(H63:S63) -> -300
B64: (M)Promotions | C64: Bonchon USA Inc | H64: 0 | I64: 0 | J64: 0 | K64: 0 | L64: 0 | M64: 0 | N64: 0 | O64: 0 | P64: 0 | Q64: -635.97 | R64: 0 | S64: 0 | T64: =SUM(H64:S64) -> -635.97
B65: (M)Promotions | C65: Frisco Roughriders LP | E65: Working | H65: 0 | I65: 0 | J65: 0 | K65: 0 | L65: 0 | M65: 0 | N65: 0 | O65: 0 | P65: 0 | Q65: -666.67 | R65: 0 | S65: 0 | T65: =SUM(H65:S65) -> -666.67
B66: (M)Promotions | C66: UPS | H66: 0 | I66: 0 | J66: 0 | K66: 0 | L66: 0 | M66: 0 | N66: 0 | O66: 0 | P66: 0 | Q66: -14.07 | R66: 0 | S66: 0 | T66: =SUM(H66:S66) -> -14.07
B67: (M)Promotions | C67: US Sweepstakes and Fulfillment Co. Laughton MKT Comm. | E67: Working | H67: 0 | I67: 0 | J67: 0 | K67: 0 | L67: 0 | M67: 0 | N67: 0 | O67: 0 | P67: 0 | Q67: 0 | R67: 0 | S67: -4800 | T67: =SUM(H67:S67) -> -4800
B68: (M)Public Relations | C68: All Points Public Relations, LLC | E68: Working | H68: -6600 | I68: -6600 | J68: -6600 | K68: -6600 | L68: -6600 | M68: -6600 | N68: -6608.58 | O68: -9070.25 | P68: -7000 | Q68: -8223 | R68: -6600 | S68: -6600 | T68: =SUM(H68:S68) -> -83701.83
B69: (M)Public Relations | C69: Bonchon.com | H69: -100 | I69: 0 | J69: 0 | K69: 0 | L69: 0 | M69: 0 | N69: 0 | O69: 0 | P69: 0 | Q69: 0 | R69: 0 | S69: 0 | T69: =SUM(H69:S69) -> -100
B70: (M)Public Relations | C70: Sunwest Communications, Inc. | H70: 0 | I70: 0 | J70: 0 | K70: 0 | L70: 0 | M70: 0 | N70: -2500 | O70: 0 | P70: 0 | Q70: 0 | R70: 0 | S70: 0 | T70: =SUM(H70:S70) -> -2500
B71: (M)Social Media | C71: Marketing Informatics LLC | E71: Working | H71: 0 | I71: -1950 | J71: -150 | K71: -450 | L71: 0 | M71: -600 | N71: 600 | O71: -600 | P71: -500 | Q71: 500 | R71: -300 | S71: -300 | T71: =SUM(H71:S71) -> -3750
B72: (M)Social Media | C72: Bonchon.com | E72: Working | H72: -250 | I72: -575 | J72: -10 | K72: 0 | L72: 0 | M72: 0 | N72: 0 | O72: 0 | P72: 0 | Q72: 0 | R72: 0 | S72: 0 | T72: =SUM(H72:S72) -> -835
B73: (M)Social Media | C73: MOMENTFEED UB, INC. | H73: -3986.84 | I73: -3986.84 | J73: -3986.84 | K73: -7945.37 | L73: -15979.69 | M73: -4097.1 | N73: -4048.55 | O73: -4048.55 | P73: -3003.79 | Q73: -6007.57 | R73: -16832.57 | S73: -6007.58 | T73: =SUM(H73:S73) -> -79931.29
B74: (M)Social Media | C74: Mindstream Media Group,LLC | E74: Working | H74: -75826.2 | I74: -53500 | J74: -60130.83 | K74: -45008.48 | L74: -45082.1 | M74: -45002.65 | N74: -55776.07 | O74: -41731.93 | P74: -43350.63 | Q74: -42577.76 | R74: -39590 | S74: -35310 | T74: =SUM(H74:S74) -> -582886.65
B75: (M)Social Media | C75: Dallas Eat More LLC | E75: Working | H75: -400 | I75: 0 | J75: 0 | K75: 0 | L75: 0 | M75: 0 | N75: 0 | O75: 0 | P75: 0 | Q75: 0 | R75: 0 | S75: 0 | T75: =SUM(H75:S75) -> -400
B76: (M)Social Media | C76: Yelp Inc | E76: Working | H76: -5537 | I76: -5659.6 | J76: -5586 | K76: -5586 | L76: -5635 | M76: -5635 | N76: -5831 | O76: -5831 | P76: -5782 | Q76: -5880 | R76: 0 | S76: 0 | T76: =SUM(H76:S76) -> -56962.6
B77: (M)Social Media | C77: Daym Good Entertainment Inc | E77: Working | H77: 0 | I77: -5000 | J77: 0 | K77: 0 | L77: 0 | M77: 0 | N77: 0 | O77: 0 | P77: 0 | Q77: 0 | R77: 0 | S77: 0 | T77: =SUM(H77:S77) -> -5000
B78: (M)Social Media | C78: Stingray Worldwide LLC | H78: 0 | I78: 0 | J78: -1395.42 | K78: 0 | L78: 0 | M78: 0 | N78: 0 | O78: 0 | P78: 0 | Q78: 0 | R78: 0 | S78: 0 | T78: =SUM(H78:S78) -> -1395.42
B79: (M)Social Media | C79: The printing center, Inc | H79: 0 | I79: 0 | J79: -7.76 | K79: 0 | L79: 0 | M79: 0 | N79: 0 | O79: 0 | P79: 0 | Q79: 0 | R79: 0 | S79: 0 | T79: =SUM(H79:S79) -> -7.76
B80: (M)Social Media | C80: Voss Management Inc | E80: Working | H80: 0 | I80: 0 | J80: 0 | K80: 0 | L80: 0 | M80: -3600 | N80: 0 | O80: 0 | P80: 0 | Q80: 0 | R80: 0 | S80: 0 | T80: =SUM(H80:S80) -> -3600
B81: (M)Social Media | C81: Klaviyo Inc. | E81: Working | H81: 0 | I81: 0 | J81: 0 | K81: 0 | L81: 0 | M81: 0 | N81: -1177.93 | O81: 0 | P81: 0 | Q81: 0 | R81: 0 | S81: 0 | T81: =SUM(H81:S81) -> -1177.93
B82: (M)Social Media | C82: Brett Austin Marketing LLC | E82: Working | H82: 0 | I82: 0 | J82: 0 | K82: 0 | L82: 0 | M82: 0 | N82: 0 | O82: -5000 | P82: 0 | Q82: 0 | R82: 0 | S82: 0 | T82: =SUM(H82:S82) -> -5000
B83: (M)Social Media | C83: Eric Htoy | E83: Working | H83: 0 | I83: 0 | J83: 0 | K83: 0 | L83: 0 | M83: 0 | N83: 0 | O83: 0 | P83: 0 | Q83: -500 | R83: 0 | S83: 0 | T83: =SUM(H83:S83) -> -500
B84: (M)Social Media | C84: Valassis Direct Mail, Inc | E84: Working | H84: 0 | I84: 0 | J84: 0 | K84: 0 | L84: 0 | M84: 0 | N84: 0 | O84: 0 | P84: 0 | Q84: 0 | R84: 0 | S84: -1000 | T84: =SUM(H84:S84) -> -1000
B85: (M)Social Media | C85: Sprout Social, Inc | H85: 0 | I85: -2875.01 | J85: 0 | K85: 0 | L85: -958.34 | M85: -958.34 | N85: -958.33 | O85: 0 | P85: -2875.02 | Q85: 0 | R85: -479.17 | S85: -958.34 | T85: =SUM(H85:S85) -> -10062.55
B86: (M)Website | C86: DigitalOcean | H86: 0 | I86: 0 | J86: -753.43 | K86: -255.78 | L86: -252.51 | M86: -253.83 | N86: -282.49 | O86: -269.03 | P86: -270.14 | Q86: -323.76 | R86: -323.88 | S86: -296.01 | T86: =SUM(H86:S86) -> -3280.86
B87: (M)Website | C87: Hello Digital | H87: 0 | I87: 0 | J87: 0 | K87: 0 | L87: 0 | M87: 0 | N87: 0 | O87: 0 | P87: 0 | Q87: 0 | R87: -4600 | S87: 0 | T87: =SUM(H87:S87) -> -4600
B88: (M)Website | C88: Pixel and Tonic, Inc | H88: 0 | I88: 0 | J88: 0 | K88: -108 | L88: -108 | M88: 0 | N88: 0 | O88: 0 | P88: 0 | Q88: 0 | R88: 0 | S88: 0 | T88: =SUM(H88:S88) -> -216
B89: (M)Website | C89: Clearpeak Interactive,Inc | H89: -1312.5 | I89: -2656.25 | J89: -2375 | K89: -4562.5 | L89: -3937.5 | M89: -6062.5 | N89: -3125 | O89: -750 | P89: -2562.5 | Q89: -3062.5 | R89: -2375 | S89: -500 | T89: =SUM(H89:S89) -> -33281.25
B90: (M)Website | C90: Bonchon Holdings LLC | H90: 0 | I90: 0 | J90: 0 | K90: 0 | L90: 0 | M90: 0 | N90: 0 | O90: 0 | P90: 0 | Q90: 0 | R90: 0 | S90: 0 | T90: =SUM(H90:S90) -> 0
B91: (M)Website | C91: Google | H91: -906.47 | I91: -833.47 | J91: -832.24 | K91: -794.16 | L91: -811.67 | M91: -759.23 | N91: -783.69 | O91: -909.75 | P91: -305.23 | Q91: 0 | R91: 0 | S91: 0 | T91: =SUM(H91:S91) -> -6935.91
B92: (M)Website | C92: Stingray Worldwide LLC | H92: 0 | I92: -1894.38 | J92: 0 | K92: 0 | L92: 0 | M92: 0 | N92: 0 | O92: 0 | P92: 0 | Q92: 0 | R92: 0 | S92: 0 | T92: =SUM(H92:S92) -> -1894.38
B93: (M)Website | C93: Nutritional Information Services | H93: 0 | I93: 0 | J93: 0 | K93: 0 | L93: -120 | M93: 0 | N93: 0 | O93: 0 | P93: 0 | Q93: 0 | R93: 0 | S93: 0 | T93: =SUM(H93:S93) -> -120
B94: Total Marketing expense | H94: =SUM(H9:H93) -> -193695.87 | I94: =SUM(I9:I93) -> -151818.39 | J94: =SUM(J9:J93) -> -330168.23 | K94: =SUM(K9:K93) -> -156428.44 | L94: =SUM(L9:L93) -> -173619.45 | M94: =SUM(M9:M93) -> -172802.61 | N94: =SUM(N9:N93) -> -241811.95 | O94: =SUM(O9:O93) -> -284818.13 | ... T94: =SUM(T9:T93) -> -2363888.9
B95: (M)Others | C95: Marketing liability | H95: 37845.99 | I95: 1244.83 | J95: 172021.92 | K95: -3290.88 | L95: 12575.05 | M95: 18267.09 | N95: 71776.19 | O95: 120021.1 | P95: -75942.72 | Q95: -47630.35 | R95: -68288.33 | S95: -130782.16 | T95: =SUM(H95:S95) -> 107817.73
B96: Check | H96: =H7+H94+H95 -> 0 | I96: =I7+I94+I95 -> 0 | J96: =J7+J94+J95 -> 0 | K96: =K7+K94+K95 -> 0 | L96: =L7+L94+L95 -> 0 | M96: =M7+M94+M95 -> 0 | N96: =N7+N94+N95 -> 0 | O96: =O7+O94+O95 -> 0 | ... T96: =T7+T94+T95 -> 0
B99: Net Marketing Fund | H99: =SUM(H7,H94) -> -37845.99 | I99: =SUM(I7,I94) -> -1244.83 | J99: =SUM(J7,J94) -> -172021.92 | K99: =SUM(K7,K94) -> 3290.88 | L99: =SUM(L7,L94) -> -12575.05 | M99: =SUM(M7,M94) -> -18267.09 | N99: =SUM(N7,N94) -> -71776.19 | O99: =SUM(O7,O94) -> -120021.1 | ... S99: =SUM(S7,S94) -> 130782.16 | T99: =SUM(H99:S99) -> -107817.73
B108: Working | H108: =SUMIF($E$8:$E$102,$B108,H$8:H$102) -> -88613.2 | I108: =SUMIF($E$8:$E$102,$B108,I$8:I$102) -> -73284.6 | J108: =SUMIF($E$8:$E$102,$B108,J$8:J$102) -> -239290.33 | K108: =SUMIF($E$8:$E$102,$B108,K$8:K$102) -> -57644.48 | L108: =SUMIF($E$8:$E$102,$B108,L$8:L$102) -> -57317.1 | M108: =SUMIF($E$8:$E$102,$B108,M$8:M$102) -> -64512.65 | N108: =SUMIF($E$8:$E$102,$B108,N$8:N$102) -> -106299.58 | O108: =SUMIF($E$8:$E$102,$B108,O$8:O$102) -> -88574.18 | ... S108: =SUMIF($E$8:$E$102,$B108,S$8:S$102) -> -53866.43 | T108: =SUM(H108:S108) -> -990072.61
B109: Non-Working | H109: =H94-H108 -> -105082.67 | I109: =I94-I108 -> -78533.79 | J109: =J94-J108 -> -90877.9 | K109: =K94-K108 -> -98783.96 | L109: =L94-L108 -> -116302.35 | M109: =M94-M108 -> -108289.96 | N109: =N94-N108 -> -135512.37 | O109: =O94-O108 -> -196243.95 | ... S109: =S94-S108 -> -77828.05 | T109: =SUM(H109:S109) -> -1373816.3
B111: 3rd Party Delivery | H111: =SUMIF($F$8:$F$102,$B111,H$8:H$102) -> 0 | I111: =SUMIF($F$8:$F$102,$B111,I$8:I$102) -> 0 | J111: =SUMIF($F$8:$F$102,$B111,J$8:J$102) -> -166813.5 | K111: =SUMIF($F$8:$F$102,$B111,K$8:K$102) -> 0 | L111: =SUMIF($F$8:$F$102,$B111,L$8:L$102) -> 0 | M111: =SUMIF($F$8:$F$102,$B111,M$8:M$102) -> 0 | N111: =SUMIF($F$8:$F$102,$B111,N$8:N$102) -> -37506 | O111: =SUMIF($F$8:$F$102,$B111,O$8:O$102) -> -26341 | ... S111: =SUMIF($F$8:$F$102,$B111,S$8:S$102) -> 0 | T111: =SUM(H111:S111) -> -230660.5

Sheet Marketing Fund 2023
B2: G/L Account | C2: Vendor in SAP | D2: Description | E2: Memo | F2: 3PD | H2: Actual
H3: F23P01 | I3: F23P02 | J3: F23P03 | K3: F23P04 | L3: F23P05 | M3: F23P06 | N3: F23P07 | O3: F23P08 | P3: F23P09 | Q3: F23P10 | R3: F23P11 | S3: F23P12 | T3: F23FY
B4: 4112211 Marketing Fee Incomes | H4: 248329.28 | I4: 236326.01 | J4: 257519.36 | K4: 255502.1 | L4: 253027.04 | M4: 195352.25 | N4: 172611.77 | O4: 227060.19 | P4: 243837.32 | Q4: 242625.91 | R4: 236007.16 | S4: 272029.42 | T4: =SUM(H4:S4) -> 2840227.8
B5: 4112212 Marketing fee incomes- Pepsi | H5: 0 | I5: 0 | J5: 35000 | K5: 0 | L5: 0 | M5: 0 | N5: 0 | O5: 7000 | P5: 0 | Q5: 0 | R5: 29113.04 | S5: 0 | T5: =SUM(H5:S5) -> 71113.04
B6: 4112213 Marketing fee incomes- Others | H6: 213.08 | I6: 265.57 | J6: 2082.62 | K6: 486.59 | L6: 740.13 | M6: 1519.62 | N6: 17.41 | O6: 95.97 | P6: 451.91 | Q6: 40.66 | R6: 5590.78 | S6: 0 | T6: =SUM(H6:S6) -> 11504.34
B7: Total Marketing income | H7: =SUM(H4:H6) -> 248542.36 | I7: =SUM(I4:I6) -> 236591.58 | J7: =SUM(J4:J6) -> 294601.98 | K7: =SUM(K4:K6) -> 255988.69 | L7: =SUM(L4:L6) -> 253767.17 | M7: =SUM(M4:M6) -> 196871.87 | N7: =SUM(N4:N6) -> 172629.18 | O7: =SUM(O4:O6) -> 234156.16 | ... T7: =SUM(T4:T6) -> 2922845.2
B9: (M)Agency | C9: Mindstream Media Group,LLC | D9: Retainer | H9: -4000 | I9: -4000 | J9: -4000 | K9: -4000 | L9: -4000 | M9: -4000 | N9: -4000 | O9: -4000 | P9: -4000 | Q9: -4000 | R9: -4000 | S9: -4000 | T9: =SUM(H9:S9) -> -48000
B10: (M)Agency | C10: Propaganda, Inc. | H10: -10000 | I10: -10000 | J10: -10000 | K10: -10000 | L10: -10000 | M10: -10000 | N10: -10000 | O10: -10000 | P10: -10000 | Q10: -10000 | R10: -10000 | S10: -10000 | T10: =SUM(H10:S10) -> -120000
B11: (M)Agency | C11: SPM COMMUNICATIONS, INC | D11: SPM: B2C PR | H11: 0 | I11: -7955 | J11: -12570 | K11: -12570 | L11: -13984.96 | M11: -13225.5 | N11: -12570 | O11: -12570 | P11: -12570 | Q11: -13225.5 | R11: -12570 | S11: -12570 | T11: =SUM(H11:S11) -> -136380.96
B12: (M)CRM/Loyalty | C12: RAF Enterprises L.L.C. | D12: Richard Flores: Customer Database | H12: 0 | I12: 0 | J12: -10562 | K12: -1500 | L12: -2193.75 | M12: -1500 | N12: -1500 | O12: -1500 | P12: -1500 | Q12: -1500 | R12: -1500 | S12: -1500 | T12: =SUM(H12:S12) -> -24755.75
B13: (M)CRM/Loyalty | C13: Salesforce.com, Inc. | H13: -15648.36 | I13: -16317.32 | J13: -15648.36 | K13: -16171.55 | L13: -16544.08 | M13: -16171.55 | N13: -16171.55 | O13: -16171.55 | P13: -16171.55 | Q13: -16171.55 | R13: -16171.55 | S13: -16171.55 | T13: =SUM(H13:S13) -> -193530.52
B14: (M)Market research | C14: Propaganda, Inc. | H14: 0 | I14: 0 | J14: -1792 | K14: 0 | L14: 0 | M14: 0 | N14: 0 | O14: 0 | P14: 0 | Q14: 0 | R14: 0 | S14: 0 | T14: =SUM(H14:S14) -> -1792
B15: (M)Market research | C15: Strop Insights | H15: 0 | I15: 0 | J15: 0 | K15: -12500 | L15: 0 | M15: 0 | N15: 0 | O15: 0 | P15: 0 | Q15: 0 | R15: 0 | S15: 0 | T15: =SUM(H15:S15) -> -12500
B16: (M)Menu | C16: The printing center, Inc | D16: Menu Printing: Print Center | H16: -503.04 | I16: -750.62 | J16: 0 | K16: -797.56 | L16: 0 | M16: 0 | N16: 0 | O16: -4033.76 | P16: 0 | Q16: -12049.33 | R16: 0 | S16: 0 | T16: =SUM(H16:S16) -> -18134.31
B17: (M)Menu Development | C17: Remarkable Culinary LLC | H17: 0 | I17: 0 | J17: -5000 | K17: -20622.26 | L17: 0 | M17: -2500 | N17: 0 | O17: 0 | P17: 0 | Q17: 0 | R17: 0 | S17: 0 | T17: =SUM(H17:S17) -> -28122.26
B18: (M)Menu Development | C18: Jake's Inc. | H18: 0 | I18: 0 | J18: 0 | K18: -495.5 | L18: 0 | M18: 0 | N18: 0 | O18: 0 | P18: 0 | Q18: 0 | R18: 0 | S18: 0 | T18: =SUM(H18:S18) -> -495.5
B19: (M)Menu Development | C19: SPM COMMUNICATIONS, INC | H19: 0 | I19: 0 | J19: 0 | K19: -1058.74 | L19: 0 | M19: 0 | N19: 0 | O19: 0 | P19: 0 | Q19: 0 | R19: 0 | S19: 0 | T19: =SUM(H19:S19) -> -1058.74
B20: (M)Menu Development | C20: Stingray Worldwide LLC | H20: 0 | I20: 0 | J20: 0 | K20: -789.9 | L20: 0 | M20: 0 | N20: 0 | O20: 0 | P20: 0 | Q20: 0 | R20: 0 | S20: 0 | T20: =SUM(H20:S20) -> -789.9
B21: (M)Menu Development | C21: DOT IT RESTAURANT LLC | H21: 0 | I21: 0 | J21: 0 | K21: 0 | L21: 0 | M21: -1092.34 | N21: 0 | O21: 0 | P21: 0 | Q21: 0 | R21: 0 | S21: 0 | T21: =SUM(H21:S21) -> -1092.34
B22: (M)Menu Development | C22: Impact Brands LLC | H22: 0 | I22: 0 | J22: 0 | K22: 0 | L22: 0 | M22: 0 | N22: 0 | O22: 0 | P22: 0 | Q22: 0 | R22: -5000 | S22: 0 | T22: =SUM(H22:S22) -> -5000
B23: (M)Misc | C23: Bank of America | H23: -5 | I23: -2 | J23: -7 | K23: -5 | L23: -14 | M23: -2 | N23: -26 | O23: -4 | P23: -4 | Q23: -14 | R23: -2 | S23: -3 | T23: =SUM(H23:S23) -> -88
B24: (M)Misc | C24: DOT IT RESTAURANT LLC | D24: Flavor Stickers | H24: 0 | I24: 0 | J24: 0 | K24: 0 | L24: 0 | M24: 0 | N24: 0 | O24: 0 | P24: 0 | Q24: 9.094947e-13 | R24: 0 | S24: -3851.35 | T24: =SUM(H24:S24) -> -3851.35
B25: (M)Misc | C25: Stingray Worldwide LLC | H25: 0 | I25: 0 | J25: 0 | K25: 0 | L25: 0 | M25: 0 | N25: 0 | O25: -147.76 | P25: 0 | Q25: 0 | R25: 0 | S25: 0 | T25: =SUM(H25:S25) -> -147.76
B26: (M)Misc | C26: Ferraro Foods | H26: 0 | I26: 0 | J26: -2525.27 | K26: 0 | L26: 0 | M26: 0 | N26: 0 | O26: 0 | P26: 0 | Q26: 0 | R26: 0 | S26: 0 | T26: =SUM(H26:S26) -> -2525.27
B27: (M)Misc | C27: Displays2go | H27: 0 | I27: 0 | J27: -1135.36 | K27: 0 | L27: 0 | M27: 0 | N27: 0 | O27: 0 | P27: 0 | Q27: 0 | R27: 0 | S27: 0 | T27: =SUM(H27:S27) -> -1135.36
B28: (M)Misc | C28: Bonchon Holdings LLC | H28: 0 | I28: 0 | J28: 0 | K28: -725 | L28: 0 | M28: 0 | N28: -950 | O28: 0 | P28: 0 | Q28: -399.69 | R28: 0 | S28: 0 | T28: =SUM(H28:S28) -> -2074.69
B29: (M)Misc | C29: The printing center, Inc | H29: 0 | I29: -48.15 | J29: -27.09 | K29: 0 | L29: 0 | M29: -157.24 | N29: -27.98 | O29: -22.92 | P29: 0 | Q29: -27.71 | R29: -33.13 | S29: 0 | T29: =SUM(H29:S29) -> -344.22
B30: (M)Music | C30: Creative Media Solutions, LLC _Juke Boxy | H30: -1095 | I30: -1520 | J30: -1350 | K30: -1110 | L30: -1170 | M30: -1185 | N30: -1185 | O30: -1185 | P30: -1185 | Q30: -1200 | R30: -1230 | S30: -1245 | T30: =SUM(H30:S30) -> -14660
B31: (M)National Advertisement | C31: Medium Giant Company, Inc Medium Giant | E31: Working | H31: 0 | I31: -600 | J31: 0 | K31: 0 | L31: 0 | M31: 0 | N31: 0 | O31: 0 | P31: 0 | Q31: 0 | R31: -1307.24 | S31: 0 | T31: =SUM(H31:S31) -> -1907.24
B32: (M)National Advertisement | C32: Cardlytics, Inc. | E32: Working | H32: 0 | I32: 0 | J32: 0 | K32: 0 | L32: 0 | M32: 0 | N32: 0 | O32: 0 | P32: 0 | Q32: 0 | R32: -140041.08 | S32: -127783 | T32: =SUM(H32:S32) -> -267824.08
B33: (M)National Advertisement | C33: Intrinsic Digital, Inc. RestaurantGeofencing.com | E33: Working | H33: 0 | I33: 0 | J33: 0 | K33: -5950 | L33: -2380 | M33: 0 | N33: 0 | O33: 0 | P33: 0 | Q33: 0 | R33: 0 | S33: 0 | T33: =SUM(H33:S33) -> -8330
B34: (M)National Advertisement | C34: Mindstream Media Group,LLC | E34: Working | H34: -50718 | I34: -109722.55 | J34: -85010.77 | K34: -98279.5 | L34: -90639.7 | M34: -55870.8 | N34: -124772.25 | O34: -110154.75 | P34: -76392.01 | Q34: -59670 | R34: -59339.55 | S34: -46726.2 | T34: =SUM(H34:S34) -> -967296.08
B35: (M)Nutrition Fact | C35: Nutritional Information Services | H35: 0 | I35: 0 | J35: 0 | K35: -270 | L35: 0 | M35: -60 | N35: -40 | O35: 0 | P35: 0 | Q35: 0 | R35: 0 | S35: 0 | T35: =SUM(H35:S35) -> -370
B36: (M)Others | C36: Blackbox Intelligence | H36: -1492.69 | I36: -1492.69 | J36: -1492.69 | K36: -1492.69 | L36: -1492.69 | M36: -1492.69 | N36: -1492.69 | O36: -1492.69 | P36: -1492.69 | Q36: -1492.69 | R36: -843.12 | S36: -843.12 | T36: =SUM(H36:S36) -> -16613.14
B37: (M)Others | C37: Mirus Information Tech Service, Inc | H37: -9246 | I37: -9322 | J37: -9272 | K37: -9372 | L37: -9348 | M37: -9398 | N37: -9467.89 | O37: -9391.89 | P37: -9624.16 | Q37: -9626.16 | R37: -9702.16 | S37: -10054.16 | T37: =SUM(H37:S37) -> -113824.42
B38: (M)Others | C38: Pepsi | H38: 0 | I38: 0 | J38: 0 | K38: 0 | L38: 0 | M38: 0 | N38: 0 | O38: -7000 | P38: 0 | Q38: 0 | R38: -8000 | S38: -10554.72 | T38: =SUM(H38:S38) -> -25554.72
B39: (M)Others | C39: Bonchon Holdings LLC | H39: 0 | I39: -2064.06 | J39: -6809.98 | K39: -6542.45 | L39: -788.13 | M39: -2188.98 | N39: -51.69 | O39: -1088.47 | P39: -1091.34 | Q39: -146.46 | R39: -2959.27 | S39: -185.12 | T39: =SUM(H39:S39) -> -23915.95
B40: (M)Others | C40: The printing center, Inc | H40: 0 | I40: 2875.01 | J40: 0 | K40: 0 | L40: 0 | M40: 0 | N40: 0 | O40: 0 | P40: 0 | Q40: 0 | R40: 0 | S40: 0 | T40: =SUM(H40:S40) -> 2875.01
B41: (M)Others | C41: Sprout Social, Inc | H41: 0 | I41: -2875.01 | J41: 0 | K41: 0 | L41: 0 | M41: 0 | N41: 0 | O41: 0 | P41: 0 | Q41: 0 | R41: 0 | S41: 0 | T41: =SUM(H41:S41) -> -2875.01
B42: (M)Others | C42: DOT IT RESTAURANT LLC | H42: 0 | I42: 0 | J42: 0 | K42: 0 | L42: 0 | M42: 0 | N42: 0 | O42: 0 | P42: -7321.55 | Q42: -518.92 | R42: 0 | S42: 0 | T42: =SUM(H42:S42) -> -7840.47
B43: (M)Others | C43: Survey Monkey | H43: 0 | I43: 0 | J43: 0 | K43: 0 | L43: 0 | M43: 0 | N43: 0 | O43: 0 | P43: -509.54 | Q43: 0 | R43: 0 | S43: 0 | T43: =SUM(H43:S43) -> -509.54
B44: (M)Others | C44: Long Mountain Partners, LLC | H44: 0 | I44: 0 | J44: 0 | K44: 0 | L44: 0 | M44: 0 | N44: 0 | O44: 0 | P44: 0 | Q44: -2500 | R44: 0 | S44: 0 | T44: =SUM(H44:S44) -> -2500
B45: (M)Others | C45: Checksforless.com | H45: 0 | I45: 0 | J45: 0 | K45: 0 | L45: 0 | M45: 0 | N45: 0 | O45: 0 | P45: 0 | Q45: 0 | R45: -66.2 | S45: 0 | T45: =SUM(H45:S45) -> -66.2
B46: (M)Others | C46: Bank Of America | H46: 0 | I46: 0 | J46: 0 | K46: 0 | L46: 0 | M46: 0 | N46: -1 | O46: 0 | P46: 0 | Q46: 0 | R46: 0 | S46: 0 | T46: =SUM(H46:S46) -> -1
... B53: (M)Photo & Video | C53: Zack Tzourtzouklis Wave Film Production | H53: 0 | I53: 0 | J53: 0 | K53: -1000 | L53: 0 | M53: -1200 | N53: 0 | O53: 0 | P53: 0 | Q53: 0 | R53: 0 | S53: 0 | T53: =SUM(H53:S53) -> -2200
B54: (M)Promotions | C54: Doordash, Inc | E54: Working | F54: 3rd Party Delivery | H54: -24999.67 | I54: 5982.9 | J54: -19996.68 | K54: 0 | L54: -19893.39 | M54: 0 | N54: 0 | O54: -13692 | P54: 0 | Q54: 0 | R54: 0 | S54: -69387.07 | T54: =SUM(H54:S54) -> -141985.91
B55: (M)Promotions | C55: The printing center, Inc | H55: -12517.24 | I55: -15361.84 | J55: -19249.27 | K55: -618.94 | L55: -625.08 | M55: -16247.64 | N55: 0 | O55: 0 | P55: 0 | Q55: -24499.78 | R55: 0 | S55: -1337.06 | T55: =SUM(H55:S55) -> -90456.85
B56: (M)Promotions | C56: Uber Portier, LLC | E56: Working | F56: 3rd Party Delivery | H56: 0 | I56: -23670.22 | J56: 0 | K56: 0 | L56: 0 | M56: 0 | N56: 0 | O56: 0 | P56: 0 | Q56: -14999.9 | R56: -3108.22 | S56: -29222.77 | T56: =SUM(H56:S56) -> -71001.11
B57: (M)Promotions | C57: Stingray Worldwide LLC | H57: 0 | I57: 0 | J57: 0 | K57: 0 | L57: -7772.35 | M57: 0 | N57: 0 | O57: 0 | P57: -475.22 | Q57: 0 | R57: 0 | S57: 0 | T57: =SUM(H57:S57) -> -8247.57
B58: (M)Promotions | C58: Bonchon Holdings LLC | D58: From Concur expense report | H58: 0 | I58: 0 | J58: -483.04 | K58: 0 | L58: 0 | M58: 0 | N58: 0 | O58: 0 | P58: 0 | Q58: -600 | R58: 0 | S58: 0 | T58: =SUM(H58:S58) -> -1083.04
B59: (M)Promotions | C59: SPM COMMUNICATIONS, INC | E59: Working | H59: 0 | I59: 0 | J59: -7000 | K59: 0 | L59: 0 | M59: -10000 | N59: -1264 | O59: -655.5 | P59: 29.5 | Q59: -7905.04 | R59: -655 | S59: 0 | T59: =SUM(H59:S59) -> -27450.04
B60: (M)Promotions | C60: Propaganda, Inc. | H60: 0 | I60: 0 | J60: -20000 | K60: 0 | L60: -1500 | M60: 0 | N60: 0 | O60: 0 | P60: 0 | Q60: 0 | R60: 0 | S60: 0 | T60: =SUM(H60:S60) -> -21500
B61: (M)Promotions | C61: Dylan Andrews | E61: Working | H61: 0 | I61: 0 | J61: -3000 | K61: 0 | L61: 0 | M61: 0 | N61: 0 | O61: 0 | P61: 0 | Q61: 0 | R61: 0 | S61: 0 | T61: =SUM(H61:S61) -> -3000
B62: (M)Promotions | C62: Kadin Shedrick | E62: Working | H62: 0 | I62: 0 | J62: -2000 | K62: 0 | L62: 0 | M62: 0 | N62: 0 | O62: 0 | P62: 0 | Q62: 0 | R62: 0 | S62: 0 | T62: =SUM(H62:S62) -> -2000
B63: (M)Promotions | C63: Kyle Jarred Filipowski | E63: Working | H63: 0 | I63: 0 | J63: -10000 | K63: 0 | L63: 0 | M63: 0 | N63: 0 | O63: 0 | P63: 0 | Q63: 0 | R63: 0 | S63: 0 | T63: =SUM(H63:S63) -> -10000
B64: (M)Promotions | C64: THREE KINGS ENTERPRISES LLC | E64: Working | H64: 0 | I64: 0 | J64: 0 | K64: -6250 | L64: -6250 | M64: -6250 | N64: -6250 | O64: -6250 | P64: -6250 | Q64: -6250 | R64: -6250 | S64: 0 | T64: =SUM(H64:S64) -> -50000
B65: (M)Promotions | C65: Sherry Shi Sherry Eat World | E65: Working | H65: 0 | I65: 0 | J65: 0 | K65: 0 | L65: -975 | M65: 0 | N65: 0 | O65: 0 | P65: 0 | Q65: 0 | R65: 0 | S65: 0 | T65: =SUM(H65:S65) -> -975
B66: (M)Promotions | C66: Chinese for Affirmative Action | E66: Working | H66: 0 | I66: 0 | J66: 0 | K66: 0 | L66: 0 | M66: -5000 | N66: 0 | O66: 0 | P66: 0 | Q66: 0 | R66: 0 | S66: 0 | T66: =SUM(H66:S66) -> -5000
B67: (M)Promotions | C67: DOT IT RESTAURANT LLC | H67: 0 | I67: 0 | J67: 0 | K67: 0 | L67: 0 | M67: 0 | N67: 0 | O67: 0 | P67: 0 | Q67: 0 | R67: 0 | S67: -5000 | T67: =SUM(H67:S67) -> -5000
B68: (M)Public Relations | C68: All Points Public Relations, LLC | E68: Working | H68: -6600 | I68: -6600 | J68: 0 | K68: 0 | L68: 0 | M68: 0 | N68: 0 | O68: 0 | P68: 0 | Q68: 0 | R68: 0 | S68: 0 | T68: =SUM(H68:S68) -> -13200
B69: (M)Social Media | C69: Face Book | E69: Working | H69: 0 | I69: 0 | J69: -225 | K69: -149.98 | L69: -199.99 | M69: -24.9 | N69: -199.95 | O69: 0 | P69: 0 | Q69: 0 | R69: 0 | S69: 0 | T69: =SUM(H69:S69) -> -799.82
B70: (M)Social Media | C70: Marketing Informatics LLC | E70: Working | H70: -150 | I70: 0 | J70: -150 | K70: -150 | L70: 0 | M70: -450 | N70: 0 | O70: -150 | P70: -150 | Q70: -150 | R70: -300 | S70: -150 | T70: =SUM(H70:S70) -> -1800
B71: (M)Social Media | C71: MOMENTFEED UB, INC. | H71: -6007.57 | I71: -16832.57 | J71: -5821.59 | K71: -5635.62 | L71: -5635.62 | M71: -5651.15 | N71: -6007.58 | O71: -6007.58 | P71: 0 | Q71: 3.6379788e-12 | R71: 0 | S71: 0 | T71: =SUM(H71:S71) -> -57599.28
B72: (M)Social Media | C72: The printing center, Inc | H72: 0 | I72: -479.17 | J72: -958.34 | K72: -958.34 | L72: -479.16 | M72: 0 | N72: 0 | O72: 0 | P72: 0 | Q72: 0 | R72: 0 | S72: 0 | T72: =SUM(H72:S72) -> -2875.01
B73: (M)Social Media | C73: Sprout Social, Inc | H73: -958.34 | I73: -479.17 | J73: 0 | K73: 0 | L73: -479.17 | M73: -958.34 | N73: -958.34 | O73: -958.32 | P73: -958.34 | Q73: -958.34 | R73: -991.87 | S73: -1025.42 | T73: =SUM(H73:S73) -> -8725.65
B74: (M)Website | C74: DigitalOcean | H74: -295.05 | I74: -299.35 | J74: -328.62 | K74: -328.96 | L74: -330.7 | M74: -325.54 | N74: -329.66 | O74: -327.05 | P74: -326.56 | Q74: -324.85 | R74: -325.74 | S74: -325.48 | T74: =SUM(H74:S74) -> -3867.56
B75: (M)Website | C75: Hello Digital | H75: -4999 | I75: -4999 | J75: -5000 | K75: -3333 | L75: -3333 | M75: -4500 | N75: -6666 | O75: -3333 | P75: -3333 | Q75: -3333 | R75: -3333 | S75: -3333 | T75: =SUM(H75:S75) -> -49495
B76: (M)Website | C76: Pixel and Tonic, Inc | H76: 0 | I76: 0 | J76: 0 | K76: 0 | L76: -216 | M76: 0 | N76: 0 | O76: 0 | P76: 0 | Q76: 0 | R76: 0 | S76: 0 | T76: =SUM(H76:S76) -> -216
B77: (M)Website | C77: Clearpeak Interactive,Inc | H77: -312.5 | I77: 0 | J77: 0 | K77: 0 | L77: 0 | M77: 0 | N77: 0 | O77: 0 | P77: 0 | Q77: 0 | R77: 0 | S77: 0 | T77: =SUM(H77:S77) -> -312.5
B78: (M)Website | C78: Bonchon Holdings LLC | H78: 0 | I78: 0 | J78: 0 | K78: 0 | L78: 0 | M78: 0 | N78: 0 | O78: 0 | P78: 0 | Q78: -408 | R78: 0 | S78: 0 | T78: =SUM(H78:S78) -> -408
B79: (M)Website | C79: MomentFeed Inc. | H79: 0 | I79: 0 | J79: 0 | K79: 0 | L79: 0 | M79: 0 | N79: 0 | O79: 0 | P79: -7393.07 | Q79: -8437.62 | R79: -8437.62 | S79: -8491.75 | T79: =SUM(H79:S79) -> -32760.06
B80: Total Marketing expense | H80: =SUM(H9:H79) -> -200061.09 | I80: =SUM(I9:I79) -> -274662.05 | J80: =SUM(J9:J79) -> -320288.99 | K80: =SUM(K9:K79) -> -263842.69 | L80: =SUM(L9:L79) -> -262832.32 | M80: =SUM(M9:M79) -> -214343.02 | N80: =SUM(N9:N79) -> -238979.29 | O80: =SUM(O9:O79) -> -247773.41 | ... T80: =SUM(T9:T79) -> -3183664.8
B81: (M)Others | C81: Marketing liability | H81: -48481.27 | I81: 38070.47 | J81: 25687.01 | K81: 7854 | L81: 9065.15 | M81: 17471.15 | N81: 66350.11 | O81: 13617.25 | P81: -58436.42 | Q81: -10599.51 | R81: 61339.54 | S81: 138882.11 | T81: =SUM(H81:S81) -> 260819.59
B82: Check | H82: =H7+H80+H81 -> 0 | I82: =I7+I80+I81 -> 8.7311491e-11 | J82: =J7+J80+J81 -> -6.5483619e-11 | K82: =K7+K80+K81 -> -5.8207661e-11 | L82: =L7+L80+L81 -> 0 | M82: =M7+M80+M81 -> 3.6379788e-11 | N82: =N7+N80+N81 -> 0 | O82: =O7+O80+O81 -> 0 | ... T82: =T7+T80+T81 -> 1.0186341e-09
B85: Net Marketing Fund | H85: =SUM(H7,H80) -> 48481.27 | I85: =SUM(I7,I80) -> -38070.47 | J85: =SUM(J7,J80) -> -25687.01 | K85: =SUM(K7,K80) -> -7854 | L85: =SUM(L7,L80) -> -9065.15 | M85: =SUM(M7,M80) -> -17471.15 | N85: =SUM(N7,N80) -> -66350.11 | O85: =SUM(O7,O80) -> -13617.25 | ... S85: =SUM(S7,S80) -> -138882.11 | T85: =SUM(H85:S85) -> -260819.59
B108: Working | H108: =SUMIF($E$8:$E$102,$B108,H$8:H$102) -> -82467.67 | I108: =SUMIF($E$8:$E$102,$B108,I$8:I$102) -> -134609.87 | J108: =SUMIF($E$8:$E$102,$B108,J$8:J$102) -> -127382.45 | K108: =SUMIF($E$8:$E$102,$B108,K$8:K$102) -> -110779.48 | L108: =SUMIF($E$8:$E$102,$B108,L$8:L$102) -> -120338.08 | M108: =SUMIF($E$8:$E$102,$B108,M$8:M$102) -> -77595.7 | N108: =SUMIF($E$8:$E$102,$B108,N$8:N$102) -> -132486.2 | O108: =SUMIF($E$8:$E$102,$B108,O$8:O$102) -> -130902.25 | ... S108: =SUMIF($E$8:$E$102,$B108,S$8:S$102) -> -273269.04 | T108: =SUM(H108:S108) -> -1572569.3
B109: Non-Working | H109: =H80-H108 -> -117593.42 | I109: =I80-I108 -> -140052.18 | J109: =J80-J108 -> -192906.54 | K109: =K80-K108 -> -153063.21 | L109: =L80-L108 -> -142494.24 | M109: =M80-M108 -> -136747.32 | N109: =N80-N108 -> -106493.09 | O109: =O80-O108 -> -116871.16 | ... S109: =S80-S108 -> -137642.49 | T109: =SUM(H109:S109) -> -1611095.5
B111: 3rd Party Delivery | H111: =SUMIF($F$8:$F$102,$B111,H$8:H$102) -> -24999.67 | I111: =SUMIF($F$8:$F$102,$B111,I$8:I$102) -> -17687.32 | J111: =SUMIF($F$8:$F$102,$B111,J$8:J$102) -> -19996.68 | K111: =SUMIF($F$8:$F$102,$B111,K$8:K$102) -> 0 | L111: =SUMIF($F$8:$F$102,$B111,L$8:L$102) -> -19893.39 | M111: =SUMIF($F$8:$F$102,$B111,M$8:M$102) -> 0 | N111: =SUMIF($F$8:$F$102,$B111,N$8:N$102) -> 0 | O111: =SUMIF($F$8:$F$102,$B111,O$8:O$102) -> -13692 | ... S111: =SUMIF($F$8:$F$102,$B111,S$8:S$102) -> -98609.84 | T111: =SUM(H111:S111) -> -212987.02

Sheet Marketing Fund 2024
B2: G/L Account | C2: Vendor in SAP | D2: Description | E2: Memo | F2: 3PD | H2: Actual
H3: F24P01 | I3: F24P02 | J3: F24P03 | K3: F24P04 | L3: F24P05 | M3: F24P06 | N3: F24P07 | O3: F24P08 | P3: F24P09 | Q3: F24P10 | R3: F24P11 | S3: F24P12 | T3: FY
B4: 4112211 Marketing Fee Incomes | H4: 241787.94 | I4: 241505.22 | J4: 271092.7 | K4: 251170.52 | L4: 258720.68 | M4: 253006.19 | N4: 253904.2 | O4: 260617.5 | P4: 241591.01 | Q4: 248120.21 | R4: 242597.7 | S4: 265391.09 | T4: =SUM(H4:S4) -> 3029505
B5: 4112212 Marketing fee incomes- Pepsi | H5: 0 | I5: 7000 | J5: 2000 | K5: 23148 | L5: 0 | M5: 0 | N5: 11000 | O5: 6000 | P5: 0 | Q5: 48680.28 | R5: 0 | S5: 0 | T5: =SUM(H5:S5) -> 97828.28
B6: 4112213 Marketing fee incomes- Others | H6: 1062.8 | I6: 1378 | J6: 3933.37 | K6: 703 | L6: 2286.95 | M6: 1944 | N6: 1953.9 | O6: 1910.95 | P6: 0 | Q6: 0 | R6: 5674.51 | S6: 1696.2 | T6: =SUM(H6:S6) -> 22543.68
B7: Total Marketing income | H7: =SUM(H4:H6) -> 242850.74 | I7: =SUM(I4:I6) -> 249883.22 | J7: =SUM(J4:J6) -> 277026.07 | K7: =SUM(K4:K6) -> 275021.52 | L7: =SUM(L4:L6) -> 261007.63 | M7: =SUM(M4:M6) -> 254950.19 | N7: =SUM(N4:N6) -> 266858.1 | O7: =SUM(O4:O6) -> 268528.45 | ... S7: =SUM(S4:S6) -> 267087.29 | T7: =SUM(H7:S7) -> 3149876.9
B9: (M)Agency | C9: Mindstream Media Group,LLC | D9: MMG: Media Retainer | H9: -9750 | I9: -9750 | J9: -9750 | K9: -4875 | L9: 0 | M9: 0 | N9: 0 | O9: 0 | P9: 0 | Q9: 0 | R9: 0 | S9: 0 | T9: =SUM(H9:S9) -> -34125
B10: (M)Agency | C10: CossmanPR LLC | D10: Crossman: B2C PR Monthly | H10: 0 | I10: -6000 | J10: -6000 | K10: -6433.33 | L10: -6433.33 | M10: -6433.34 | N10: -6250 | O10: -6250 | P10: -6250 | Q10: -6216.67 | R10: -6216.67 | S10: -6216.66 | T10: =SUM(H10:S10) -> -68700
B11: (M)Agency | C11: Propaganda, Inc. | D11: Creative Agency Propoganda: (ends in May 17) | H11: -10000 | I11: -10000 | J11: -10000 | K11: -10000 | L11: -5667 | M11: 0 | N11: 0 | O11: 0 | P11: 0 | Q11: 0 | R11: 0 | S11: 0 | T11: =SUM(H11:S11) -> -45667
B12: (M)Agency | C12: CarsonDoyle Creative Agency,Ltd. | D12: Creeative Retainer: Carson & Doyle | H12: 0 | I12: 0 | J12: 0 | K12: 0 | L12: 0 | M12: 0 | N12: -19145 | O12: -35725 | P12: -15000 | Q12: -17900 | R12: -15000 | S12: -15000 | T12: =SUM(H12:S12) -> -117770
B13: (M)Agency | D13: Creative, out of scope | H13: 0 | I13: 0 | J13: 0 | K13: -5700 | L13: 0 | M13: -1200 | N13: 0 | O13: 0 | P13: 0 | Q13: 0 | R13: 0 | S13: 0 | T13: =SUM(H13:S13) -> -6900
B14: (M)Agency | C14: Calise Partners, LLC Imaginuity | D14: Imaginuity: SEO Set Up | H14: 0 | I14: 0 | J14: 0 | K14: 0 | L14: -10009.74 | M14: 0 | N14: 0 | O14: 0 | P14: 0 | Q14: 0 | R14: 0 | S14: 0 | T14: =SUM(H14:S14) -> -10009.74
B15: (M)Agency | C15: Calise Partners, LLC Imaginuity | D15: Imaginuity: Site Optimization MGMT | H15: 0 | I15: 0 | J15: 0 | K15: 0 | L15: 0 | M15: 0 | N15: 0 | O15: -2457.13 | P15: -2457.13 | Q15: -2457.13 | R15: -2457.13 | S15: -2457.13 | T15: =SUM(H15:S15) -> -12285.65
B16: (M)Agency | C16: Wasserman Media Group, LLC | D16: MMG: Media Retainer 1 | H16: 0 | I16: 0 | J16: -10500 | K16: 0 | L16: 0 | M16: 0 | N16: 0 | O16: 0 | P16: 0 | Q16: 0 | R16: 0 | S16: 0 | T16: =SUM(H16:S16) -> -10500
B17: (M)Agency | C17: SPM COMMUNICATIONS, INC | D17: SPM: B2C PR | H17: -12570 | I17: -17304.6 | J17: 0 | K17: 0 | L17: 0 | M17: 0 | N17: 0 | O17: 0 | P17: 0 | Q17: 0 | R17: 0 | S17: 0 | T17: =SUM(H17:S17) -> -29874.6
B18: (M)CRM/Loyalty | C18: RAF Enterprises L.L.C. | D18: Richard Flores: Customer Database | H18: -1500 | I18: -1500 | J18: -1500 | K18: -1500 | L18: -1500 | M18: -1500 | N18: -1500 | O18: -1500 | P18: -1500 | Q18: -1500 | R18: -1500 | S18: -1500 | T18: =SUM(H18:S18) -> -18000
B19: (M)CRM/Loyalty | C19: Salesforce.com, Inc. | D19: Salesforce: Cost Per Month | H19: -16171.52 | I19: -16171.52 | J19: -16171.67 | K19: -16171.55 | L19: -16171.55 | M19: -16171.55 | N19: -16171.55 | O19: -16171.55 | P19: -16171.52 | Q19: -16171.55 | R19: -16171.55 | S19: -16171.55 | T19: =SUM(H19:S19) -> -194058.63
B20: (M)Market research | C20: Survey Monkey | D20: Survey Monkey Subscription | H20: 0 | I20: 0 | J20: 0 | K20: 0 | L20: 0 | M20: 0 | N20: 0 | O20: 0 | P20: -509.54 | Q20: 0 | R20: 0 | S20: 0 | T20: =SUM(H20:S20) -> -509.54
B21: (M)Market research | C21: GetTattle Inc | D21: Tattle: Guest Sat Program Pilot Test | H21: 0 | I21: 0 | J21: 0 | K21: -1250 | L21: 0 | M21: -1250 | N21: -1250 | O21: 0 | P21: 0 | Q21: 0 | R21: 0 | S21: -14700 | T21: =SUM(H21:S21) -> -18450
B22: (M)Market research | C22: GetTattle Inc | D22: Tattle: Guest Sat System Rollout | H22: 0 | I22: 0 | J22: 0 | K22: 0 | L22: 0 | M22: 0 | N22: -7050 | O22: 0 | P22: -7050 | Q22: -7050 | R22: -7050 | S22: 0 | T22: =SUM(H22:S22) -> -28200
B23: (M)Market research | C23: Cassandra Cornell, LLC | D23: Meda Spend, Restaurant Profiles, Trailblazer (all LSM) | H23: 0 | I23: 0 | J23: 0 | K23: 0 | L23: -2500 | M23: -3000 | N23: -5625 | O23: 0 | P23: 0 | Q23: 0 | R23: 0 | S23: -3500 | T23: =SUM(H23:S23) -> -14625
B24: (M)Market research | C24: U30 Group, Inc. | D24: Ethnography | H24: 0 | I24: -36200 | J24: 0 | K24: -38758.76 | L24: 0 | M24: 0 | N24: 0 | O24: 0 | P24: 0 | Q24: 0 | R24: 0 | S24: 0 | T24: =SUM(H24:S24) -> -74958.76
B25: (M)Menu | C25: The printing center, Inc | D25: Menu Printing: Print Center | H25: -1294.25 | I25: -12172.87 | J25: -535.1 | K25: -11528.6 | L25: 0 | M25: 0 | N25: -15136.31 | O25: 0 | P25: 0 | Q25: 0 | R25: 0 | S25: 0 | T25: =SUM(H25:S25) -> -40667.13
... B41: (M)National Advertisement | C41: Wasserman Media Group, LLC | D41: Amplification Media | H41: 0 | I41: 0 | J41: -70000 | K41: 0 | L41: 0 | M41: 0 | N41: 0 | O41: 0 | P41: 0 | Q41: 0 | R41: 0 | S41: 0 | T41: =SUM(H41:S41) -> -70000
B42: (M)National Advertisement | C42: Medium Giant Company, Inc Medium Giant | D42: Medium Giant Company, Inc Medium Giant | E42: Working | H42: 0 | I42: 0 | J42: -2225.76 | K42: 0 | L42: 0 | M42: 0 | N42: 0 | O42: 0 | P42: 0 | Q42: 0 | R42: 0 | S42: 0 | T42: =SUM(H42:S42) -> -2225.76
B43: (M)National Advertisement | C43: Marden-Kane Inc | D43: Local Activation/Influencer/Social Content 1 | E43: Working | H43: 0 | I43: 0 | J43: -4548 | K43: 0 | L43: 0 | M43: 0 | N43: 0 | O43: 0 | P43: 0 | Q43: 0 | R43: 0 | S43: 0 | T43: =SUM(H43:S43) -> -4548
B44: (M)National Advertisement | C44: Wasserman Media Group, LLC | D44: Local Activation/Influencer/Social Content | E44: Working | H44: 0 | I44: 0 | J44: -20000 | K44: 0 | L44: -20000 | M44: 0 | N44: 0 | O44: 0 | P44: 0 | Q44: 0 | R44: 0 | S44: 0 | T44: =SUM(H44:S44) -> -40000
B45: (M)National Advertisement | C45: CossmanPR LLC | D45: Local Activation/Influencer/Social Content 2 | E45: Working | H45: 0 | I45: 0 | J45: 0 | K45: 0 | L45: 0 | M45: 0 | N45: -7000 | O45: 0 | P45: -7000 | Q45: 0 | R45: 4940.46 | S45: 0 | T45: =SUM(H45:S45) -> -9059.54
B46: (M)National Advertisement | C46: D. Augustine & Associates Augustine Agency | D46: D. Augustine & Associates Augustine Agency | E46: Working | H46: 0 | I46: -12616 | J46: 0 | K46: 0 | L46: -20475 | M46: 0 | N46: 0 | O46: 0 | P46: 0 | Q46: 0 | R46: 0 | S46: 0 | T46: =SUM(H46:S46) -> -33091
B47: (M)National Advertisement | C47: Calise Partners, LLC Imaginuity | D47: Media 1 | E47: Working | H47: 0 | I47: 0 | J47: 0 | K47: 0 | L47: -64000 | M47: -64000 | N47: -153987.82 | O47: -133177.8 | P47: -131096.9 | Q47: -153986.84 | R47: -25922.29 | S47: 0 | T47: =SUM(H47:S47) -> -726171.65
B48: (M)National Advertisement | C48: Mindstream Media Group,LLC | D48: Media | E48: Working | H48: -37617.97 | I48: -65941.37 | J48: -79356.73 | K48: -13303.98 | L48: 0 | M48: 0 | N48: 0 | O48: 0 | P48: 0 | Q48: 0 | R48: 0 | S48: 0 | T48: =SUM(H48:S48) -> -196220.05
B49: (M)Others | C49: Blackbox Intelligence | D49: Black Box: Industry Data | H49: -843.12 | I49: -843.12 | J49: -843.12 | K49: -843.12 | L49: -843.12 | M49: -843.12 | N49: -843.12 | O49: -843.12 | P49: -843.12 | Q49: -843.12 | R49: 0 | S49: 0 | T49: =SUM(H49:S49) -> -8431.2
B50: (M)Others | C50: Mirus Information Tech Service, Inc | D50: Mirus: Data Feed | H50: -9923.89 | I50: -10073.89 | J50: -10125.89 | K50: -10403.89 | L50: -10379.89 | M50: -10536 | N50: -10842 | O50: -11194 | P50: -10944 | Q50: -11196 | R50: -11172 | S50: -11298 | T50: =SUM(H50:S50) -> -128089.45
B51: (M)Others | C51: Pepsi | D51: Pepsi | H51: 0 | I51: -7000 | J51: -2000 | K51: -13074 | L51: 0 | M51: 0 | N51: -11000 | O51: -6000 | P51: 0 | Q51: -24340.14 | R51: 0 | S51: -0.02 | T51: =SUM(H51:S51) -> -63414.16
B52: (M)Others | C52: Bonchon Holdings LLC | D52: Brand Expenses (Reports) | H52: -1112.94 | I52: -2461.88 | J52: -8323.22 | K52: -4041.14 | L52: -225.89 | M52: -4463.32 | N52: -2292.18 | O52: -1558.73 | P52: -10531.24 | Q52: -954.98 | R52: -2648.31 | S52: -867.5 | T52: =SUM(H52:S52) -> -39481.33
B53: (M)Others | C53: Fedex | D53: Fedex | H53: 0 | I53: 0 | J53: 0 | K53: 0 | L53: -282.9 | M53: -1937.39 | N53: -192.72 | O53: 0 | P53: 0 | Q53: 0 | R53: 0 | S53: 0 | T53: =SUM(H53:S53) -> -2413.01
B54: (M)Others | C54: Stevenson Ranch CA | D54: Stevenson Ranch CA | H54: 0 | I54: 0 | J54: 0 | K54: 0 | L54: 0 | M54: 0 | N54: 0 | O54: 0 | P54: 0 | Q54: -5000 | R54: 0 | S54: 0 | T54: =SUM(H54:S54) -> -5000
B55: (M)Others | C55: COLORMARK, L.C. | D55: COLORMARK, L.C. | H55: 0 | I55: 0 | J55: 0 | K55: 0 | L55: 0 | M55: 0 | N55: 0 | O55: 0 | P55: 0 | Q55: 0 | R55: 0 | S55: -220 | T55: =SUM(H55:S55) -> -220
B56: (M)Overhead expense | C56: Overhead | D56: Team Salaries & Benefits | H56: -46135.76 | I56: -52316.55 | J56: -44001.09 | K56: -45371.28 | L56: -47294.11 | M56: -23346.68 | N56: -37010.74 | O56: -40316.01 | P56: -38247.92 | Q56: -41409.56 | R56: -38329.39 | S56: -41164.02 | T56: =SUM(H56:S56) -> -494943.11
B57: (M)Photo & Video | C57: Propaganda, Inc. | D57: Video Shoot & Editing DC | H57: 0 | I57: 0 | J57: -3840 | K57: 0 | L57: -1200 | M57: 0 | N57: 0 | O57: 0 | P57: 0 | Q57: 0 | R57: 0 | S57: 0 | T57: =SUM(H57:S57) -> -5040
B58: (M)Photo & Video | C58: Bonchon Holdings LLC | D58: Bonchon Holdings LLC | H58: -369.02 | I58: -409.21 | J58: 0 | K58: 0 | L58: 0 | M58: 0 | N58: 0 | O58: 0 | P58: 0 | Q58: 0 | R58: 0 | S58: 0 | T58: =SUM(H58:S58) -> -778.23
B59: (M)Photo & Video | C59: Robert Tsai Photography | D59: Photo Shoots - Robert | H59: 0 | I59: -4286.7 | J59: 0 | K59: 0 | L59: -4286.7 | M59: 0 | N59: -4286.7 | O59: 0 | P59: -13560.1 | Q59: 0 | R59: 0 | S59: -4286.7 | T59: =SUM(H59:S59) -> -30706.9
B60: (M)Photo & Video | C60: House of Features Jeremy Klefeker | D60: Photo Shoots - House of Features (Social Footage/Drum Trio) | H60: -1400 | I60: 0 | J60: 0 | K60: 0 | L60: 0 | M60: 0 | N60: 0 | O60: 0 | P60: 0 | Q60: 0 | R60: 0 | S60: 0 | T60: =SUM(H60:S60) -> -1400
... B63: (M)Photo & Video | C63: The Luupe, Inc. | D63: Social video shoot for March Maddness | H63: 0 | I63: -6500 | J63: 0 | K63: 0 | L63: 0 | M63: 0 | N63: 0 | O63: 0 | P63: 0 | Q63: 0 | R63: 0 | S63: 0 | T63: =SUM(H63:S63) -> -6500
B64: (M)Promotions | C64: Doordash, Inc | D64: Door Dash Placements/Promos | E64: Working | F64: 3rd Party Delivery | H64: -40275.84 | I64: -20000 | J64: 5558 | K64: 0.11 | L64: -5367.04 | M64: 0 | N64: 0 | O64: 0 | P64: 0 | Q64: 0 | R64: 0 | S64: 0 | T64: =SUM(H64:S64) -> -60084.77
B65: (M)Promotions | C65: The printing center, Inc | D65: Print Center | H65: -3940.19 | I65: 0 | J65: -61.52 | K65: -11346.96 | L65: 0 | M65: 0 | N65: 0 | O65: 0 | P65: 0 | Q65: 0 | R65: 0 | S65: 0 | T65: =SUM(H65:S65) -> -15348.67
B66: (M)Promotions | C66: Uber Portier, LLC | D66: Uber Eats Placements/Promos | E66: Working | F66: 3rd Party Delivery | H66: 0 | I66: -100000 | J66: -42731.38 | K66: -23639.16 | L66: 0 | M66: -25622.21 | N66: -2154.59 | O66: 0 | P66: 0 | Q66: 0 | R66: -8717.39 | S66: -22082.17 | T66: =SUM(H66:S66) -> -224946.9
B67: (M)Promotions | C67: Stingray Worldwide LLC | D67: Stingray | H67: -96.53 | I67: 0 | J67: 0 | K67: 0 | L67: 0 | M67: 0 | N67: 0 | O67: 0 | P67: 0 | Q67: 0 | R67: 0 | S67: 0 | T67: =SUM(H67:S67) -> -96.53
B68: (M)Promotions | C68: Bonchon Holdings LLC | D68: Bonchon Holdings LLC | H68: 0 | I68: -2425 | J68: 0 | K68: 0 | L68: 0 | M68: 0 | N68: 0 | O68: 0 | P68: 0 | Q68: 0 | R68: 0 | S68: 0 | T68: =SUM(H68:S68) -> -2425
B69: (M)Promotions | C69: Cardlytics, Inc. | D69: Cardlytics | E69: Working | H69: -40654 | I69: 51584.28 | J69: 0 | K69: -104224 | L69: -14598.01 | M69: 223.47 | N69: 8068.25 | O69: 0 | P69: 0 | Q69: 0 | R69: 0 | S69: 0 | T69: =SUM(H69:S69) -> -99600.01
B70: (M)Promotions | C70: COLORMARK, L.C. | D70: Colormark | H70: 0 | I70: 0 | J70: 0 | K70: 0 | L70: 0 | M70: 0 | N70: 0 | O70: -4595.57 | P70: 0 | Q70: 0 | R70: -26395.99 | S70: -16142.73 | T70: =SUM(H70:S70) -> -47134.29
B71: (M)Promotions | C71: CossmanPR LLC | D71: CossmanPR LLC | E71: Working | H71: 0 | I71: 0 | J71: 0 | K71: 0 | L71: 0 | M71: 0 | N71: 0 | O71: 0 | P71: 0 | Q71: 0 | R71: 0 | S71: -3861.19 | T71: =SUM(H71:S71) -> -3861.19
B72: (M)Social Media | C72: Face Book | D72: Face Book | E72: Working | H72: 0 | I72: 0 | J72: 0 | K72: 0 | L72: 0 | M72: 0 | N72: -149.73 | O72: -383 | P72: -75 | Q72: 0 | R72: 0 | S72: -138 | T72: =SUM(H72:S72) -> -745.73
B73: (M)Social Media | C73: Marketing Informatics LLC | D73: Marketing Informatics | H73: 0 | I73: -300 | J73: 0 | K73: -150 | L73: -150 | M73: 0 | N73: 0 | O73: 0 | P73: 0 | Q73: 0 | R73: 0 | S73: 0 | T73: =SUM(H73:S73) -> -600
B74: (M)Social Media | C74: Sprout Social, Inc | D74: Sprout: Social Reviews | H74: -1025.42 | I74: -1025.43 | J74: -1025.43 | K74: -1025.42 | L74: -1025.43 | M74: -1025.42 | N74: -1025.42 | O74: -1025.42 | P74: -1025.4 | Q74: -1025.4 | R74: -1025.41 | S74: -1025.42 | T74: =SUM(H74:S74) -> -12305.02
B75: (M)Website | C75: DigitalOcean | D75: Digital Ocean: Hosting | H75: -323.93 | I75: -323.67 | J75: 0 | K75: -694.62 | L75: -345.8 | M75: -345.74 | N75: -341.54 | O75: -336.08 | P75: -310.19 | Q75: 0 | R75: 0 | S75: 0 | T75: =SUM(H75:S75) -> -3021.57
B76: (M)Website | C76: Hello Digital | D76: Hello: ADA Scan | H76: 0 | I76: 0 | J76: 0 | K76: 0 | L76: 0 | M76: 0 | N76: 0 | O76: 0 | P76: -7000 | Q76: 0 | R76: 0 | S76: 0 | T76: =SUM(H76:S76) -> -7000
B77: (M)Website | C77: Hello Digital | D77: Hello: Site Support | H77: -3333 | I77: 333 | J77: -1500 | K77: -1500 | L77: -1500 | M77: -1500 | N77: -1500 | O77: -1500 | P77: -1500 | Q77: -1500 | R77: -1500 | S77: -1500 | T77: =SUM(H77:S77) -> -18000
B78: (M)Website | C78: Craft Massachusetts | D78: Craft Massachusetts | O78: -307 | P78: 0 | Q78: 0 | R78: 0 | S78: 0 | T78: =SUM(H78:S78) -> -307
B79: (M)Website | C79: Pixel and Tonic, Inc | D79: Pixel and Tonic, Inc | H79: 0 | I79: 0 | J79: 0 | K79: 0 | L79: 0 | M79: 0 | N79: -454 | O79: 0 | P79: -158 | Q79: -79 | R79: -79 | S79: -79 | T79: =SUM(H79:S79) -> -849
B80: (M)Website | C80: MomentFeed Inc. | D80: Uberall: Cost Per Month | H80: -8545.9 | I80: -8545.9 | J80: -8545.9 | K80: -9114.43 | L80: -8924.92 | M80: -8924.92 | N80: -9379.72 | O80: -9379.72 | P80: -8014.53 | Q80: -6649.35 | R80: -6649.35 | S80: -6973.07 | T80: =SUM(H80:S80) -> -99647.71
B81: Total Marketing expense | H81: =SUM(H9:H80) -> -258163.82 | I81: =SUM(I9:I80) -> -360128.53 | J81: =SUM(J9:J80) -> -359656.31 | K81: =SUM(K9:K80) -> -347991.5 | L81: =SUM(L9:L80) -> -272149.68 | M81: =SUM(M9:M80) -> -180076.87 | N81: =SUM(N9:N80) -> -358827.88 | O81: =SUM(O9:O80) -> -340190.26 | ... S81: =SUM(S9:S80) -> -185293.88 | T81: =SUM(H81:S81) -> -3459733.4
B82: (M)Others | C82: Marketing liability | D82: Marketing liability | H82: 15313.08 | I82: 110245.31 | J82: 82630.24 | K82: 72969.98 | L82: 11142.05 | M82: -74873.32 | N82: 91969.78 | O82: 71661.81 | P82: 74101.2 | Q82: -136449.78 | R82: 11664.88 | S82: -56792.23 | T82: =SUM(H82:S82) -> 273583
B83: Check | H83: =SUM(H4:H6)+H81+H82 -> 0 | I83: =SUM(I4:I6)+I81+I82 -> 0 | J83: =SUM(J4:J6)+J81+J82 -> 0 | K83: =SUM(K4:K6)+K81+K82 -> 0 | L83: =SUM(L4:L6)+L81+L82 -> 1.4551915e-11 | M83: =SUM(M4:M6)+M81+M82 -> 0 | N83: =SUM(N4:N6)+N81+N82 -> 1.4551915e-10 | O83: =SUM(O4:O6)+O81+O82 -> 0 | P83: =SUM(P4:P6)+P81+P82+P99 -> 0 | Q83: =SUM(Q4:Q6)+Q81+Q82+Q99 -> 0 | R83: =SUM(R4:R6)+R81+R82+R99 -> 0 | S83: =SUM(S4:S6)+S81+S82+S99 -> 0 | T83: =SUM(H83:S83) -> 1.6007107e-10
B84: From DD Fund | P84: =P99 -> -23059.44 | Q84: =Q99 -> 155820.98 | R84: =R99 -> -71486.89 | S84: =S99 -> -25001.18 | T84: =SUM(H84:S84) -> 36273.47
B86: Net Marketing Fund | H86: =SUM(H7,H81) -> -15313.08 | I86: =SUM(I7,I81) -> -110245.31 | J86: =SUM(J7,J81) -> -82630.24 | K86: =SUM(K7,K81) -> -72969.98 | L86: =SUM(L7,L81) -> -11142.05 | M86: =SUM(M7,M81) -> 74873.32 | N86: =SUM(N7,N81) -> -91969.78 | O86: =SUM(O7,O81) -> -71661.81 | ... T86: =SUM(T7,T81) -> -309856.47
B89: DoorDash Fund
B90: 4112213 Marketing fee incomes- Others | P90: 0 | Q90: 200000 | T90: =SUM(P90:S90) -> 200000
B91: Total DoorDash income | P91: =SUM(P90) -> 0 | Q91: =SUM(Q90) -> 200000 | R91: =SUM(R90) -> 0 | S91: =SUM(S90) -> 0 | T91: =SUM(T90) -> 200000
B93: (M)Photo & Video | C93: CarsonDoyle Creative Agency, Ltd. | D93: Ad creative and POP material | P93: 0 | Q93: 0 | R93: 0 | S93: 0 | T93: =SUM(P93:S93) -> 0
B94: (M)Promotions | C94: Doordash, Inc | D94: DoorDash Promotion | E94: Working | F94: 3rd Party Delivery | P94: -23059.44 | Q94: -44179.02 | R94: -13938.32 | S94: -25001.18 | T94: =SUM(P94:S94) -> -106177.96
B95: (M)Promotions | C95: Doordash, Inc | D95: DoorDash Promotion- Sep | E95: Working | F95: 3rd Party Delivery | Q95: 0 | R95: -5623.5 | S95: 0 | T95: =SUM(P95:S95) -> -5623.5
B96: (M)Menu | C96: COLORMARK, L.C. | D96: Menu Printing, System | P96: 0 | Q96: 0 | R96: -51925.07 | S96: 0 | T96: =SUM(P96:S96) -> -51925.07
B97: Total DoorDash expense | P97: =SUM(P93:P96) -> -23059.44 | Q97: =SUM(Q93:Q96) -> -44179.02 | R97: =SUM(R93:R96) -> -71486.89 | S97: =SUM(S93:S96) -> -25001.18 | T97: =SUM(T93:T96) -> -163726.53
B99: Net DoorDash Fund | P99: =SUM(P91,P97) -> -23059.44 | Q99: =SUM(Q91,Q97) -> 155820.98 | R99: =SUM(R91,R97) -> -71486.89 | S99: =SUM(S91,S97) -> -25001.18 | T99: =SUM(T91,T97) -> 36273.47
B108: Working | H108: =SUMIF($E$8:$E$102,$B108,H$8:H$102) -> -118547.81 | I108: =SUMIF($E$8:$E$102,$B108,I$8:I$102) -> -146973.09 | J108: =SUMIF($E$8:$E$102,$B108,J$8:J$102) -> -143303.87 | K108: =SUMIF($E$8:$E$102,$B108,K$8:K$102) -> -141167.03 | L108: =SUMIF($E$8:$E$102,$B108,L$8:L$102) -> -124440.05 | M108: =SUMIF($E$8:$E$102,$B108,M$8:M$102) -> -89398.74 | N108: =SUMIF($E$8:$E$102,$B108,N$8:N$102) -> -155223.89 | O108: =SUMIF($E$8:$E$102,$B108,O$8:O$102) -> -133560.8 | ... S108: =SUMIF($E$8:$E$102,$B108,S$8:S$102) -> -51082.54 | T108: =SUM(H108:S108) -> -1512356.1
B109: Non-Working | H109: =H81+H97-H108 -> -139616.01 | I109: =I81+I97-I108 -> -213155.44 | J109: =J81+J97-J108 -> -216352.44 | K109: =K81+K97-K108 -> -206824.47 | L109: =L81+L97-L108 -> -147709.63 | M109: =M81+M97-M108 -> -90678.13 | N109: =N81+N97-N108 -> -203603.99 | O109: =O81+O97-O108 -> -206629.46 | ... S109: =S81+S97-S108 -> -159212.52 | T109: =SUM(H109:S109) -> -2111103.9
B111: 3rd Party Delivery | H111: =SUMIF($F$8:$F$102,$B111,H$8:H$102) -> -40275.84 | I111: =SUMIF($F$8:$F$102,$B111,I$8:I$102) -> -120000 | J111: =SUMIF($F$8:$F$102,$B111,J$8:J$102) -> -37173.38 | K111: =SUMIF($F$8:$F$102,$B111,K$8:K$102) -> -23639.05 | L111: =SUMIF($F$8:$F$102,$B111,L$8:L$102) -> -5367.04 | M111: =SUMIF($F$8:$F$102,$B111,M$8:M$102) -> -25622.21 | N111: =SUMIF($F$8:$F$102,$B111,N$8:N$102) -> -2154.59 | O111: =SUMIF($F$8:$F$102,$B111,O$8:O$102) -> 0 | ... S111: =SUMIF($F$8:$F$102,$B111,S$8:S$102) -> -47083.35 | T111: =SUM(H111:S111) -> -396833.13

Sheet Marketing Fund 2025
B2: G/L Account | C2: Vendor in SAP | D2: Description | E2: Memo | F2: 3PD | H2: Actual | V2: -1
H3: F25P01 | I3: F25P02 | J3: F25P03 | K3: F25P04 | L3: F25P05 | M3: F25P06 | N3: F25P07 | O3: F25P08 | P3: F25P09 | Q3: F25P10 | R3: F25P11 | S3: F25P12 | T3: FY
B4: 4112211 Marketing Fee Incomes | H4: 250044.62 | I4: 233033.91 | J4: 261841.98 | K4: 251985.57 | L4: 270270.3 | M4: 261691.28 | N4: 272963.39 | O4: 281699.74 | P4: 258868.17 | Q4: 272695.04 | R4: 268056.97 | S4: 284302.68 | T4: =SUM(H4:S4) -> 3167453.7
B5: 4112212 Marketing fee incomes- Pepsi | H5: 6000 | I5: 0 | J5: 0 | K5: 25116 | L5: 0 | M5: 3000 | N5: 0 | O5: 0 | P5: 4000 | Q5: 57682.77 | R5: 0 | S5: 0 | T5: =SUM(H5:S5) -> 95798.77
B6: 4112213 Marketing fee incomes- Others | H6: 0 | I6: 3709.81 | J6: 0 | K6: 17329.81 | L6: 3620.55 | M6: 0 | N6: 0 | O6: 0 | P6: 3493.31 | Q6: 0 | R6: 0 | S6: 0 | T6: =SUM(H6:S6) -> 28153.48
B7: Total Marketing income | H7: =SUM(H4:H6) -> 256044.62 | I7: =SUM(I4:I6) -> 236743.72 | J7: =SUM(J4:J6) -> 261841.98 | K7: =SUM(K4:K6) -> 294431.38 | L7: =SUM(L4:L6) -> 273890.85 | M7: =SUM(M4:M6) -> 264691.28 | N7: =SUM(N4:N6) -> 272963.39 | O7: =SUM(O4:O6) -> 281699.74 | ... S7: =SUM(S4:S6) -> 284302.68 | T7: =SUM(H7:S7) -> 3291405.9
B9: (M)Agency | C9: CarsonDoyle Creative Agency,Ltd. | D9: Retainer | H9: -19000 | I9: -24000 | J9: -26000 | K9: -26000 | L9: -26000 | M9: -26000 | N9: -26000 | O9: -26000 | P9: -26000 | Q9: -27800 | R9: -26000 | S9: -26000 | T9: =SUM(H9:S9) -> -304800
B10: (M)Agency | C10: COLORMARK, L.C. | H10: 0 | I10: 0 | J10: 0 | K10: 0 | L10: -3472.53 | M10: 0 | N10: 0 | O10: 0 | P10: 0 | Q10: 0 | R10: 0 | S10: 0 | T10: =SUM(H10:S10) -> -3472.53
B11: (M)Agency | C11: Brandverge, Inc. | H11: 0 | I11: 0 | J11: 0 | K11: 0 | L11: 0 | M11: -15600 | N11: 0 | O11: 0 | P11: 0 | Q11: 0 | R11: 0 | S11: 0 | T11: =SUM(H11:S11) -> -15600
B12: (M)Agency | C12: Calise Partners, LLC Imaginuity | H12: -2457.13 | I12: -2457.13 | J12: -2457.13 | K12: 0 | L12: 0 | M12: 0 | N12: 0 | O12: 0 | P12: 0 | Q12: 0 | R12: 0 | S12: 0 | T12: =SUM(H12:S12) -> -7371.39
B13: (M)Agency | C13: Veylan Inc | D13: AI Marketing Tool | H13: 0 | I13: 0 | J13: 0 | K13: 0 | L13: 0 | M13: 0 | N13: 0 | O13: 0 | P13: 0 | Q13: 0 | R13: -10000 | S13: -10000 | T13: =SUM(H13:S13) -> -20000
B14: (M)Agency | C14: CossmanPR LLC | H14: -6433.33 | I14: -6433.33 | J14: -6433.34 | K14: -6233 | L14: -6233 | M14: -6233 | N14: -6233 | O14: -6233 | P14: -6233 | Q14: -6000 | R14: -7584.17 | S14: -6000 | T14: =SUM(H14:S14) -> -76282.17
B15: (M)CRM/Loyalty | C15: RAF Enterprises L.L.C. | H15: -1500 | I15: -1500 | J15: -1500 | K15: -1500 | L15: 0 | M15: 0 | N15: 0 | O15: 0 | P15: 0 | Q15: 0 | R15: 0 | S15: 0 | T15: =SUM(H15:S15) -> -6000
B16: (M)CRM/Loyalty | C16: Salesforce.com | H16: -16171.55 | I16: -16171.55 | J16: -16171.53 | K16: 0 | L16: 0 | M16: 0 | N16: 0 | O16: 0 | P16: 0 | Q16: 0 | R16: 0 | S16: 0 | T16: =SUM(H16:S16) -> -48514.63
B17: (M)CRM/Loyalty | C17: Fishbowl Inc. | H17: 0 | I17: -2083.33 | J17: -2083.33 | K17: -2083.33 | L17: -2128.33 | M17: -2173.33 | N17: -2083.33 | O17: -2083.33 | P17: -2083.33 | Q17: -2083.33 | R17: -2083.33 | S17: -2083.33 | T17: =SUM(H17:S17) -> -23051.63
B18: (M)Market research | C18: Survey Monkey | H18: 0 | I18: 0 | J18: 0 | K18: 0 | L18: 0 | M18: 0 | N18: 0 | O18: 0 | P18: -509.54 | Q18: 0 | R18: 0 | S18: 0 | T18: =SUM(H18:S18) -> -509.54
B19: (M)Market research | C19: GetTattle Inc | D19: Tattle responses | H19: 0 | I19: 0 | J19: 0 | K19: 0 | L19: 0 | M19: 0 | N19: 0 | O19: 0 | P19: 0 | Q19: -1750 | R19: 0 | S19: 0 | T19: =SUM(H19:S19) -> -1750
B20: (M)Market research | C20: GetTattle Inc | H20: -7750 | I20: -7900 | J20: -7850 | K20: -7900 | L20: -7900 | M20: -8000 | N20: -8000 | O20: -7850 | P20: -7800 | Q20: -7750 | R20: -7750 | S20: -7750 | T20: =SUM(H20:S20) -> -94200
B21: (M)Menu | C21: COLORMARK, L.C. | H21: 0 | I21: -433.79 | J21: -432.11 | K21: 0 | L21: 0 | M21: -54150.71 | N21: 0 | O21: 0 | P21: 0 | Q21: 0 | R21: 0 | S21: -183.24 | T21: =SUM(H21:S21) -> -55199.85
B22: (M)Menu | C22: COLORMARK, L.C. | D22: System Menu | H22: 0 | I22: 0 | J22: 0 | K22: 0 | L22: 0 | M22: 0 | N22: 0 | O22: 0 | P22: 0 | Q22: 0 | R22: 0 | S22: -31964.9 | T22: =SUM(H22:S22) -> -31964.9
B23: (M)Menu Development | C23: COLORMARK, L.C. | D23: Value Meal | H23: 0 | I23: 0 | J23: -1534.07 | K23: 0 | L23: 0 | M23: 0 | N23: 0 | O23: 0 | P23: 0 | Q23: 0 | R23: 0 | S23: 0 | T23: =SUM(H23:S23) -> -1534.07
B24: (M)Menu Development | C24: COLORMARK, L.C. | H24: 0 | I24: -309.63 | J24: 0 | K24: 0 | L24: 0 | M24: -737.64 | N24: 0 | O24: 0 | P24: 0 | Q24: 0 | R24: 0 | S24: 0 | T24: =SUM(H24:S24) -> -1047.27
B25: (M)Menu Development | C25: TK America, Inc | D25: TK Sauce Development | H25: 0 | I25: 0 | J25: 0 | K25: -5000 | L25: -5000 | M25: 0 | N25: 0 | O25: 0 | P25: 0 | Q25: 0 | R25: 0 | S25: 0 | T25: =SUM(H25:S25) -> -10000
B26: (M)Misc | C26: COLORMARK, L.C. | D26: Reprint of Dots | H26: -2000 | I26: 0 | J26: 0 | K26: 0 | L26: 0 | M26: 0 | N26: 0 | O26: 0 | P26: 0 | Q26: 0 | R26: 0 | S26: 0 | T26: =SUM(H26:S26) -> -2000
B27: (M)Misc | C27: COLORMARK, L.C. | D27: misc | H27: 0 | I27: 0 | J27: 0 | K27: 0 | L27: 0 | M27: -720.21 | N27: -1420.33 | O27: 0 | P27: 0 | Q27: 0 | R27: -12939.39 | S27: -1092.02 | T27: =SUM(H27:S27) -> -16171.95
B28: (M)Misc | C28: Misc | H28: 0 | I28: 0 | J28: 0 | K28: 0 | L28: 0 | M28: 0 | N28: 0 | O28: 0 | P28: 0 | Q28: 0 | R28: -178.98 | S28: 0 | T28: =SUM(H28:S28) -> -178.98
B29: (M)Misc | C29: Stingray Worldwide LLC | D29: Misc | H29: 0 | I29: 0 | J29: 0 | K29: 0 | L29: 0 | M29: 0 | N29: 0 | O29: 0 | P29: 0 | Q29: 0 | R29: 0 | S29: -4500.59 | T29: =SUM(H29:S29) -> -4500.59
B30: (M)Music | C30: Creative Media Solutions, LLC _Juke Boxy | H30: -1520 | I30: -1482 | J30: -1482 | K30: -1501 | L30: -1501 | M30: -1425 | N30: -1653 | O30: -1653 | P30: -1653 | Q30: -8731 | R30: -2204 | S30: -2223 | T30: =SUM(H30:S30) -> -27028
B31: (M)National Advertisement | C31: Calise Partners, LLC Imaginuity | D31: Paid Media | E31: Working | H31: -45000 | I31: -65000 | J31: -70000 | K31: -120000 | L31: -200000 | M31: -206000 | N31: 44407.77 | O31: 0 | P31: 0 | Q31: 0 | R31: 0 | S31: 0 | T31: =SUM(H31:S31) -> -661592.23
B32: (M)National Advertisement | C32: Brandverge, Inc. | D32: Paid Media | E32: Working | H32: 0 | I32: 0 | J32: 0 | K32: 0 | L32: 0 | M32: 0 | N32: -200000 | O32: -200000 | P32: -200000 | Q32: -160000 | R32: -160000 | S32: -160330 | T32: =SUM(H32:S32) -> -1080330
B33: (M)National Advertisement | C33: Marketing Informatics LLC | D33: Digital Ads Platfrom | E33: Working | H33: 0 | I33: 0 | J33: 0 | K33: 0 | L33: -1000 | M33: -500 | N33: -500 | O33: -1000 | P33: -500 | Q33: -500 | R33: -500 | S33: -500 | T33: =SUM(H33:S33) -> -5000
B34: (M)National Advertisement | C34: Calise Partners, LLC Imaginuity | D34: NRO/ Local Media | E34: Working | H34: 0 | I34: 0 | J34: 0 | K34: -28499.6 | L34: 0 | M34: -3921.57 | N34: -3921.57 | O34: -3921.57 | P34: 0 | Q34: 0 | R34: 0 | S34: 0 | T34: =SUM(H34:S34) -> -40264.31
B35: (M)National Advertisement | C35: Brandverge, Inc. | D35: NRO/ Local Media | E35: Working | H35: 0 | I35: 0 | J35: 0 | K35: 0 | L35: 0 | M35: 0 | N35: 0 | O35: 0 | P35: 0 | Q35: 0 | R35: 0 | S35: -3299 | T35: =SUM(H35:S35) -> -3299
B36: (M)National Advertisement | C36: CossmanPR LLC | D36: NRO/ Local Media | E36: Working | H36: 0 | I36: 0 | J36: 0 | K36: 0 | L36: -1948.33 | M36: 0 | N36: 0 | O36: 0 | P36: 0 | Q36: 0 | R36: 0 | S36: 0 | T36: =SUM(H36:S36) -> -1948.33
B37: (M)Nutrition Fact | C37: Nutritional Information Services | D37: New Recipes, Par Frying, etc | H37: 0 | I37: -150 | J37: 0 | K37: 0 | L37: 0 | M37: 0 | N37: -40 | O37: 0 | P37: 0 | Q37: 0 | R37: 0 | S37: 0 | T37: =SUM(H37:S37) -> -190
B38: (M)Others | C38: Freshworks Inc Dept # 880636 | D38: Software | H38: 0 | I38: 0 | J38: 0 | K38: 0 | L38: -2187.44 | M38: 0 | N38: 0 | O38: 0 | P38: 0 | Q38: 0 | R38: 0 | S38: 0 | T38: =SUM(H38:S38) -> -2187.44
B39: (M)Others | C39: Mirus Information Tech Service, Inc | D39: Data Management | H39: -11378.43 | I39: -11304.43 | J39: -11476 | K39: -11828 | L39: -11628 | M39: -11780 | N39: -12232 | O39: -11780 | P39: -11552 | Q39: -11728 | R39: -11752 | S39: -11552 | T39: =SUM(H39:S39) -> -139990.86
B40: (M)Others | C40: Bonchon Holdings LLC | D40: Travel & Expenses | H40: -343.52 | I40: -1341.33 | J40: -3120.36 | K40: -841.44 | L40: -317.36 | M40: -1448.49 | N40: -1376.74 | O40: -7886.16 | P40: -821.18 | Q40: -3085.49 | R40: -968.69 | S40: -1411.51 | T40: =SUM(H40:S40) -> -22962.27
B41: (M)Others | C41: COLORMARK, L.C. | D41: Misc | H41: 0 | I41: 0 | J41: -3304.74 | K41: 0 | L41: 0 | M41: 0 | N41: 0 | O41: 0 | P41: 0 | Q41: 0 | R41: 0 | S41: 0 | T41: =SUM(H41:S41) -> -3304.74
B42: (M)Others | C42: Ada settlement | H42: 0 | I42: 0 | J42: 0 | K42: 0 | L42: 0 | M42: -6500 | N42: 0 | O42: 0 | P42: -16500 | Q42: 0 | R42: 0 | S42: 0 | T42: =SUM(H42:S42) -> -23000
B43: (M)Others | C43: Bank of America | H43: 0 | I43: 0 | J43: 0 | K43: 0 | L43: 0 | M43: -9394.7 | N43: 9394.7 | O43: 0 | P43: 0 | Q43: 0 | R43: 0 | S43: 0 | T43: =SUM(H43:S43) -> 0
B44: (M)Others | C44: DCI | H44: 0 | I44: 0 | J44: 0 | K44: 0 | L44: 0 | M44: 0 | N44: -583.2 | O44: 0 | P44: 0 | Q44: 0 | R44: 0 | S44: 0 | T44: =SUM(H44:S44) -> -583.2
B45: (M)Others | C45: Pepsi | H45: -6000 | I45: 0 | J45: 0 | K45: -18558 | L45: 0 | M45: -3000 | N45: 0 | O45: 0 | P45: -4000 | Q45: -28841.38 | R45: 0 | S45: 0 | T45: =SUM(H45:S45) -> -60399.38
B46: (M)Overhead expense | C46: Overhead | H46: -30871.3 | I46: -29341.95 | J46: -27412.07 | K46: -29370.55 | L46: -31418.58 | M46: -30169.51 | N46: -31341.61 | O46: -30169.52 | P46: -40994.6 | Q46: -46578.62 | R46: -39753.55 | S46: -44456.88 | T46: =SUM(H46:S46) -> -411878.74
B47: (M)Photo & Video | C47: Robert Tsai Photography | D47: new plateware | H47: -4300 | I47: 4300 | J47: 0 | K47: 0 | L47: 0 | M47: 0 | N47: 0 | O47: 0 | P47: 0 | Q47: 0 | R47: 0 | S47: 0 | T47: =SUM(H47:S47) -> 0
B48: (M)Photo & Video | C48: Robert Tsai Photography | D48: Muckbang & Value | H48: 0 | I48: -4286.7 | J48: 0 | K48: 0 | L48: 0 | M48: 0 | N48: 0 | O48: 0 | P48: 0 | Q48: 0 | R48: 0 | S48: 0 | T48: =SUM(H48:S48) -> -4286.7
B49: (M)Photo & Video | C49: Robert Tsai Photography | D49: Lemongrass Ginger, Salad, Kimchi Fries, Curds | H49: 0 | I49: 0 | J49: 0 | K49: 0 | L49: 0 | M49: -4300 | N49: -1.7 | O49: 0 | P49: 0 | Q49: 0 | R49: 0 | S49: 0 | T49: =SUM(H49:S49) -> -4301.7
B50: (M)Photo & Video | C50: Robert Tsai Photography | D50: Ramen | H50: 0 | I50: 0 | J50: 0 | K50: 0 | L50: 0 | M50: 0 | N50: 0 | O50: 0 | P50: -4300 | Q50: 4300 | R50: 0 | S50: 0 | T50: =SUM(H50:S50) -> 0
B51: (M)Photo & Video | C51: Robert Tsai Photography | D51: Catering, Gift Cards | H51: 0 | I51: 0 | J51: 0 | K51: 0 | L51: 0 | M51: 0 | N51: 0 | O51: 0 | P51: 0 | Q51: 0 | R51: -4300 | S51: -1.7 | T51: =SUM(H51:S51) -> -4301.7
B52: (M)Photo & Video | C52: Robert Tsai Photography | D52: Lifestyle | H52: 0 | I52: 0 | J52: 0 | K52: 0 | L52: 0 | M52: 0 | N52: 0 | O52: 0 | P52: -9500 | Q52: 2626.28 | R52: 0 | S52: 0 | T52: =SUM(H52:S52) -> -6873.72
B53: (M)Photo & Video | C53: Korean Freelancers | D53: Freelance designer | H53: 0 | I53: 0 | J53: -700 | K53: 0 | L53: 0 | M53: 0 | N53: 0 | O53: 0 | P53: 0 | Q53: 0 | R53: 0 | S53: -178.76 | T53: =SUM(H53:S53) -> -878.76
B54: (M)Photo & Video | C54: TBD | D54: Lifestyle Talent | H54: 0 | I54: 0 | J54: 0 | K54: 0 | L54: 0 | M54: 0 | N54: 0 | O54: 0 | P54: -5000 | Q54: 5000 | R54: 0 | S54: 0 | T54: =SUM(H54:S54) -> 0
B55: (M)Photo & Video | C55: CarsonDoyle Creative Agency, Ltd. | D55: Video Production | H55: 0 | I55: 0 | J55: 0 | K55: 0 | L55: 0 | M55: 0 | N55: -52509 | O55: -26254 | P55: -26254 | Q55: 0 | R55: 0 | S55: 0 | T55: =SUM(H55:S55) -> -105017
B56: (M)Photo & Video | C56: CarsonDoyle Creative Agency, Ltd. | D56: Lifestyle | H56: 0 | I56: 0 | J56: 0 | K56: 0 | L56: 0 | M56: 0 | N56: 0 | O56: 0 | P56: -8000 | Q56: 8000 | R56: 0 | S56: 0 | T56: =SUM(H56:S56) -> 0
B57: (M)Promotions | C57: COLORMARK, L.C. | D57: Lunar NY, Super Bowl, Liners | H57: -10660.52 | I57: 0 | J57: 0 | K57: 0 | L57: 0 | M57: 0 | N57: 0 | O57: 0 | P57: 0 | Q57: 0 | R57: 0 | S57: 0 | T57: =SUM(H57:S57) -> -10660.52
B58: (M)Promotions | C58: COLORMARK, L.C. | D58: Value Meal | H58: 0 | I58: 0 | J58: 0 | K58: -27000 | L58: 9948.25 | M58: 0 | N58: 0 | O58: 0 | P58: 0 | Q58: 0 | R58: 0 | S58: 0 | T58: =SUM(H58:S58) -> -17051.75
... B62: (M)Promotions | C62: Amazon | D62: Gift Cards for GC contest winners | H62: -2370 | I62: 270 | J62: 0 | K62: 0 | L62: 0 | M62: 0 | N62: 0 | O62: 0 | P62: 0 | Q62: 0 | R62: 0 | S62: 0 | T62: =SUM(H62:S62) -> -2100
B63: (M)Promotions | C63: CossmanPR LLC | D63: Influncers - Lunar NY, Super Bowl | E63: Working | H63: 0 | I63: -10000 | J63: 2712.31 | K63: 0 | L63: 0 | M63: 0 | N63: 0 | O63: 0 | P63: 0 | Q63: 0 | R63: 0 | S63: 0 | T63: =SUM(H63:S63) -> -7287.69
B64: (M)Promotions | C64: CossmanPR LLC | D64: NIL | E64: Working | H64: 0 | I64: 0 | J64: -20000 | K64: 0 | L64: 0 | M64: 0 | N64: 0 | O64: 0 | P64: 0 | Q64: 0 | R64: 0 | S64: 0 | T64: =SUM(H64:S64) -> -20000
B65: (M)Promotions | C65: CossmanPR LLC | D65: Influencers - classic crunch | E65: Working | H65: 0 | I65: 0 | J65: 0 | K65: 0 | L65: -5000 | M65: 3680.91 | N65: 0 | O65: 0 | P65: 0 | Q65: 0 | R65: 0 | S65: 0 | T65: =SUM(H65:S65) -> -1319.09
B66: (M)Promotions | C66: CossmanPR LLC | D66: Influencers - Bulgogi takeover | E66: Working | H66: 0 | I66: 0 | J66: 0 | K66: 0 | L66: 0 | M66: -4175 | N66: 0 | O66: 0 | P66: 0 | Q66: 0 | R66: 0 | S66: 0 | T66: =SUM(H66:S66) -> -4175
B67: (M)Promotions | C67: CossmanPR LLC | D67: Influencers - football | E67: Working | H67: 0 | I67: 0 | J67: 0 | K67: 0 | L67: 0 | M67: 0 | N67: 0 | O67: 0 | P67: 0 | Q67: -6928.47 | R67: 0 | S67: 0 | T67: =SUM(H67:S67) -> -6928.47
B68: (M)Promotions | C68: CossmanPR LLC | D68: Influencers - brand ambassedors | E68: Working | H68: 0 | I68: 0 | J68: 0 | K68: 0 | L68: 0 | M68: 0 | N68: 0 | O68: 0 | P68: -10000 | Q68: 10000 | R68: 0 | S68: 0 | T68: =SUM(H68:S68) -> 0
B69: (M)Promotions | C69: CarsonDoyle Creative Agency, Ltd. | D69: Influencers - brand ambassedors | E69: Working | H69: 0 | I69: 0 | J69: 0 | K69: 0 | L69: 0 | M69: 0 | N69: 0 | O69: 0 | P69: -25000 | Q69: -13333.33 | R69: -38333.33 | S69: -38333.34 | T69: =SUM(H69:S69) -> -115000
B70: (M)Promotions | C70: Stingray Worldwide LLC | D70: Lunar NY Bags | E70: Working | H70: -22278.38 | I70: 0 | J70: 0 | K70: 0 | L70: 0 | M70: 0 | N70: 0 | O70: 0 | P70: 0 | Q70: 0 | R70: 0 | S70: 0 | T70: =SUM(H70:S70) -> -22278.38
B71: (M)Promotions | C71: Uber Portier, Llc | D71: Delivery Promo | E71: Working | F71: 3rd Party Delivery | H71: -10000 | I71: -35619.47 | J71: -14832.25 | K71: -31816.3 | L71: -52500 | M71: -81790.3 | N71: -80311.81 | O71: -72129.06 | P71: -63719.94 | Q71: -65963.08 | R71: -68032.65 | S71: -69546.37 | T71: =SUM(H71:S71) -> -646261.23
B72: (M)Promotions | C72: Doordash, Inc | D72: Delivery Promo | E72: Working | F72: 3rd Party Delivery | H72: -15000 | I72: -13639.87 | J72: -21343.4 | K72: -43207.32 | L72: -40000 | M72: -80125.8 | N72: -47338.3 | O72: -48693.8 | P72: -58272.74 | Q72: -53393.5 | R72: -55818.17 | S72: -62143.38 | T72: =SUM(H72:S72) -> -538976.28
B73: (M)Promotions | C73: ezCarter, Inc | D73: Catering Promo | E73: Working | F73: 3rd Party Delivery | H73: 0 | I73: 0 | J73: 0 | K73: 0 | L73: 0 | M73: 0 | N73: 0 | O73: 0 | P73: -5000 | Q73: 0 | R73: 0 | S73: -10000 | T73: =SUM(H73:S73) -> -15000
B74: (M)Promotions | C74: Doordash, Inc | D74: $4 off 2.5 day promotion | E74: Working | F74: 3rd Party Delivery | H74: -8250 | I74: 0 | J74: 0 | K74: 66.4 | L74: 0 | M74: 0 | N74: 0 | O74: 0 | P74: 0 | Q74: 0 | R74: 0 | S74: 0 | T74: =SUM(H74:S74) -> -8183.6
B75: (M)Promotions | C75: Misc | H75: 0 | I75: 0 | J75: 0 | K75: 0 | L75: 0 | M75: 0 | N75: 0 | O75: 0 | P75: 0 | Q75: 0 | R75: 0 | S75: 2535.53 | T75: =SUM(H75:S75) -> 2535.53
B76: (M)Promotions | C76: Grubhub Holdings Inc | D76: Delivery Promo | E76: Working | F76: 3rd Party Delivery | H76: 0 | I76: 0 | J76: 0 | K76: 0 | L76: 0 | M76: -9000 | N76: 0 | O76: 0 | P76: 0 | Q76: 0 | R76: 0 | S76: 0 | T76: =SUM(H76:S76) -> -9000
B77: (M)Promotions | C77: Franchisee | D77: Donut promotion | E77: Working | H77: 0 | I77: 0 | J77: 0 | K77: 0 | L77: 0 | M77: 0 | N77: 0 | O77: 0 | P77: 0 | Q77: 0 | R77: -2057.5 | S77: -3559.31 | T77: =SUM(H77:S77) -> -5616.81
B78: (M)Promotions | C78: Franchisee | D78: $5 promotion | E78: Working | H78: 0 | I78: 0 | J78: 0 | K78: 0 | L78: 0 | M78: 0 | N78: -6220 | O78: 0 | P78: 0 | Q78: 0 | R78: 0 | S78: 0 | T78: =SUM(H78:S78) -> -6220
B79: (M)Promotions | C79: The NCC Group of LA LLC New Catering Connections | D79: Catering Test - DFW, Boston, 15 sessions | E79: Working | H79: -6257.32 | I79: -6257.32 | J79: -6257.33 | K79: -3058.33 | L79: -3058.33 | M79: -3058.34 | N79: -5845 | O79: -5845 | P79: -5845 | Q79: -5471.66 | R79: -5471.66 | S79: -5471.68 | T79: =SUM(H79:S79) -> -61896.97
B80: (M)Social Media | C80: Face Book | D80: Boosting organic social | E80: =VLOOKUP($C80,'Marketing Fund 2022'!C:E,3,FALSE) -> Working | H80: -351.64 | I80: 0 | J80: 0 | K80: 0 | L80: 0 | M80: 0 | N80: 0 | O80: 0 | P80: 0 | Q80: 0 | R80: 0 | S80: 0 | T80: =SUM(H80:S80) -> -351.64
B81: (M)Social Media | C81: Sprout Social, Inc | H81: -1025.42 | I81: -1025.43 | J81: -1673.98 | K81: -1025.42 | L81: -1025.43 | M81: -1673.98 | N81: -1025.42 | O81: -1025.42 | P81: -1369.51 | Q81: -1025.4 | R81: -1176.97 | S81: -1328.51 | T81: =SUM(H81:S81) -> -14400.89
B82: (M)Website | C82: Hello Digital | D82: ADA Scan | H82: 0 | I82: 0 | J82: 0 | K82: 0 | L82: 0 | M82: 0 | N82: 0 | O82: 0 | P82: 0 | Q82: 0 | R82: 0 | S82: 0 | T82: =SUM(H82:S82) -> 0
B83: (M)Website | C83: Hello Digital | D83: Site Support | H83: -1500 | I83: -1500 | J83: -1500 | K83: -1500 | L83: -1500 | M83: -1500 | N83: -1500 | O83: -1500 | P83: -1500 | Q83: -1500 | R83: -1500 | S83: -1500 | T83: =SUM(H83:S83) -> -18000
B84: (M)Website | C84: Hello Digital | D84: Platform updates | H84: 0 | I84: 0 | J84: 0 | K84: 0 | L84: 0 | M84: 0 | N84: 0 | O84: 0 | P84: 0 | Q84: 0 | R84: 0 | S84: 0 | T84: =SUM(H84:S84) -> 0
B85: (M)Website | C85: Pixel and Tonic, Inc | D85: Hosting | H85: -79 | I85: -79 | J85: -79 | K85: -79 | L85: -375 | M85: -79 | N85: -158 | O85: -79 | P85: -128 | Q85: -79 | R85: -79 | S85: -79 | T85: =SUM(H85:S85) -> -1372
B86: (M)Website | C86: Ipage by Network Solutions | H86: 0 | I86: 0 | J86: 0 | K86: 0 | L86: 0 | M86: 0 | N86: 0 | O86: 0 | P86: -132.83 | Q86: 0 | R86: 0 | S86: 0 | T86: =SUM(H86:S86) -> -132.83
B87: (M)Website | C87: Marqii, Inc | H87: 0 | I87: 0 | J87: 0 | K87: 0 | L87: 0 | M87: 0 | N87: 0 | O87: 0 | P87: -1312.5 | Q87: 0 | R87: -7138.28 | S87: -5845.78 | T87: =SUM(H87:S87) -> -14296.56
B88: (M)Website | C88: MomentFeed Inc. | H88: -6649.35 | I88: -7134.96 | J88: -6737.03 | K88: -6824.7 | L88: -7714.98 | M88: -7141.69 | N88: -6649.35 | O88: -7013.55 | P88: -3324.68 | Q88: 0 | R88: 0 | S88: 0 | T88: =SUM(H88:S88) -> -59190.29
B89: Total Marketing expense | H89: =SUM(H9:H88) -> -239146.89 | I89: =SUM(I9:I88) -> -244881.22 | J89: =SUM(J9:J88) -> -251770.2 | K89: =SUM(K9:K88) -> -373759.59 | L89: =SUM(L9:L88) -> -402282.26 | M89: =SUM(M9:M88) -> -576917.36 | N89: =SUM(N9:N88) -> -446638.34 | O89: =SUM(O9:O88) -> -474074.76 | ... S89: =SUM(S9:S88) -> -508798.77 | T89: =SUM(H89:S89) -> -4958269.5
B90: (M)Others | C90: Marketing liability | H90: -16897.73 | I90: 44410.5 | J90: -10071.78 | K90: 79328.21 | L90: 128391.41 | M90: 312226.08 | N90: 173674.95 | O90: 192375.02 | P90: 285400.96 | Q90: 92238.17 | R90: 197564.7 | S90: 224496.09 | T90: =SUM(H90:S90) -> 1703136.6
B91: Check | K91: =SUM(K4:K6)+K89+K90 -> 0 | L91: =SUM(L4:L6)+L89+L90 -> 0 | M91: =SUM(M4:M6)+M89+M90 -> 0 | N91: =SUM(N4:N6)+N89+N90 -> 0 | O91: =SUM(O4:O6)+O89+O90 -> 0 | P91: =SUM(P4:P6)+P89+P90 -> 0 | Q91: =SUM(Q4:Q6)+Q89+Q90 -> 0 | R91: =SUM(R4:R6)+R89+R90 -> 0 | S91: =SUM(S4:S6)+S89+S90 -> 0 | T91: =SUM(H91:S91) -> 0
B94: Net Marketing Fund | H94: =SUM(H7,H89) -> 16897.73 | I94: =SUM(I7,I89) -> -8137.5 | J94: =SUM(J7,J89) -> 10071.78 | K94: =SUM(K7,K89) -> -79328.21 | L94: =SUM(L7,L89) -> -128391.41 | M94: =SUM(M7,M89) -> -312226.08 | N94: =SUM(N7,N89) -> -173674.95 | O94: =SUM(O7,O89) -> -192375.02 | ... T94: =SUM(T7,T89) -> -1666863.6
B97: DoorDash Fund
D98: Doordash | H98: 0 | I98: 0 | T98: =SUM(H98:S98) -> 0
B99: Total DoorDash income | H99: =SUM(H98) -> 0 | I99: =SUM(I98) -> 0 | P99: =SUM(P98) -> 0 | Q99: =SUM(Q98) -> 0 | R99: =SUM(R98) -> 0 | S99: =SUM(S98) -> 0 | T99: =SUM(H99:S99) -> 0
T100: =SUM(H100:S100) -> 0
B101: (M)Promotions | C101: Doordash, Inc | D101: Doordash | E101: Working | F101: 3rd Party Delivery | I101: -24273 | T101: =SUM(H101:S101) -> -24273
B102: (M)Promotions | C102: Sysco Boston, LLC | D102: Doordash | I102: -12000 | T102: =SUM(H102:S102) -> -12000
B103: Total DoorDash expense | H103: =SUM(H101:H102) -> 0 | I103: =SUM(I101:I102) -> -36273 | P103: =SUM(P101:P102) -> 0 | Q103: =SUM(Q101:Q102) -> 0 | R103: =SUM(R101:R102) -> 0 | S103: =SUM(S101:S102) -> 0 | T103: =SUM(H103:S103) -> -36273
B105: Net DoorDash Fund | H105: =H99+H103 -> 0 | I105: =I99+I103 -> -36273 | P105: =SUM(P99,P103) -> 0 | Q105: =SUM(Q99,Q103) -> 0 | R105: =SUM(R99,R103) -> 0 | S105: =SUM(S99,S103) -> 0 | T105: =SUM(T99,T103) -> -36273
B107: Working | H107: =SUMIF($E$8:$E$102,$B107,H$8:H$102) -> -107137.34 | I107: =SUMIF($E$8:$E$102,$B107,I$8:I$102) -> -154789.66 | J107: =SUMIF($E$8:$E$102,$B107,J$8:J$102) -> -129720.67 | K107: =SUMIF($E$8:$E$102,$B107,K$8:K$102) -> -226515.15 | L107: =SUMIF($E$8:$E$102,$B107,L$8:L$102) -> -303506.66 | M107: =SUMIF($E$8:$E$102,$B107,M$8:M$102) -> -384890.1 | N107: =SUMIF($E$8:$E$102,$B107,N$8:N$102) -> -299728.91 | O107: =SUMIF($E$8:$E$102,$B107,O$8:O$102) -> -331589.43 | ... S107: =SUMIF($E$8:$E$102,$B107,S$8:S$102) -> -353183.08 | T107: =SUM(H107:S107) -> -3285202
B108: Non-Working | H108: =H89+H103-H107 -> -132009.55 | I108: =I89+I103-I107 -> -126364.56 | J108: =J89+J103-J107 -> -122049.53 | K108: =K89+K103-K107 -> -147244.44 | L108: =L89+L103-L107 -> -98775.6 | M108: =M89+M103-M107 -> -192027.26 | N108: =N89+N103-N107 -> -146909.43 | O108: =O89+O103-O107 -> -142485.33 | ... S108: =S89+S103-S107 -> -155615.69 | T108: =SUM(H108:S108) -> -1709340.5
B110: 3rd Party Delivery | H110: =SUMIF($F$8:$F$102,$B110,H$8:H$102) -> -33250 | I110: =SUMIF($F$8:$F$102,$B110,I$8:I$102) -> -73532.34 | J110: =SUMIF($F$8:$F$102,$B110,J$8:J$102) -> -36175.65 | K110: =SUMIF($F$8:$F$102,$B110,K$8:K$102) -> -74957.22 | L110: =SUMIF($F$8:$F$102,$B110,L$8:L$102) -> -92500 | M110: =SUMIF($F$8:$F$102,$B110,M$8:M$102) -> -170916.1 | N110: =SUMIF($F$8:$F$102,$B110,N$8:N$102) -> -127650.11 | O110: =SUMIF($F$8:$F$102,$B110,O$8:O$102) -> -120822.86 | ... S110: =SUMIF($F$8:$F$102,$B110,S$8:S$102) -> -141689.75 | T110: =SUM(H110:S110) -> -1241694.1

Sheet Marketing Fund 2026 Plan
E1: -1
B2: G/L Account | C2: Vendor in SAP | D2: Description | E2: Memo | F2: 3PD | H2: Plan
H3: F26P01 | I3: F26P02 | J3: F26P03 | K3: F26P04 | L3: F26P05 | M3: F26P06 | N3: F26P07 | O3: F26P08 | P3: F26P09 | Q3: F26P10 | R3: F26P11 | S3: F26P12 | T3: FY
B4: 4112211 Marketing Fee Incomes | H4: 278297.64 | I4: 254978.11 | J4: 277449.73 | K4: 271510.46 | L4: 290630.55 | M4: 278280.59 | N4: 541292.27 | O4: 573539.1 | P4: 539469.96 | Q4: 588719.06 | R4: 567395.9 | S4: 630609.47 | T4: =SUM(H4:S4) -> 5092172.9
B5: 4112212 Marketing fee incomes- Pepsi | H5: 0 | I5: 0 | J5: 0 | K5: 0 | L5: 0 | M5: 0 | N5: 0 | O5: 0 | P5: 0 | Q5: 0 | R5: 0 | S5: 0 | T5: =SUM(H5:S5) -> 0
B6: 4112213 Marketing fee incomes- Others | H6: 0 | I6: 0 | J6: 0 | K6: 0 | L6: 0 | M6: 0 | N6: 0 | O6: 0 | P6: 0 | Q6: 0 | R6: 0 | S6: 0 | T6: =SUM(H6:S6) -> 0
B7: Total Marketing income | H7: =SUM(H4:H6) -> 278297.64 | I7: =SUM(I4:I6) -> 254978.11 | J7: =SUM(J4:J6) -> 277449.73 | K7: =SUM(K4:K6) -> 271510.46 | L7: =SUM(L4:L6) -> 290630.55 | M7: =SUM(M4:M6) -> 278280.59 | N7: =SUM(N4:N6) -> 541292.27 | O7: =SUM(O4:O6) -> 573539.1 | ... U7: =SUM(U4:U6) -> 0
T8: =SUM(H8:H8) -> 0
B9: (M)Agency | C9: CarsonDoyle Creative Agency, Ltd. | D9: Retainer | H9: -26000 | I9: -26000 | J9: -26000 | K9: -26000 | L9: -26000 | M9: -26000 | N9: -26000 | O9: -26000 | P9: -26000 | Q9: -26000 | R9: -26000 | S9: -26000 | T9: =SUM(H9:S9) -> -312000
B10: (M)Agency | C10: CossmanPR LLC | D10: Retainer | H10: -6500 | I10: -6500 | J10: -6500 | K10: -6500 | L10: -6500 | M10: -6500 | N10: -6500 | O10: -6500 | P10: -6500 | Q10: -6500 | R10: -6500 | S10: -6500 | T10: =SUM(H10:S10) -> -78000
B11: (M)Agency | C11: Veylan Inc | D11: Retainer/AI Media/Marketing Tool | H11: -10000 | I11: -10000 | J11: -10000 | K11: -10000 | L11: -10000 | M11: -10000 | N11: -10000 | O11: -10000 | P11: -10000 | Q11: -10000 | R11: -10000 | S11: -10000 | T11: =SUM(H11:S11) -> -120000
B12: (M)CRM/Loyalty | C12: Fishbowl Inc. | D12: Crunch Club Email Sends | H12: -6700 | I12: -6700 | J12: -6700 | K12: -6700 | L12: -6700 | M12: -6700 | N12: -6700 | O12: -6700 | P12: -6700 | Q12: -6700 | R12: -6700 | S12: -6700 | T12: =SUM(H12:S12) -> -80400
B13: (M)Market Research | C13: GetTattle Inc | D13: Guest Recovery | H13: -1500 | I13: 0 | J13: 0 | K13: -1500 | L13: 0 | M13: 0 | N13: -1500 | O13: 0 | P13: 0 | Q13: -1500 | R13: 0 | S13: 0 | T13: =SUM(H13:S13) -> -6000
B14: (M)Market Research | C14: GetTattle Inc | D14: Guest Survey Platform | H14: -7900 | I14: -8000 | J14: -8100 | K14: -8200 | L14: -8300 | M14: -8400 | N14: -8500 | O14: -8600 | P14: -8700 | Q14: -8800 | R14: -8900 | S14: -9000 | T14: =SUM(H14:S14) -> -101400
B15: (M)Market Research | C15: Survey Monkey | D15: Platform Subscription | H15: 0 | I15: 0 | J15: 0 | K15: 0 | L15: 0 | M15: 0 | N15: 0 | O15: 0 | P15: -550 | Q15: 0 | R15: 0 | S15: 0 | T15: =SUM(H15:S15) -> -550
B16: (M)Menu Development | D16: AI menu pricing Tool | H16: 0 | I16: 0 | J16: 0 | K16: 0 | L16: -15000 | M16: -15000 | N16: -15000 | O16: 0 | P16: 0 | Q16: 0 | R16: 0 | S16: 0 | T16: =SUM(H16:S16) -> -45000
B17: (M)Menu Development | C17: COLORMARK, L.C. | D17: System Menu | H17: 0 | I17: 0 | J17: -70000 | K17: 0 | L17: 0 | M17: 0 | N17: -70000 | O17: 0 | P17: 0 | Q17: 0 | R17: 0 | S17: -70000 | T17: =SUM(H17:S17) -> -210000
B18: (M)Menu Development | C18: COLORMARK, L.C. | D18: Monthly Promotions | H18: -1000 | I18: -1000 | J18: -1000 | K18: -1000 | L18: -1000 | M18: -1000 | N18: -1000 | O18: -1000 | P18: -1000 | Q18: -1000 | R18: -1000 | S18: -1000 | T18: =SUM(H18:S18) -> -12000
B19: (M)Misc | C19: COLORMARK, L.C. | D19: Misc Print Production | H19: -500 | I19: -500 | J19: -500 | K19: -500 | L19: -500 | M19: -500 | N19: -500 | O19: -500 | P19: -500 | Q19: -500 | R19: -500 | S19: -500 | T19: =SUM(H19:S19) -> -6000
B20: (M)Misc | C20: Stingray Worldwide LLC | D20: Uniforms | H20: 0 | I20: 0 | J20: -3000 | K20: 0 | L20: 0 | M20: -3000 | N20: 0 | O20: 0 | P20: -3000 | Q20: 0 | R20: 0 | S20: 0 | T20: =SUM(H20:S20) -> -9000
B21: (M)Misc | D21: Misc | H21: -3500 | I21: -3500 | J21: -3500 | K21: -3500 | L21: -3500 | M21: -3500 | N21: -3500 | O21: -3500 | P21: -3500 | Q21: -3500 | R21: -3500 | S21: -3500 | T21: =SUM(H21:S21) -> -42000
B22: (M)Music | C22: Creative Media Solutions, LLC _Juke Boxy | D22: Playlist Subscription | H22: -2320 | I22: -2360 | J22: -2400 | K22: -2440 | L22: -2480 | M22: -2520 | N22: -2560 | O22: -2600 | P22: -2640 | Q22: -2680 | R22: -2720 | S22: -2760 | T22: =SUM(H22:S22) -> -30480
B23: (M)National Advertisement | C23: Marketing Informatics LLC | D23: Local Media | E23: Working | H23: -1000 | I23: -1000 | J23: -1000 | K23: -1000 | L23: -1000 | M23: -1000 | N23: -1000 | O23: -1000 | P23: -1000 | Q23: -1000 | R23: -1000 | S23: -1000 | T23: =SUM(H23:S23) -> -12000
B24: (M)National Advertisement | C24: CossmanPR LLC | D24: Local Media | E24: Working | H24: -5000 | I24: -5000 | J24: -5000 | K24: -5000 | L24: -5000 | M24: -5000 | N24: -5000 | O24: -5000 | P24: -5000 | Q24: -5000 | R24: -5000 | S24: -5000 | T24: =SUM(H24:S24) -> -60000
B25: (M)National Advertisement | C25: Brandverge, Inc. | D25: NRO Media | E25: Working | H25: -5000 | I25: -5000 | J25: -5000 | K25: -5000 | L25: -5000 | M25: -5000 | N25: -5000 | O25: -5000 | P25: -5000 | Q25: -5000 | R25: -5000 | S25: -5000 | T25: =SUM(H25:S25) -> -60000
B26: (M)National Advertisement | C26: Veylan Inc | D26: National Digital Paid Media | E26: Working | H26: -150000 | I26: -150000 | J26: -150000 | K26: -150000 | L26: -150000 | M26: -150000 | N26: -150000 | O26: -150000 | P26: -150000 | Q26: -150000 | R26: -150000 | S26: -150000 | T26: =SUM(H26:S26) -> -1800000
B27: (M)Nutrition Fact | C27: Nutritional Information Services | D27: New/Revised Recipes | H27: 0 | I27: 0 | J27: -300 | K27: 0 | L27: 0 | M27: -300 | N27: 0 | O27: 0 | P27: -300 | Q27: 0 | R27: 0 | S27: -300 | T27: =SUM(H27:S27) -> -1200
B28: (M)Overhead expense | C28: Overhead | D28: Overhead | H28: -50000 | I28: -55000 | J28: -55000 | K28: -55000 | L28: -55000 | M28: -55000 | N28: -55000 | O28: -55000 | P28: -55000 | Q28: -55000 | R28: -55000 | S28: -55000 | T28: =SUM(H28:S28) -> -655000
B29: (M)Photo & Video | C29: CarsonDoyle Creative Agency,Ltd. | D29: Content Production | H29: 0 | I29: 0 | J29: 0 | K29: 0 | L29: 0 | M29: 0 | N29: -100000 | O29: 0 | P29: 0 | Q29: 0 | R29: 0 | S29: 0 | T29: =SUM(H29:S29) -> -100000
B30: (M)Photo & Video | C30: Korean Freelancers | D30: Freelance Designer | H30: 0 | I30: 0 | J30: -700 | K30: 0 | L30: 0 | M30: -700 | N30: 0 | O30: 0 | P30: -700 | Q30: 0 | R30: 0 | S30: -700 | T30: =SUM(H30:S30) -> -2800
B31: (M)Photo & Video | C31: Robert Tsai Photography | D31: Menu/Lifestyle Photography | H31: 0 | I31: -4300 | J31: 0 | K31: -4300 | L31: 0 | M31: -4300 | N31: 0 | O31: -4300 | P31: 0 | Q31: -4300 | R31: 0 | S31: -4300 | T31: =SUM(H31:S31) -> -25800
B32: (M)Promotions | C32: Doordash, Inc | D32: 3PD Media | E32: Working | F32: 3rd Party Delivery | H32: -58000 | I32: -55000 | J32: -58000 | K32: -50000 | L32: -50000 | M32: -50000 | N32: -50000 | O32: -50000 | P32: -50000 | Q32: -50000 | R32: -58000 | S32: -58000 | T32: =SUM(H32:S32) -> -637000
B33: (M)Promotions | C33: ezCarter, Inc | D33: Catering Promo | E33: Working | F33: 3rd Party Delivery | H33: 0 | I33: 0 | J33: -10000 | K33: 0 | L33: 0 | M33: -10000 | N33: 0 | O33: 0 | P33: -10000 | Q33: 0 | R33: 0 | S33: -10000 | T33: =SUM(H33:S33) -> -40000
B34: (M)Promotions | C34: Uber Portier, Llc | D34: 3PD Media | E34: Working | F34: 3rd Party Delivery | H34: -68000 | I34: -65000 | J34: -68000 | K34: -60000 | L34: -60000 | M34: -60000 | N34: -60000 | O34: -60000 | P34: -60000 | Q34: -60000 | R34: -68000 | S34: -68000 | T34: =SUM(H34:S34) -> -757000
B35: (M)Promotions | C35: Doordash, Inc | D35: Promotional Activation | E35: Working | F35: 3rd Party Delivery | H35: 0 | I35: -10000 | J35: 0 | K35: -10000 | L35: 0 | M35: -10000 | N35: 0 | O35: -10000 | P35: 0 | Q35: -10000 | R35: 0 | S35: -10000 | T35: =SUM(H35:S35) -> -60000
B36: (M)Promotions | C36: CossmanPR LLC | D36: Influencers - Brand Ambassedors | E36: Working | H36: -30000 | I36: -30000 | J36: -30000 | K36: -30000 | L36: -30000 | M36: -30000 | N36: -30000 | O36: -30000 | P36: -30000 | Q36: -30000 | R36: -30000 | S36: -30000 | T36: =SUM(H36:S36) -> -360000
B37: (M)Promotions | C37: COLORMARK, L.C. | D37: National Rollout POP Production | H37: -20000 | I37: 0 | J37: -20000 | K37: 0 | L37: -20000 | M37: 0 | N37: -20000 | O37: 0 | P37: -20000 | Q37: 0 | R37: -20000 | S37: 0 | T37: =SUM(H37:S37) -> -120000
B38: (M)Promotions | C38: CossmanPR LLC | D38: National Rollout PR Activation | E38: Working | H38: -5000 | I38: -5000 | J38: -5000 | K38: -5000 | L38: -5000 | M38: -5000 | N38: -5000 | O38: -5000 | P38: -5000 | Q38: -5000 | R38: -5000 | S38: -5000 | T38: =SUM(H38:S38) -> -60000
B39: (M)Promotions | C39: Stingray Worldwide LLC | D39: Merchandising | H39: -5000 | I39: 0 | J39: 0 | K39: -5000 | L39: 0 | M39: 0 | N39: -5000 | O39: 0 | P39: -5000 | Q39: 0 | R39: -5000 | S39: 0 | T39: =SUM(H39:S39) -> -25000
B40: (M)Social Media | C40: Sprout Social, Inc | D40: Social Scheduling and Analytics | H40: -1200 | I40: -1200 | J40: -1200 | K40: -1200 | L40: -1200 | M40: -1200 | N40: -1200 | O40: -1200 | P40: -1200 | Q40: -1200 | R40: -1200 | S40: -1200 | T40: =SUM(H40:S40) -> -14400
B41: (M)Others | C41: Bonchon Holdings LLC | D41: G&A | H41: -2500 | I41: -2500 | J41: -2500 | K41: -2500 | L41: -2500 | M41: -2500 | N41: -2500 | O41: -2500 | P41: -2500 | Q41: -2500 | R41: -2500 | S41: -2500 | T41: =SUM(H41:S41) -> -30000
B42: (M)Others | C42: Freshworks Inc Dept # 880636 | D42: Creative Request Platform | H42: -100 | I42: -100 | J42: -100 | K42: -100 | L42: -100 | M42: -100 | N42: -100 | O42: -100 | P42: -100 | Q42: -100 | R42: -100 | S42: -100 | T42: =SUM(H42:S42) -> -1200
B43: (M)Others | C43: Mirus Information Tech Service, Inc | D43: Sales Report | H43: -11804 | I43: -11880 | J43: -11956 | K43: -12035 | L43: -12284 | M43: -12436 | N43: -12412 | O43: -13192 | P43: -13396 | Q43: -13524 | R43: -13928 | S43: -14584 | T43: =SUM(H43:S43) -> -153431
B44: (M)Others | C44: Franchisee | D44: Promotional Funding/Redemption | H44: 0 | I44: 0 | J44: -6000 | K44: 0 | L44: 0 | M44: -6000 | N44: 0 | O44: 0 | P44: -6000 | Q44: 0 | R44: 0 | S44: -6000 | T44: =SUM(H44:S44) -> -24000
B45: (M)Website | C45: Ada settlement | D45: Website Legal Settlement | H45: 0 | I45: 0 | J45: 0 | K45: 0 | L45: 0 | M45: -10000 | N45: 0 | O45: 0 | P45: 0 | Q45: 0 | R45: 0 | S45: -10000 | T45: =SUM(H45:S45) -> -20000
B46: (M)Website | C46: Hello Digital LLC | D46: ADA Scan | H46: 0 | I46: 0 | J46: 0 | K46: 0 | L46: 0 | M46: -6000 | N46: 0 | O46: 0 | P46: 0 | Q46: 0 | R46: 0 | S46: -6000 | T46: =SUM(H46:S46) -> -12000
B47: (M)Website | C47: Hello Digital LLC | D47: Site Support | H47: -1500 | I47: -1500 | J47: -1500 | K47: -1500 | L47: -1500 | M47: -1500 | N47: -1500 | O47: -1500 | P47: -1500 | Q47: -1500 | R47: -1500 | S47: -1500 | T47: =SUM(H47:S47) -> -18000
B48: (M)Website | C48: Hello Digital LLC | D48: Platform updates | H48: 0 | I48: 0 | J48: 0 | K48: 0 | L48: 0 | M48: -5000 | N48: 0 | O48: 0 | P48: 0 | Q48: 0 | R48: 0 | S48: -3000 | T48: =SUM(H48:S48) -> -8000
B49: (M)Website | C49: Ipage by Network Solutions | D49: Platform | H49: 0 | I49: 0 | J49: 0 | K49: 0 | L49: 0 | M49: -300 | N49: 0 | O49: 0 | P49: 0 | Q49: 0 | R49: 0 | S49: 0 | T49: =SUM(H49:S49) -> -300
B50: (M)Website | C50: Marqii, Inc | D50: Platform - Location/Listings | H50: -6700 | I50: -6780 | J50: -6860 | K50: -6940 | L50: -7020 | M50: -7100 | N50: -7180 | O50: -7260 | P50: -7340 | Q50: -7420 | R50: -7500 | S50: -7580 | T50: =SUM(H50:S50) -> -85680
B51: (M)Website | C51: Pixel and Tonic, Inc | D51: Hosting | H51: -125 | I51: -125 | J51: -125 | K51: -125 | L51: -125 | M51: -125 | N51: -125 | O51: -125 | P51: -125 | Q51: -125 | R51: -125 | S51: -125 | T51: =SUM(H51:S51) -> -1500
B52: (M)Website | D52: Olo Catering Pilot | H52: 0 | I52: 0 | J52: 0 | K52: 0 | L52: 0 | M52: -3000 | N52: -3000 | O52: -3000 | P52: 0 | Q52: 0 | R52: 0 | S52: 0 | T52: =SUM(H52:S52) -> -9000
B53: Total Marketing expense | H53: =SUM(H9:H52) -> -486849 | I53: =SUM(I9:I52) -> -473945 | J53: =SUM(J9:J52) -> -575941 | K53: =SUM(K9:K52) -> -471040 | L53: =SUM(L9:L52) -> -485709 | M53: =SUM(M9:M52) -> -524681 | N53: =SUM(N9:N52) -> -665777 | O53: =SUM(O9:O52) -> -469577 | ... U53: =SUM(U9:U52) -> 0
B54: (M)Others | C54: Marketing liability | H54: =-(H53+H7) -> 208551.36 | I54: =-(I53+I7) -> 218966.89 | J54: =-(J53+J7) -> 298491.27 | K54: =-(K53+K7) -> 199529.54 | L54: =-(L53+L7) -> 195078.45 | M54: =-(M53+M7) -> 246400.41 | N54: =-(N53+N7) -> 124484.73 | O54: =-(O53+O7) -> -103962.1 | ... S54: =-(S53+S7) -> -39760.475 | T54: =SUM(H54:N54) -> 1491502.6
B55: Check | T55: =SUM(H55:N55) -> 0
B58: Net Marketing Fund | H58: =SUM(H7,H53) -> -208551.36 | I58: =SUM(I7,I53) -> -218966.89 | J58: =SUM(J7,J53) -> -298491.27 | K58: =SUM(K7,K53) -> -199529.54 | L58: =SUM(L7,L53) -> -195078.45 | M58: =SUM(M7,M53) -> -246400.41 | N58: =SUM(N7,N53) -> -124484.73 | O58: =SUM(O7,O53) -> 103962.1 | ... S58: =SUM(S7,S53) -> 39760.475 | T58: =SUM(H58:N58) -> -1491502.6
B108: Working | H108: =SUMIF($E$8:$E$57,$B108,H$8:H$57) -> -322000 | I108: =SUMIF($E$8:$E$57,$B108,I$8:I$57) -> -326000 | J108: =SUMIF($E$8:$E$57,$B108,J$8:J$57) -> -332000 | K108: =SUMIF($E$8:$E$57,$B108,K$8:K$57) -> -316000 | L108: =SUMIF($E$8:$E$57,$B108,L$8:L$57) -> -306000 | M108: =SUMIF($E$8:$E$57,$B108,M$8:M$57) -> -326000 | N108: =SUMIF($E$8:$E$57,$B108,N$8:N$57) -> -306000 | O108: =SUMIF($E$8:$E$57,$B108,O$8:O$57) -> -316000 | ... S108: =SUMIF($E$8:$E$57,$B108,S$8:S$57) -> -342000 | T108: =SUM(H108:S108) -> -3846000 | U108: =SUMIF($E$8:$E$57,$B108,U$8:U$57) -> 0
B109: Non-Working | H109: =H53-H108 -> -164849 | I109: =I53-I108 -> -147945 | J109: =J53-J108 -> -243941 | K109: =K53-K108 -> -155040 | L109: =L53-L108 -> -179709 | M109: =M53-M108 -> -198681 | N109: =N53-N108 -> -359777 | O109: =O53-O108 -> -153577 | ... S109: =S53-S108 -> -248849 | T109: =SUM(H109:S109) -> -2360141 | U109: =U53-U108 -> 0
B111: 3rd Party Delivery | H111: =SUMIF($F$8:$F$57,$B111,H$8:H$57) -> -126000 | I111: =SUMIF($F$8:$F$57,$B111,I$8:I$57) -> -130000 | J111: =SUMIF($F$8:$F$57,$B111,J$8:J$57) -> -136000 | K111: =SUMIF($F$8:$F$57,$B111,K$8:K$57) -> -120000 | L111: =SUMIF($F$8:$F$57,$B111,L$8:L$57) -> -110000 | M111: =SUMIF($F$8:$F$57,$B111,M$8:M$57) -> -130000 | N111: =SUMIF($F$8:$F$57,$B111,N$8:N$57) -> -110000 | O111: =SUMIF($F$8:$F$57,$B111,O$8:O$57) -> -120000 | ... S111: =SUMIF($F$8:$F$57,$B111,S$8:S$57) -> -146000 | T111: =SUM(H111:S111) -> -1494000 | U111: =SUMIF($F$8:$F$57,$B111,U$8:U$57) -> 0
